Workbook

Sheet 0) SL Project Structure
A1: SL Project Services Functional Strategy Project Landscape Map (Coded by Principle Current Commercial Delivery Framework) (Projects with Lifecycle Forecast over £20M)
A2: Total Lifetime EAC Value of SL Projects over £20M = | G2: =I5+P5+W5+AK5+P56 -> 9662.5718
D4: Project Delivery Directorate (PDD) | K4: Remediation | R4: Retrievals | AC4: Site Project Office
D5: Director / Lead: A. Sharples | G5: Lifecycle Value: | I5: =C15+C21+C27+C33+C39+C45+C51+G15+G21+G27+G33 -> 6641.1444 | K5: Director / Lead: G. McCracken | N5: Lifecycle Value: | P5: =L15+L21+L27+L33 -> 328.098 | R5: Director / Lead: J. Millington | S5: C. Carruthers | U5: Lifecycle Value: | W5: =S15+S21+S27+S33+S39+S45+S51 -> 1604.5912 | AC5: Director / Lead: M. Johns | AI5: Lifecycle Value: | AK5: =AD9+AD28+AD46+AL9 -> 1061.8363
D6: PC Lead: Lee Edgar & SPCMs | K6: PC Lead: A Grainger | R6: PC Lead: Programme PCMs | AC6: PC Lead: J Irving
Y8: Categorised / Value Streams | AG8: Infrastructure
D9: PPP | H9: Legacy | Y9: Director / Lead: J. Brocklebank | AB9: Lifecycle Value: | AD9: =+Z17+Z24 -> 63.090549 | AG9: Director / Lead: C. Mills | AJ9: Lifecycle Value: | AL9: =+AH17+AH24+AH31+AH38+AH45+AH52+AH59 -> 717.26252
R10: N.B. Project very close to completion | AG10: PC Lead: S Jackson
B11: Proj No: | C11: 35/09592 | F11: Proj No: | G11: 35/10137 | K11: Proj No: | L11: 35/05396 | R11: Proj No: | S11: 35/10095
B12: Programme: | C12: SNM Future State | F12: Programme: | G12: Magnox Swarf Storage Silo | K12: Programme: | L12: *1 - Final Decommissioning | R12: Programme: | S12: Pile Fuel Cladding Silo
B13: Title: | C13: Sellafield Product & Residue Store Retreatment Plant | F13: Title: | G13: Box Encapsulation Plant | K13: Title: | L13: Chimney Decommissioning Phase 2F | R13: Title: | S13: Box Encapsulation Plant Product Store Direct Import Facility | Y13: Proj No: | Z13: 35/10188 | AG13: Proj No: | AH13: 35/09140
B14: SRO | C14: Jeremy Hunt | F14: SPA | G14: Phil Reeve | K14: SPA | L14: Glenn McCracken | R14: SPA | S14: Kevin Brown | Y14: Programme: | Z14: AGROP | AG14: Programme: | AH14: Utilities and Future Energy
B15: Lifecycle P50: | C15: =VLOOKUP(C13,'5a)NDA MPPR'!$B$9:$AK$61,21,FALSE) -> 1466.5527 | F15: Lifecycle P50: | G15: =VLOOKUP(G13,'5a)NDA MPPR'!$B$9:$AK$61,21,FALSE) -> 1445.0751 | K15: Lifecycle P50: | L15: =VLOOKUP(L13,'5a)NDA MPPR'!$B$9:$AK$61,21,FALSE) -> 148.90141 | R15: Lifecycle P50: | S15: =VLOOKUP(S13,'5a)NDA MPPR'!$B$9:$AK$61,21,FALSE) -> 458.24396 | Y15: Title: | Z15: THORP Receipt & Storage Control Systems Replacement | AG15: Title: | AH15: Electrical Supply - New Construction
Y16: SPA | Z16: Andrew Pringle | AG16: SRO | AH16: Gavin Askew
B17: Proj No: | C17: 35/09343 | F17: Proj No: | G17: 35/09975 | K17: Proj No: | L17: 35/09707 | R17: Proj No: | S17: 35/06075 | Y17: Lifecycle P50: | Z17: =VLOOKUP(Z15,'4b) SL EPO Extended Data Sheet'!$A$5:$AB$176,17,FALSE)/1000000 -> 23.356291 | AG17: Lifecycle P50: | AH17: =VLOOKUP(AH15,'5a)NDA MPPR'!$B$9:$AK$61,21,FALSE) -> 427.81347
B18: Programme: | C18: SIXEP Capability | F18: Programme: | G18: Unified Command & Control | K18: Programme: | L18: *1 - Final Decommissioning | R18: Programme: | S18: Magnox Swarf Storage Silo | AG18: Infrastructure
B19: Title: | C19: SIXEP Continuity Plant | F19: Title: | G19: Security Systems Architecture Upgrade (SSAU) | K19: Title: | L19: LAETP Floc Retrieval | R19: Title: | S19: SEP Solid Waste Storage Retrievals
B20: SRO | C20: Jeremy Hunt | F20: SPA | G20: Michael Askew | K20: SPA | L20: Glenn McCracken | R20: SPA | S20: Phil Reeve | Y20: Proj No: | Z20: 35/10151 | AG20: Proj No: | AH20: 35/10565
B21: Lifecycle P50: | C21: =VLOOKUP(C19,'5a)NDA MPPR'!$B$9:$AK$61,21,FALSE) -> 1120.8757 | F21: Lifecycle P50: | G21: =VLOOKUP(G19,'5a)NDA MPPR'!$B$9:$AK$61,21,FALSE) -> 315.08361 | K21: Lifecycle P50: | L21: =VLOOKUP(L19,'5a)NDA MPPR'!$B$9:$AK$61,21,FALSE) -> 87.561965 | R21: Lifecycle P50: | S21: =VLOOKUP(S19,'5a)NDA MPPR'!$B$9:$AK$61,21,FALSE) -> 887.19569 | Y21: Programme: | Z21: No Programme | AG21: Programme: | AH21: No Programme
Y22: Title: | Z22: FHP & SIXEP Roof Replacement | AG22: Title: | AH22: EMRMS (Emergency Management Radiological Monitoring System)
B23: Proj No: | C23: 35/07654 | F23: Proj No: | G23: 35/09968 | K23: Proj No: | L23: 35/09000 | R23: Proj No: | S23: 35/05684 | Y23: SPA | Z23: Stuart Pearson | AG23: SPA | AH23: Rob Hargreaves
B24: Programme: | C24: Retrievals Value Stream Waste Capabilities | F24: Programme: | G24: Unified Command & Control | K24: Programme: | L24: *1 - Final Decommissioning | R24: Programme: | S24: Magnox Swarf Storage Silo | Y24: Lifecycle P50: | Z24: =VLOOKUP(Z22,'4b) SL EPO Extended Data Sheet'!$A$5:$AB$176,17,FALSE)/1000000 -> 39.734258 | AG24: Lifecycle P50: | AH24: =VLOOKUP(AH22,'4b) SL EPO Extended Data Sheet'!$A$5:$AB$176,17,FALSE)/1000000 -> 32.00067
B25: Title: | C25: BEPPS2 | F25: Title: | G25: CNC Operational Unit | K25: Title: | L25: Heat Exchanger Deplanting - Main Project | R25: Title: | S25: MSSS Upgrades for Retrievals & Resilience | AG25: Analytical Services
B26: SRO | C26: Kathryn McCloghrie | F26: SPA | G26: Michael Askew | K26: SPA | L26: Glenn McCracken | R26: SPA | S26: Phil Reeve
B27: Lifecycle P50: | C27: =VLOOKUP(C25,'5a)NDA MPPR'!$B$9:$AK$61,21,FALSE) -> 749.16803 | F27: Lifecycle P50: | G27: =VLOOKUP(G25,'5a)NDA MPPR'!$B$9:$AK$61,21,FALSE) -> 71.079063 | K27: Lifecycle P50: | L27: =VLOOKUP(L25,'5a)NDA MPPR'!$B$9:$AK$61,21,FALSE) -> 53.218374 | R27: Lifecycle P50: | S27: =VLOOKUP(S25,'4b) SL EPO Extended Data Sheet'!$A$5:$AB$176,17,FALSE)/1000000 -> 101.98066 | Y27: Special Nuclear Materials (SNM) | AG27: Proj No: | AH27: 35/10475
Y28: Director / Lead: P. Nichol | AB28: Lifecycle Value: | AD28: =Z35+Z42 -> 122.47097 | AG28: Programme: | AH28: Land and Infrastructure Future State
B29: Proj No: | C29: 35/09203 | F29: Proj No: | G29: 35/09976 | K29: Proj No: | L29: 35/10398 | R29: Proj No: | S29: 35/10242 | AG29: Title: | AH29: Product Zone Power Supply
B30: Programme: | C30: Decommissioning Higher Active Waste Capability (DHAWC) | F30: Programme: | G30: Unified Command & Control | K30: Programme: | L30: *1 - Final Decommissioning | R30: Programme: | S30: Pile Fuel Cladding Silo | AG30: SRO | AH30: Gavin Askew
B31: Title: | C31: Lightly Shielded Store (LSS) | F31: Title: | G31: Enhanced CNC Airwave System (Encrypted Comms) | K31: Title: | L31: Calder Land Clearance | R31: Title: | S31: PFCS Full Retrievals - Project 1 | Y31: Proj No: | Z31: 35/09244 | AG31: Lifecycle P50: | AH31: =VLOOKUP(AH29,'4b) SL EPO Extended Data Sheet'!$A$5:$AB$176,17,FALSE)/1000000 -> 82.916699
B32: SRO | C32: Kathryn McCloghrie | F32: SPA | G32: Michael Askew | K32: SPA | L32: Jeremy Hunt | R32: SPA | S32: Kevin Brown | Y32: Programme: | Z32: SNM Future State
B33: Lifecycle P50: | C33: =VLOOKUP(C31,'4b) SL EPO Extended Data Sheet'!$A$5:$AB$176,17,FALSE)/1000000 -> 157.94101 | F33: Lifecycle P50: | G33: =VLOOKUP(G31,'5a)NDA MPPR'!$B$9:$AK$61,21,FALSE) -> 18.769073 | K33: Lifecycle P50: | L33: =VLOOKUP(L31,'4b) SL EPO Extended Data Sheet'!$A$5:$AB$176,17,FALSE)/1000000 -> 38.416249 | R33: Lifecycle P50: | S33: =VLOOKUP(S31,'5a)NDA MPPR'!$B$9:$AK$61,21,FALSE) -> 72.459952 | Y33: Title: | Z33: FGFL Ventilation Extract System Upgrade
F34: N.B. Project paused | K34: N.B *1 - Final Decommissioning OU is not a programme in the new construct | Y34: SPA | Z34: Simon Bremer | AG34: Proj No: | AH34: 35/10545
B35: Proj No: | C35: 35/10371 | R35: Proj No: | S35: 35/09198 | Y35: Lifecycle P50: | Z35: =VLOOKUP(Z33,'4b) SL EPO Extended Data Sheet'!$A$5:$AB$176,17,FALSE)/1000000 -> 84.193985 | AG35: Programme: | AH35: No Programme
B36: Programme: | C36: First Generation Magnox Storage Pond | R36: Programme: | S36: Pile Fuel Cladding Silo | AG36: Title: | AH36: Degradation of Pipebridge 57 (PB57) L14, L15, L16 Refurbishment
B37: Title: | C37: Sludge Handling & Export Plant | R37: Title: | S37: Sellafield 3m3 Box Supply - Tranche A | AG37: SPA | AH37: Stuart Latham
B38: SPA | C38: Carl Carruthers | R38: SPA | S38: Kevin Brown | Y38: Proj No: | Z38: 35/09357 | AG38: Lifecycle P50: | AH38: =VLOOKUP(AH36,'4b) SL EPO Extended Data Sheet'!$A$5:$AB$176,17,FALSE)/1000000 -> 31.203278
B39: Lifecycle P50: | C39: =VLOOKUP(C37,'4b) SL EPO Extended Data Sheet'!$A$5:$AB$176,17,FALSE)/1000000 -> 341.04335 | R39: Lifecycle P50: | S39: =VLOOKUP(S37,'4b) SL EPO Extended Data Sheet'!$A$5:$AB$176,17,FALSE)/1000000 -> 36.17178 | Y39: Programme: | Z39: SNM Future State | AG39: Utilites | AO39: Principle Project Commercial Delivery Framework Key
Y40: Title: | Z40: PMF North Transfers Project
B41: Proj No: | C41: 35/10417 | R41: Proj No: | S41: 35/10342 | Y41: SRO SPA | Z41: Jeremy Hunt Paul Nichol | AG41: Proj No: | AH41: 35/09248 | AQ41: Programme and Project Partners (PPP)
B42: Programme: | C42: Land and Infrastructure Future State | R42: Programme: | S42: Magnox Swarf Storage Silos | Y42: Lifecycle P50: | Z42: =VLOOKUP(Z40,'4b) SL EPO Extended Data Sheet'!$A$5:$AB$176,17,FALSE)/1000000 -> 38.276981 | AG42: Programme: | AH42: Utilities and Future Energy
B43: Title: | C43: ILW East Land Excavation | R43: Title: | S43: MSSS SEP3 Rails & Brackets | AG43: Title: | AH43: Substations 6 & 7 Replacement | AQ43: Legacy Bespoke Contracts (ie. BEP JV)
B44: SPA | C44: Gavin Askew | R44: SPA | S44: Phil Reeve | AG44: SRO | AH44: Gavin Askew
B45: Lifecycle P50: | C45: =VLOOKUP(C43,'5a)NDA MPPR'!$B$9:$AK$61,21,FALSE) -> 35.500379 | R45: Lifecycle P50: | S45: =VLOOKUP(S43,'4b) SL EPO Extended Data Sheet'!$A$5:$AB$176,17,FALSE)/1000000 -> 20.468821 | Y45: Spent Fuel Management (SFM) | AG45: Lifecycle P50: | AH45: =VLOOKUP(AH43,'4b) SL EPO Extended Data Sheet'!$A$5:$AB$176,17,FALSE)/1000000 -> 58.647951 | AQ45: Decommissioning Delivery Partner (DDP)
Y46: Director / Lead: S. Pearson | AB46: Lifecycle Value: | AD46: =Z52 -> 159.01226
B47: Proj No: | C47: 35/10505 | R47: Proj No: | S47: 35/10274 | AQ47: Design Services Alliance (DSA)
B48: Programme: | C48: SIXEP Capability | R48: Programme: | S48: Magnox Swarf Storage Silos | Y48: Proj No: | Z48: 35/10192 | AG48: Proj No: | AH48: 35/10563
B49: Title: | C49: SIXEP Receipt Facility | R49: Title: | S49: MSSS Electrical Distribution Upgrade for Retrievals | Y49: Programme: | Z49: AGROP | AG49: Programme: | AH49: Utilities and Future Energy | AQ49: Infrastructure Services Alliance (ISA)
B50: SRO | C50: Jeremy Hunt | R50: SPA | S50: Phil Reeve | Y50: Title: | Z50: TR&S Replacement Cooling System | AG50: Title: | AH50: Substation 10 Replacement
B51: Lifecycle P50: | C51: =VLOOKUP(C49,'4b) SL EPO Extended Data Sheet'!$A$5:$AB$176,17,FALSE)/1000000 -> 920.05646 | R51: Lifecycle P50: | S51: =VLOOKUP(S49,'4b) SL EPO Extended Data Sheet'!$A$5:$AB$176,17,FALSE)/1000000 -> 28.070365 | Y51: SPA | Z51: Steve Wordsworth | AG51: SRO | AH51: Gavin Askew
B52: N.B. Project known as SWMRF | Y52: Lifecycle P50: | Z52: =VLOOKUP(Z50,'4b) SL EPO Extended Data Sheet'!$A$5:$AB$176,17,FALSE)/1000000 -> 159.01226 | AG52: Lifecycle P50: | AH52: =VLOOKUP(AH50,'4b) SL EPO Extended Data Sheet'!$A$5:$AB$176,17,FALSE)/1000000 -> 42.41638
B53: Proj No: | C53: TBC
B54: Programme: | C54: SNM Future State
B55: Title: | C55: SNM Future Stores | K55: ISO | AG55: Proj No: | AH55: 35/10564
B56: Lifecycle P50: | C56: TBC | K56: Director / Lead: G. Slater | N56: Lifecycle Value: | P56: =L64+L77 -> 26.901908 | AG56: Programme: | AH56: Utilities and Future Energy
F57: Future PPP Pipeline Projects currently in Study Phase and not currently reflected as a gated project | K57: PC Lead: J Beetham | AG57: Title: | AH57: Substation 15 Replacement
B58: Proj No: | C58: 35/10489 | AG58: SRO | AH58: Gavin Askew
B59: Programme: | C59: No Programme | AG59: Lifecycle P50: | AH59: =VLOOKUP(AH57,'4b) SL EPO Extended Data Sheet'!$A$5:$AB$176,17,FALSE)/1000000 -> 42.264072
B60: Title: | C60: Common Data Environment (CDE) | K60: Proj No: | L60: 35/10351
B61: Lifecycle P50: | C61: TBC | K61: Programme: | L61: No Programme
K62: Title: | L62: Data Centre Replacement Project
B63: Proj No: | C63: TBC | K63: SPA | L63: Dominic Fitzsimmons
B64: Programme: | C64: Analytical Services | K64: Lifecycle P50: | L64: =VLOOKUP(L62,'4b) SL EPO Extended Data Sheet'!$A$5:$AB$176,17,FALSE)/1000000 -> 26.901908
B65: Title: | C65: RAP Option Selection
B66: Lifecycle P50: | C66: TBC

Sheet 0) SL Project Structure OLD
A1: SL Project Services Functional Strategy Project Landscape Map (Coded by Principle Current Commercial Delivery Framework) (Projects with Lifecycle Forecast over £20M)
A2: Total Lifetime EAC Value of SL Projects over £20M = | G2: =I5+P5+W5+AH5+P53 -> #N/A
D4: Project Delivery Directorate (PDD) | K4: Remediation | R4: Retrievals | AC4: Site Management Projects (SMPro)
D5: Director / Lead: A. Sharples | G5: Lifecycle Value: | I5: =C14+C19+C24+C29+C34+C39+C44+C49+G14+G19+G24+G29 -> #N/A | K5: Director / Lead: G. McCracken | N5: Lifecycle Value: | P5: =L14+L19+L24+L29+L34+L39 -> #N/A | R5: Director / Lead: A. Armett | U5: Lifecycle Value: | W5: =S14+S19+S24+S29+S34+S39+S44+S49 -> #N/A | AC5: Director / Lead: M. Johns | AF5: Lifecycle Value: | AH5: =AD9+AD47+AD60+AL9 -> #N/A
D6: PC Lead: Lee Edgar & SPCMs | K6: PC Lead: A Grainger | R6: PC Lead: J Kolbe | AC6: PC Lead: J Irving
Y8: Site Management | AG8: Infrastructure
D9: PPP | H9: Legacy | Y9: Director / Lead: J. Brocklebank | AB9: Lifecycle Value: | AD9: =Z14+Z19+Z24+Z29+Z34+Z39+Z44 -> 676.02499 | AG9: Director / Lead: C. Mills | AJ9: Lifecycle Value: | AL9: =AH16+AH22+AH28 -> #N/A
R10: N.B. Project very close to completion | AG10: PC Lead: S Jackson
B11: Proj No: | C11: 35/09592 | F11: Proj No: | G11: 35/10137 | K11: Proj No: | L11: 35/05396 | R11: Proj No: | S11: 35/10095 | Y11: Proj No: | Z11: 35/09140
B12: Title: | C12: Sellafield Product & Residue Store Retreatment Plant | F12: Title: | G12: Box Encapsulation Plant | K12: Title: | L12: Chimney Decommissioning Phase 2F | R12: Title: | S12: Box Encapsulation Plant Product Store Direct Import Facility | Y12: Title: | Z12: Electrical Supply - New Construction | AG12: Infrastructure
B13: SRO | C13: Jeremy Hunt | F13: SPA | G13: Phil Reeve | K13: SPA | L13: Glenn McCracken | R13: SPA | S13: Kevin Brown | Y13: SRO | Z13: Gavin Askew | AG13: Proj No: | AH13: 35/10565
B14: Lifecycle P50: | C14: =VLOOKUP(C12,'5a)NDA MPPR'!$B$9:$AK$61,21,FALSE) -> 1466.5527 | F14: Lifecycle P50: | G14: =VLOOKUP(G12,'5a)NDA MPPR'!$B$9:$AK$61,21,FALSE) -> 1445.0751 | K14: Lifecycle P50: | L14: =VLOOKUP(L12,'5a)NDA MPPR'!$B$9:$AK$61,21,FALSE) -> 148.90141 | R14: Lifecycle P50: | S14: =VLOOKUP(S12,'5a)NDA MPPR'!$B$9:$AK$61,21,FALSE) -> 458.24396 | Y14: Lifecycle P50: | Z14: =VLOOKUP(Z12,'5a)NDA MPPR'!$B$9:$AK$61,21,FALSE) -> 427.81347 | AG14: Title: | AH14: EMRMS (Emergency Management Radiological Monitoring System)
AG15: SPA | AH15: Rob Hargreaves
B16: Proj No: | C16: 35/09343 | F16: Proj No: | G16: 35/09975 | K16: Proj No: | L16: 35/09707 | R16: Proj No: | S16: 35/06075 | Y16: Proj No: | Z16: 35/10188 | AG16: Lifecycle P50: | AH16: =VLOOKUP(AH14,'4b) SL EPO Extended Data Sheet'!$A$5:$AB$176,16,FALSE)/1000000 -> 32.152519
B17: Title: | C17: SIXEP Continuity Plant | F17: Title: | G17: Security Systems Architecture Upgrade (SSAU) | K17: Title: | L17: LAETP Floc Retrieval | R17: Title: | S17: SEP Solid Waste Storage Retrievals | Y17: Title: | Z17: THORP Receipt & Storage Control Systems Replacement
B18: SRO | C18: Jeremy Hunt | F18: SPA | G18: Michael Askew | K18: SPA | L18: Glenn McCracken | R18: SPA | S18: Phil Reeve | Y18: SPA | Z18: Andrew Pringle | AG18: Utilites
B19: Lifecycle P50: | C19: =VLOOKUP(C17,'5a)NDA MPPR'!$B$9:$AK$61,21,FALSE) -> 1120.8757 | F19: Lifecycle P50: | G19: =VLOOKUP(G17,'5a)NDA MPPR'!$B$9:$AK$61,21,FALSE) -> 315.08361 | K19: Lifecycle P50: | L19: =VLOOKUP(L17,'5a)NDA MPPR'!$B$9:$AK$61,21,FALSE) -> 87.561965 | R19: Lifecycle P50: | S19: =VLOOKUP(S17,'5a)NDA MPPR'!$B$9:$AK$61,21,FALSE) -> 887.19569 | Y19: Lifecycle P50: | Z19: =VLOOKUP(Z17,'4b) SL EPO Extended Data Sheet'!$A$5:$AB$176,16,FALSE)/1000000 -> 20.914989 | AG19: Proj No: | AH19: 35/09248
AG20: Title: | AH20: Substations 6 & 7 Replacement
B21: Proj No: | C21: 35/09269 | F21: Proj No: | G21: 35/09968 | K21: Proj No: | L21: 35/09000 | R21: Proj No: | S21: 35/05684 | Y21: Proj No: | Z21: 35/10151 | AG21: SRO | AH21: Gavin Askew
B22: Title: | C22: Replacement Analytical Project | F22: Title: | G22: CNC Operational Unit | K22: Title: | L22: Heat Exchanger Deplanting - Main Project | R22: Title: | S22: MSSS Upgrades for Retrievals & Resilience | Y22: Title: | Z22: FHP & SIXEP Roof Replacement | AG22: Lifecycle P50: | AH22: =VLOOKUP(AH20,'4b) SL EPO Extended Data Sheet'!$A$5:$AB$176,16,FALSE)/1000000 -> 64.421715
B23: SRO | C23: Gavin Askew | F23: SPA | G23: Michael Askew | K23: SPA | L23: Glenn McCracken | R23: SPA | S23: Phil Reeve | Y23: SPA | Z23: Stuart Pearson
B24: Lifecycle P50: | C24: =VLOOKUP(C22,'5a)NDA MPPR'!$B$9:$AK$61,21,FALSE) -> #N/A | F24: Lifecycle P50: | G24: =VLOOKUP(G22,'5a)NDA MPPR'!$B$9:$AK$61,21,FALSE) -> 71.079063 | K24: Lifecycle P50: | L24: =VLOOKUP(L22,'5a)NDA MPPR'!$B$9:$AK$61,21,FALSE) -> 53.218374 | R24: Lifecycle P50: | S24: =VLOOKUP(S22,'4b) SL EPO Extended Data Sheet'!$A$5:$AB$176,16,FALSE)/1000000 -> 103.81815 | Y24: Lifecycle P50: | Z24: =VLOOKUP(Z22,'4b) SL EPO Extended Data Sheet'!$A$5:$AB$176,16,FALSE)/1000000 -> 26.545167 | AG24: Analytical Services
B25: N.B. Project paused | AG25: Proj No: | AH25: 35/10523
B26: Proj No: | C26: 35/07654 | F26: Proj No: | G26: 35/09976 | K26: Proj No: | L26: 35/10398 | R26: Proj No: | S26: 35/10242 | Y26: Proj No: | Z26: 35/10475 | AG26: Title: | AH26: Sample Management Capability
B27: Title: | C27: BEPPS2 | F27: Title: | G27: Enhanced CNC Airwave System (Encrypted Comms) | K27: Title: | L27: Calder Land Clearance | R27: Title: | S27: PFCS Full Retrievals - Project 1 | Y27: Title: | Z27: Product Zone Power Supply | AG27: SRO | AH27: Gavin Askew
B28: SRO | C28: Kathryn McCloghrie | F28: SPA | G28: Michael Askew | K28: SPA | L28: Jeremy Hunt | R28: SPA | S28: Kevin Brown | Y28: SRO | Z28: Gavin Askew | AG28: Lifecycle P50: | AH28: =VLOOKUP(AH26,'4b) SL EPO Extended Data Sheet'!$A$5:$AB$176,16,FALSE)/1000000 -> #N/A
B29: Lifecycle P50: | C29: =VLOOKUP(C27,'5a)NDA MPPR'!$B$9:$AK$61,21,FALSE) -> 749.16803 | F29: Lifecycle P50: | G29: =VLOOKUP(G27,'5a)NDA MPPR'!$B$9:$AK$61,21,FALSE) -> 18.769073 | K29: Lifecycle P50: | L29: =VLOOKUP(L27,'4b) SL EPO Extended Data Sheet'!$A$5:$AB$176,16,FALSE)/1000000 -> 38.593832 | R29: Lifecycle P50: | S29: =VLOOKUP(S27,'5a)NDA MPPR'!$B$9:$AK$61,21,FALSE) -> 72.459952 | Y29: Lifecycle P50: | Z29: =VLOOKUP(Z27,'4b) SL EPO Extended Data Sheet'!$A$5:$AB$176,16,FALSE)/1000000 -> 84.328299
F30: N.B. Project paused
B31: Proj No: | C31: 35/09203 | K31: Proj No: | L31: 35/10401 | R31: Proj No: | S31: 35/09198 | Y31: Proj No: | Z31: 35/10545 | AG31: Principle Project Commercial Delivery Framework Key
B32: Title: | C32: Lightly Shielded Store (LSS) | K32: Title: | L32: Decommissioning Encapsulation Plant | R32: Title: | S32: Sellafield 3m3 Box Supply - Tranche A | Y32: Title: | Z32: Degradation of Pipebridge 57 (PB57) L14, L15, L16 Refurbishment
B33: SRO | C33: Kathryn McCloghrie | K33: SRO | L33: Kathryn McCloghrie | R33: SPA | S33: Kevin Brown | Y33: SPA | Z33: Stuart Latham | AH33: Programme and Project Partners (PPP)
B34: Lifecycle P50: | C34: =VLOOKUP(C32,'4b) SL EPO Extended Data Sheet'!$A$5:$AB$176,16,FALSE)/1000000 -> 142.42994 | K34: Lifecycle P50: | L34: =VLOOKUP(L32,'4b) SL EPO Extended Data Sheet'!$A$5:$AB$176,16,FALSE)/1000000 -> #N/A | R34: Lifecycle P50: | S34: =VLOOKUP(S32,'4b) SL EPO Extended Data Sheet'!$A$5:$AB$176,16,FALSE)/1000000 -> 74.471369 | Y34: Lifecycle P50: | Z34: =VLOOKUP(Z32,'4b) SL EPO Extended Data Sheet'!$A$5:$AB$176,16,FALSE)/1000000 -> 30.826939
AH35: Legacy Bespoke Contracts (ie. BEP JV)
B36: Proj No: | C36: 35/10371 | K36: Proj No: | L36: 35/10402 | R36: Proj No: | S36: 35/10128 | Y36: Proj No: | Z36: 35/10563
B37: Title: | C37: Sludge Handling & Export Plant | K37: Title: | L37: Remote Handlable Intermediate Level Waste (RHILW) | R37: Title: | S37: Self Shielded Boxes Design and Manufacture | Y37: Title: | Z37: Substation 10 Replacement | AH37: Decommissioning Delivery Partner (DDP)
B38: SPA | C38: Carl Carruthers | K38: SRO | L38: Kathryn McCloghrie | R38: SPA | S38: Carl Carruthers | Y38: SRO | Z38: Gavin Askew
B39: Lifecycle P50: | C39: =VLOOKUP(C37,'4b) SL EPO Extended Data Sheet'!$A$5:$AB$176,16,FALSE)/1000000 -> 340 | K39: Lifecycle P50: | L39: =VLOOKUP(L37,'4b) SL EPO Extended Data Sheet'!$A$5:$AB$176,16,FALSE)/1000000 -> #N/A | R39: Lifecycle P50: | S39: =VLOOKUP(S37,'4b) SL EPO Extended Data Sheet'!$A$5:$AB$176,16,FALSE)/1000000 -> #N/A | Y39: Lifecycle P50: | Z39: =VLOOKUP(Z37,'4b) SL EPO Extended Data Sheet'!$A$5:$AB$176,16,FALSE)/1000000 -> 42.841254 | AH39: Design Services Alliance (DSA)
B41: Proj No: | C41: 35/10417 | R41: Proj No: | S41: 35/10342 | Y41: Proj No: | Z41: 35/10564 | AH41: Infrastructure Services Alliance (ISA)
B42: Title: | C42: ILW East Land Excavation | R42: Title: | S42: MSSS SEP3 Rails & Brackets | Y42: Title: | Z42: Substation 15 Replacement
B43: SPA | C43: Gavin Askew | R43: SPA | S43: Phil Reeve | Y43: SRO | Z43: Gavin Askew
B44: Lifecycle P50: | C44: =VLOOKUP(C42,'5a)NDA MPPR'!$B$9:$AK$61,21,FALSE) -> 35.500379 | R44: Lifecycle P50: | S44: =VLOOKUP(S42,'4b) SL EPO Extended Data Sheet'!$A$5:$AB$176,16,FALSE)/1000000 -> 19.192466 | Y44: Lifecycle P50: | Z44: =VLOOKUP(Z42,'4b) SL EPO Extended Data Sheet'!$A$5:$AB$176,16,FALSE)/1000000 -> 42.754873
B46: Proj No: | C46: 35/10505 | R46: Proj No: | S46: 35/10274 | Y46: Special Nuclear Materials (SNM)
B47: Title: | C47: SIXEP Receipt Facility | R47: Title: | S47: MSSS Electrical Distribution Upgrade for Retrievals | Y47: Director / Lead: P. Nichol | AB47: Lifecycle Value: | AD47: =Z52+Z57 -> 102.14704
B48: SRO | C48: Jeremy Hunt | R48: SPA | S48: Phil Reeve
B49: Lifecycle P50: | C49: =VLOOKUP(C47,'4b) SL EPO Extended Data Sheet'!$A$5:$AB$176,16,FALSE)/1000000 -> 919.61826 | R49: Lifecycle P50: | S49: =VLOOKUP(S47,'4b) SL EPO Extended Data Sheet'!$A$5:$AB$176,16,FALSE)/1000000 -> 18.788383 | Y49: Proj No: | Z49: 35/09244
B50: N.B. Project known as SWMRF | Y50: Title: | Z50: FGFL Ventilation Extract System Upgrade
B51: Proj No: | C51: TBC | Y51: SPA | Z51: Simon Bremer
B52: Title: | C52: SNM Future Stores | K52: ISO | Y52: Lifecycle P50: | Z52: =VLOOKUP(Z50,'4b) SL EPO Extended Data Sheet'!$A$5:$AB$176,16,FALSE)/1000000 -> 66.045682
B53: Lifecycle P50: | C53: TBC | K53: Director / Lead: G. Slater | N53: Lifecycle Value: | P53: =L59+L64 -> #N/A
F54: Future PPP Pipeline Projects currently in Study Phase and not currently reflected as a gated project | K54: PC Lead: J Beetham / D Burns | Y54: Proj No: | Z54: 35/09357
B55: Proj No: | C55: 35/10489 | Y55: Title: | Z55: PMF North Transfers Project
B56: Title: | C56: Commoc Data Environment (CDE) | K56: Proj No: | L56: 35/10478 | Y56: SRO SPA | Z56: Jeremy Hunt Paul Nichol
B57: Lifecycle P50: | C57: TBC | K57: Title: | L57: ASC Exit (PICTS) | Y57: Lifecycle P50: | Z57: =VLOOKUP(Z55,'4b) SL EPO Extended Data Sheet'!$A$5:$AB$176,16,FALSE)/1000000 -> 36.101355
K58: SPA | L58: Graeme Slater
B59: Proj No: | C59: TBC | K59: Lifecycle P50: | L59: =VLOOKUP(L57,'4b) SL EPO Extended Data Sheet'!$A$5:$AB$176,16,FALSE)/1000000 -> #N/A | Y59: Spent Fual Management (SFM)
B60: Title: | C60: RAP Option Selection | Y60: Director / Lead: S. Pearson | AB60: Lifecycle Value: | AD60: =Z65 -> 155.65567
B61: Lifecycle P50: | C61: TBC | K61: Proj No: | L61: 35/10351
K62: Title: | L62: Data Centre Replacement Project | Y62: Proj No: | Z62: 35/10192
K63: SPA | L63: Dominic Fitzsimmons | Y63: Title: | Z63: TR&S Replacement Cooling System
K64: Lifecycle P50: | L64: =VLOOKUP(L62,'4b) SL EPO Extended Data Sheet'!$A$5:$AB$176,16,FALSE)/1000000 -> 31.971082 | Y64: SPA | Z64: Steve Wordsworth
Y65: Lifecycle P50: | Z65: =VLOOKUP(Z63,'4b) SL EPO Extended Data Sheet'!$A$5:$AB$176,16,FALSE)/1000000 -> 155.65567

Sheet 1) Report
B3: Project Number | C3: Project Name | D3: Occom | F3: Approved Business Case and Sanction | R3: Baseline | AM3: Capability and Capacity | AO3: DCA Comparison | AS3: Baseline RAG Comparison | AV3: Previous Period Data for Variance Calcs | AY3: Changes to Current Baseline (P50)
F4: Delivery Confidence Assessment (DCA) | I4: Approved Business Case | O4: Sanction | R4: Baseline RAG | U4: Current Baseline in Effect From | W4: Whole Life | AE4: Cumulative vs. Current Baseline
I5: Business Case Approval Date | J5: Project Cost | L5: Project End Date | O5: Sanction Approved to NDA | P5: Sanction Released to OpCo | W5: Project Cost | AA5: Project End Date | AE5: Budgeted Cost Work Scheduled (BCWS) | AF5: Budgeted Cost Work Performed (BCWP) | AG5: Actual Cost Work Performed (ACWP) | AH5: Cost Perf. Index (CPI) | AI5: Schedule Perf. Index (SPI) | AJ5: % Complete | AO5: EAC vs. Approved BC WLC (P80) | AP5: EAC vs. Sanction Approved to NDA (P80) | AQ5: Forecast End Date vs. Approved BC (P80) | AS5: EAC vs. Current Baseline (P50) | AT5: Forecast End Date vs. Current Baseline (P50) | AV5: Cost | AW5: End Date | AY5: Project Cost | BA5: Project End Date
J6: Business Case (P50) | K6: Business Case (P80) | L6: Business Case (P50) | M6: Business Case (P80) | W6: Current Baseline (P50) | X6: Estimate At Complete (EAC) | Y6: EAC vs. Last Period | AA6: Current Baseline (P50) | AB6: Forecast | AC6: Forecast vs. Last Period (Days) | AJ6: Plan | AK6: Actual | AV6: EAC Last Period | AW6: Forecast Last Period | AY6: Baseline (P50) Last Period | AZ6: Change to Baseline (P50) | BA6: Baseline (P50) Last Period | BB6: Change to Baseline (P50)
B8: Security & Resilience
B10: Portfolio Summary
B11: n/a | C11: Sellafield Security Enhancement Programme (SSEP) | D11: Sellafield | F11: =VLOOKUP(C11,'5a)NDA MPPR'!$B$9:$AK$61,3,FALSE) -> G | G11: =VLOOKUP(C11,'5a)NDA MPPR'!$B$9:$AK$61,4,FALSE) -> 0 | I11: =VLOOKUP(C11,'5a)NDA MPPR'!$B$9:$AK$61,6,FALSE) -> PBC (Jun-24) | J11: =VLOOKUP(C11,'5a)NDA MPPR'!$B$9:$AK$61,7,FALSE) -> 904 | K11: =VLOOKUP(C11,'5a)NDA MPPR'!$B$9:$AK$61,8,FALSE) -> 921.8 | L11: =VLOOKUP(C11,'5a)NDA MPPR'!$B$9:$AK$61,9,FALSE) -> 46022 | M11: =VLOOKUP(C11,'5a)NDA MPPR'!$B$9:$AK$61,10,FALSE) -> 46234 | O11: =VLOOKUP(C11,'5a)NDA MPPR'!$B$9:$AK$61,12,FALSE) -> 921.8 | P11: =VLOOKUP(C11,'5a)NDA MPPR'!$B$9:$AK$61,13,FALSE) -> 921.8 | R11: =VLOOKUP(C11,'5a)NDA MPPR'!$B$9:$AK$61,15,FALSE) -> N/A | S11: =VLOOKUP(C11,'5a)NDA MPPR'!$B$9:$AK$61,16,FALSE) -> 0 | U11: =VLOOKUP(C11,'5a)NDA MPPR'!$B$9:$AK$61,18,FALSE) -> PBC (Oct-21) | W11: =VLOOKUP(C11,'5a)NDA MPPR'!$B$9:$AK$61,20,FALSE) -> - | X11: =VLOOKUP(C11,'5a)NDA MPPR'!$B$9:$AK$61,21,FALSE) -> 914.56678 | Y11: =VLOOKUP(C11,'5a)NDA MPPR'!$B$9:$AK$61,22,FALSE) -> -6.9 | AA11: =VLOOKUP(C11,'5a)NDA MPPR'!$B$9:$AK$61,24,FALSE) -> - | AB11: =VLOOKUP(C11,'5a)NDA MPPR'!$B$9:$AK$61,25,FALSE) -> 46234 | AC11: =VLOOKUP(C11,'5a)NDA MPPR'!$B$9:$AK$61,26,FALSE) -> 0 | AE11: =VLOOKUP(C11,'5a)NDA MPPR'!$B$9:$AK$61,28,FALSE) -> 0 | AF11: =VLOOKUP(C11,'5a)NDA MPPR'!$B$9:$AK$61,29,FALSE) -> 0 | AG11: =VLOOKUP(C11,'5a)NDA MPPR'!$B$9:$AK$61,30,FALSE) -> 909.09983 | AH11: =VLOOKUP(C11,'5a)NDA MPPR'!$B$9:$AK$61,31,FALSE) -> 0 | AI11: =VLOOKUP(C11,'5a)NDA MPPR'!$B$9:$AK$61,32,FALSE) -> 0 | AJ11: =VLOOKUP(C11,'5a)NDA MPPR'!$B$9:$AK$61,33,FALSE) -> 0 | AK11: =VLOOKUP(C11,'5a)NDA MPPR'!$B$9:$AK$61,34,FALSE) -> 0 | AM11: =VLOOKUP(C11,'5a)NDA MPPR'!$B$9:$AK$61,36,FALSE) -> N/A | AV11: 921.42523 | AW11: 46234 | AY11: 0 | BA11: -
A12: =C11 -> Sellafield Security Enhancement Programme (SSEP) | B12: =VLOOKUP($C11,'5a)NDA MPPR'!$A$9:$AK$61,2,FALSE) -> The Sellafield Security Enhancement Programme (SSEP) represents a series of interdependent security enhancement projects, which encompass site-wide improvement initiatives, and some facility-specific asset improvements. The Delivery Confidence Assessment remains Green. The NDA revised Programme Business Case value of £921.8m was released to SL in June 2024, with Department for Energy Security and Net Zero (DESNZ) PIC holding the upper range figure of £929.8m. The SSAU and CNC OU P80 sanction request submissions were approved at the NDA Group Investment Committee (GIC) in September 2024. The assessment work on Encrypted Comms project is complete resulting in a significant reduction in the project scope. The project EAC has therefore been reduced accordingly. Formal governance steps will conclude during period 8. The programme lifecycle EAC has therefore been reduced to reflect the EC position. The Programme Ready for FOC, based on the latest SSAU project data, remains forecast as March 2026 due to delays to the progression of the Legacy SMS migrations, which are scheduled to take place after the L1 commissioning of the new boundaries.. This is subject to ongoing reviews of the available operational, engineering and maintenance resources needed to review and sign off the various systems and assets being delivered by the projects to underpin the Custody Transfer Certificate (CTC). The overall outturn project delivery performance remains in line with sanctioned plans. Security Systems Architecture Upgrade (SSAU), Encrypted Comms (EC) & Civil Nuclear Constabulary (CNC) Operational Unit (CNC OU) Projects (all reported as projects in their own right on the MPPR) are, based on the respective projects latest EAC figures, affordable within the released SSEP sanction. The Main Site Command Facility (MSCF) continues to improve its operational capability with Phases 1 & 2 of the revised 3 Phase Capability Delivery Plan now complete. (Phase 1: The High Security Area (HSA)1 Boundary declared operational in March 2024 & Phase 2: The achievement of a Green rating for the complex and challenging Level 1 Regulator Evaluated Demonstration Exercise in November 2024). As a consequence the Regulator confirmed in December 2024, Physical Security no longer needs to be monitored at the “Enhanced Level” and has therefore been returned to “Routine Level” with the Nuclear Site Security Plan (NSSP) and Security Improvement Schedule (SIS) updated accordingly; a significant achievement for the Sellafield Site. Phase 3 will achieve the agreed security outcomes and associated security risk reduction benefits by no later than May 2027 for Full Operating Capability (FOC). The latest programme forecast aligns with the current CNC OU P80 sanction date of 31 July 2026. The programme remains within its sanctioned tolerances.
B14: Project Delivery Directorate
B16: Portfolio Summary
B17: 35/09976 | C17: Enhanced CNC Airwave System (Encrypted Comms) | D17: Sellafield | F17: =VLOOKUP(C17,'5a)NDA MPPR'!$B$9:$AK$61,3,FALSE) -> R | G17: =VLOOKUP(C17,'5a)NDA MPPR'!$B$9:$AK$61,4,FALSE) -> 0 | I17: =VLOOKUP(C17,'5a)NDA MPPR'!$B$9:$AK$61,6,FALSE) -> OBC (Mar-20) | J17: =VLOOKUP(C17,'5a)NDA MPPR'!$B$9:$AK$61,7,FALSE) -> 25.838 | K17: =VLOOKUP(C17,'5a)NDA MPPR'!$B$9:$AK$61,8,FALSE) -> 31.94 | L17: =VLOOKUP(C17,'5a)NDA MPPR'!$B$9:$AK$61,9,FALSE) -> 45058 | M17: =VLOOKUP(C17,'5a)NDA MPPR'!$B$9:$AK$61,10,FALSE) -> 45412 | N17: ='3) BC and Sanction'!I94 -> 0 | O17: =VLOOKUP(C17,'5a)NDA MPPR'!$B$9:$AK$61,12,FALSE) -> 31.9 | P17: =VLOOKUP(C17,'5a)NDA MPPR'!$B$9:$AK$61,13,FALSE) -> 25.8 | R17: =VLOOKUP(C17,'5a)NDA MPPR'!$B$9:$AK$61,15,FALSE) -> R | S17: =VLOOKUP(C17,'5a)NDA MPPR'!$B$9:$AK$61,16,FALSE) -> 0 | U17: =VLOOKUP(C17,'5a)NDA MPPR'!$B$9:$AK$61,18,FALSE) -> OBC (Mar-25) | W17: =VLOOKUP(C17,'5a)NDA MPPR'!$B$9:$AK$61,20,FALSE) -> 25.979194 | X17: =VLOOKUP(C17,'5a)NDA MPPR'!$B$9:$AK$61,21,FALSE) -> 18.769073 | Y17: =VLOOKUP(C17,'5a)NDA MPPR'!$B$9:$AK$61,22,FALSE) -> -7 | AA17: =VLOOKUP(C17,'5a)NDA MPPR'!$B$9:$AK$61,24,FALSE) -> 45058 | AB17: =VLOOKUP(C17,'5a)NDA MPPR'!$B$9:$AK$61,25,FALSE) -> 46175 | AC17: =VLOOKUP(C17,'5a)NDA MPPR'!$B$9:$AK$61,26,FALSE) -> 0 | AE17: =VLOOKUP(C17,'5a)NDA MPPR'!$B$9:$AK$61,28,FALSE) -> 19.634303 | AF17: =VLOOKUP(C17,'5a)NDA MPPR'!$B$9:$AK$61,29,FALSE) -> 19.634303 | AG17: =VLOOKUP(C17,'5a)NDA MPPR'!$B$9:$AK$61,30,FALSE) -> 16.969073 | AH17: =VLOOKUP(C17,'5a)NDA MPPR'!$B$9:$AK$61,31,FALSE) -> 1.1570639 | AI17: =VLOOKUP(C17,'5a)NDA MPPR'!$B$9:$AK$61,32,FALSE) -> 1 | AJ17: =VLOOKUP(C17,'5a)NDA MPPR'!$B$9:$AK$61,33,FALSE) -> 0.75577028 | AK17: =VLOOKUP(C17,'5a)NDA MPPR'!$B$9:$AK$61,34,FALSE) -> 0.75577029 | AM17: =VLOOKUP(C17,'5a)NDA MPPR'!$B$9:$AK$61,36,FALSE) -> G | AO17: =#REF!-#REF! -> #REF! | AP17: =#REF!-#REF! -> #REF! | AQ17: =#REF!-#REF! -> #REF! | AS17: =#REF!-#REF! -> #REF! | AT17: =#REF!-#REF! -> #REF! | AV17: 25.769102 | AW17: 46175 | AY17: 25.979194 | AZ17: =W17-AY17 -> 0 | BA17: 45058 | BB17: =AA17-BA17 -> 0
A18: =C17 -> Enhanced CNC Airwave System (Encrypted Comms) | B18: =VLOOKUP($C17,'5a)NDA MPPR'!$A$9:$AK$61,2,FALSE) -> The Encrypted Communications (EC) project will deliver the ability for the Civil Nuclear Constabulary (CNC), and other emergency responders utilising current Airwave and/or future Emergency Services Network, to clearly communicate with their Command and Control, both during routine patrols and in emergency response, within a number of identified facilities. The Delivery Confidence Assessment remains Red, since the forecast end date is outside of the Business Case P80 date due to the project currently being on hold pending a future scope delivery decision by the Security & Resilience Programme. The project has to date provided a proven technical infrastructure solution to two initial facilities (which will fully operationalise in late 2025). The decision timeline for further scope delivery has been linked to the production by S&R of Facility Security Plans and their associated Physical Security Vulnerability Assessments (PSVA), since this gives the most robust answer (for both the EC project and the PSVA process) in terms of need. The assessment work on Encrypted Comms project is now complete, resulting in a significant reduction in the project scope. The project EAC has therefore been reduced accordingly. Formal governance steps will conclude during Period 8. The Baseline status is Red, reflective of the current pause. The project has implemented a deferral change control reflecting the impact of the pause to the project; this is within SL delegation and went to the Group Investment Panel (GIC) for noting in late April. Capability and Capacity RAG is Green and it should be noted minimal resource is assigned as the project is on hold.
B20: 35/10137 | C20: Box Encapsulation Plant | D20: Sellafield | F20: =VLOOKUP(C20,'5a)NDA MPPR'!$B$9:$AK$61,3,FALSE) -> A | G20: =VLOOKUP(C20,'5a)NDA MPPR'!$B$9:$AK$61,4,FALSE) -> -1 | I20: =VLOOKUP(C20,'5a)NDA MPPR'!$B$9:$AK$61,6,FALSE) -> FBC (Jul-22) | J20: =VLOOKUP(C20,'5a)NDA MPPR'!$B$9:$AK$61,7,FALSE) -> 1316 | K20: =VLOOKUP(C20,'5a)NDA MPPR'!$B$9:$AK$61,8,FALSE) -> 1512 | L20: =VLOOKUP(C20,'5a)NDA MPPR'!$B$9:$AK$61,9,FALSE) -> 46332 | M20: =VLOOKUP(C20,'5a)NDA MPPR'!$B$9:$AK$61,10,FALSE) -> 46847 | N20: ='3) BC and Sanction'!I97 -> 0 | O20: =VLOOKUP(C20,'5a)NDA MPPR'!$B$9:$AK$61,12,FALSE) -> 1512 | P20: =VLOOKUP(C20,'5a)NDA MPPR'!$B$9:$AK$61,13,FALSE) -> 1389.2 | R20: =VLOOKUP(C20,'5a)NDA MPPR'!$B$9:$AK$61,15,FALSE) -> A | S20: =VLOOKUP(C20,'5a)NDA MPPR'!$B$9:$AK$61,16,FALSE) -> 0 | U20: =VLOOKUP(C20,'5a)NDA MPPR'!$B$9:$AK$61,18,FALSE) -> FBC Re. (Nov-24) | W20: =VLOOKUP(C20,'5a)NDA MPPR'!$B$9:$AK$61,20,FALSE) -> 1335.4604 | X20: =VLOOKUP(C20,'5a)NDA MPPR'!$B$9:$AK$61,21,FALSE) -> 1445.0751 | Y20: =VLOOKUP(C20,'5a)NDA MPPR'!$B$9:$AK$61,22,FALSE) -> 0 | AA20: =VLOOKUP(C20,'5a)NDA MPPR'!$B$9:$AK$61,24,FALSE) -> 46402 | AB20: =VLOOKUP(C20,'5a)NDA MPPR'!$B$9:$AK$61,25,FALSE) -> 46609 | AC20: =VLOOKUP(C20,'5a)NDA MPPR'!$B$9:$AK$61,26,FALSE) -> 0 | AE20: =VLOOKUP(C20,'5a)NDA MPPR'!$B$9:$AK$61,28,FALSE) -> 1268.0733 | AF20: =VLOOKUP(C20,'5a)NDA MPPR'!$B$9:$AK$61,29,FALSE) -> 1213.6179 | AG20: =VLOOKUP(C20,'5a)NDA MPPR'!$B$9:$AK$61,30,FALSE) -> 1338.8089 | AH20: =VLOOKUP(C20,'5a)NDA MPPR'!$B$9:$AK$61,31,FALSE) -> 0.90649081 | AI20: =VLOOKUP(C20,'5a)NDA MPPR'!$B$9:$AK$61,32,FALSE) -> 0.95705662 | AJ20: =VLOOKUP(C20,'5a)NDA MPPR'!$B$9:$AK$61,33,FALSE) -> 0.94954015 | AK20: =VLOOKUP(C20,'5a)NDA MPPR'!$B$9:$AK$61,34,FALSE) -> 0.90876368 | AM20: =VLOOKUP(C20,'5a)NDA MPPR'!$B$9:$AK$61,36,FALSE) -> G | AO20: =T27-G27 -> 0 | AP20: =T27-K27 -> 0 | AQ20: =X27-I27 -> 0 | AS20: =T27-S27 -> 0 | AT20: =X27-W27 -> 0 | AV20: 1445.0751 | AW20: 46609 | AY20: 1335.4604 | AZ20: =W20-AY20 -> 0 | BA20: 46402 | BB20: =AA20-BA20 -> 0
A21: =C20 -> Box Encapsulation Plant | B21: =VLOOKUP($C20,'5a)NDA MPPR'!$A$9:$AK$61,2,FALSE) -> The BEP Project provides the Magnox Swarf Storage Silos (MSSS) Programme the capability to receive, package, inspect, and transfer Intermediate Level Waste to interim stores. At completion, BEP will enable waste retrieval at pace, to maintain an As Low as Reasonably Practicable (ALARP) position, a fundamental requirement of Sellafield Ltd site license conditions. The first project benefit: Regulatory approval to Start Active Commissioning is forecast 10th August 2027. Estimated date for first MSSS box into BEP and Active Commissioning of MSSS waste is November 2027, with benefits realisation associated with the start of Operations April 2028. Project Completion including governance is currently forecast as August 2028, within the period of ‘up to 12 months’ after the Start of Active Commissioning defined in the approved Resubmitted Business Case. The Delivery Confidence Assessment (DCA) has changed to Amber to recognise the Project challenges that are being managed, the Baseline RAG remains Amber. Lifetime EAC is beyond sanction P50 but within sanction P80 cost. The preparation of a P80 Drawdown is underway, targeting executive decisions by end of this calendar year. There is no change in period to the Start Active Commissioning forecast and lifecycle EAC. The project acknowledges pressure on the forecast P50 position following cost growth and schedule slippage in the deterministic Joint Venture (JV) EAC and programme from the impact of Fault Observations (FOBs) on critical path commissioning activities and on-going construction delays impacting the handover of Safety Transfer Certificates (STCs) to commissioning. These delays reflect the projects strategic decision to target more complex STCs first with the majority of these STCs due to be delivered in the coming months. Whilst these delays have resulted in deterministic float erosion and caused a narrowing of the forecasted range (August to November 2027 and £1,445m to £1,475m) confidence remains in delivering within P80 parameters. Highlights in period the handover of 250 STC (WTC Decontamination & Maintenance) from Construction to Commissioning achieved . Grout Plant Engineering Orders (EOs) and Technical Requisitions (TRs) complete. The Capability and Capacity status remains Green this period as the project continues the transition from Construction to Commissioning, with resource transition plans developed.
B23: 35/09592 | C23: Sellafield Product & Residue Store Retreatment Plant | D23: Sellafield | F23: =VLOOKUP(C23,'5a)NDA MPPR'!$B$9:$AK$61,3,FALSE) -> A | G23: =VLOOKUP(C23,'5a)NDA MPPR'!$B$9:$AK$61,4,FALSE) -> -1 | I23: =VLOOKUP(C23,'5a)NDA MPPR'!$B$9:$AK$61,6,FALSE) -> FBC (Jul-21) | J23: =VLOOKUP(C23,'5a)NDA MPPR'!$B$9:$AK$61,7,FALSE) -> 1335.43 | K23: =VLOOKUP(C23,'5a)NDA MPPR'!$B$9:$AK$61,8,FALSE) -> 1673 | L23: =VLOOKUP(C23,'5a)NDA MPPR'!$B$9:$AK$61,9,FALSE) -> 47400 | M23: =VLOOKUP(C23,'5a)NDA MPPR'!$B$9:$AK$61,10,FALSE) -> 48274 | N23: ='3) BC and Sanction'!I106 -> 0 | O23: =VLOOKUP(C23,'5a)NDA MPPR'!$B$9:$AK$61,12,FALSE) -> 1673 | P23: =VLOOKUP(C23,'5a)NDA MPPR'!$B$9:$AK$61,13,FALSE) -> 1482.9 | R23: =VLOOKUP(C23,'5a)NDA MPPR'!$B$9:$AK$61,15,FALSE) -> A | S23: =VLOOKUP(C23,'5a)NDA MPPR'!$B$9:$AK$61,16,FALSE) -> -1 | U23: =VLOOKUP(C23,'5a)NDA MPPR'!$B$9:$AK$61,18,FALSE) -> FBC (Oct-25) | W23: =VLOOKUP(C23,'5a)NDA MPPR'!$B$9:$AK$61,20,FALSE) -> 1479.319 | X23: =VLOOKUP(C23,'5a)NDA MPPR'!$B$9:$AK$61,21,FALSE) -> 1466.5527 | Y23: =VLOOKUP(C23,'5a)NDA MPPR'!$B$9:$AK$61,22,FALSE) -> 0 | AA23: =VLOOKUP(C23,'5a)NDA MPPR'!$B$9:$AK$61,24,FALSE) -> 47574 | AB23: =VLOOKUP(C23,'5a)NDA MPPR'!$B$9:$AK$61,25,FALSE) -> 47574 | AC23: =VLOOKUP(C23,'5a)NDA MPPR'!$B$9:$AK$61,26,FALSE) -> 0 | AE23: =VLOOKUP(C23,'5a)NDA MPPR'!$B$9:$AK$61,28,FALSE) -> 1122.4112 | AF23: =VLOOKUP(C23,'5a)NDA MPPR'!$B$9:$AK$61,29,FALSE) -> 976.10644 | AG23: =VLOOKUP(C23,'5a)NDA MPPR'!$B$9:$AK$61,30,FALSE) -> 1030.0308 | AH23: =VLOOKUP(C23,'5a)NDA MPPR'!$B$9:$AK$61,31,FALSE) -> 0.94764781 | AI23: =VLOOKUP(C23,'5a)NDA MPPR'!$B$9:$AK$61,32,FALSE) -> 0.86965137 | AJ23: =VLOOKUP(C23,'5a)NDA MPPR'!$B$9:$AK$61,33,FALSE) -> 0.75873505 | AK23: =VLOOKUP(C23,'5a)NDA MPPR'!$B$9:$AK$61,34,FALSE) -> 0.65983498 | AM23: =VLOOKUP(C23,'5a)NDA MPPR'!$B$9:$AK$61,36,FALSE) -> A | AO23: =T21-G21 -> 0 | AP23: =T21-K21 -> 0 | AQ23: =X21-I21 -> 0 | AS23: =T21-S21 -> 0 | AT23: =X21-W21 -> 0 | AV23: 1466.5523 | AW23: 47574 | AY23: 1479.319 | AZ23: =W23-AY23 -> -1.0000001e-06 | BA23: 47574 | BB23: =AA23-BA23 -> 0
A24: =C23 -> Sellafield Product & Residue Store Retreatment Plant | B24: =VLOOKUP($C23,'5a)NDA MPPR'!$A$9:$AK$61,2,FALSE) -> The Sellafield Product & Residue Store Retreatment Plant (SRP) project is a key element of the Sellafield Ltd ‘Special Nuclear Materials (SNM) Future State Programme’. The SRP is a complex major project required to provide the capability to receive special nuclear material in existing packages, from existing stores on the Sellafield site, and process the material into a form and package suitable for safe and secure long-term interim storage. The SRO Delivery Confidence Assessment (DCA) has moved from Green to Amber against the P80 cost and schedule from the Full Business Case (FBC) approved by HMG in July 2021. This is primarily reflective of the previously reported emerging issue relating to legislative changes to Passive Fire Protection standards, following the implementation of the Building Safety Act 2022. This Act represents a major regulatory shift in the UK construction industry, particularly in fire safety aiming to improve accountability and safety following the Grenfell Tower Inquiry. The impact of the Passive Fire Protection standards will require a significant amount of engineering design rework and additional installation work in the facility; the main impact is expected to be on the timescales to achieve readiness of the facility for Glove box installation, which has now become the critical path. The initial assessment has been carried out and is currently being quantified and assured and an assessment is also being made as to how this issue should be considered in terms of the projects current P80 sanctioned cost and schedule. Additionally, as previously reported the project has been impacted by extraordinary inflation incurred to date. Following the DESNZ PIC decision in Q2 24/25 to postpone the £164.6m Inflation Sanction relief, the project has had to absorb inflationary costs using its existing contingency. As a result, £128.9m of the P50–P80 sanctioned contingency has been utilised, leaving £190m remaining. This erosion of contingency increases the likelihood of a future re-sanction request for additional P50–P80 funding, particularly as further events may arise that impact the remaining contingency. The project will be requesting P80 cost and schedule relief to DESNZ PIC when appropriate. Key recommendations and actions from the last Gate 0/ Annual Review have been addressed and a review of the effectiveness of the close out actions will be carried out in Quarter 4. These included the requirement to ensure sufficient design engineering resource was in place to support safety case, and mitigation of the risk of delays relating to furnace manufacture (impacting installation of both Glove Boxes and MEICA equipment). The Capability and Capacity RAG status remains Amber with ongoing challenges in recruitment principally across several disciplines including construction, engineering, commissioning, and quality. Finally, the successful active commissioning and future operations of the SRP facility are contingent upon several dependencies managed within the SNM Future State Programme. A critical dependency is the availability of SNM analytical capability, which is essential to support both commissioning and ongoing operational activities. To address this, a dedicated project is being developed and delivered through the PPP to ensure the required analytical capability is in place. The SNM Future State Programme team is responsible for managing all dependencies associated with SRP, with the overarching goal of ensuring that all necessary capabilities are aligned and available to enable the delivery of SRP outcomes and the realisation of associated benefits.
B26: 35/09975 | C26: Security Systems Architecture Upgrade (SSAU) | D26: Sellafield | F26: =VLOOKUP(C26,'5a)NDA MPPR'!$B$9:$AK$61,3,FALSE) -> G | G26: =VLOOKUP(C26,'5a)NDA MPPR'!$B$9:$AK$61,4,FALSE) -> 0 | I26: =VLOOKUP(C26,'5a)NDA MPPR'!$B$9:$AK$61,6,FALSE) -> FBC (Mar-20) | J26: =VLOOKUP(C26,'5a)NDA MPPR'!$B$9:$AK$61,7,FALSE) -> 305.9 | K26: =VLOOKUP(C26,'5a)NDA MPPR'!$B$9:$AK$61,8,FALSE) -> 315.4 | L26: =VLOOKUP(C26,'5a)NDA MPPR'!$B$9:$AK$61,9,FALSE) -> 46053 | M26: =VLOOKUP(C26,'5a)NDA MPPR'!$B$9:$AK$61,10,FALSE) -> 46112 | N26: ='3) BC and Sanction'!I91 -> 0 | O26: =VLOOKUP(C26,'5a)NDA MPPR'!$B$9:$AK$61,12,FALSE) -> 315.4 | P26: =VLOOKUP(C26,'5a)NDA MPPR'!$B$9:$AK$61,13,FALSE) -> 315.4 | R26: =VLOOKUP(C26,'5a)NDA MPPR'!$B$9:$AK$61,15,FALSE) -> R | S26: =VLOOKUP(C26,'5a)NDA MPPR'!$B$9:$AK$61,16,FALSE) -> 0 | U26: =VLOOKUP(C26,'5a)NDA MPPR'!$B$9:$AK$61,18,FALSE) -> FBC (Oct-24) | W26: =VLOOKUP(C26,'5a)NDA MPPR'!$B$9:$AK$61,20,FALSE) -> 297.38168 | X26: =VLOOKUP(C26,'5a)NDA MPPR'!$B$9:$AK$61,21,FALSE) -> 315.08361 | Y26: =VLOOKUP(C26,'5a)NDA MPPR'!$B$9:$AK$61,22,FALSE) -> 0.1 | AA26: =VLOOKUP(C26,'5a)NDA MPPR'!$B$9:$AK$61,24,FALSE) -> 46107 | AB26: =VLOOKUP(C26,'5a)NDA MPPR'!$B$9:$AK$61,25,FALSE) -> 46107 | AC26: =VLOOKUP(C26,'5a)NDA MPPR'!$B$9:$AK$61,26,FALSE) -> 0 | AE26: =VLOOKUP(C26,'5a)NDA MPPR'!$B$9:$AK$61,28,FALSE) -> 292.98492 | AF26: =VLOOKUP(C26,'5a)NDA MPPR'!$B$9:$AK$61,29,FALSE) -> 292.39722 | AG26: =VLOOKUP(C26,'5a)NDA MPPR'!$B$9:$AK$61,30,FALSE) -> 312.99395 | AH26: =VLOOKUP(C26,'5a)NDA MPPR'!$B$9:$AK$61,31,FALSE) -> 0.93419448 | AI26: =VLOOKUP(C26,'5a)NDA MPPR'!$B$9:$AK$61,32,FALSE) -> 0.99799409 | AJ26: =VLOOKUP(C26,'5a)NDA MPPR'!$B$9:$AK$61,33,FALSE) -> 0.9852151 | AK26: =VLOOKUP(C26,'5a)NDA MPPR'!$B$9:$AK$61,34,FALSE) -> 0.98323885 | AM26: =VLOOKUP(C26,'5a)NDA MPPR'!$B$9:$AK$61,36,FALSE) -> A | AO26: =T18-G18 -> 0 | AP26: =T18-K18 -> 0 | AQ26: =X18-I18 -> 0 | AS26: =T18-S18 -> 0 | AT26: =X18-W18 -> 0 | AV26: 314.93422 | AW26: 46107 | AY26: 297.38168 | AZ26: =W26-AY26 -> 0 | BA26: 46107 | BB26: =AA26-BA26 -> 0
A27: =C26 -> Security Systems Architecture Upgrade (SSAU) | B27: =VLOOKUP($C26,'5a)NDA MPPR'!$A$9:$AK$61,2,FALSE) -> The SSAU project will provide infrastructure and equipment that will provide security and emergency response teams with a significantly improved capability to react to and manage security and/or emergency events on the Sellafield site. The first project benefit is equipment which, once operational in the command centre, will provide a significantly improved capability to react and manage security and/or emergency events on the Sellafield site - thereby complying with the standards, expectations and objectives set by nuclear regulators. The Delivery Confidence Assessment remains stable at Green recognising forecast delivery within the Projects P80 Sanction. The Baseline RAG has remained Red in period, as the Cost forecast remains beyond the P50 baseline. The Project is still however forecasting to deliver within the P80 Sanction released to Sellafield. In period the Lifecycle EAC has increased slightly, but still within the P80 Sanction, due to the Level 1 Commissioning Date and Legacy Building Migration moving out slightly from January 2026 to February 2026 due to minor technical issues found in commissioning and impact of the strikes leading to retention of commissioning resources for a further period. In period good progress continues with commissioning with some issues delaying the work as they are resolved, the strike has reduce working time slightly each day but the team are working around this where possible. The next stage of strikes will have an impact as scaffolding is required to access an area of fence which needs minor sensor repairs before commissioning. The Amber rating on the Capability and Capacity RAG recognises that schedule adherence is reliant on skilled resources and the project team is now a very thin layer and any loss of resources would impact delivery.
B29: 35/09968 | C29: CNC Operational Unit | D29: Sellafield | F29: =VLOOKUP(C29,'5a)NDA MPPR'!$B$9:$AK$61,3,FALSE) -> G | G29: =VLOOKUP(C29,'5a)NDA MPPR'!$B$9:$AK$61,4,FALSE) -> 0 | I29: =VLOOKUP(C29,'5a)NDA MPPR'!$B$9:$AK$61,6,FALSE) -> FBC (Jun-24) | J29: =VLOOKUP(C29,'5a)NDA MPPR'!$B$9:$AK$61,7,FALSE) -> 72.6 | K29: =VLOOKUP(C29,'5a)NDA MPPR'!$B$9:$AK$61,8,FALSE) -> 79 | L29: =VLOOKUP(C29,'5a)NDA MPPR'!$B$9:$AK$61,9,FALSE) -> 46106 | M29: =VLOOKUP(C29,'5a)NDA MPPR'!$B$9:$AK$61,10,FALSE) -> 46234 | N29: ='3) BC and Sanction'!I85 -> 0 | O29: =VLOOKUP(C29,'5a)NDA MPPR'!$B$9:$AK$61,12,FALSE) -> 72.6 | P29: =VLOOKUP(C29,'5a)NDA MPPR'!$B$9:$AK$61,13,FALSE) -> 72.6 | R29: =VLOOKUP(C29,'5a)NDA MPPR'!$B$9:$AK$61,15,FALSE) -> G | S29: =VLOOKUP(C29,'5a)NDA MPPR'!$B$9:$AK$61,16,FALSE) -> 0 | U29: =VLOOKUP(C29,'5a)NDA MPPR'!$B$9:$AK$61,18,FALSE) -> FBC (Sep-24) | W29: =VLOOKUP(C29,'5a)NDA MPPR'!$B$9:$AK$61,20,FALSE) -> 72.672543 | X29: =VLOOKUP(C29,'5a)NDA MPPR'!$B$9:$AK$61,21,FALSE) -> 71.079063 | Y29: =VLOOKUP(C29,'5a)NDA MPPR'!$B$9:$AK$61,22,FALSE) -> 0 | AA29: =VLOOKUP(C29,'5a)NDA MPPR'!$B$9:$AK$61,24,FALSE) -> 46106 | AB29: =VLOOKUP(C29,'5a)NDA MPPR'!$B$9:$AK$61,25,FALSE) -> 46106 | AC29: =VLOOKUP(C29,'5a)NDA MPPR'!$B$9:$AK$61,26,FALSE) -> 0 | AE29: =VLOOKUP(C29,'5a)NDA MPPR'!$B$9:$AK$61,28,FALSE) -> 72.6204 | AF29: =VLOOKUP(C29,'5a)NDA MPPR'!$B$9:$AK$61,29,FALSE) -> 64.52305 | AG29: =VLOOKUP(C29,'5a)NDA MPPR'!$B$9:$AK$61,30,FALSE) -> 69.60177 | AH29: =VLOOKUP(C29,'5a)NDA MPPR'!$B$9:$AK$61,31,FALSE) -> 0.92703174 | AI29: =VLOOKUP(C29,'5a)NDA MPPR'!$B$9:$AK$61,32,FALSE) -> 0.88849759 | AJ29: =VLOOKUP(C29,'5a)NDA MPPR'!$B$9:$AK$61,33,FALSE) -> 0.99928249 | AK29: =VLOOKUP(C29,'5a)NDA MPPR'!$B$9:$AK$61,34,FALSE) -> 0.88786008 | AM29: =VLOOKUP(C29,'5a)NDA MPPR'!$B$9:$AK$61,36,FALSE) -> G | AO29: =T24-G24 -> 0 | AP29: =T24-K24 -> 0 | AQ29: =X24-I24 -> 0 | AS29: =T24-S24 -> 0 | AT29: =X24-W24 -> 0 | AV29: 71.086868 | AW29: 46106 | AY29: 72.672543 | AZ29: =W29-AY29 -> 0 | BA29: 46106 | BB29: =AA29-BA29 -> 0
A30: =C29 -> CNC Operational Unit | B30: =VLOOKUP($C29,'5a)NDA MPPR'!$A$9:$AK$61,2,FALSE) -> The Civil Nuclear Constabulary (CNC) Operational Unit project will provide one location on site to house all CNC personnel, with space allowance for future uplift of officers, whilst mitigating health and safety risks associated with the current facilities. The Delivery Confidence Assessment (DCA) is stable at Green as the Resubmission Full Business Case (FBC) has received approval from His Majesty’s Treasury (HMT) in June 2024. Bulk Construction is nearing completion but has been delayed until November, in part due to strike action and reprioritisation of resources to complete critical path works in the Level 1 Board rooms. The completion of the Level 1 Board rooms was initially impacted by the replacement of the non-complaint glands, has been further impacted by the strike action as well as slower than anticipated progress of the other works required to be completed and higher level of snagging than anticipated following contractor and client inspections. These delays have been compounded through the loss of opportunity to recover through additional weekend working due the Union imposed overtime ban related to the on-going industrial action. The completion and commissioning of the Level 1 Boards is the enabler for the release of all future commissioning works. CNSL with support of Amentum Executives, have explored the opportunity to exploit the 120-day duration for Commissioning and Handover, this has seen more efficient planning of the commissioning phase, reducing the duration from 120 days to 93 days to maintain current forecast end date. On-site work continues to progress well, civils scope is focused on external works and building finishes, Control, Electrical & Instrumentation (CE&I) works is focused on ensuring the Level 1 boards are ready for commissioning with the Project working closely with Utilities. Heat, Ventilation and Air Conditioning (HVAC) installation works is almost complete. The Capability and Capacity RAG remains Green for the period with no current vacancies.
B32: 35/07654 | C32: BEPPS2 | D32: Sellafield | F32: =VLOOKUP(C32,'5a)NDA MPPR'!$B$9:$AK$61,3,FALSE) -> G | G32: =VLOOKUP(C32,'5a)NDA MPPR'!$B$9:$AK$61,4,FALSE) -> 0 | I32: =VLOOKUP(C32,'5a)NDA MPPR'!$B$9:$AK$61,6,FALSE) -> OBC (Sep-23) | J32: =VLOOKUP(C32,'5a)NDA MPPR'!$B$9:$AK$61,7,FALSE) -> 776 | K32: =VLOOKUP(C32,'5a)NDA MPPR'!$B$9:$AK$61,8,FALSE) -> 837 | L32: =VLOOKUP(C32,'5a)NDA MPPR'!$B$9:$AK$61,9,FALSE) -> 49490 | M32: =VLOOKUP(C32,'5a)NDA MPPR'!$B$9:$AK$61,10,FALSE) -> 49795 | N32: ='3) BC and Sanction'!I103 -> 0 | O32: =VLOOKUP(C32,'5a)NDA MPPR'!$B$9:$AK$61,12,FALSE) -> 382 | P32: =VLOOKUP(C32,'5a)NDA MPPR'!$B$9:$AK$61,13,FALSE) -> 186 | R32: =VLOOKUP(C32,'5a)NDA MPPR'!$B$9:$AK$61,15,FALSE) -> G | S32: =VLOOKUP(C32,'5a)NDA MPPR'!$B$9:$AK$61,16,FALSE) -> 0 | U32: =VLOOKUP(C32,'5a)NDA MPPR'!$B$9:$AK$61,18,FALSE) -> OBC (Mar-23) | W32: =VLOOKUP(C32,'5a)NDA MPPR'!$B$9:$AK$61,20,FALSE) -> 751.17472 | X32: =VLOOKUP(C32,'5a)NDA MPPR'!$B$9:$AK$61,21,FALSE) -> 749.16803 | Y32: =VLOOKUP(C32,'5a)NDA MPPR'!$B$9:$AK$61,22,FALSE) -> 0 | AA32: =VLOOKUP(C32,'5a)NDA MPPR'!$B$9:$AK$61,24,FALSE) -> 49490 | AB32: =VLOOKUP(C32,'5a)NDA MPPR'!$B$9:$AK$61,25,FALSE) -> 49490 | AC32: =VLOOKUP(C32,'5a)NDA MPPR'!$B$9:$AK$61,26,FALSE) -> 0 | AE32: =VLOOKUP(C32,'5a)NDA MPPR'!$B$9:$AK$61,28,FALSE) -> 120.8995 | AF32: =VLOOKUP(C32,'5a)NDA MPPR'!$B$9:$AK$61,29,FALSE) -> 111.56263 | AG32: =VLOOKUP(C32,'5a)NDA MPPR'!$B$9:$AK$61,30,FALSE) -> 100.76855 | AH32: =VLOOKUP(C32,'5a)NDA MPPR'!$B$9:$AK$61,31,FALSE) -> 1.1071175 | AI32: =VLOOKUP(C32,'5a)NDA MPPR'!$B$9:$AK$61,32,FALSE) -> 0.92277163 | AJ32: =VLOOKUP(C32,'5a)NDA MPPR'!$B$9:$AK$61,33,FALSE) -> 0.16094724 | AK32: =VLOOKUP(C32,'5a)NDA MPPR'!$B$9:$AK$61,34,FALSE) -> 0.14851755 | AM32: =VLOOKUP(C32,'5a)NDA MPPR'!$B$9:$AK$61,36,FALSE) -> G | AO32: =T30-G30 -> 0 | AP32: =T30-K30 -> 0 | AQ32: =X30-I30 -> 0 | AS32: =T30-S30 -> 0 | AT32: =X30-W30 -> 0 | AV32: 749.16803 | AW32: 49490 | AY32: 751.17472 | AZ32: =W32-AY32 -> 0 | BA32: 49490 | BB32: =AA32-BA32 -> 0
A33: =C32 -> BEPPS2 | B33: =VLOOKUP($C32,'5a)NDA MPPR'!$A$9:$AK$61,2,FALSE) -> The Box Encapsulation Plant Product Store 2 (BEPPS2) is a critical enabler for continued high hazard retrievals from the Magnox Swarf Storage Silo (MSSS) and Pile Fuel Cladding Silo (PFCS). It will provide modern, safe and secure long term interim storage for approximately 7,500 packages of Intermediate Level Waste. The strategic requirement has been confirmed. The first project benefit is the ability to receive packages from MSSS and PFCS without constraining hazard reduction programmes. The Senior Responsible Owner (SRO) Delivery Confidence Assessment is Green and the project remains on track against its P50 cost and schedule targets. The project is in the Define Phase, progressing detailed design for transition to civil construction and procurement of long-lead items. The critical path runs through civil construction, mechanical and electrical installation, and commissioning. A sub-critical path flows through the Multi-Disciplinary Design Review (MDDR), which will confirm design maturity and support release of the Outline Business Case (OBC) sanction hold point. The MDDR will be held during Period 8. Engagement with Programme and Project Partnership (PPP) Key Delivery Partners is ongoing to underpin delivery phase planning, cost estimation, and Quantitative Risk Analysis (QRA), informing the Full Business Case (FBC) submission planned for FY2026/27. Site establishment and bulk excavation works are progressing well. The civil construction contract delivery strategy is under review by PPP to ensure value for money. The SPI reflects both historic design delays due to historic resource constraints and the non-utilisation of risk and estimating uncertainty. The forthcoming OBC sanction hold point release submission (January 2026 to IRP & GIC and March 2026 to DESNZ PIC) will include updates on the lifecycle cost estimates that will be underpinned by an updated QRA and will reflect proactive management of opportunities and realisation of threats during the Define Stage. Capability RAG remains Green.
B35: 35/09343 | C35: SIXEP Continuity Plant | D35: Sellafield | F35: =VLOOKUP(C35,'5a)NDA MPPR'!$B$9:$AK$61,3,FALSE) -> G | G35: =VLOOKUP(C35,'5a)NDA MPPR'!$B$9:$AK$61,4,FALSE) -> 0 | I35: =VLOOKUP(C35,'5a)NDA MPPR'!$B$9:$AK$61,6,FALSE) -> FBC (Dec-21) | J35: =VLOOKUP(C35,'5a)NDA MPPR'!$B$9:$AK$61,7,FALSE) -> 1007 | K35: =VLOOKUP(C35,'5a)NDA MPPR'!$B$9:$AK$61,8,FALSE) -> 1182 | L35: =VLOOKUP(C35,'5a)NDA MPPR'!$B$9:$AK$61,9,FALSE) -> 47849 | M35: =VLOOKUP(C35,'5a)NDA MPPR'!$B$9:$AK$61,10,FALSE) -> 48611 | N35: ='3) BC and Sanction'!I109 -> 0 | O35: =VLOOKUP(C35,'5a)NDA MPPR'!$B$9:$AK$61,12,FALSE) -> 1182 | P35: =VLOOKUP(C35,'5a)NDA MPPR'!$B$9:$AK$61,13,FALSE) -> 1150.7 | R35: =VLOOKUP(C35,'5a)NDA MPPR'!$B$9:$AK$61,15,FALSE) -> G | S35: =VLOOKUP(C35,'5a)NDA MPPR'!$B$9:$AK$61,16,FALSE) -> 0 | U35: =VLOOKUP(C35,'5a)NDA MPPR'!$B$9:$AK$61,18,FALSE) -> FBC (Jan-24) | W35: =VLOOKUP(C35,'5a)NDA MPPR'!$B$9:$AK$61,20,FALSE) -> 1133.0636 | X35: =VLOOKUP(C35,'5a)NDA MPPR'!$B$9:$AK$61,21,FALSE) -> 1120.8757 | Y35: =VLOOKUP(C35,'5a)NDA MPPR'!$B$9:$AK$61,22,FALSE) -> 0 | AA35: =VLOOKUP(C35,'5a)NDA MPPR'!$B$9:$AK$61,24,FALSE) -> 48142 | AB35: =VLOOKUP(C35,'5a)NDA MPPR'!$B$9:$AK$61,25,FALSE) -> 48142 | AC35: =VLOOKUP(C35,'5a)NDA MPPR'!$B$9:$AK$61,26,FALSE) -> 0 | AE35: =VLOOKUP(C35,'5a)NDA MPPR'!$B$9:$AK$61,28,FALSE) -> 759.67017 | AF35: =VLOOKUP(C35,'5a)NDA MPPR'!$B$9:$AK$61,29,FALSE) -> 718.60177 | AG35: =VLOOKUP(C35,'5a)NDA MPPR'!$B$9:$AK$61,30,FALSE) -> 744.39202 | AH35: =VLOOKUP(C35,'5a)NDA MPPR'!$B$9:$AK$61,31,FALSE) -> 0.96535394 | AI35: =VLOOKUP(C35,'5a)NDA MPPR'!$B$9:$AK$61,32,FALSE) -> 0.94593918 | AJ35: =VLOOKUP(C35,'5a)NDA MPPR'!$B$9:$AK$61,33,FALSE) -> 0.67045675 | AK35: =VLOOKUP(C35,'5a)NDA MPPR'!$B$9:$AK$61,34,FALSE) -> 0.63421131 | AM35: =VLOOKUP(C35,'5a)NDA MPPR'!$B$9:$AK$61,36,FALSE) -> G | AO35: =T33-G33 -> 0 | AP35: =T33-K33 -> 0 | AQ35: =X33-I33 -> 0 | AS35: =T33-S33 -> 0 | AT35: =X33-W33 -> 0 | AV35: 1120.8916 | AW35: 48142 | AY35: 1133.0636 | AZ35: =W35-AY35 -> 0 | BA35: 48142 | BB35: =AA35-BA35 -> 0
A36: =C35 -> SIXEP Continuity Plant | B36: =VLOOKUP($C35,'5a)NDA MPPR'!$A$9:$AK$61,2,FALSE) -> The SIXEP Continuity Plant (SCP) is required to deliver a continued site effluent treatment capability in support of radioactive liquid effluent discharge permits, fuel pond management, high hazard reduction projects and the overall NDA mission. This project provides a replacement for the existing SIXEP Sea Discharge Treatment plant and is therefore mission critical to the safe operation of the site. The SRO Delivery Confidence Assessment (DCA) currently remains green however there is a significant risk posed by the impact of extraordinary inflation that has been incurred to date. This follows the decision made by PIC in Q2 24/25 to not approve the P80 Inflation Sanction relief for SCP. The NDA have released £108.7m sanction to SL from P80 as an interim measure to deal with the inflation impact, however this substantially erodes the P80 contingency. The first scope driven P80 drawdown for the project has been approved this quarter. Combined, these two drawdowns result in a net £31M P80 contingency remaining. The SRO considers that this is likely to be insufficient for the next 4 years and has submitted a sanction release paper to the Department in September, with review pending. Without this additional sanction the current DCA rating would change from Green to Red, hence this will be kept under review by the SRO throughout 2025/26. From a project performance perspective, the SRO DCA remains Green, echoed by National Infrastructure and Service Transformation Authority (NISTA) Green rating received in June 25/26. The Baseline RAG remains Green. Fabrication of off-site pipework planned for completion Q4 25/26. Site pipework and vessel install is progressing well in both the Effluent Treatment Cell (ETC) and Bulk Storage Tank (BST) cells. Both halves of the reception pumping tank now in position and welding has commenced within the ETC, marking another significant milestone for the project. marking another milestone for the project. Works continue to progress across all floors within the Service Building prior to handover over to Mechanical, Electrical, Instrumentation, Control & Automation (MEICA) trades. Bulk Storage Tanks – welding of the first tank continues to progress in cell. Project Wide Objectives - PWO4 - Handover of BST cell to Commissioning, PWO5 - Handover Services Building to Commissioning and PWO6 - Handover of ETC to Commissioning are all currently forecasting to be delayed with further impending strike action (Industrial Relations issues) however, these are not a threat to the critical path and project remains within P50. The last milestone on the journey is commencement of active commissioning (licence instrument approvals). Post scope driven P80 drawdown impact the baseline date is now 22nd July 2030 (P50) along with the P50 Lifecycle baseline end date moving to 21st October 2031. The forecast dates and lifecycle EAC remain stable. The Capability and Capacity RAG remains Green with no issues to report.
B38: 35/10417 | C38: ILW East Land Excavation | D38: Sellafield | F38: =VLOOKUP(C38,'5a)NDA MPPR'!$B$9:$AK$61,3,FALSE) -> G | G38: =VLOOKUP(C38,'5a)NDA MPPR'!$B$9:$AK$61,4,FALSE) -> 0 | I38: =VLOOKUP(C38,'5a)NDA MPPR'!$B$9:$AK$61,6,FALSE) -> FBC (Jun-24) | J38: =VLOOKUP(C38,'5a)NDA MPPR'!$B$9:$AK$61,7,FALSE) -> 69.1 | K38: =VLOOKUP(C38,'5a)NDA MPPR'!$B$9:$AK$61,8,FALSE) -> 75.8 | L38: =VLOOKUP(C38,'5a)NDA MPPR'!$B$9:$AK$61,9,FALSE) -> 46295 | M38: =VLOOKUP(C38,'5a)NDA MPPR'!$B$9:$AK$61,10,FALSE) -> 46446 | N38: ='3) BC and Sanction'!I112 -> 0 | O38: =VLOOKUP(C38,'5a)NDA MPPR'!$B$9:$AK$61,12,FALSE) -> n/a | P38: =VLOOKUP(C38,'5a)NDA MPPR'!$B$9:$AK$61,13,FALSE) -> 69.1 | R38: =VLOOKUP(C38,'5a)NDA MPPR'!$B$9:$AK$61,15,FALSE) -> G | S38: =VLOOKUP(C38,'5a)NDA MPPR'!$B$9:$AK$61,16,FALSE) -> 0 | U38: =VLOOKUP(C38,'5a)NDA MPPR'!$B$9:$AK$61,18,FALSE) -> FBC (Mar-23) | W38: =VLOOKUP(C38,'5a)NDA MPPR'!$B$9:$AK$61,20,FALSE) -> 67.414678 | X38: =VLOOKUP(C38,'5a)NDA MPPR'!$B$9:$AK$61,21,FALSE) -> 35.500379 | Y38: =VLOOKUP(C38,'5a)NDA MPPR'!$B$9:$AK$61,22,FALSE) -> 0 | AA38: =VLOOKUP(C38,'5a)NDA MPPR'!$B$9:$AK$61,24,FALSE) -> 46266 | AB38: =VLOOKUP(C38,'5a)NDA MPPR'!$B$9:$AK$61,25,FALSE) -> 46112 | AC38: =VLOOKUP(C38,'5a)NDA MPPR'!$B$9:$AK$61,26,FALSE) -> 0 | AE38: =VLOOKUP(C38,'5a)NDA MPPR'!$B$9:$AK$61,28,FALSE) -> 61.06499 | AF38: =VLOOKUP(C38,'5a)NDA MPPR'!$B$9:$AK$61,29,FALSE) -> 60.119926 | AG38: =VLOOKUP(C38,'5a)NDA MPPR'!$B$9:$AK$61,30,FALSE) -> 35.120399 | AH38: =VLOOKUP(C38,'5a)NDA MPPR'!$B$9:$AK$61,31,FALSE) -> 1.7118235 | AI38: =VLOOKUP(C38,'5a)NDA MPPR'!$B$9:$AK$61,32,FALSE) -> 0.98452362 | AJ38: =VLOOKUP(C38,'5a)NDA MPPR'!$B$9:$AK$61,33,FALSE) -> 0.9058115 | AK38: =VLOOKUP(C38,'5a)NDA MPPR'!$B$9:$AK$61,34,FALSE) -> 0.89179282 | AM38: =VLOOKUP(C38,'5a)NDA MPPR'!$B$9:$AK$61,36,FALSE) -> G | AO38: =T36-G36 -> 0 | AP38: =T36-K36 -> 0 | AQ38: =X36-I36 -> 0 | AS38: =T36-S36 -> 0 | AT38: =X36-W36 -> 0 | AV38: 35.50088 | AW38: 46112 | AY38: 67.414678 | AZ38: =W38-AY38 -> 0 | BA38: 46266 | BB38: =AA38-BA38 -> 0
A39: =C38 -> ILW East Land Excavation | B39: =VLOOKUP($C38,'5a)NDA MPPR'!$A$9:$AK$61,2,FALSE) -> The ILW EZ Phase 1 Excavation Project is a key enabler to allow the future major project Lightly Shielded Store 1 (LSS1) to commence construction and also de-risks LSS1 construction. The delays in issuing the Service Commencement Notification (SCN) and late Pre-Construction Information (PCI) caused a 4-month delay to the beginning of delivery, however the excavation work has now recovered. The first project benefit: This project delivers a number of benefits, both direct as a key enabler for LSS1, and indirect in adopting an Enterprise approach to zonal development. The Baseline remains green. All issues have now been rectified. All works are now complete and awaiting isolations to be removed before sign off. Walk rounds have taken place and a meeting to arrange the CTC transfer is being set up. Lifecycle EAC and the forecast date for close out of the Project remain stable. The Capability and Capacity RAG remains Green.
B41: 35/09203 | C41: Lightly Shielded Store (LSS) | D41: Sellafield | F41: =VLOOKUP($C41,'4b) SL EPO Extended Data Sheet'!$A$5:$AB$176,2,FALSE) -> N/A | G41: =VLOOKUP($C41,'4b) SL EPO Extended Data Sheet'!$A$5:$AB$176,3, FALSE) -> 0 | I41: =VLOOKUP($C41,'4b) SL EPO Extended Data Sheet'!$A$5:$AD$176,30, FALSE) -> N/A | J41: =VLOOKUP($C41,'4b) SL EPO Extended Data Sheet'!$A$5:$AC$176,6, FALSE)/1000000 -> 46.4 | K41: =VLOOKUP($C41,'4b) SL EPO Extended Data Sheet'!$A$5:$AC$176,7, FALSE)/1000000 -> 0 | L41: =VLOOKUP($C41,'4b) SL EPO Extended Data Sheet'!$A$5:$AB$176,8, FALSE) -> 46812 | M41: =VLOOKUP($C41,'4b) SL EPO Extended Data Sheet'!$A$5:$AC$176,9, FALSE) | N41: =VLOOKUP($C41,'4b) SL EPO Extended Data Sheet'!$A$5:$AB$176,5, FALSE) | O41: =VLOOKUP($C41,'4b) SL EPO Extended Data Sheet'!$A$5:$AC$176,10, FALSE)/1000000 -> 0 | P41: =VLOOKUP($C41,'4b) SL EPO Extended Data Sheet'!$A$5:$AC$176,11, FALSE)/1000000 -> 46.4 | R41: =VLOOKUP($C41,'4b) SL EPO Extended Data Sheet'!$A$5:$AC$176,12,FALSE) -> N/A | S41: =VLOOKUP($C41,'4b) SL EPO Extended Data Sheet'!$A$5:$AC$176,13,FALSE) -> 0 | U41: =VLOOKUP($C41,'4b) SL EPO Extended Data Sheet'!$A$5:$AE$176,31,FALSE) -> N/A (Aug-23) | W41: =VLOOKUP($C41,'4b) SL EPO Extended Data Sheet'!$A$5:$AC$176,16,FALSE)/1000000 -> 142.42994 | X41: =VLOOKUP($C41,'4b) SL EPO Extended Data Sheet'!$A$5:$AC$176,17,FALSE)/1000000 -> 157.94101 | Y41: =VLOOKUP($C41,'4b) SL EPO Extended Data Sheet'!$A$5:$AC$176,18,FALSE)/1000000 -> -0.16431294 | Z41: =VLOOKUP($C41,'4b) SL EPO Extended Data Sheet'!$A$5:$AB$176,16,FALSE)/1000000 -> 142.42994 | AA41: =VLOOKUP($C41,'4b) SL EPO Extended Data Sheet'!$A$5:$AC$176,19,FALSE) -> 46951 | AB41: =VLOOKUP($C41,'4b) SL EPO Extended Data Sheet'!$A$5:$AC$176,20,FALSE) -> 46951 | AC41: =VLOOKUP($C41,'4b) SL EPO Extended Data Sheet'!$A$5:$AC$176,21,FALSE) -> 0 | AD41: =VLOOKUP($C41,'4b) SL EPO Extended Data Sheet'!$A$5:$AB$176,15,FALSE)/1000000 -> 0.045163 | AE41: =VLOOKUP($C41,'4b) SL EPO Extended Data Sheet'!$A$5:$AC$176,22,FALSE)/1000000 -> 29.903685 | AF41: =VLOOKUP($C41,'4b) SL EPO Extended Data Sheet'!$A$5:$AC$176,23,FALSE)/1000000 -> 18.198193 | AG41: =VLOOKUP($C41,'4b) SL EPO Extended Data Sheet'!$A$5:$AC$176,24,FALSE)/1000000 -> 26.057378 | AH41: =VLOOKUP($C41,'4b) SL EPO Extended Data Sheet'!$A$5:$AC$176,25,FALSE) -> 0.69838926 | AI41: =VLOOKUP($C41,'4b) SL EPO Extended Data Sheet'!$A$5:$AC$176,26,FALSE) -> 0.60856021 | AJ41: =VLOOKUP($C41,'4b) SL EPO Extended Data Sheet'!$A$5:$AC$176,27,FALSE) -> 0.20995364 | AK41: =VLOOKUP($C41,'4b) SL EPO Extended Data Sheet'!$A$5:$AC$176,28,FALSE) -> 0.12776943 | AL41: =VLOOKUP($C41,'4b) SL EPO Extended Data Sheet'!$A$6:$AB$176,15,FALSE) -> 45163 | AM41: =VLOOKUP($C41,'4b) SL EPO Extended Data Sheet'!$A$5:$AC$176,29,FALSE) -> G | AO41: =T39-G39 -> 0 | AP41: =T39-K39 -> 0 | AQ41: =X39-I39 -> 0 | AS41: =T39-S39 -> 0 | AT41: =X39-W39 -> 0 | AV41: 158.10532 | AW41: 46951 | AY41: 142.42994 | AZ41: =W41-AY41 -> 0 | BA41: 46951 | BB41: =AA41-BA41 -> 0
A42: =C41 -> Lightly Shielded Store (LSS) | B42: This project will provide safe and secure storage capacity for Contact Handleable Intermediate Level Waste (CHILW) packages until final treatment and disposal. The first project benefit will be receipt of the first package. The CHILW Programme Brief has been endorsed by the SL Enterprise Development Committee (EDC); this includes the LSS1 revised preferred option which incorporates identified optimisation opportunities. The Outline Business Case (OBC) Strategic and Economic Cases have been endorsed in principle by the Enterprise Development Committee (EDC). The project are revising the OBC baseline to align to both the updated preferred option and affordability assumptions. Sellafield Project Execution Review (SPER) commenced in Period 6 for stages 1&2 and is forecast to complete Q3 FY2025/2026, leading to SL Investment Review Panel (IRP) in Q4 FY2025/2026. Current sanction approval gives the project financial coverage until Q4 2026/2027. This sanction enables conclusion of the Appraise & Select phase whilst progressing the Define stage design in parallel, which will maintain momentum on the project critical path until the OBC is approved by HMT during FY2026/2027. Key interfaces will be funded by the Enterprise and provided prior to site establishment, including provision of services to the construction site (power is becoming critical due to lead times of equipment). The Lifecycle EAC decrease, in period, is an error that will be corrected next month. The Baseline and Lifecycle EAC will be updated once the OBC CCR has been implemented. The Capability and Capacity RAG remains Green.
B44: Value Stream: Spent Fuel Management | AO44: =T42-G42 -> 0 | AP44: =T42-K42 -> 0 | AQ44: =X42-I42 -> 0 | AS44: =T42-S42 -> 0 | AT44: =X42-W42 -> 0
B45: Portfolio Summary | AV45: 70.5 | AW45: 46106 | AY45: 72.617237 | AZ45: -72.617237 | BA45: 46106 | BB45: -46106
B47: 35/10505 | C47: SIXEP Receipt Facility | D47: Sellafield | F47: =VLOOKUP($C47,'4b) SL EPO Extended Data Sheet'!$A$5:$AB$176,2,FALSE) -> N/A | G47: =VLOOKUP($C47,'4b) SL EPO Extended Data Sheet'!$A$5:$AB$176,3, FALSE) -> 0 | I47: =VLOOKUP($C47,'4b) SL EPO Extended Data Sheet'!$A$5:$AD$176,30, FALSE) -> N/A (Mar-24) | J47: =VLOOKUP($C47,'4b) SL EPO Extended Data Sheet'!$A$5:$AB$176,6, FALSE)/1000000 -> 87 | K47: =VLOOKUP($C47,'4b) SL EPO Extended Data Sheet'!$A$5:$AB$176,7, FALSE)/1000000 -> 91 | L47: =VLOOKUP($C47,'4b) SL EPO Extended Data Sheet'!$A$5:$AB$176,8, FALSE) | M47: =VLOOKUP($C47,'4b) SL EPO Extended Data Sheet'!$A$5:$AB$176,9, FALSE) -> 47361 | N47: =VLOOKUP($C47,'4b) SL EPO Extended Data Sheet'!$A$5:$AB$176,5, FALSE) -> 45371 | O47: =VLOOKUP($C47,'4b) SL EPO Extended Data Sheet'!$A$5:$AB$176,10, FALSE)/1000000 -> 0 | P47: =VLOOKUP($C47,'4b) SL EPO Extended Data Sheet'!$A$5:$AB$176,11, FALSE)/1000000 -> 53 | R47: =VLOOKUP($C47,'4b) SL EPO Extended Data Sheet'!$A$5:$AB$176,12,FALSE) -> G | S47: 0 | U47: =VLOOKUP($C47,'4b) SL EPO Extended Data Sheet'!$A$5:$AE$176,31,FALSE) -> N/A (Mar-25) | W47: =VLOOKUP($C47,'4b) SL EPO Extended Data Sheet'!$A$5:$AC$176,16,FALSE)/1000000 -> 919.61826 | X47: =VLOOKUP($C47,'4b) SL EPO Extended Data Sheet'!$A$5:$AC$176,17,FALSE)/1000000 -> 920.05646 | Y47: =VLOOKUP($C47,'4b) SL EPO Extended Data Sheet'!$A$5:$AC$176,18,FALSE)/1000000 -> 0 | Z47: =VLOOKUP($C47,'4b) SL EPO Extended Data Sheet'!$A$5:$AB$176,16,FALSE)/1000000 -> 919.61826 | AA47: =VLOOKUP($C47,'4b) SL EPO Extended Data Sheet'!$A$5:$AC$176,19,FALSE) -> 50724 | AB47: =VLOOKUP($C47,'4b) SL EPO Extended Data Sheet'!$A$5:$AC$176,20,FALSE) -> 50724 | AC47: =VLOOKUP($C47,'4b) SL EPO Extended Data Sheet'!$A$5:$AC$176,21,FALSE) -> 0 | AD47: =VLOOKUP($C47,'4b) SL EPO Extended Data Sheet'!$A$5:$AB$176,15,FALSE)/1000000 -> 0.04573 | AE47: =VLOOKUP($C47,'4b) SL EPO Extended Data Sheet'!$A$5:$AC$176,22,FALSE)/1000000 -> 36.213925 | AF47: =VLOOKUP($C47,'4b) SL EPO Extended Data Sheet'!$A$5:$AC$176,23,FALSE)/1000000 -> 38.522021 | AG47: =VLOOKUP($C47,'4b) SL EPO Extended Data Sheet'!$A$5:$AC$176,24,FALSE)/1000000 -> 18.315673 | AH47: =VLOOKUP($C47,'4b) SL EPO Extended Data Sheet'!$A$5:$AC$176,25,FALSE) -> 2.1032272 | AI47: =VLOOKUP($C47,'4b) SL EPO Extended Data Sheet'!$A$5:$AC$176,26,FALSE) -> 1.0637351 | AJ47: =VLOOKUP($C47,'4b) SL EPO Extended Data Sheet'!$A$5:$AC$176,27,FALSE) -> 0.039379301 | AK47: =VLOOKUP($C47,'4b) SL EPO Extended Data Sheet'!$A$5:$AC$176,28,FALSE) -> 0.041889144 | AL47: =VLOOKUP($C47,'4b) SL EPO Extended Data Sheet'!$A$6:$AB$176,15,FALSE) -> 45730 | AM47: =VLOOKUP($C47,'4b) SL EPO Extended Data Sheet'!$A$5:$AC$176,29,FALSE) -> G | AO47: =#REF!-#REF! -> #REF! | AP47: =#REF!-#REF! -> #REF! | AQ47: =#REF!-#REF! -> #REF! | AS47: =#REF!-#REF! -> #REF! | AT47: =#REF!-#REF! -> #REF! | AV47: 920.05646 | AW47: 50724 | AY47: 919.61826 | AZ47: =W47-AY47 -> 0 | BA47: 50724 | BB47: =AA47-BA47 -> 0
A48: =C47 -> SIXEP Receipt Facility | B48: The Receipt Facility will provide additional waste storage capacity until a final waste treatment capability is available to maintain effluent treatment operations and support mission critical activities. The project benefit is the provision of this additional storage capacity. The Strategic Outline Case (SOC) indicates start of active commissioning in 2038. The SOC was approved at Group Investment Committee (GIC) November 2024 with the supporting change control being approved by the NDA and implemented in pd12 FY24/2520. An additional £24m sanction (cumulative £53m) was approved which will take the project to approval of Preferred Option (June 2026 P50, the project is looking to accelerate this to the end of this calendar year) which will include input from the Pumpable Intermediate Level Waste (PILW) study output. The Baseline RAG remains Green. The full lifecycle EAC (£920.1m) is unchanged from last month. This remains marginally higher than the baseline (£919.6m) due to a legacy issue whereby early feasibility scope had to remain on the study project, as part of the first Change Control Record (CCR) in 2023. Work continues on the Enabling Works ground investigation (a separate project) with further progress on other areas of the enabling works design packs (The Enabling Works have now transitioned to PPP). The Enterprise Development Committee (EDC) has approved the Straight to Treatment decision and now the RF project (this project) is starting to ramp down and the new SWMTF (SIXEP Waste Management Treatment Facility) project commencing. This is being funded by this project pending an Investment Review Panel (IRP) paper for re-use of existing sanction that will be presented at the December IRP and GIC meetings. Capability and Capacity RAG remains Green.
B50: Value Stream: Site Projects Office | AO50: =T48-G48 -> 0 | AP50: =T48-K48 -> 0 | AQ50: =X48-I48 -> 0 | AS50: =T48-S48 -> 0 | AT50: =X48-W48 -> 0
B52: Portfolio Summary | AV52: 70.5 | AW52: 46106 | AY52: 72.617237 | AZ52: -72.617237 | BA52: 46106 | BB52: -46106
AO53: =T51-G51 -> 0 | AP53: =T51-K51 -> 0 | AQ53: =X51-I51 -> 0 | AS53: =T51-S51 -> 0 | AT53: =X51-W51 -> 0
B54: 35/10188 | C54: THORP Receipt & Storage Control Systems Replacement | D54: Sellafield | F54: =VLOOKUP($C54,'4b) SL EPO Extended Data Sheet'!$A$5:$AB$176,2,FALSE) -> R | G54: =VLOOKUP($C54,'4b) SL EPO Extended Data Sheet'!$A$5:$AB$176,3, FALSE) -> 0 | I54: =VLOOKUP($C54,'4b) SL EPO Extended Data Sheet'!$A$5:$AD$176,30, FALSE) -> N/A (May-15) | J54: =VLOOKUP($C54,'4b) SL EPO Extended Data Sheet'!$A$5:$AB$176,6, FALSE)/1000000 -> 0 | K54: =VLOOKUP($C54,'4b) SL EPO Extended Data Sheet'!$A$5:$AB$176,7, FALSE)/1000000 -> 0 | L54: =VLOOKUP($C54,'4b) SL EPO Extended Data Sheet'!$A$5:$AB$176,8, FALSE) | M54: =VLOOKUP($C54,'4b) SL EPO Extended Data Sheet'!$A$5:$AB$176,9, FALSE) | N54: =VLOOKUP($C54,'4b) SL EPO Extended Data Sheet'!$A$5:$AB$176,5, FALSE) -> 42125 | O54: =VLOOKUP($C54,'4b) SL EPO Extended Data Sheet'!$A$5:$AB$176,10, FALSE)/1000000 -> 0 | P54: =VLOOKUP($C54,'4b) SL EPO Extended Data Sheet'!$A$5:$AB$176,11, FALSE)/1000000 -> 11.867767 | R54: =VLOOKUP($C54,'4b) SL EPO Extended Data Sheet'!$A$5:$AC$176,12,FALSE) -> R | S54: =VLOOKUP($C54,'4b) SL EPO Extended Data Sheet'!$A$5:$AB$176,13,FALSE) -> 0 | U54: =VLOOKUP($C54,'4b) SL EPO Extended Data Sheet'!$A$5:$AE$176,31,FALSE) -> N/A (Aug-18) | W54: =VLOOKUP($C54,'4b) SL EPO Extended Data Sheet'!$A$5:$AC$176,16,FALSE)/1000000 -> 20.914989 | X54: =VLOOKUP($C54,'4b) SL EPO Extended Data Sheet'!$A$5:$AC$176,17,FALSE)/1000000 -> 23.356291 | Y54: =VLOOKUP($C54,'4b) SL EPO Extended Data Sheet'!$A$5:$AC$176,18,FALSE)/1000000 -> 0.06075403 | Z54: =VLOOKUP($C54,'4b) SL EPO Extended Data Sheet'!$A$5:$AB$176,16,FALSE)/1000000 -> 20.914989 | AA54: =VLOOKUP($C54,'4b) SL EPO Extended Data Sheet'!$A$5:$AC$176,19,FALSE) -> 46356 | AB54: =VLOOKUP($C54,'4b) SL EPO Extended Data Sheet'!$A$5:$AC$176,20,FALSE) -> 48183 | AC54: =VLOOKUP($C54,'4b) SL EPO Extended Data Sheet'!$A$5:$AC$176,21,FALSE) -> 0 | AD54: =VLOOKUP($C54,'4b) SL EPO Extended Data Sheet'!$A$5:$AB$176,15,FALSE)/1000000 -> 0.043332 | AE54: =VLOOKUP($C54,'4b) SL EPO Extended Data Sheet'!$A$5:$AC$176,22,FALSE)/1000000 -> 20.062174 | AF54: =VLOOKUP($C54,'4b) SL EPO Extended Data Sheet'!$A$5:$AC$176,23,FALSE)/1000000 -> 7.7218341 | AG54: =VLOOKUP($C54,'4b) SL EPO Extended Data Sheet'!$A$5:$AC$176,24,FALSE)/1000000 -> 8.9821388 | AH54: =VLOOKUP($C54,'4b) SL EPO Extended Data Sheet'!$A$5:$AC$176,25,FALSE) -> 0.85968769 | AI54: =VLOOKUP($C54,'4b) SL EPO Extended Data Sheet'!$A$5:$AC$176,26,FALSE) -> 0.38489517 | AJ54: =VLOOKUP($C54,'4b) SL EPO Extended Data Sheet'!$A$5:$AC$176,27,FALSE) -> 0.95922472 | AK54: =VLOOKUP($C54,'4b) SL EPO Extended Data Sheet'!$A$5:$AC$176,28,FALSE) -> 0.36920096 | AL54: =VLOOKUP($C54,'4b) SL EPO Extended Data Sheet'!$A$6:$AB$176,15,FALSE) -> 43332 | AM54: =VLOOKUP($C54,'4b) SL EPO Extended Data Sheet'!$A$5:$AC$176,29,FALSE) -> G | AV54: 23.295537 | AW54: 48183 | AY54: 20.914989 | AZ54: =W54-AY54 -> 0 | BA54: 46356 | BB54: =AA54-BA54 -> 0
A55: =C54 -> THORP Receipt & Storage Control Systems Replacement | B55: Within the THORP Receipt and Store (R&S) and Feed pond areas, pond handler machines manoeuvre flasks or skips within the inlet, main and feed ponds, these are the Inlet Pond Handler (IPH); the Main Pond Handler (MPH); the Rack Transfer Machine (RTM). These machines provide the essential material move capability to support fuel reprocessing operations. Each of these pond handlers is controlled by programmable controller systems installed in the late 1980s, which are now obsolete, and spares are increasingly difficult to source. The Delivery Confidence Assessment remains Red, reflecting the history of the project which has suffered several scope and strategy challenges from programme, preventing progress and impacting the baseline. The project was split into six discrete Work Packages, with a phased delivery and sanction strategy, as a single portfolio approved through local Operational Unit Sentencing Board (OUSB) and accepted at the Investment Review Panel (IRP) February 2015. Three of the six work packs had not progressed in over eighteen months due to scope and strategy changes emerging from the programme and a Change Control Request (CCR) has been implemented to remove this scope. The remainder of the scope is currently under consideration for a further CCR with baseline management. Project cost forecast increase due to internal labour forecast, resulting from extra effort in period to collaboratively progress design assurance to ascertain suitable way forward. Capability and Capacity RAG remains Green, reflecting the scope of 35/10188. Resources are assigned to support deliverability
AO56: =T54-G54 -> 0 | AP56: =T54-K54 -> 0 | AQ56: =X54-I54 -> #VALUE! | AS56: =T54-S54 -> 0 | AT56: =X54-W54 -> 2.4413019
B57: 35/09140 | C57: Electrical Supply - New Construction | D57: Sellafield | F57: =VLOOKUP(C57,'5a)NDA MPPR'!$B$9:$AK$61,3,FALSE) -> A | G57: =VLOOKUP(C57,'5a)NDA MPPR'!$B$9:$AK$61,4,FALSE) -> 0 | I57: =VLOOKUP(C57,'5a)NDA MPPR'!$B$9:$AK$61,6,FALSE) -> FBC (May-23) | J57: =VLOOKUP(C57,'5a)NDA MPPR'!$B$9:$AK$61,7,FALSE) -> 403.5 | K57: =VLOOKUP(C57,'5a)NDA MPPR'!$B$9:$AK$61,8,FALSE) -> 430.4 | L57: =VLOOKUP(C57,'5a)NDA MPPR'!$B$9:$AK$61,9,FALSE) -> 47362 | M57: =VLOOKUP(C57,'5a)NDA MPPR'!$B$9:$AK$61,10,FALSE) -> 47665 | O57: =VLOOKUP(C57,'5a)NDA MPPR'!$B$9:$AK$61,12,FALSE) -> 430.4 | P57: =VLOOKUP(C57,'5a)NDA MPPR'!$B$9:$AK$61,13,FALSE) -> 403.5 | R57: =VLOOKUP(C57,'5a)NDA MPPR'!$B$9:$AK$61,15,FALSE) -> A | S57: =VLOOKUP(C57,'5a)NDA MPPR'!$B$9:$AK$61,16,FALSE) -> 0 | U57: =VLOOKUP(C57,'5a)NDA MPPR'!$B$9:$AK$61,18,FALSE) -> FBC (Jan-23) | W57: =VLOOKUP(C57,'5a)NDA MPPR'!$B$9:$AK$61,20,FALSE) -> 435.38198 | X57: =VLOOKUP(C57,'5a)NDA MPPR'!$B$9:$AK$61,21,FALSE) -> 427.81347 | Y57: =VLOOKUP(C57,'5a)NDA MPPR'!$B$9:$AK$61,22,FALSE) -> -0.1 | AA57: =VLOOKUP(C57,'5a)NDA MPPR'!$B$9:$AK$61,24,FALSE) -> 47364 | AB57: =VLOOKUP(C57,'5a)NDA MPPR'!$B$9:$AK$61,25,FALSE) -> 47826 | AC57: =VLOOKUP(C57,'5a)NDA MPPR'!$B$9:$AK$61,26,FALSE) -> 0 | AE57: =VLOOKUP(C57,'5a)NDA MPPR'!$B$9:$AK$61,28,FALSE) -> 335.61003 | AF57: =VLOOKUP(C57,'5a)NDA MPPR'!$B$9:$AK$61,29,FALSE) -> 300.59318 | AG57: =VLOOKUP(C57,'5a)NDA MPPR'!$B$9:$AK$61,30,FALSE) -> 297.43585 | AH57: =VLOOKUP(C57,'5a)NDA MPPR'!$B$9:$AK$61,31,FALSE) -> 1.0106152 | AI57: =VLOOKUP(C57,'5a)NDA MPPR'!$B$9:$AK$61,32,FALSE) -> 0.89566208 | AJ57: =VLOOKUP(C57,'5a)NDA MPPR'!$B$9:$AK$61,33,FALSE) -> 0.77084043 | AK57: =VLOOKUP(C57,'5a)NDA MPPR'!$B$9:$AK$61,34,FALSE) -> 0.69041254 | AM57: =VLOOKUP(C57,'5a)NDA MPPR'!$B$9:$AK$61,36,FALSE) -> A | AV57: 427.94134 | AW57: 47826 | AY57: 435.38198 | AZ57: =W57-AY57 -> 0 | BA57: 47364 | BB57: =AA57-BA57 -> 0
A58: =C57 -> Electrical Supply - New Construction | B58: =VLOOKUP($C57,'5a)NDA MPPR'!$A$9:$AK$61,2,FALSE) -> The Electrical Distribution Network Upgrade Project (EDNUP) relates to the refurbishment of the Sellafield Site’s electricity network. The project will bolster the emergency power generation capability and improve site resilience which is important particularly in the event of a National Grid failure. The Delivery Confidence Assessment remains at Amber noting that the latest forecast for completion exceeds the current P80. An update paper was acknowledged at NDA GIC in June 2025, which noted that a P80 draw down will be necessary to enable continuity of project delivery (current forecast required in 2026/27 Q1). The full lifecycle cost forecast is stable in period although under significant increasing pressure from strike delay costs and further realised risks with in-ground conditions and increases in subcontract costs. The further review of the P50 to P80 delta and inflationary impact will be included in the next sanction request. The schedule is stable with no overall movement to the end date in period, although realised risks and strike action are impacting schedule float. The baseline RAG remains Amber as the project completion date is beyond the P50 baseline. The current P50 baseline and approved NDA sanction differs as a result of indexation and historical positive cost variance on the project pre implementation of change control associated with the Full Business Case (FBC) resubmission. The project plan and progress to date indicates a steady recovery of the variance. Grid Transformer 2 has now been re-energised and grid power is now available to the new Sub111, which is the first new substation asset to be delivered by EDNUP, with grid connection allowing for future asset risk reduction benefits . Cable route construction is progressing on multiple fronts, including a ringfenced risk mitigation advanced dig team who are discovering a significant number of uncharted services and obstructions. Reoccurrences of radiological contamination are hindering interconnector critical path progress and causing reducing overall project float. A peer assist has identified opportunities to improve delivery arrangements in future changeover stages and interconnector delivery, which will be developed over the coming periods. Strike action has impacted several workfaces including the temporary cable installation which will mitigate delays to electrical isolations necessary for excavations near aged buried cables. Management and characterisation of waste from the site continues to be onerous. The Capability and Capacity RAG remains at Amber in period due to Pre-Operations, Construction and Protection Engineer resource issues, which are now becoming critical, with timescales for backfill still to be determined.
AO59: =T57-G57 -> 0 | AP59: =T57-K57 -> -430.4 | AQ59: =X57-I57 -> #VALUE! | AS59: =T57-S57 -> 0 | AT59: =X57-W57 -> -7.5685059
B60: 35/10192 | C60: TR&S Replacement Cooling System | D60: Sellafield | F60: =VLOOKUP($C60,'4b) SL EPO Extended Data Sheet'!$A$5:$AB$176,2,FALSE) -> A | G60: =VLOOKUP($C60,'4b) SL EPO Extended Data Sheet'!$A$5:$AB$176,3, FALSE) -> 0 | I60: =VLOOKUP($C60,'4b) SL EPO Extended Data Sheet'!$A$5:$AD$176,30, FALSE) -> SOC (Apr-24) | J60: =VLOOKUP($C60,'4b) SL EPO Extended Data Sheet'!$A$5:$AB$176,6, FALSE)/1000000 -> 16 | K60: =VLOOKUP($C60,'4b) SL EPO Extended Data Sheet'!$A$5:$AB$176,7, FALSE)/1000000 -> 17 | L60: =VLOOKUP($C60,'4b) SL EPO Extended Data Sheet'!$A$5:$AB$176,8, FALSE) -> 48519 | M60: =VLOOKUP($C60,'4b) SL EPO Extended Data Sheet'!$A$5:$AB$176,9, FALSE) | N60: =VLOOKUP($C60,'4b) SL EPO Extended Data Sheet'!$A$5:$AB$176,5, FALSE) -> 45394 | O60: =VLOOKUP($C60,'4b) SL EPO Extended Data Sheet'!$A$5:$AB$176,10, FALSE)/1000000 -> 0 | P60: =VLOOKUP($C60,'4b) SL EPO Extended Data Sheet'!$A$5:$AB$176,11, FALSE)/1000000 -> 16 | R60: =VLOOKUP($C60,'4b) SL EPO Extended Data Sheet'!$A$5:$AB$176,12,FALSE) -> A | S60: =VLOOKUP($C60,'4b) SL EPO Extended Data Sheet'!$A$5:$AB$176,13,FALSE) -> -1 | U60: =VLOOKUP($C60,'4b) SL EPO Extended Data Sheet'!$A$5:$AE$176,31,FALSE) -> SOC (Feb-24) | W60: =VLOOKUP($C60,'4b) SL EPO Extended Data Sheet'!$A$5:$AC$176,16,FALSE)/1000000 -> 155.65567 | X60: =VLOOKUP($C60,'4b) SL EPO Extended Data Sheet'!$A$5:$AC$176,17,FALSE)/1000000 -> 159.01226 | Y60: =VLOOKUP($C60,'4b) SL EPO Extended Data Sheet'!$A$5:$AC$176,18,FALSE)/1000000 -> 0.02984795 | Z60: =VLOOKUP($C60,'4b) SL EPO Extended Data Sheet'!$A$5:$AB$176,16,FALSE)/1000000 -> 155.65567 | AA60: =VLOOKUP($C60,'4b) SL EPO Extended Data Sheet'!$A$5:$AC$176,19,FALSE) -> 48530 | AB60: =VLOOKUP($C60,'4b) SL EPO Extended Data Sheet'!$A$5:$AC$176,20,FALSE) -> 48530 | AC60: =VLOOKUP($C60,'4b) SL EPO Extended Data Sheet'!$A$5:$AC$176,21,FALSE) -> 0 | AD60: =VLOOKUP($C60,'4b) SL EPO Extended Data Sheet'!$A$5:$AB$176,15,FALSE)/1000000 -> 0.04533 | AE60: =VLOOKUP($C60,'4b) SL EPO Extended Data Sheet'!$A$5:$AC$176,22,FALSE)/1000000 -> 9.8565824 | AF60: =VLOOKUP($C60,'4b) SL EPO Extended Data Sheet'!$A$5:$AC$176,23,FALSE)/1000000 -> 7.0608812 | AG60: =VLOOKUP($C60,'4b) SL EPO Extended Data Sheet'!$A$5:$AC$176,24,FALSE)/1000000 -> 10.352648 | AH60: =VLOOKUP($C60,'4b) SL EPO Extended Data Sheet'!$A$5:$AC$176,25,FALSE) -> 0.68203628 | AI60: =VLOOKUP($C60,'4b) SL EPO Extended Data Sheet'!$A$5:$AC$176,26,FALSE) -> 0.71636202 | AJ60: =VLOOKUP($C60,'4b) SL EPO Extended Data Sheet'!$A$5:$AC$176,27,FALSE) -> 0.063322991 | AK60: =VLOOKUP($C60,'4b) SL EPO Extended Data Sheet'!$A$5:$AC$176,28,FALSE) -> 0.045362186 | AL60: =VLOOKUP($C60,'4b) SL EPO Extended Data Sheet'!$A$6:$AB$176,15,FALSE) -> 45330 | AM60: =VLOOKUP($C60,'4b) SL EPO Extended Data Sheet'!$A$5:$AC$176,29,FALSE) -> A | AV60: 158.96283 | AW60: 48530 | AY60: 155.65567 | AZ60: =W60-AY60 -> 0 | BA60: 48530 | BB60: =AA60-BA60 -> 0
A61: =C60 -> TR&S Replacement Cooling System | B61: This project is to provide the long-term cooling requirements for Thorp Receipt and Storage (TR&S) facility. The first project benefit is to provide a modern and efficient cooling system to support the unconstrained & timely import of the Advanced Gas Reactor (AGR) Fuel for Long Term Interim Safe Storage. This period, the Delivery Confidence Assessment remains Amber, following evaluation of the decision to relocate the cooling system from the South to East side of the building. Baseline RAG status has changed to Amber this period whilst the project team continue a review the impact of the strategic change on the get to gate plan (movement of Plant and Equipment Room from Product Zone). The Capability and Capacity RAG remains Amber due to the resource shortfalls now affecting delivery confidence. Senior Project Engineering Manager, Project Controls (P/T) and Commercial lead are required, a Senior Project Manager and Project Controls Manager were appointed during Period 7.
B63: 35/09244 | C63: FGFL Ventilation Extract System Upgrade | D63: Sellafield | F63: =VLOOKUP($C63,'4b) SL EPO Extended Data Sheet'!$A$5:$AB$176,2,FALSE) -> G | G63: =VLOOKUP($C63,'4b) SL EPO Extended Data Sheet'!$A$5:$AB$176,3, FALSE) -> 0 | I63: =VLOOKUP($C63,'4b) SL EPO Extended Data Sheet'!$A$5:$AD$176,30, FALSE) -> SOC (Mar-22) | J63: =VLOOKUP($C63,'4b) SL EPO Extended Data Sheet'!$A$5:$AB$176,6, FALSE)/1000000 -> 67.607 | K63: =VLOOKUP($C63,'4b) SL EPO Extended Data Sheet'!$A$5:$AB$176,7, FALSE)/1000000 -> 94.587 | L63: =VLOOKUP($C63,'4b) SL EPO Extended Data Sheet'!$A$5:$AB$176,8, FALSE) | M63: =VLOOKUP($C63,'4b) SL EPO Extended Data Sheet'!$A$5:$AB$176,9, FALSE) | O63: =VLOOKUP($C63,'4b) SL EPO Extended Data Sheet'!$A$5:$AB$176,10, FALSE)/1000000 -> 0 | P63: =VLOOKUP($C63,'4b) SL EPO Extended Data Sheet'!$A$5:$AB$176,11, FALSE)/1000000 -> 19.209 | R63: =VLOOKUP($C63,'4b) SL EPO Extended Data Sheet'!$A$5:$AB$176,12,FALSE) -> A | S63: =VLOOKUP($C63,'4b) SL EPO Extended Data Sheet'!$A$5:$AB$176,13,FALSE) -> 0 | U63: =VLOOKUP($C63,'4b) SL EPO Extended Data Sheet'!$A$5:$AE$176,31,FALSE) -> SOC (Feb-23) | W63: =VLOOKUP($C63,'4b) SL EPO Extended Data Sheet'!$A$5:$AC$176,16,FALSE)/1000000 -> 66.045682 | X63: =VLOOKUP($C63,'4b) SL EPO Extended Data Sheet'!$A$5:$AC$176,17,FALSE)/1000000 -> 84.193985 | Y63: =VLOOKUP($C63,'4b) SL EPO Extended Data Sheet'!$A$5:$AC$176,18,FALSE)/1000000 -> -0.26673302 | Z63: =VLOOKUP($C63,'4b) SL EPO Extended Data Sheet'!$A$5:$AB$176,16,FALSE)/1000000 -> 66.045682 | AA63: =VLOOKUP($C63,'4b) SL EPO Extended Data Sheet'!$A$5:$AC$176,19,FALSE) -> 48760 | AB63: =VLOOKUP($C63,'4b) SL EPO Extended Data Sheet'!$A$5:$AC$176,20,FALSE) -> 49061 | AC63: =VLOOKUP($C63,'4b) SL EPO Extended Data Sheet'!$A$5:$AC$176,21,FALSE) -> 0 | AD63: =VLOOKUP($C63,'4b) SL EPO Extended Data Sheet'!$A$5:$AB$176,15,FALSE)/1000000 -> 0.044966 | AE63: =VLOOKUP($C63,'4b) SL EPO Extended Data Sheet'!$A$5:$AC$176,22,FALSE)/1000000 -> 25.50187 | AF63: =VLOOKUP($C63,'4b) SL EPO Extended Data Sheet'!$A$5:$AC$176,23,FALSE)/1000000 -> 21.477604 | AG63: =VLOOKUP($C63,'4b) SL EPO Extended Data Sheet'!$A$5:$AC$176,24,FALSE)/1000000 -> 16.377628 | AH63: =VLOOKUP($C63,'4b) SL EPO Extended Data Sheet'!$A$5:$AC$176,25,FALSE) -> 1.3113989 | AI63: =VLOOKUP($C63,'4b) SL EPO Extended Data Sheet'!$A$5:$AC$176,26,FALSE) -> 0.84219722 | AJ63: =VLOOKUP($C63,'4b) SL EPO Extended Data Sheet'!$A$5:$AC$176,27,FALSE) -> 0.38612471 | AK63: =VLOOKUP($C63,'4b) SL EPO Extended Data Sheet'!$A$5:$AC$176,28,FALSE) -> 0.32519316 | AL63: =VLOOKUP($C63,'4b) SL EPO Extended Data Sheet'!$A$6:$AB$176,15,FALSE) -> 44966 | AM63: =VLOOKUP($C63,'4b) SL EPO Extended Data Sheet'!$A$5:$AC$176,29,FALSE) -> A | AV63: 84.460718 | AW63: 49061 | AY63: 66.045682 | AZ63: =W63-AY63 -> 0 | BA63: 48760 | BB63: =AA63-BA63 -> 0
A64: =C63 -> FGFL Ventilation Extract System Upgrade | B64: The Ventilation Extract System Upgrade (VESU) project is required to replace the existing ventilation system in Special Nuclear Materials (SNM), the current system is in a degraded state and requires replacement. The first project benefit is the capability of a new ventilation system that meets all regulations and enables safe operations. Project Lifecycle: Stage 3 - Define stage via continuity funding whilst proceeding through sanction. The Delivery Confidence Assessment RAG remains Green. An Infrastructure and Projects Authority (IPA) style review took place in May 2025 and achieved an Amber/Green. The Outline Business Case (OBC) predicted to be at Government Q4 2025/26. Completed Investment Review Panel (IRP) in October 2025. now progressing to NDA GIC November 2025. The baseline RAG is Amber and will remain Amber until the OBC Change Control request (CCR) is implemented (Q4 2025/26). There is a discrepancy of £950k for costs prior to Performance Plan 2014, this is under review by reporting team, the EAC is to be reviewed as no change was expected this period. Schedule is reflective of the requirement to proceed to Government to secure sanction. Capability & Capacity RAG is Amber due to delay in securing sanction which places resources at risk.
B66: 35/09357 | C66: PMF North Transfers Project | D66: Sellafield | F66: =VLOOKUP($C66,'4b) SL EPO Extended Data Sheet'!$A$5:$AB$176,2,FALSE) -> G | G66: =VLOOKUP($C66,'4b) SL EPO Extended Data Sheet'!$A$5:$AB$176,3, FALSE) -> 1 | I66: =VLOOKUP($C66,'4b) SL EPO Extended Data Sheet'!$A$5:$AD$176,30, FALSE) -> OBC (Feb-21) | J66: =VLOOKUP($C66,'4b) SL EPO Extended Data Sheet'!$A$5:$AB$176,6, FALSE)/1000000 -> 30.216 | K66: =VLOOKUP($C66,'4b) SL EPO Extended Data Sheet'!$A$5:$AB$176,7, FALSE)/1000000 -> 31.312 | L66: =VLOOKUP($C66,'4b) SL EPO Extended Data Sheet'!$A$5:$AB$176,8, FALSE) -> 46660 | M66: =VLOOKUP($C66,'4b) SL EPO Extended Data Sheet'!$A$5:$AB$176,9, FALSE) -> 46782 | O66: =VLOOKUP($C66,'4b) SL EPO Extended Data Sheet'!$A$5:$AB$176,10, FALSE)/1000000 -> 0 | P66: =VLOOKUP($C66,'4b) SL EPO Extended Data Sheet'!$A$5:$AB$176,11, FALSE)/1000000 -> 13.911625 | R66: =VLOOKUP($C66,'4b) SL EPO Extended Data Sheet'!$A$5:$AB$176,12,FALSE) -> G | S66: =VLOOKUP($C66,'4b) SL EPO Extended Data Sheet'!$A$5:$AB$176,13,FALSE) -> 1 | U66: =VLOOKUP($C66,'4b) SL EPO Extended Data Sheet'!$A$5:$AE$176,31,FALSE) -> OBC (Aug-21) | W66: =VLOOKUP($C66,'4b) SL EPO Extended Data Sheet'!$A$5:$AC$176,16,FALSE)/1000000 -> 36.101355 | X66: =VLOOKUP($C66,'4b) SL EPO Extended Data Sheet'!$A$5:$AC$176,17,FALSE)/1000000 -> 38.276981 | Y66: =VLOOKUP($C66,'4b) SL EPO Extended Data Sheet'!$A$5:$AC$176,18,FALSE)/1000000 -> -2e-08 | Z66: =VLOOKUP($C66,'4b) SL EPO Extended Data Sheet'!$A$5:$AB$176,16,FALSE)/1000000 -> 36.101355 | AA66: =VLOOKUP($C66,'4b) SL EPO Extended Data Sheet'!$A$5:$AC$176,19,FALSE) -> 47367 | AB66: =VLOOKUP($C66,'4b) SL EPO Extended Data Sheet'!$A$5:$AC$176,20,FALSE) -> 47367 | AC66: =VLOOKUP($C66,'4b) SL EPO Extended Data Sheet'!$A$5:$AC$176,21,FALSE) -> 27 | AD66: =VLOOKUP($C66,'4b) SL EPO Extended Data Sheet'!$A$5:$AB$176,15,FALSE)/1000000 -> 0.044439 | AE66: =VLOOKUP($C66,'4b) SL EPO Extended Data Sheet'!$A$5:$AC$176,22,FALSE)/1000000 -> 14.96497 | AF66: =VLOOKUP($C66,'4b) SL EPO Extended Data Sheet'!$A$5:$AC$176,23,FALSE)/1000000 -> 14.96497 | AG66: =VLOOKUP($C66,'4b) SL EPO Extended Data Sheet'!$A$5:$AC$176,24,FALSE)/1000000 -> 10.956863 | AH66: =VLOOKUP($C66,'4b) SL EPO Extended Data Sheet'!$A$5:$AC$176,25,FALSE) -> 1.3658078 | AI66: =VLOOKUP($C66,'4b) SL EPO Extended Data Sheet'!$A$5:$AC$176,26,FALSE) -> 0.99999999 | AJ66: =VLOOKUP($C66,'4b) SL EPO Extended Data Sheet'!$A$5:$AC$176,27,FALSE) -> 0.41452654 | AK66: =VLOOKUP($C66,'4b) SL EPO Extended Data Sheet'!$A$5:$AC$176,28,FALSE) -> 0.41452654 | AL66: =VLOOKUP($C66,'4b) SL EPO Extended Data Sheet'!$A$6:$AB$176,15,FALSE) -> 44439 | AM66: =VLOOKUP($C66,'4b) SL EPO Extended Data Sheet'!$A$5:$AC$176,29,FALSE) -> G | AV66: 38.276981 | AW66: 47340 | AY66: 36.101355 | AZ66: =W66-AY66 -> 0 | BA66: 46653 | BB66: =AA66-BA66 -> 714
A67: =C66 -> PMF North Transfers Project | B67: The Plutonium Management Facility (PMF) North Transfers Project will deliver the capability to retrieve and transport Safety Function Class (SFC) 1 packages from Special Nuclear Materials (SNM) North Stores to the Sellafield Product and Residue Store Retreatment Plant (SRP), enabling the retreatment and repackaging of plutonium for long term, safe and secure storage. The Delivery Confidence Assessment is Green based on the recent re-baseline, which was approved October 2025. This change was requested by programme following scope change which required additional engineering and safety assessments. Current SRP delivery dates are unaffected by this change. Baseline RAG rating is Green following the approval of the Investment Review Panel (IRP) paper. A Change Control request (CCR) for this change was implemented in October 2025. The project remains on track to realise project and NDA benefits. The capability and capacity RAG status is Green due to adequate resources being in place to deliver the scope. North Transfers Project will commence get to gate activities in November 2025.
AO68: =T66-G66 -> -1 | AP68: =T66-K66 -> -31.312 | AQ68: =X66-I66 -> #VALUE! | AS68: =T66-S66 -> -1 | AT68: =X66-W66 -> 2.1756265
B69: 35/10151 | C69: FHP & SIXEP Roof Replacement | D69: Sellafield | F69: =VLOOKUP($C69,'4b) SL EPO Extended Data Sheet'!$A$5:$AB$176,2,FALSE) -> G | G69: =VLOOKUP($C69,'4b) SL EPO Extended Data Sheet'!$A$5:$AB$176,3, FALSE) -> 0 | I69: =VLOOKUP($C69,'4b) SL EPO Extended Data Sheet'!$A$5:$AD$176,30, FALSE) -> OBC (Jan-25) | J69: =VLOOKUP($C69,'4b) SL EPO Extended Data Sheet'!$A$5:$AB$176,6, FALSE)/1000000 -> 28.586 | K69: =VLOOKUP($C69,'4b) SL EPO Extended Data Sheet'!$A$5:$AB$176,7, FALSE)/1000000 -> 29.889 | L69: =VLOOKUP($C69,'4b) SL EPO Extended Data Sheet'!$A$5:$AB$176,8, FALSE) -> 48373 | M69: =VLOOKUP($C69,'4b) SL EPO Extended Data Sheet'!$A$5:$AB$176,9, FALSE) -> 48373 | N69: =VLOOKUP($C69,'4b) SL EPO Extended Data Sheet'!$A$5:$AB$176,5, FALSE) -> 45681 | O69: =VLOOKUP($C69,'4b) SL EPO Extended Data Sheet'!$A$5:$AB$176,10, FALSE)/1000000 -> 0 | P69: =VLOOKUP($C69,'4b) SL EPO Extended Data Sheet'!$A$5:$AB$176,11, FALSE)/1000000 -> 3.30948 | R69: =VLOOKUP($C69,'4b) SL EPO Extended Data Sheet'!$A$5:$AB$176,12,FALSE) -> G | S69: =VLOOKUP($C69,'4b) SL EPO Extended Data Sheet'!$A$5:$AB$176,13,FALSE) -> 0 | U69: =VLOOKUP($C69,'4b) SL EPO Extended Data Sheet'!$A$5:$AE$176,31,FALSE) -> OBC (Mar-25) | W69: =VLOOKUP($C69,'4b) SL EPO Extended Data Sheet'!$A$5:$AC$176,16,FALSE)/1000000 -> 26.545167 | X69: =VLOOKUP($C69,'4b) SL EPO Extended Data Sheet'!$A$5:$AC$176,17,FALSE)/1000000 -> 39.734258 | Y69: =VLOOKUP($C69,'4b) SL EPO Extended Data Sheet'!$A$5:$AC$176,18,FALSE)/1000000 -> 13.520627 | Z69: =VLOOKUP($C69,'4b) SL EPO Extended Data Sheet'!$A$5:$AB$176,16,FALSE)/1000000 -> 26.545167 | AA69: =VLOOKUP($C69,'4b) SL EPO Extended Data Sheet'!$A$5:$AC$176,19,FALSE) -> 48374 | AB69: =VLOOKUP($C69,'4b) SL EPO Extended Data Sheet'!$A$5:$AC$176,20,FALSE) -> 48410 | AC69: =VLOOKUP($C69,'4b) SL EPO Extended Data Sheet'!$A$5:$AC$176,21,FALSE) -> 0 | AD69: =VLOOKUP($C69,'4b) SL EPO Extended Data Sheet'!$A$5:$AB$176,15,FALSE)/1000000 -> 0.04572 | AE69: =VLOOKUP($C69,'4b) SL EPO Extended Data Sheet'!$A$5:$AC$176,22,FALSE)/1000000 -> 3.0325401 | AF69: =VLOOKUP($C69,'4b) SL EPO Extended Data Sheet'!$A$5:$AC$176,23,FALSE)/1000000 -> 3.0156972 | AG69: =VLOOKUP($C69,'4b) SL EPO Extended Data Sheet'!$A$5:$AC$176,24,FALSE)/1000000 -> 3.0152259 | AH69: =VLOOKUP($C69,'4b) SL EPO Extended Data Sheet'!$A$5:$AC$176,25,FALSE) -> 1.0001563 | AI69: =VLOOKUP($C69,'4b) SL EPO Extended Data Sheet'!$A$5:$AC$176,26,FALSE) -> 0.99444595 | AJ69: =VLOOKUP($C69,'4b) SL EPO Extended Data Sheet'!$A$5:$AC$176,27,FALSE) -> 0.11424076 | AK69: =VLOOKUP($C69,'4b) SL EPO Extended Data Sheet'!$A$5:$AC$176,28,FALSE) -> 0.11360626 | AL69: =VLOOKUP($C69,'4b) SL EPO Extended Data Sheet'!$A$6:$AB$176,15,FALSE) -> 45720 | AM69: =VLOOKUP($C69,'4b) SL EPO Extended Data Sheet'!$A$5:$AC$176,29,FALSE) -> A | AV69: 26.210706 | AW69: 48410 | AY69: 26.545167 | AZ69: =W69-AY69 -> 0 | BA69: 48374 | BB69: =AA69-BA69 -> 0
A70: =C69 -> FHP & SIXEP Roof Replacement | B70: The scope of this project is to remove and replace the existing Fuel Handling Plant (FHP) and Site Ion Exchange Effluent Plant (SIXEP) roofs with a new Kalzip Roof. The first project benefit to be realised will be the completion of the SIXEP Roof, enabling them to continue in delivery of their mission through to completion with the same benefit being realised for FHP some years later. The Delivery Confidence Assessment is Green following the approval of the revised OBC at OUSB. The Baseline is Green and will remain green for the foreseeable future, SPER has been completed this period with minimal findings so remains on track for IRP in December. The Capability & Capacity RAG has remained at Amber. This will move to green once approval is gained at IRP and the contracts are in place to progress this project through to completion, not expected until Q4 FY 2025/26. Whole Life EAC has increased inline with Estimate produced for FBC. The FBC is scheduled to go to the Investment Review Committee (IRP) on the 1st December 2025, with CCR implementation forecast for February 2026.
AO71: =T69-G69 -> 0 | AP71: =T69-K69 -> -29.889 | AQ71: =X69-I69 -> #VALUE! | AS71: =T69-S69 -> 0 | AT71: =X69-W69 -> 13.189091
B72: 35/10565 | C72: EMRMS (Emergency Management Radiological Monitoring System) | D72: Sellafield | F72: =VLOOKUP($C72,'4b) SL EPO Extended Data Sheet'!$A$5:$AB$176,2,FALSE) -> G | G72: =VLOOKUP($C72,'4b) SL EPO Extended Data Sheet'!$A$5:$AB$176,3, FALSE) -> 0 | I72: =VLOOKUP($C72,'4b) SL EPO Extended Data Sheet'!$A$5:$AD$176,30, FALSE) -> SOC (Sep-23) | J72: =VLOOKUP($C72,'4b) SL EPO Extended Data Sheet'!$A$5:$AB$176,6, FALSE)/1000000 -> 2.173096 | K72: =VLOOKUP($C72,'4b) SL EPO Extended Data Sheet'!$A$5:$AB$176,7, FALSE)/1000000 -> 0 | L72: =VLOOKUP($C72,'4b) SL EPO Extended Data Sheet'!$A$5:$AB$176,8, FALSE) -> 46722 | M72: =VLOOKUP($C72,'4b) SL EPO Extended Data Sheet'!$A$5:$AB$176,9, FALSE) | N72: =VLOOKUP($C72,'4b) SL EPO Extended Data Sheet'!$A$5:$AB$176,5, FALSE) -> 45170 | O72: =VLOOKUP($C72,'4b) SL EPO Extended Data Sheet'!$A$5:$AB$176,10, FALSE)/1000000 -> 0 | P72: =VLOOKUP($C72,'4b) SL EPO Extended Data Sheet'!$A$5:$AB$176,11, FALSE)/1000000 -> 2.173096 | R72: =VLOOKUP($C72,'4b) SL EPO Extended Data Sheet'!$A$5:$AB$176,12,FALSE) -> G | S72: =VLOOKUP($C72,'4b) SL EPO Extended Data Sheet'!$A$5:$AB$176,13,FALSE) -> 0 | U72: =VLOOKUP($C72,'4b) SL EPO Extended Data Sheet'!$A$5:$AE$176,31,FALSE) -> SOC (Sep-23) | W72: =VLOOKUP($C72,'4b) SL EPO Extended Data Sheet'!$A$5:$AC$176,16,FALSE)/1000000 -> 32.152519 | X72: =VLOOKUP($C72,'4b) SL EPO Extended Data Sheet'!$A$5:$AC$176,17,FALSE)/1000000 -> 32.00067 | Y72: =VLOOKUP($C72,'4b) SL EPO Extended Data Sheet'!$A$5:$AC$176,18,FALSE)/1000000 -> 0.38633336 | Z72: =VLOOKUP($C72,'4b) SL EPO Extended Data Sheet'!$A$5:$AB$176,16,FALSE)/1000000 -> 32.152519 | AA72: =VLOOKUP($C72,'4b) SL EPO Extended Data Sheet'!$A$5:$AC$176,19,FALSE) -> 46744 | AB72: =VLOOKUP($C72,'4b) SL EPO Extended Data Sheet'!$A$5:$AC$176,20,FALSE) -> 46744 | AC72: =VLOOKUP($C72,'4b) SL EPO Extended Data Sheet'!$A$5:$AC$176,21,FALSE) -> 0 | AD72: =VLOOKUP($C72,'4b) SL EPO Extended Data Sheet'!$A$5:$AB$176,15,FALSE)/1000000 -> 0.045188 | AE72: =VLOOKUP($C72,'4b) SL EPO Extended Data Sheet'!$A$5:$AC$176,22,FALSE)/1000000 -> 2.264228 | AF72: =VLOOKUP($C72,'4b) SL EPO Extended Data Sheet'!$A$5:$AC$176,23,FALSE)/1000000 -> 1.4955498 | AG72: =VLOOKUP($C72,'4b) SL EPO Extended Data Sheet'!$A$5:$AC$176,24,FALSE)/1000000 -> 1.3249386 | AH72: =VLOOKUP($C72,'4b) SL EPO Extended Data Sheet'!$A$5:$AC$176,25,FALSE) -> 1.1287691 | AI72: =VLOOKUP($C72,'4b) SL EPO Extended Data Sheet'!$A$5:$AC$176,26,FALSE) -> 0.66051199 | AJ72: =VLOOKUP($C72,'4b) SL EPO Extended Data Sheet'!$A$5:$AC$176,27,FALSE) -> 0.070421482 | AK72: =VLOOKUP($C72,'4b) SL EPO Extended Data Sheet'!$A$5:$AC$176,28,FALSE) -> 0.046514233 | AL72: =VLOOKUP($C72,'4b) SL EPO Extended Data Sheet'!$A$6:$AB$176,15,FALSE) -> 45188 | AM72: =VLOOKUP($C72,'4b) SL EPO Extended Data Sheet'!$A$5:$AC$176,29,FALSE) -> G | AV72: 31.614337 | AW72: 46744 | AY72: 32.152519 | AZ72: =W72-AY72 -> 0 | BA72: 46744 | BB72: =AA72-BA72 -> 0
A73: =C72 -> EMRMS (Emergency Management Radiological Monitoring System) | B73: The Emergency Management Radiological Monitoring System (EMRMS) Project is being developed to replace both the Site Perimeter Monitoring System (SPMS) and the Site Emergency Monitoring Point System (SEMPS) which are both beyond their designed lifespans. The Delivery Confidence Assessment (DCA) remains Green that represents delivery against the Strategic Outline Case (SOC) that was approved by the Environment, Safety and Security (E&SS) Asset Management and Oversight Committee (AMOC) in September 2023 and storyboard approval at Security and Resilience (S&R) Operating Unit Sentencing board (OUSB) in March 2024. The project Outline Requirements Specification (ORS) and Project Functional Specifications (PFS) have both been approved, however, upon review by the requirements Management Capability it was deemed that some improvements could be made and these are being incorporated before the next gate. The next project benefit which is the Single Viable Option (SVO) was agreed in March 2025. The project has developed and assured a Single Preferred (engineering) Solution (SPS) which will be subjected to an Infrastructure Design Engineering assurance review in November 2025. The project team augmentation for the key supply chain proposal is complete, noting this has been approved at Infrastructure Strategic Alliance (ISA) Change Board and noted at S&R Ops Board in December 2024 and now includes Sellafield Project Execution Review (SPER) support from the relevant Responsible Engineers (RE’s). The end of phase date is now deemed to be April 2026 and has been affected by the resource augmentation and design impact assessment which highlighted the need, agreed (6th June 2025) at the PFS review, for capturing the Plume Assessment recommendations. The Outline Business Case (OBC) development has recommenced on confirmation of the supply chain resource augmentation, capture of the Plume Assessment recommendations and development of the Delivery Strategy. Although additional scope and the requirements are better understood, and are being addressed, the Delivery Confidence Assessment and baseline RAG status remains green as a new estimate has been developed. Capability and Capacity RAG status remains Green as the impact assessment is fully understood as this has affected the proposed SPER and Sanction request dates. The team are aligning the EAC forecast with the P50 estimate to enable stable forecasting up to the next maturity point, therefore the forecast has increased by £0.4m this month but stayed within the P50 limit. Additional resources may be required in the run up to gate.
B75: 35/10475 | C75: Product Zone Power Supply | D75: Sellafield | F75: =VLOOKUP($C75,'4b) SL EPO Extended Data Sheet'!$A$5:$AB$176,2,FALSE) -> G | G75: =VLOOKUP($C75,'4b) SL EPO Extended Data Sheet'!$A$5:$AB$176,3, FALSE) -> 0 | I75: =VLOOKUP($C75,'4b) SL EPO Extended Data Sheet'!$A$5:$AD$176,30, FALSE) -> SOC (Mar-24) | J75: =VLOOKUP($C75,'4b) SL EPO Extended Data Sheet'!$A$5:$AB$176,6, FALSE)/1000000 -> 81.71669 | K75: =VLOOKUP($C75,'4b) SL EPO Extended Data Sheet'!$A$5:$AB$176,7, FALSE)/1000000 -> 164.37964 | L75: =VLOOKUP($C75,'4b) SL EPO Extended Data Sheet'!$A$5:$AB$176,8, FALSE) -> 48549 | M75: =VLOOKUP($C75,'4b) SL EPO Extended Data Sheet'!$A$5:$AB$176,9, FALSE) -> 49310 | N75: =VLOOKUP($C75,'4b) SL EPO Extended Data Sheet'!$A$5:$AB$176,5, FALSE) -> 45352 | O75: =VLOOKUP($C75,'4b) SL EPO Extended Data Sheet'!$A$5:$AB$176,10, FALSE)/1000000 -> 0 | P75: =VLOOKUP($C75,'4b) SL EPO Extended Data Sheet'!$A$5:$AB$176,11, FALSE)/1000000 -> 11.961 | R75: =VLOOKUP($C75,'4b) SL EPO Extended Data Sheet'!$A$5:$AB$176,12,FALSE) -> G | S75: =VLOOKUP($C75,'4b) SL EPO Extended Data Sheet'!$A$5:$AB$176,13,FALSE) -> 1 | U75: =VLOOKUP($C75,'4b) SL EPO Extended Data Sheet'!$A$5:$AE$176,31,FALSE) -> SOC (Feb-24) | W75: =VLOOKUP($C75,'4b) SL EPO Extended Data Sheet'!$A$5:$AC$176,16,FALSE)/1000000 -> 84.328299 | X75: =VLOOKUP($C75,'4b) SL EPO Extended Data Sheet'!$A$5:$AC$176,17,FALSE)/1000000 -> 82.916699 | Y75: =VLOOKUP($C75,'4b) SL EPO Extended Data Sheet'!$A$5:$AC$176,18,FALSE)/1000000 -> -0.00099992 | Z75: =VLOOKUP($C75,'4b) SL EPO Extended Data Sheet'!$A$5:$AB$176,16,FALSE)/1000000 -> 84.328299 | AA75: =VLOOKUP($C75,'4b) SL EPO Extended Data Sheet'!$A$5:$AC$176,19,FALSE) -> 48234 | AB75: =VLOOKUP($C75,'4b) SL EPO Extended Data Sheet'!$A$5:$AC$176,20,FALSE) -> 48110 | AC75: =VLOOKUP($C75,'4b) SL EPO Extended Data Sheet'!$A$5:$AC$176,21,FALSE) -> 0 | AD75: =VLOOKUP($C75,'4b) SL EPO Extended Data Sheet'!$A$5:$AB$176,15,FALSE)/1000000 -> 0.045329 | AE75: =VLOOKUP($C75,'4b) SL EPO Extended Data Sheet'!$A$5:$AC$176,22,FALSE)/1000000 -> 9.1904491 | AF75: =VLOOKUP($C75,'4b) SL EPO Extended Data Sheet'!$A$5:$AC$176,23,FALSE)/1000000 -> 7.4664117 | AG75: =VLOOKUP($C75,'4b) SL EPO Extended Data Sheet'!$A$5:$AC$176,24,FALSE)/1000000 -> 5.9714513 | AH75: =VLOOKUP($C75,'4b) SL EPO Extended Data Sheet'!$A$5:$AC$176,25,FALSE) -> 1.2503513 | AI75: =VLOOKUP($C75,'4b) SL EPO Extended Data Sheet'!$A$5:$AC$176,26,FALSE) -> 0.81240989 | AJ75: =VLOOKUP($C75,'4b) SL EPO Extended Data Sheet'!$A$5:$AC$176,27,FALSE) -> 0.10898416 | AK75: =VLOOKUP($C75,'4b) SL EPO Extended Data Sheet'!$A$5:$AC$176,28,FALSE) -> 0.088539812 | AL75: =VLOOKUP($C75,'4b) SL EPO Extended Data Sheet'!$A$6:$AB$176,15,FALSE) -> 45329 | AM75: =VLOOKUP($C75,'4b) SL EPO Extended Data Sheet'!$A$5:$AC$176,29,FALSE) -> G | AV75: 82.882503 | AW75: 48110 | AY75: 84.328299 | AZ75: =W75-AY75 -> 0 | BA75: 48234 | BB75: =AA75-BA75 -> 0
A76: =C75 -> Product Zone Power Supply | B76: The existing site electrical distribution network is expected to be overloaded in c2030. The Product Zone Power Supply Project (PZPSP) exists to improve electrical distribution system reliability through installation of new modular substations and interconnectors that will complete the site end state network upgrades (Substation 78) and provide capacity to feed the new Product Zone areas of site (Substation 48). The first project benefit is enabling the completion of the end state network. Project Lifecycle: Stage 2 'Appraise & Select'. The SRO Delivery Confidence Assessment (DCA) remains Green, representing delivery against the Strategic Outline Case (SOC) approved by the Nuclear Decommissioning Authority (NDA). The P50 completion cost has minor change in period <10k. The P50 schedule has been maintained in period. The Baseline RAG status has improved to Green this period, now Programme have had the Strategic Timing paper approved at the Enterprise Development Committee to defer the PZPS - Substation 48 scope, as the requirements will not be available until a decision point in 2027. This will result in a configuration change control this financial year to remove this scope from the project to a placeholder baseline in the future. An updated Project Functional Specification has been issued to the project to progress the site end state network upgrades scope (Substation 78) and can continue to progress to the Outline Business Case (OBC) preparation, Appraise & Select stage, with a change control to align to the OBC expected to follow in 2026/27. Capability & Capacity are Green as there are no current resource issues on the Project.
B78: 35/09248 | C78: Substations 6 & 7 Replacement | D78: Sellafield | F78: =VLOOKUP($C78,'4b) SL EPO Extended Data Sheet'!$A$5:$AB$176,2,FALSE) -> G | G78: =VLOOKUP($C78,'4b) SL EPO Extended Data Sheet'!$A$5:$AB$176,3, FALSE) -> 0 | I78: =VLOOKUP($C78,'4b) SL EPO Extended Data Sheet'!$A$5:$AD$176,30, FALSE) -> FBC (Feb-16) | J78: =VLOOKUP($C78,'4b) SL EPO Extended Data Sheet'!$A$5:$AB$176,6, FALSE)/1000000 -> 64.272 | K78: =VLOOKUP($C78,'4b) SL EPO Extended Data Sheet'!$A$5:$AB$176,7, FALSE)/1000000 -> 66.533 | L78: =VLOOKUP($C78,'4b) SL EPO Extended Data Sheet'!$A$5:$AB$176,8, FALSE) -> 44530 | M78: =VLOOKUP($C78,'4b) SL EPO Extended Data Sheet'!$A$5:$AB$176,9, FALSE) | N78: =VLOOKUP($C78,'4b) SL EPO Extended Data Sheet'!$A$5:$AB$176,5, FALSE) -> 42404 | O78: =VLOOKUP($C78,'4b) SL EPO Extended Data Sheet'!$A$5:$AB$176,10, FALSE)/1000000 -> 60.457 | P78: =VLOOKUP($C78,'4b) SL EPO Extended Data Sheet'!$A$5:$AB$176,11, FALSE)/1000000 -> 58.957 | R78: =VLOOKUP($C78,'4b) SL EPO Extended Data Sheet'!$A$5:$AB$176,12,FALSE) -> G | S78: =VLOOKUP($C78,'4b) SL EPO Extended Data Sheet'!$A$5:$AB$176,13,FALSE) -> 0 | U78: =VLOOKUP($C78,'4b) SL EPO Extended Data Sheet'!$A$5:$AE$176,31,FALSE) -> FBC (Mar-15) | W78: =VLOOKUP($C78,'4b) SL EPO Extended Data Sheet'!$A$5:$AC$176,16,FALSE)/1000000 -> 64.421715 | X78: =VLOOKUP($C78,'4b) SL EPO Extended Data Sheet'!$A$5:$AC$176,17,FALSE)/1000000 -> 58.647951 | Y78: =VLOOKUP($C78,'4b) SL EPO Extended Data Sheet'!$A$5:$AC$176,18,FALSE)/1000000 -> 0.01521575 | Z78: =VLOOKUP($C78,'4b) SL EPO Extended Data Sheet'!$A$5:$AB$176,16,FALSE)/1000000 -> 64.421715 | AA78: =VLOOKUP($C78,'4b) SL EPO Extended Data Sheet'!$A$5:$AC$176,19,FALSE) -> 44054 | AB78: =VLOOKUP($C78,'4b) SL EPO Extended Data Sheet'!$A$5:$AC$176,20,FALSE) -> 46007 | AC78: =VLOOKUP($C78,'4b) SL EPO Extended Data Sheet'!$A$5:$AC$176,21,FALSE) -> 42 | AD78: =VLOOKUP($C78,'4b) SL EPO Extended Data Sheet'!$A$5:$AB$176,15,FALSE)/1000000 -> 0.04208 | AE78: =VLOOKUP($C78,'4b) SL EPO Extended Data Sheet'!$A$5:$AC$176,22,FALSE)/1000000 -> 64.421715 | AF78: =VLOOKUP($C78,'4b) SL EPO Extended Data Sheet'!$A$5:$AC$176,23,FALSE)/1000000 -> 64.352226 | AG78: =VLOOKUP($C78,'4b) SL EPO Extended Data Sheet'!$A$5:$AC$176,24,FALSE)/1000000 -> 58.591612 | AH78: =VLOOKUP($C78,'4b) SL EPO Extended Data Sheet'!$A$5:$AC$176,25,FALSE) -> 1.0983181 | AI78: =VLOOKUP($C78,'4b) SL EPO Extended Data Sheet'!$A$5:$AC$176,26,FALSE) -> 0.99892133 | AJ78: =VLOOKUP($C78,'4b) SL EPO Extended Data Sheet'!$A$5:$AC$176,27,FALSE) -> 1 | AK78: =VLOOKUP($C78,'4b) SL EPO Extended Data Sheet'!$A$5:$AC$176,28,FALSE) -> 0.99892134 | AL78: =VLOOKUP($C78,'4b) SL EPO Extended Data Sheet'!$A$6:$AB$176,15,FALSE) -> 42080 | AM78: =VLOOKUP($C78,'4b) SL EPO Extended Data Sheet'!$A$5:$AC$176,29,FALSE) -> G | AV78: 58.632735 | AW78: 45965 | AY78: 64.421715 | AZ78: =W78-AY78 -> 0 | BA78: 44054 | BB78: =AA78-BA78 -> 0
A79: =C78 -> Substations 6 & 7 Replacement | B79: Project Lifecycle: Stage 4 'Deliver'. The project benefit is the provision of a stable supply. The SRO Delivery Confidence Assessment (DCA) remains Green, representing stable delivery of route to closeout. Construction was completed in January 2025 with final SL commissioning commencing as planned. Gate 5 Sellafield Project Execution Review (SPER) actions continue to be progressed with the majority dependent on completion of SL scope. The P50 Completion cost has increased in period due to final design costs received. The P50 schedule has increased in period as this has now been aligned to the latest Post Investment Appraisal (PIA) governance now confirmed for December 2025. The Baseline RAG status remains Green. Capability & Capacity RAG has improved to Green in period as all fault observations and PIA SPER actions have been closed.
B80: .
B81: 35/10563 | C81: Substation 10 Replacement | D81: Sellafield | F81: =VLOOKUP($C81,'4b) SL EPO Extended Data Sheet'!$A$5:$AB$176,2,FALSE) -> G | G81: =VLOOKUP($C81,'4b) SL EPO Extended Data Sheet'!$A$5:$AB$176,3, FALSE) -> 0 | I81: =VLOOKUP($C81,'4b) SL EPO Extended Data Sheet'!$A$5:$AD$176,30, FALSE) -> SOC (Nov-23) | J81: =VLOOKUP($C81,'4b) SL EPO Extended Data Sheet'!$A$5:$AB$176,6, FALSE)/1000000 -> 44.848309 | K81: =VLOOKUP($C81,'4b) SL EPO Extended Data Sheet'!$A$5:$AB$176,7, FALSE)/1000000 -> 45.887309 | L81: =VLOOKUP($C81,'4b) SL EPO Extended Data Sheet'!$A$5:$AB$176,8, FALSE) -> 47543 | M81: =VLOOKUP($C81,'4b) SL EPO Extended Data Sheet'!$A$5:$AB$176,9, FALSE) | N81: =VLOOKUP($C81,'4b) SL EPO Extended Data Sheet'!$A$5:$AB$176,5, FALSE) -> 45239 | O81: =VLOOKUP($C81,'4b) SL EPO Extended Data Sheet'!$A$5:$AB$176,10, FALSE)/1000000 -> 0 | P81: =VLOOKUP($C81,'4b) SL EPO Extended Data Sheet'!$A$5:$AB$176,11, FALSE)/1000000 -> 3.087102 | R81: =VLOOKUP($C81,'4b) SL EPO Extended Data Sheet'!$A$5:$AB$176,12,FALSE) -> G | S81: =VLOOKUP($C81,'4b) SL EPO Extended Data Sheet'!$A$5:$AB$176,13,FALSE) -> 0 | U81: =VLOOKUP($C81,'4b) SL EPO Extended Data Sheet'!$A$5:$AE$176,31,FALSE) -> SOC (Jan-24) | W81: =VLOOKUP($C81,'4b) SL EPO Extended Data Sheet'!$A$5:$AC$176,16,FALSE)/1000000 -> 42.841254 | X81: =VLOOKUP($C81,'4b) SL EPO Extended Data Sheet'!$A$5:$AC$176,17,FALSE)/1000000 -> 42.41638 | Y81: =VLOOKUP($C81,'4b) SL EPO Extended Data Sheet'!$A$5:$AC$176,18,FALSE)/1000000 -> -0.0011102 | Z81: =VLOOKUP($C81,'4b) SL EPO Extended Data Sheet'!$A$5:$AB$176,16,FALSE)/1000000 -> 42.841254 | AA81: =VLOOKUP($C81,'4b) SL EPO Extended Data Sheet'!$A$5:$AC$176,19,FALSE) -> 47416 | AB81: =VLOOKUP($C81,'4b) SL EPO Extended Data Sheet'!$A$5:$AC$176,20,FALSE) -> 47416 | AC81: =VLOOKUP($C81,'4b) SL EPO Extended Data Sheet'!$A$5:$AC$176,21,FALSE) -> 0 | AD81: =VLOOKUP($C81,'4b) SL EPO Extended Data Sheet'!$A$5:$AB$176,15,FALSE)/1000000 -> 0.045306 | AE81: =VLOOKUP($C81,'4b) SL EPO Extended Data Sheet'!$A$5:$AC$176,22,FALSE)/1000000 -> 3.2519153 | AF81: =VLOOKUP($C81,'4b) SL EPO Extended Data Sheet'!$A$5:$AC$176,23,FALSE)/1000000 -> 2.4458196 | AG81: =VLOOKUP($C81,'4b) SL EPO Extended Data Sheet'!$A$5:$AC$176,24,FALSE)/1000000 -> 2.2005269 | AH81: =VLOOKUP($C81,'4b) SL EPO Extended Data Sheet'!$A$5:$AC$176,25,FALSE) -> 1.11147 | AI81: =VLOOKUP($C81,'4b) SL EPO Extended Data Sheet'!$A$5:$AC$176,26,FALSE) -> 0.75211664 | AJ81: =VLOOKUP($C81,'4b) SL EPO Extended Data Sheet'!$A$5:$AC$176,27,FALSE) -> 0.075906165 | AK81: =VLOOKUP($C81,'4b) SL EPO Extended Data Sheet'!$A$5:$AC$176,28,FALSE) -> 0.05709029 | AL81: =VLOOKUP($C81,'4b) SL EPO Extended Data Sheet'!$A$6:$AB$176,15,FALSE) -> 45306 | AM81: =VLOOKUP($C81,'4b) SL EPO Extended Data Sheet'!$A$5:$AC$176,29,FALSE) -> G | AV81: 42.416284 | AW81: 47416 | AY81: 42.841254 | AZ81: =W81-AY81 -> 0 | BA81: 47416 | BB81: =AA81-BA81 -> 0
A82: =C81 -> Substation 10 Replacement | B82: Project Lifecycle: Stage 1 'Feasibility'. The project benefit is the provision of a stable supply. The SRO Delivery Confidence Assessment (DCA) remains Green, representing progress against shortlisting activities. The P50 completion cost has minor changes <£10k. The P50 schedule position has been maintained in period as we are preparing for the Strategic Outline Case. The Strategic Outline Case Single Phase SPER was completed in October 2025. Post period end, a Green rating and 0 critical findings have been confirmed. Investment Review Panel is planned for January 2026, and an expected Change Control this financial year following approval of the business case in February 2026 at NDA Group Investment Committee. The Baseline RAG status remains Green. Capability & Capacity RAG status remains Green.
B84: 35/10564 | C84: Substation 15 Replacement | D84: Sellafield | F84: =VLOOKUP($C84,'4b) SL EPO Extended Data Sheet'!$A$5:$AB$176,2,FALSE) -> G | G84: =VLOOKUP($C84,'4b) SL EPO Extended Data Sheet'!$A$5:$AB$176,3, FALSE) -> 0 | I84: =VLOOKUP($C84,'4b) SL EPO Extended Data Sheet'!$A$5:$AD$176,30, FALSE) -> SOC (Sep-23) | J84: =VLOOKUP($C84,'4b) SL EPO Extended Data Sheet'!$A$5:$AB$176,6, FALSE)/1000000 -> 44 | K84: =VLOOKUP($C84,'4b) SL EPO Extended Data Sheet'!$A$5:$AB$176,7, FALSE)/1000000 -> 45.039 | L84: =VLOOKUP($C84,'4b) SL EPO Extended Data Sheet'!$A$5:$AB$176,8, FALSE) -> 47119 | M84: =VLOOKUP($C84,'4b) SL EPO Extended Data Sheet'!$A$5:$AB$176,9, FALSE) | N84: =VLOOKUP($C84,'4b) SL EPO Extended Data Sheet'!$A$5:$AB$176,5, FALSE) -> 45170 | O84: =VLOOKUP($C84,'4b) SL EPO Extended Data Sheet'!$A$5:$AB$176,10, FALSE)/1000000 -> 0 | P84: =VLOOKUP($C84,'4b) SL EPO Extended Data Sheet'!$A$5:$AB$176,11, FALSE)/1000000 -> 2.601 | R84: =VLOOKUP($C84,'4b) SL EPO Extended Data Sheet'!$A$5:$AB$176,12,FALSE) -> G | S84: =VLOOKUP($C84,'4b) SL EPO Extended Data Sheet'!$A$5:$AB$176,13,FALSE) -> 0 | U84: =VLOOKUP($C84,'4b) SL EPO Extended Data Sheet'!$A$5:$AE$176,31,FALSE) -> SOC (Jan-24) | W84: =VLOOKUP($C84,'4b) SL EPO Extended Data Sheet'!$A$5:$AC$176,16,FALSE)/1000000 -> 42.754873 | X84: =VLOOKUP($C84,'4b) SL EPO Extended Data Sheet'!$A$5:$AC$176,17,FALSE)/1000000 -> 42.264072 | Y84: =VLOOKUP($C84,'4b) SL EPO Extended Data Sheet'!$A$5:$AC$176,18,FALSE)/1000000 -> 0.00044286 | Z84: =VLOOKUP($C84,'4b) SL EPO Extended Data Sheet'!$A$5:$AB$176,16,FALSE)/1000000 -> 42.754873 | AA84: =VLOOKUP($C84,'4b) SL EPO Extended Data Sheet'!$A$5:$AC$176,19,FALSE) -> 47129 | AB84: =VLOOKUP($C84,'4b) SL EPO Extended Data Sheet'!$A$5:$AC$176,20,FALSE) -> 47129 | AC84: =VLOOKUP($C84,'4b) SL EPO Extended Data Sheet'!$A$5:$AC$176,21,FALSE) -> 0 | AD84: =VLOOKUP($C84,'4b) SL EPO Extended Data Sheet'!$A$5:$AB$176,15,FALSE)/1000000 -> 0.045306 | AE84: =VLOOKUP($C84,'4b) SL EPO Extended Data Sheet'!$A$5:$AC$176,22,FALSE)/1000000 -> 3.9444487 | AF84: =VLOOKUP($C84,'4b) SL EPO Extended Data Sheet'!$A$5:$AC$176,23,FALSE)/1000000 -> 2.1716493 | AG84: =VLOOKUP($C84,'4b) SL EPO Extended Data Sheet'!$A$5:$AC$176,24,FALSE)/1000000 -> 2.3977164 | AH84: =VLOOKUP($C84,'4b) SL EPO Extended Data Sheet'!$A$5:$AC$176,25,FALSE) -> 0.90571568 | AI84: =VLOOKUP($C84,'4b) SL EPO Extended Data Sheet'!$A$5:$AC$176,26,FALSE) -> 0.5505584 | AJ84: =VLOOKUP($C84,'4b) SL EPO Extended Data Sheet'!$A$5:$AC$176,27,FALSE) -> 0.092257289 | AK84: =VLOOKUP($C84,'4b) SL EPO Extended Data Sheet'!$A$5:$AC$176,28,FALSE) -> 0.050793025 | AL84: =VLOOKUP($C84,'4b) SL EPO Extended Data Sheet'!$A$6:$AB$176,15,FALSE) -> 45306 | AM84: =VLOOKUP($C84,'4b) SL EPO Extended Data Sheet'!$A$5:$AC$176,29,FALSE) -> G | AV84: 42.262478 | AW84: 47129 | AY84: 42.754873 | AZ84: =W84-AY84 -> 0 | BA84: 47129 | BB84: =AA84-BA84 -> 0
A85: =C84 -> Substation 15 Replacement | B85: Project Lifecycle: Stage 1 'Feasibility'. The project benefit is the provision of a stable supply. The SRO Delivery Confidence Assessment (DCA) remains Green, representing progress against shortlisting activities. The Strategic Outline Case SPER in August 25, resulted in a red rating, all actions have been Closed Out and the learning transferred to Substation 10. Investment Review Panel is planned for January 2026, with an expected change control this financial year following approval of the business case in February 2026 at NDA Group Investment Committee. The P50 completion cost has minor changes <£10k. The P50 schedule position has been maintained. The Baseline RAG status remains Green. Capability & Capacity RAG status remains Green.
B87: 35/10545 | C87: Degradation of Pipebridge 57 (PB57) L14, L15, L16 Refurbishment | D87: Sellafield | F87: =VLOOKUP($C87,'4b) SL EPO Extended Data Sheet'!$A$5:$AB$176,2,FALSE) -> N/A | G87: =VLOOKUP($C87,'4b) SL EPO Extended Data Sheet'!$A$5:$AB$176,3, FALSE) -> 0 | I87: =VLOOKUP($C87,'4b) SL EPO Extended Data Sheet'!$A$5:$AD$176,30, FALSE) -> OBC (Jul-23) | J87: =VLOOKUP($C87,'4b) SL EPO Extended Data Sheet'!$A$5:$AB$176,6, FALSE)/1000000 -> 30 | K87: =VLOOKUP($C87,'4b) SL EPO Extended Data Sheet'!$A$5:$AB$176,7, FALSE)/1000000 -> 31.039 | L87: =VLOOKUP($C87,'4b) SL EPO Extended Data Sheet'!$A$5:$AB$176,8, FALSE) | M87: =VLOOKUP($C87,'4b) SL EPO Extended Data Sheet'!$A$5:$AB$176,9, FALSE) | N87: =VLOOKUP($C87,'4b) SL EPO Extended Data Sheet'!$A$5:$AB$176,5, FALSE) -> 45108 | O87: =VLOOKUP($C87,'4b) SL EPO Extended Data Sheet'!$A$5:$AB$176,10, FALSE)/1000000 -> 0 | P87: =VLOOKUP($C87,'4b) SL EPO Extended Data Sheet'!$A$5:$AB$176,11, FALSE)/1000000 -> 3.393 | R87: =VLOOKUP($C87,'4b) SL EPO Extended Data Sheet'!$A$5:$AB$176,12,FALSE) -> G | S87: =VLOOKUP($C87,'4b) SL EPO Extended Data Sheet'!$A$5:$AB$176,13,FALSE) -> 1 | U87: =VLOOKUP($C87,'4b) SL EPO Extended Data Sheet'!$A$5:$AE$176,31,FALSE) -> OBC (Dec-23) | W87: =VLOOKUP($C87,'4b) SL EPO Extended Data Sheet'!$A$5:$AC$176,16,FALSE)/1000000 -> 30.826939 | X87: =VLOOKUP($C87,'4b) SL EPO Extended Data Sheet'!$A$5:$AC$176,17,FALSE)/1000000 -> 31.203278 | Y87: =VLOOKUP($C87,'4b) SL EPO Extended Data Sheet'!$A$5:$AC$176,18,FALSE)/1000000 -> 0 | Z87: =VLOOKUP($C87,'4b) SL EPO Extended Data Sheet'!$A$5:$AB$176,16,FALSE)/1000000 -> 30.826939 | AA87: =VLOOKUP($C87,'4b) SL EPO Extended Data Sheet'!$A$5:$AC$176,19,FALSE) -> 47204 | AB87: =VLOOKUP($C87,'4b) SL EPO Extended Data Sheet'!$A$5:$AC$176,20,FALSE) -> 47529 | AC87: =VLOOKUP($C87,'4b) SL EPO Extended Data Sheet'!$A$5:$AC$176,21,FALSE) -> 0 | AD87: =VLOOKUP($C87,'4b) SL EPO Extended Data Sheet'!$A$5:$AB$176,15,FALSE)/1000000 -> 0.045271 | AE87: =VLOOKUP($C87,'4b) SL EPO Extended Data Sheet'!$A$5:$AC$176,22,FALSE)/1000000 -> 4.8831998 | AF87: =VLOOKUP($C87,'4b) SL EPO Extended Data Sheet'!$A$5:$AC$176,23,FALSE)/1000000 -> 1.8341167 | AG87: =VLOOKUP($C87,'4b) SL EPO Extended Data Sheet'!$A$5:$AC$176,24,FALSE)/1000000 -> 2.4118858 | AH87: =VLOOKUP($C87,'4b) SL EPO Extended Data Sheet'!$A$5:$AC$176,25,FALSE) -> 0.76044924 | AI87: =VLOOKUP($C87,'4b) SL EPO Extended Data Sheet'!$A$5:$AC$176,26,FALSE) -> 0.37559732 | AJ87: =VLOOKUP($C87,'4b) SL EPO Extended Data Sheet'!$A$5:$AC$176,27,FALSE) -> 0.1584069 | AK87: =VLOOKUP($C87,'4b) SL EPO Extended Data Sheet'!$A$5:$AC$176,28,FALSE) -> 0.059497206 | AL87: =VLOOKUP($C87,'4b) SL EPO Extended Data Sheet'!$A$6:$AB$176,15,FALSE) -> 45271 | AM87: =VLOOKUP($C87,'4b) SL EPO Extended Data Sheet'!$A$5:$AC$176,29,FALSE) -> G | AV87: 31.203685 | AW87: 47529 | AY87: 30.826939 | AZ87: =W87-AY87 -> 0 | BA87: 47204 | BB87: =AA87-BA87 -> 0
A88: =C87 -> Degradation of Pipebridge 57 (PB57) L14, L15, L16 Refurbishment | B88: Project Lifecycle: Stage 2 'Appraise & Select'. Pipebridge 57 spans the river Calder from East to West of site. The civil structure and services carried across it have been exposed to coastal conditions and are in an advanced state of degradation. The PB57 project exists to provide continuity of Mechanical & Control, Electrical & Instrumentation (CE&I) services currently supplied by PB57 to end users across the site network and to remove risk to the SL & external environment resulting from bridge and support collapse as it reaches end of life. The first project benefit focusses on achievement of the successful diversion of key services from PB57 whilst maintaining continuity of services to end users. The Delivery Confidence Assessment (DCA) remains stable (N/A due to no requirement for Strategic Outline Case (SOC)). The Baseline RAG been improved in period to Green due to the review of the stress modelling to underpin and present an optimised solution to mitigate the risk sooner. The project is currently reviewing the delivery strategy inline with these discussions and a Change Control Record (CCR) will follow next financial year in alignment to the Outline Business Case (OBC). The P50 completion cost has minor changes in period <£10k and the schedule position has been maintained. The Capability & Capacity RAG status remains Green.
B90: Value Stream: Retrievals
B91: Portfolio Summary | AV91: 70.5 | AW91: 46106 | AY91: 72.617237 | AZ91: -72.617237 | BA91: 46106 | BB91: -46075.173
B93: n/a(1) | C93: MSSS 2nd and 3rd Extension Sub-Programme | D93: Sellafield | F93: =VLOOKUP(C93,'5a)NDA MPPR'!$B$9:$AK$61,3,FALSE) -> A | G93: =VLOOKUP(C93,'5a)NDA MPPR'!$B$9:$AK$61,4,FALSE) -> 0 | I93: =VLOOKUP(C93,'5a)NDA MPPR'!$B$9:$AK$61,6,FALSE) -> FBC (Oct-23) | J93: =VLOOKUP(C93,'5a)NDA MPPR'!$B$9:$AK$61,7,FALSE) -> 130 | K93: =VLOOKUP(C93,'5a)NDA MPPR'!$B$9:$AK$61,8,FALSE) -> 200 | L93: =VLOOKUP(C93,'5a)NDA MPPR'!$B$9:$AK$61,9,FALSE) -> - | M93: =VLOOKUP(C93,'5a)NDA MPPR'!$B$9:$AK$61,10,FALSE) -> - | O93: =VLOOKUP(C93,'5a)NDA MPPR'!$B$9:$AK$61,12,FALSE) -> 200 | P93: =VLOOKUP(C93,'5a)NDA MPPR'!$B$9:$AK$61,13,FALSE) -> 200 | R93: =VLOOKUP(C93,'5a)NDA MPPR'!$B$9:$AK$61,15,FALSE) -> A | S93: =VLOOKUP(C93,'5a)NDA MPPR'!$B$9:$AK$61,16,FALSE) -> 0 | U93: =VLOOKUP(C93,'5a)NDA MPPR'!$B$9:$AK$61,18,FALSE) -> FBC (Nov-23) | W93: =VLOOKUP(C93,'5a)NDA MPPR'!$B$9:$AK$61,20,FALSE) -> 127.73208 | X93: =VLOOKUP(C93,'5a)NDA MPPR'!$B$9:$AK$61,21,FALSE) -> 141.51045 | Y93: =VLOOKUP(C93,'5a)NDA MPPR'!$B$9:$AK$61,22,FALSE) -> 0 | AA93: =VLOOKUP(C93,'5a)NDA MPPR'!$B$9:$AK$61,24,FALSE) -> 48935 | AB93: =VLOOKUP(C93,'5a)NDA MPPR'!$B$9:$AK$61,25,FALSE) -> 48935 | AC93: =VLOOKUP(C93,'5a)NDA MPPR'!$B$9:$AK$61,26,FALSE) -> 0 | AE93: =VLOOKUP(C93,'5a)NDA MPPR'!$B$9:$AK$61,28,FALSE) -> 0 | AF93: =VLOOKUP(C93,'5a)NDA MPPR'!$B$9:$AK$61,29,FALSE) -> 0 | AG93: =VLOOKUP(C93,'5a)NDA MPPR'!$B$9:$AK$61,30,FALSE) -> 34.480168 | AH93: =VLOOKUP(C93,'5a)NDA MPPR'!$B$9:$AK$61,31,FALSE) -> 0 | AI93: =VLOOKUP(C93,'5a)NDA MPPR'!$B$9:$AK$61,32,FALSE) -> 0 | AJ93: =VLOOKUP(C93,'5a)NDA MPPR'!$B$9:$AK$61,33,FALSE) -> 0 | AK93: =VLOOKUP(C93,'5a)NDA MPPR'!$B$9:$AK$61,34,FALSE) -> 0 | AM93: =VLOOKUP(C93,'5a)NDA MPPR'!$B$9:$AK$61,36,FALSE) -> R | AV93: 141.47171 | AW93: 48935 | AY93: 127.73208 | AZ93: =W93-AY93 -> 0 | BA93: 48935 | BB93: =AA93-BA93 -> 0
A94: =C93 -> MSSS 2nd and 3rd Extension Sub-Programme | B94: =VLOOKUP($C93,'5a)NDA MPPR'!$A$9:$AK$61,2,FALSE) -> In October 2023, the Magnox Swarf Storage Silos (MSSS) Retrievals Programme received re-sanctioning approval, establishing an overall upper funding limit of £1,098m. As part of that endorsement, a revised management framework and sanctioning strategy was introduced to govern the MSSS 2nd Extension (2E) & 3rd Extension (3E) Tranche, as discrete projects. These projects are delivering critical enablers that will facilitate the commencement of waste retrieval operations from Silo Emptying Plant (SEP) 3. They have an upper sanction limit of £200m. The key enablers included are 1) SEP3; Complete design/rectification, installation and commissioning of the machine and associated components. 2) Final manufacture and installation scope for the Nitrogen Inlet system. 3) 2E Liquor Level management system. 4) The remaining Packages required to support full retrievals. The programme has prioritised the OB/FE and as a result the expected specialist resources (e.g. design capability) will not be available to concurrently deliver SEP3. Without further action the delivery will take substantially longer, challenging tolerances. To address this SL is pursuing an alternative delivery model with a fully integrated programme partner that is expected to increase efficiency and critically access a different part of the skill market we have previously failed to harness. As Nuclear Decommissioning Solutions have now been appointed as Lot 3 partner we are working on the alternative delivery strategy. This appears credible with a significant opportunity to protect or improve the schedule. Therefore the Delivery Confidence Assessment remains Amber. There has been no change to the EAC during this period. The project remains in the early stages of its lifecycle, with only six of the nine 2E/3E projects sanctioned, and a total released value of £64.4m. While future cost and schedule pressures are anticipated, the project is forecasting lifecycle EAC within the sanctioned upper limit of £200m and to timelines that align with the critical path of the Magnox Swarf Storage Silo (MSSS) Programme and as such, no direct impact is expected on sustained retrievals. The capability and capacity RAG is Red driven by resource constraints and commercial disruption following the administration of a key supply chain partner. In response, the integrated team is actively working with administrators to recover part-manufactured equipment, having identified secure interim storage, and identified a replacement supplier to complete outstanding packages, with direct award contract placements expected next period. This disruption has led to increased in-year expenditure due to associated recovery and transition costs. The Baseline RAG status is Amber, reflecting anticipated impacts from ongoing commercial challenges and supply chain, but also in acknowledgement of the recovery plan currently being enacted by the project team to ensure delivery of packages in support of the programme requirements.
B96: 35/10342 | C96: MSSS SEP3 Rails & Brackets | D96: Sellafield | F96: =VLOOKUP($C96,'4b) SL EPO Extended Data Sheet'!$A$5:$AB$176,2,FALSE) -> A | G96: =VLOOKUP($C96,'4b) SL EPO Extended Data Sheet'!$A$5:$AB$176,3, FALSE) -> 0 | I96: =VLOOKUP($C96,'4b) SL EPO Extended Data Sheet'!$A$5:$AD$176,30, FALSE) -> FBC (Dec-21) | J96: =VLOOKUP($C96,'4b) SL EPO Extended Data Sheet'!$A$5:$AB$176,6, FALSE)/1000000 -> 20.366653 | K96: =VLOOKUP($C96,'4b) SL EPO Extended Data Sheet'!$A$5:$AB$176,7, FALSE)/1000000 -> 21.84146 | L96: =VLOOKUP($C96,'4b) SL EPO Extended Data Sheet'!$A$5:$AB$176,8, FALSE) -> 46234 | M96: =VLOOKUP($C96,'4b) SL EPO Extended Data Sheet'!$A$5:$AB$176,9, FALSE) -> 46477 | O96: =VLOOKUP($C96,'4b) SL EPO Extended Data Sheet'!$A$5:$AB$176,10, FALSE)/1000000 -> 0 | P96: =VLOOKUP($C96,'4b) SL EPO Extended Data Sheet'!$A$5:$AB$176,11, FALSE)/1000000 -> 20.366653 | R96: =VLOOKUP($C96,'4b) SL EPO Extended Data Sheet'!$A$5:$AB$176,12,FALSE) -> A | S96: =VLOOKUP($C96,'4b) SL EPO Extended Data Sheet'!$A$5:$AB$176,13,FALSE) -> 0 | U96: =VLOOKUP($C96,'4b) SL EPO Extended Data Sheet'!$A$5:$AE$176,31,FALSE) -> FBC (Mar-22) | W96: =VLOOKUP($C96,'4b) SL EPO Extended Data Sheet'!$A$5:$AC$176,16,FALSE)/1000000 -> 19.192466 | X96: =VLOOKUP($C96,'4b) SL EPO Extended Data Sheet'!$A$5:$AC$176,17,FALSE)/1000000 -> 20.468821 | Y96: =VLOOKUP($C96,'4b) SL EPO Extended Data Sheet'!$A$5:$AC$176,18,FALSE)/1000000 -> -0.01684508 | Z96: =VLOOKUP($C96,'4b) SL EPO Extended Data Sheet'!$A$5:$AB$176,16,FALSE)/1000000 -> 19.192466 | AA96: =VLOOKUP($C96,'4b) SL EPO Extended Data Sheet'!$A$5:$AC$176,19,FALSE) -> 46230 | AB96: =VLOOKUP($C96,'4b) SL EPO Extended Data Sheet'!$A$5:$AC$176,20,FALSE) -> 47018 | AC96: =VLOOKUP($C96,'4b) SL EPO Extended Data Sheet'!$A$5:$AC$176,21,FALSE) -> 0 | AD96: =VLOOKUP($C96,'4b) SL EPO Extended Data Sheet'!$A$5:$AB$176,15,FALSE)/1000000 -> 0.044651 | AE96: =VLOOKUP($C96,'4b) SL EPO Extended Data Sheet'!$A$5:$AC$176,22,FALSE)/1000000 -> 18.458137 | AF96: =VLOOKUP($C96,'4b) SL EPO Extended Data Sheet'!$A$5:$AC$176,23,FALSE)/1000000 -> 14.173705 | AG96: =VLOOKUP($C96,'4b) SL EPO Extended Data Sheet'!$A$5:$AC$176,24,FALSE)/1000000 -> 16.500456 | AH96: =VLOOKUP($C96,'4b) SL EPO Extended Data Sheet'!$A$5:$AC$176,25,FALSE) -> 0.85898868 | AI96: =VLOOKUP($C96,'4b) SL EPO Extended Data Sheet'!$A$5:$AC$176,26,FALSE) -> 0.76788384 | AJ96: =VLOOKUP($C96,'4b) SL EPO Extended Data Sheet'!$A$5:$AC$176,27,FALSE) -> 0.9617387 | AK96: =VLOOKUP($C96,'4b) SL EPO Extended Data Sheet'!$A$5:$AC$176,28,FALSE) -> 0.73850361 | AL96: =VLOOKUP($C96,'4b) SL EPO Extended Data Sheet'!$A$6:$AB$176,15,FALSE) -> 44651 | AM96: =VLOOKUP($C96,'4b) SL EPO Extended Data Sheet'!$A$5:$AC$176,29,FALSE) -> A | AV96: 20.479915 | AW96: 47018 | AY96: 19.192466 | AZ96: =W96-AY96 -> 0 | BA96: 46230 | BB96: =AA96-BA96 -> 0
A97: =C96 -> MSSS SEP3 Rails & Brackets | B97: This project relates to the manufacture and installation of the Rails supporting Silo Emptying Plant 3 (SEP3) and is prioritised into zones, aligned with installation and retrievals. The first project benefit was delivered on the 6th February 2025 with the installation of the Zone 1 rails, ready for the start of SEP3 installation. The Delivery Confidence Assessment is Amber as full project delivery is now not forecast until after the P80 date of March 2027. The project is currently forecast to be delivered for less than the P80 sanction value of £21.8m, however ongoing supply chain issues are likely to impact this. The Baseline RAG status is Amber, this is due to strategic priorities and performance of a tier 3 supplier. Following the supply chain contractor entering administration in June 2025, the project and commercial teams are working with the administrator to progress the retrieval of the part-manufactured equipment, secure a medium-term storage facility and identify an alternative supply chain partner to complete the packages. Lifetime EAC may deteriorate due to the impact of the supply chain issues. However, it is currently expected that the project can still be delivered within sanction value and within timescales acceptable to the critical path of the Magnox Swarf Storage Silo (MSSS) Programme and will not directly impact Sustained Retrievals as the Zone 3 rails are not a requirement for the installation of the SEP3 machine. For this reason the DCA & Baseline RAG can be rated at Amber rather than Red. Capability & Capacity RAG status is Amber due to the ongoing supply chain issues.
B99: 35/10371 | C99: Sludge Handling & Export Plant | D99: Sellafield | F99: =VLOOKUP($C99,'4b) SL EPO Extended Data Sheet'!$A$5:$AB$176,2,FALSE) -> A | G99: =VLOOKUP($C99,'4b) SL EPO Extended Data Sheet'!$A$5:$AB$176,3, FALSE) -> 0 | I99: =VLOOKUP($C99,'4b) SL EPO Extended Data Sheet'!$A$5:$AD$176,30, FALSE) -> SOC (Sep-21) | J99: =VLOOKUP($C99,'4b) SL EPO Extended Data Sheet'!$A$5:$AB$176,6, FALSE)/1000000 -> 38.1 | K99: =VLOOKUP($C99,'4b) SL EPO Extended Data Sheet'!$A$5:$AB$176,7, FALSE)/1000000 -> 0 | L99: =VLOOKUP($C99,'4b) SL EPO Extended Data Sheet'!$A$5:$AB$176,8, FALSE) | M99: =VLOOKUP($C99,'4b) SL EPO Extended Data Sheet'!$A$5:$AB$176,9, FALSE) | O99: =VLOOKUP($C99,'4b) SL EPO Extended Data Sheet'!$A$5:$AB$176,10, FALSE)/1000000 -> 0 | P99: =VLOOKUP($C99,'4b) SL EPO Extended Data Sheet'!$A$5:$AB$176,11, FALSE)/1000000 -> 38.1 | R99: =VLOOKUP($C99,'4b) SL EPO Extended Data Sheet'!$A$5:$AB$176,12,FALSE) -> A | S99: =VLOOKUP($C99,'4b) SL EPO Extended Data Sheet'!$A$5:$AB$176,13,FALSE) -> 0 | U99: =VLOOKUP($C99,'4b) SL EPO Extended Data Sheet'!$A$5:$AE$176,31,FALSE) -> SOC (Feb-23) | W99: =VLOOKUP($C99,'4b) SL EPO Extended Data Sheet'!$A$5:$AC$176,16,FALSE)/1000000 -> 340 | X99: =VLOOKUP($C99,'4b) SL EPO Extended Data Sheet'!$A$5:$AC$176,17,FALSE)/1000000 -> 341.04335 | Y99: =VLOOKUP($C99,'4b) SL EPO Extended Data Sheet'!$A$5:$AC$176,18,FALSE)/1000000 -> 0.02773263 | Z99: =VLOOKUP($C99,'4b) SL EPO Extended Data Sheet'!$A$5:$AB$176,16,FALSE)/1000000 -> 340 | AA99: =VLOOKUP($C99,'4b) SL EPO Extended Data Sheet'!$A$5:$AC$176,19,FALSE) -> 48746 | AB99: =VLOOKUP($C99,'4b) SL EPO Extended Data Sheet'!$A$5:$AC$176,20,FALSE) -> 48850 | AC99: =VLOOKUP($C99,'4b) SL EPO Extended Data Sheet'!$A$5:$AC$176,21,FALSE) -> 0 | AD99: =VLOOKUP($C99,'4b) SL EPO Extended Data Sheet'!$A$5:$AB$176,15,FALSE)/1000000 -> 0.044985 | AE99: =VLOOKUP($C99,'4b) SL EPO Extended Data Sheet'!$A$5:$AC$176,22,FALSE)/1000000 -> 30.313656 | AF99: =VLOOKUP($C99,'4b) SL EPO Extended Data Sheet'!$A$5:$AC$176,23,FALSE)/1000000 -> 26.779048 | AG99: =VLOOKUP($C99,'4b) SL EPO Extended Data Sheet'!$A$5:$AC$176,24,FALSE)/1000000 -> 26.590553 | AH99: =VLOOKUP($C99,'4b) SL EPO Extended Data Sheet'!$A$5:$AC$176,25,FALSE) -> 1.0070888 | AI99: =VLOOKUP($C99,'4b) SL EPO Extended Data Sheet'!$A$5:$AC$176,26,FALSE) -> 0.88339884 | AJ99: =VLOOKUP($C99,'4b) SL EPO Extended Data Sheet'!$A$5:$AC$176,27,FALSE) -> 0.089157811 | AK99: =VLOOKUP($C99,'4b) SL EPO Extended Data Sheet'!$A$5:$AC$176,28,FALSE) -> 0.078761906 | AL99: =VLOOKUP($C99,'4b) SL EPO Extended Data Sheet'!$A$6:$AB$176,15,FALSE) -> 44985 | AM99: =VLOOKUP($C99,'4b) SL EPO Extended Data Sheet'!$A$5:$AC$176,29,FALSE) -> A | AV99: 340.95985 | AW99: 48850 | AY99: 340 | AZ99: =W99-AY99 -> 0 | BA99: 48746 | BB99: =AA99-BA99 -> 0
A100: =C99 -> Sludge Handling & Export Plant | B100: Sludge Handling & Export Plant aims to provide a capability to receive and process sludge from Sludge Packaging Plant 1 (SPP1) and export it to a downstream facility to enable the safe treatment into a suitable waste form/product for interim storage. Delivery Confidence Assessment is Amber, the project is still within its appraise and select phase and uncertainty will remain until Outline Business Case (OBC) assurance and governance is complete. This has management oversight and is being worked through accordingly. The down-selected preferred solution (Option 1 -Sludge dewatering in a 500-litre drum in a flask and export to Waste Encapsulation Plant (WEP) for conditioning and interim storage of the resultant waste product in Encapsulated Product Store 3 (EPS3)) is now being further developed in parallel to project planning to support submission of the OBC. Ground investigation work is completed and awaiting final reports. Schedule has been updated in line with GIC paper approval for OBC May 2026 (forecast date) and remains within P50 sanction date of June 2026. Now in delivery of the integrated PDD assurance activities, Triage requirements, NDA lifecycle cost review and transition plans, monitored through detailed get to gate plan. A progressively assured estimate build has been agreed, target completion end of November 2025, this remains challenging. Get to gate assurance schedule is now under change control with PPP intervention points 1A and 1B and Triage carried out. Project are now addressing outputs. Cumulative sanction released to the project is £30.6m to deliver OBC (forecast May 2026) at SL Investment Review Panel (IRP). SL IRP are currently holding a further £7.442m bringing the overall sanction to £38.1m. Baseline RAG is Amber to reflect the current forecast OBC date of May 2026 being later than the current baseline. A Change Control Request will be prepared and implemented to update the baseline following OBC Approval. Capability and Capacity remains amber. Internal project resource challenges remain, however have addressed Construction PM, Commercial Lead and Environmental and Sustainability resources. Further ramp up to support transition to PPP has been put on hold. Additional assurance requirements remain a capacity challenge to balance with delivery. Programme resources have been identified and mobilised to support the ‘get to gate’ plan. Programme continues to assess the output of the first pass schedule date, now reviewed 2036/37 (active commissioning) and cost range of £438m base cost to Reference Class Forecast (RCF) £900m with respect to the construction/ assessment of the economic case.
B102: 35/10095 | C102: Box Encapsulation Plant Product Store Direct Import Facility | D102: Sellafield | F102: =VLOOKUP(C102,'5a)NDA MPPR'!$B$9:$AK$61,3,FALSE) -> A | G102: =VLOOKUP(C102,'5a)NDA MPPR'!$B$9:$AK$61,4,FALSE) -> 0 | I102: =VLOOKUP(C102,'5a)NDA MPPR'!$B$9:$AK$61,6,FALSE) -> FBC (Mar-22) | J102: =VLOOKUP(C102,'5a)NDA MPPR'!$B$9:$AK$61,7,FALSE) -> 458.9 | K102: =VLOOKUP(C102,'5a)NDA MPPR'!$B$9:$AK$61,8,FALSE) -> 466.4 | L102: =VLOOKUP(C102,'5a)NDA MPPR'!$B$9:$AK$61,9,FALSE) -> 45244 | M102: =VLOOKUP(C102,'5a)NDA MPPR'!$B$9:$AK$61,10,FALSE) -> 45361 | O102: =VLOOKUP(C102,'5a)NDA MPPR'!$B$9:$AK$61,12,FALSE) -> 466.4 | P102: =VLOOKUP(C102,'5a)NDA MPPR'!$B$9:$AK$61,13,FALSE) -> 458.9 | R102: =VLOOKUP(C102,'5a)NDA MPPR'!$B$9:$AK$61,15,FALSE) -> A | S102: =VLOOKUP(C102,'5a)NDA MPPR'!$B$9:$AK$61,16,FALSE) -> 0 | U102: =VLOOKUP(C102,'5a)NDA MPPR'!$B$9:$AK$61,18,FALSE) -> FBC Add. (Mar-21) | W102: =VLOOKUP(C102,'5a)NDA MPPR'!$B$9:$AK$61,20,FALSE) -> 419.95364 | X102: =VLOOKUP(C102,'5a)NDA MPPR'!$B$9:$AK$61,21,FALSE) -> 458.24396 | Y102: =VLOOKUP(C102,'5a)NDA MPPR'!$B$9:$AK$61,22,FALSE) -> 0 | AA102: =VLOOKUP(C102,'5a)NDA MPPR'!$B$9:$AK$61,24,FALSE) -> 45050 | AB102: =VLOOKUP(C102,'5a)NDA MPPR'!$B$9:$AK$61,25,FALSE) -> 46142 | AC102: =VLOOKUP(C102,'5a)NDA MPPR'!$B$9:$AK$61,26,FALSE) -> 0 | AE102: =VLOOKUP(C102,'5a)NDA MPPR'!$B$9:$AK$61,28,FALSE) -> 419.95364 | AF102: =VLOOKUP(C102,'5a)NDA MPPR'!$B$9:$AK$61,29,FALSE) -> 419.90913 | AG102: =VLOOKUP(C102,'5a)NDA MPPR'!$B$9:$AK$61,30,FALSE) -> 458.19396 | AH102: =VLOOKUP(C102,'5a)NDA MPPR'!$B$9:$AK$61,31,FALSE) -> 0.91644407 | AI102: =VLOOKUP(C102,'5a)NDA MPPR'!$B$9:$AK$61,32,FALSE) -> 0.99989402 | AJ102: =VLOOKUP(C102,'5a)NDA MPPR'!$B$9:$AK$61,33,FALSE) -> 1 | AK102: =VLOOKUP(C102,'5a)NDA MPPR'!$B$9:$AK$61,34,FALSE) -> 0.99989402 | AM102: =VLOOKUP(C102,'5a)NDA MPPR'!$B$9:$AK$61,36,FALSE) -> G | AV102: 458.24383 | AW102: 46142 | AY102: 419.95364 | AZ102: =W102-AY102 -> 0 | BA102: 45050 | BB102: =AA102-BA102 -> 0
A103: =C102 -> Box Encapsulation Plant Product Store Direct Import Facility | B103: =VLOOKUP($C102,'5a)NDA MPPR'!$A$9:$AK$61,2,FALSE) -> BEPPS-DIF project is essential to remediation of Pile Fuel Cladding Silo (PFCS) and provides capability to receive and store waste from remediation work. PFCS boxes required for active commissioning all received in BEPPS-DIF. All physical activities relating to active commissioning now complete. Project is on close out of fault observations (FOBs) and remaining project scope. Duly Authorised Person (DAP) move to support Advanced Gas Reactor (AGR) / Encapsulated Product Store (EPS) transfers may challenge end date for commissioning and rectifying subsequent faults in parallel with plant operations. Project resources are substantially redeployed on other scope for Retrievals Operations keeping project spend to a minimum. Endorsement to operate is now planned for 31/03/2026. Delivery Confidence Assessment remains Amber. Baseline RAG remains Amber. Capability and Capacity RAG remains Green, project has resource to complete scope. The project completion date remains April 2026, which is aligned with the anticipated IRP date of the Post Investment Appraisal.
B105: 35/10242 | C105: PFCS Full Retrievals - Project 1 | D105: Sellafield | F105: =VLOOKUP(C105,'5a)NDA MPPR'!$B$9:$AK$61,3,FALSE) -> A | G105: =VLOOKUP(C105,'5a)NDA MPPR'!$B$9:$AK$61,4,FALSE) -> 0 | I105: =VLOOKUP(C105,'5a)NDA MPPR'!$B$9:$AK$61,6,FALSE) -> FBC (Apr-24) | J105: =VLOOKUP(C105,'5a)NDA MPPR'!$B$9:$AK$61,7,FALSE) -> 68.5 | K105: =VLOOKUP(C105,'5a)NDA MPPR'!$B$9:$AK$61,8,FALSE) -> 74.6 | L105: =VLOOKUP(C105,'5a)NDA MPPR'!$B$9:$AK$61,9,FALSE) -> 45834 | M105: =VLOOKUP(C105,'5a)NDA MPPR'!$B$9:$AK$61,10,FALSE) -> 45911 | O105: =VLOOKUP(C105,'5a)NDA MPPR'!$B$9:$AK$61,12,FALSE) -> n/a | P105: =VLOOKUP(C105,'5a)NDA MPPR'!$B$9:$AK$61,13,FALSE) -> 74.6 | R105: =VLOOKUP(C105,'5a)NDA MPPR'!$B$9:$AK$61,15,FALSE) -> A | S105: =VLOOKUP(C105,'5a)NDA MPPR'!$B$9:$AK$61,16,FALSE) -> 0 | U105: =VLOOKUP(C105,'5a)NDA MPPR'!$B$9:$AK$61,18,FALSE) -> FBC (May-24) | W105: =VLOOKUP(C105,'5a)NDA MPPR'!$B$9:$AK$61,20,FALSE) -> 75.794335 | X105: =VLOOKUP(C105,'5a)NDA MPPR'!$B$9:$AK$61,21,FALSE) -> 72.459952 | Y105: =VLOOKUP(C105,'5a)NDA MPPR'!$B$9:$AK$61,22,FALSE) -> -0.1 | AA105: =VLOOKUP(C105,'5a)NDA MPPR'!$B$9:$AK$61,24,FALSE) -> 45834 | AB105: =VLOOKUP(C105,'5a)NDA MPPR'!$B$9:$AK$61,25,FALSE) -> 45988 | AC105: =VLOOKUP(C105,'5a)NDA MPPR'!$B$9:$AK$61,26,FALSE) -> 0 | AE105: =VLOOKUP(C105,'5a)NDA MPPR'!$B$9:$AK$61,28,FALSE) -> 75.794335 | AF105: =VLOOKUP(C105,'5a)NDA MPPR'!$B$9:$AK$61,29,FALSE) -> 73.803319 | AG105: =VLOOKUP(C105,'5a)NDA MPPR'!$B$9:$AK$61,30,FALSE) -> 72.459952 | AH105: =VLOOKUP(C105,'5a)NDA MPPR'!$B$9:$AK$61,31,FALSE) -> 1.0185394 | AI105: =VLOOKUP(C105,'5a)NDA MPPR'!$B$9:$AK$61,32,FALSE) -> 0.97373133 | AJ105: =VLOOKUP(C105,'5a)NDA MPPR'!$B$9:$AK$61,33,FALSE) -> 1 | AK105: =VLOOKUP(C105,'5a)NDA MPPR'!$B$9:$AK$61,34,FALSE) -> 0.97373133 | AM105: =VLOOKUP(C105,'5a)NDA MPPR'!$B$9:$AK$61,36,FALSE) -> G | AV105: 72.538784 | AW105: 45988 | AY105: 75.794335 | AZ105: =W105-AY105 -> 0 | BA105: 45834 | BB105: =AA105-BA105 -> 0
A106: =C105 -> PFCS Full Retrievals - Project 1 | B106: =VLOOKUP($C105,'5a)NDA MPPR'!$A$9:$AK$61,2,FALSE) -> Full Retrievals Project 1 (FRP1) will provide capability to continue progress made in Pile Fuel Cladding Silo (PFCS) Early Retrievals Project and is delivering the first 5 of 18 scope areas required to complete Full Retrievals operations. The first project benefit is a reduction in radiological risk to workers, public and the environment, which is an overall programme benefit included in the FRP1 Business Case with a forecast date of 2030, which has been communicated via the Enterprise Benefit Register. The benefit can only be realised after the start of Full Retrievals operations, not only the completion of FRP1. P80 sanction approved 29th April 2024, taking cumulative sanction released to £74.6m “not to exceed value of £75m” for the re-scoped project at the request of NDA Accounting Officer. The Delivery Confidence Assessment remains Amber. This is based on the current forecast project end date of November 2025. The lifetime EAC remains at £72.5m, with the actual cost at completion to be confirmed next period, following close out of final accounting and Gate 5. Baseline RAG also remains Amber, which reflects the current forecast end date of November 2025, 5 months later than current baseline. The P50 baseline is slightly greater than the sanction released due to indexation. In period the Post Investment Appraisal (PIA) was endorsed at PFCS Programme Board, with actions placed at Retrievals Portfolio Board to provide updates to the paper, and feedback for approval at Retrievals weekly team meeting. The gate 5 SPER was held on 21st October 2025, achieving a rating of Green for cost & schedule, and Amber for requirements and resources. There is no risk to project close-out on the basis that the amber ratings will be managed in the Programme’s forward strategy for full retrievals capability. The project is progressing the SPER findings and Retrievals Board actions ahead of the Readiness review, which would confirm readiness for PIA submission to the December Gated Project Oversight Committee (GPOC). Close out activities have not been impacted by the recent strike action. The Capability and Capacity RAG remains Green with no issues to report.
B108: 35/10274 | C108: MSSS Electrical Distribution Upgrade for Retrievals | D108: Sellafield | F108: =VLOOKUP($C108,'4b) SL EPO Extended Data Sheet'!$A$5:$AB$176,2,FALSE) -> A | G108: =VLOOKUP($C108,'4b) SL EPO Extended Data Sheet'!$A$5:$AB$176,3, FALSE) -> 0 | I108: =VLOOKUP($C108,'4b) SL EPO Extended Data Sheet'!$A$5:$AD$176,30, FALSE) -> FBC (Jan-23) | J108: =VLOOKUP($C108,'4b) SL EPO Extended Data Sheet'!$A$5:$AB$176,6, FALSE)/1000000 -> 27.608 | K108: =VLOOKUP($C108,'4b) SL EPO Extended Data Sheet'!$A$5:$AB$176,7, FALSE)/1000000 -> 28.241 | L108: =VLOOKUP($C108,'4b) SL EPO Extended Data Sheet'!$A$5:$AB$176,8, FALSE) -> 46053 | M108: =VLOOKUP($C108,'4b) SL EPO Extended Data Sheet'!$A$5:$AB$176,9, FALSE) -> 46203 | O108: =VLOOKUP($C108,'4b) SL EPO Extended Data Sheet'!$A$5:$AB$176,10, FALSE)/1000000 -> 0 | P108: =VLOOKUP($C108,'4b) SL EPO Extended Data Sheet'!$A$5:$AB$176,11, FALSE)/1000000 -> 28.241 | R108: =VLOOKUP($C108,'4b) SL EPO Extended Data Sheet'!$A$5:$AB$176,12,FALSE) -> A | S108: =VLOOKUP($C108,'4b) SL EPO Extended Data Sheet'!$A$5:$AB$176,13,FALSE) -> 0 | U108: =VLOOKUP($C108,'4b) SL EPO Extended Data Sheet'!$A$5:$AE$176,31,FALSE) -> FBC (Mar-23) | W108: =VLOOKUP($C108,'4b) SL EPO Extended Data Sheet'!$A$5:$AC$176,16,FALSE)/1000000 -> 18.788383 | X108: =VLOOKUP($C108,'4b) SL EPO Extended Data Sheet'!$A$5:$AC$176,17,FALSE)/1000000 -> 28.070365 | Y108: =VLOOKUP($C108,'4b) SL EPO Extended Data Sheet'!$A$5:$AC$176,18,FALSE)/1000000 -> 0.0241206 | Z108: =VLOOKUP($C108,'4b) SL EPO Extended Data Sheet'!$A$5:$AB$176,16,FALSE)/1000000 -> 18.788383 | AA108: =VLOOKUP($C108,'4b) SL EPO Extended Data Sheet'!$A$5:$AC$176,19,FALSE) -> 46043 | AB108: =VLOOKUP($C108,'4b) SL EPO Extended Data Sheet'!$A$5:$AC$176,20,FALSE) -> 46469 | AC108: =VLOOKUP($C108,'4b) SL EPO Extended Data Sheet'!$A$5:$AC$176,21,FALSE) -> 0 | AD108: =VLOOKUP($C108,'4b) SL EPO Extended Data Sheet'!$A$5:$AB$176,15,FALSE)/1000000 -> 0.045015 | AE108: =VLOOKUP($C108,'4b) SL EPO Extended Data Sheet'!$A$5:$AC$176,22,FALSE)/1000000 -> 26.770141 | AF108: =VLOOKUP($C108,'4b) SL EPO Extended Data Sheet'!$A$5:$AC$176,23,FALSE)/1000000 -> 26.108119 | AG108: =VLOOKUP($C108,'4b) SL EPO Extended Data Sheet'!$A$5:$AC$176,24,FALSE)/1000000 -> 27.674314 | AH108: =VLOOKUP($C108,'4b) SL EPO Extended Data Sheet'!$A$5:$AC$176,25,FALSE) -> 0.9434062 | AI108: =VLOOKUP($C108,'4b) SL EPO Extended Data Sheet'!$A$5:$AC$176,26,FALSE) -> 0.97527014 | AJ108: =VLOOKUP($C108,'4b) SL EPO Extended Data Sheet'!$A$5:$AC$176,27,FALSE) -> 1.4248241 | AK108: =VLOOKUP($C108,'4b) SL EPO Extended Data Sheet'!$A$5:$AC$176,28,FALSE) -> 1.3895884 | AL108: =VLOOKUP($C108,'4b) SL EPO Extended Data Sheet'!$A$6:$AB$176,15,FALSE) -> 45015 | AM108: =VLOOKUP($C108,'4b) SL EPO Extended Data Sheet'!$A$5:$AC$176,29,FALSE) -> G | AV108: 28.046245 | AW108: 46469 | AY108: 18.788383 | AZ108: =W108-AY108 -> 0 | BA108: 46043 | BB108: =AA108-BA108 -> 0
A109: =C108 -> MSSS Electrical Distribution Upgrade for Retrievals | B109: The Electrical Distribution project is required to replace the aged and obsolete building electrical “Level 2” infrastructure with modern Power Distribution boards which will power the Silo Emptying Plant (SEP) machines throughout waste retrieval operation. The project is in the final stages of construction following energisation of the board and continues with load transfers. The first project benefit was realised in support of Magnox Swarf Storage Silo (MSSS) Facility resilience at the start of retrievals in April 2022. The Delivery Confidence Assessment is Amber with the date unlikely to be recovered but still forecast to complete within the business case P80 sanction (which has now been fully released to the project), with a close out date of March 2027. The Baseline RAG is also Amber with delivery beyond the baseline P50 date however transfer of all critical systems and power to SEP 1 and 2 have been delivered, ongoing load transfers address obsolescence issues on some existing equipment. The Baseline RAG status is Amber as not all load transfers will take place ahead of the baseline P50 date. Many of the remaining load transfers require outages and are now aligned with the programme integrated schedule to minimise disruption of plant. This schedule is, however, being pressured by the impact from current contractor strike action although the project will mitigate this by adjusting the order of transfers where possible. Note: The Baseline is showing a much lower value than the sanction, as some previous early works were completed under a different project (Sanction transferred, but Baseline not included). Capability & Capacity RAG status is Green.
B111: 35/06075 | C111: SEP Solid Waste Storage Retrievals | D111: Sellafield | F111: =VLOOKUP(C111,'5a)NDA MPPR'!$B$9:$AK$61,3,FALSE) -> A | G111: =VLOOKUP(C111,'5a)NDA MPPR'!$B$9:$AK$61,4,FALSE) -> 0 | I111: =VLOOKUP(C111,'5a)NDA MPPR'!$B$9:$AK$61,6,FALSE) -> FBC (Oct-23) | J111: =VLOOKUP(C111,'5a)NDA MPPR'!$B$9:$AK$61,7,FALSE) -> 866.7 | K111: =VLOOKUP(C111,'5a)NDA MPPR'!$B$9:$AK$61,8,FALSE) -> 897.9 | L111: =VLOOKUP(C111,'5a)NDA MPPR'!$B$9:$AK$61,9,FALSE) -> 46505 | M111: =VLOOKUP(C111,'5a)NDA MPPR'!$B$9:$AK$61,10,FALSE) -> 47053 | O111: =VLOOKUP(C111,'5a)NDA MPPR'!$B$9:$AK$61,12,FALSE) -> 897.9 | P111: =VLOOKUP(C111,'5a)NDA MPPR'!$B$9:$AK$61,13,FALSE) -> 897.9 | R111: =VLOOKUP(C111,'5a)NDA MPPR'!$B$9:$AK$61,15,FALSE) -> A | S111: =VLOOKUP(C111,'5a)NDA MPPR'!$B$9:$AK$61,16,FALSE) -> 0 | U111: =VLOOKUP(C111,'5a)NDA MPPR'!$B$9:$AK$61,18,FALSE) -> FBC (Apr-22) | W111: =VLOOKUP(C111,'5a)NDA MPPR'!$B$9:$AK$61,20,FALSE) -> 803.03225 | X111: =VLOOKUP(C111,'5a)NDA MPPR'!$B$9:$AK$61,21,FALSE) -> 887.19569 | Y111: =VLOOKUP(C111,'5a)NDA MPPR'!$B$9:$AK$61,22,FALSE) -> 0.1 | AA111: =VLOOKUP(C111,'5a)NDA MPPR'!$B$9:$AK$61,24,FALSE) -> 46505 | AB111: =VLOOKUP(C111,'5a)NDA MPPR'!$B$9:$AK$61,25,FALSE) -> 46717 | AC111: =VLOOKUP(C111,'5a)NDA MPPR'!$B$9:$AK$61,26,FALSE) -> 0 | AE111: =VLOOKUP(C111,'5a)NDA MPPR'!$B$9:$AK$61,28,FALSE) -> 798.33897 | AF111: =VLOOKUP(C111,'5a)NDA MPPR'!$B$9:$AK$61,29,FALSE) -> 785.30334 | AG111: =VLOOKUP(C111,'5a)NDA MPPR'!$B$9:$AK$61,30,FALSE) -> 869.84961 | AH111: =VLOOKUP(C111,'5a)NDA MPPR'!$B$9:$AK$61,31,FALSE) -> 0.90280358 | AI111: =VLOOKUP(C111,'5a)NDA MPPR'!$B$9:$AK$61,32,FALSE) -> 0.98367156 | AJ111: =VLOOKUP(C111,'5a)NDA MPPR'!$B$9:$AK$61,33,FALSE) -> 0.99415555 | AK111: =VLOOKUP(C111,'5a)NDA MPPR'!$B$9:$AK$61,34,FALSE) -> 0.97792254 | AM111: =VLOOKUP(C111,'5a)NDA MPPR'!$B$9:$AK$61,36,FALSE) -> G | AV111: 887.10816 | AW111: 46717 | AY111: 803.03225 | AZ111: =W111-AY111 -> 0 | BA111: 46505 | BB111: =AA111-BA111 -> 0
A112: =C111 -> SEP Solid Waste Storage Retrievals | B112: =VLOOKUP($C111,'5a)NDA MPPR'!$A$9:$AK$61,2,FALSE) -> This project enables retrievals in Magnox Swarf Storage Silos (MSSS) Original Building and the 1st Extension. This includes completion of Silo Emptying Plant (SEP) 2 and SEP 1. The first project benefit was completed in 2022, enabling the successful start of Retrievals from SEP 2. The Delivery Confidence Assessment remains Amber in light of challenges to the SEP1 commissioning schedule, although in the context of the full project, issues appear resolvable and should not threaten P80 values. The project has reviewed assumptions underpinning the SEP 1 inactive and active commissioning and based on the feedback is taking steps to address perceived delivery gaps, including addressing potential inefficiencies in the approach to commissioning and pre-operations (teams shape and size, working patterns etc). Challenges in delivering commissioning tasks ahead of the SEP1 move between compartments later this year resulted in an impact on YE BCWP and additional commissioning resource usage resulted in an EAC increase in period. This flowed through to a minor movement of the planned first skip out date in November 2027. The Baseline RAG status remains Amber. This period, the project continued to deliver commissioning activities on SEP1, although efficiency was impacted by strike action. On SEP2 raking was successfully completed, which has resulted in a level waste bed for retrievals later this FY. The Project team also commenced a review to inform configuration management across SEP1 and SEP2, with a focus on the activities required to close out SEP2. The Vent project has continued to work through inactive commissioning scope, with utilities supporting next period for energisation of new capability in the Lateral Restraint Tower. Although there is a significant negative cost variance between the EAC and Baseline, £64.3m of this was historical (prior to 2022) and although included in the current sanction, is not included in the Baseline. The Capability and Capacity remains Green, based on the assumption that resources will be made available to support the prioritised Original Building/1st Extension scope. Design capability resource requests are to be submitted in November. Several programme requirements need to be delivered in parallel with the retrievals project scope to enable a full retrieval capability, this includes the Skip Fill Optimisation opportunity and key SEP Machine improvements such as to manage large items, deal with pressurised containers and manage waste craters. The project and programme are working together to minimise the impact of implementation of this scope, (which is additional to the sanctioned Business Case), on the project deliverables.
B114: 35/05684 | C114: MSSS Upgrades for Retrievals & Resilience | D114: Sellafield | F114: =VLOOKUP($C114,'4b) SL EPO Extended Data Sheet'!$A$5:$AB$176,2,FALSE) -> G | G114: =VLOOKUP($C114,'4b) SL EPO Extended Data Sheet'!$A$5:$AB$176,3, FALSE) -> 0 | I114: =VLOOKUP($C114,'4b) SL EPO Extended Data Sheet'!$A$5:$AD$176,30, FALSE) -> FBC (Feb-23) | J114: =VLOOKUP($C114,'4b) SL EPO Extended Data Sheet'!$A$5:$AB$176,6, FALSE)/1000000 -> 105 | K114: =VLOOKUP($C114,'4b) SL EPO Extended Data Sheet'!$A$5:$AB$176,7, FALSE)/1000000 -> 105.5 | L114: =VLOOKUP($C114,'4b) SL EPO Extended Data Sheet'!$A$5:$AB$176,8, FALSE) -> 45747 | M114: =VLOOKUP($C114,'4b) SL EPO Extended Data Sheet'!$A$5:$AB$176,9, FALSE) -> 47361 | O114: =VLOOKUP($C114,'4b) SL EPO Extended Data Sheet'!$A$5:$AB$176,10, FALSE)/1000000 -> 0 | P114: =VLOOKUP($C114,'4b) SL EPO Extended Data Sheet'!$A$5:$AB$176,11, FALSE)/1000000 -> 105.5 | R114: =VLOOKUP($C114,'4b) SL EPO Extended Data Sheet'!$A$5:$AB$176,12,FALSE) -> A | S114: =VLOOKUP($C114,'4b) SL EPO Extended Data Sheet'!$A$5:$AB$176,13,FALSE) -> 0 | U114: =VLOOKUP($C114,'4b) SL EPO Extended Data Sheet'!$A$5:$AE$176,31,FALSE) -> FBC (Oct-22) | W114: =VLOOKUP($C114,'4b) SL EPO Extended Data Sheet'!$A$5:$AC$176,16,FALSE)/1000000 -> 103.81815 | X114: =VLOOKUP($C114,'4b) SL EPO Extended Data Sheet'!$A$5:$AC$176,17,FALSE)/1000000 -> 101.98066 | Y114: =VLOOKUP($C114,'4b) SL EPO Extended Data Sheet'!$A$5:$AC$176,18,FALSE)/1000000 -> 0.0318267 | Z114: =VLOOKUP($C114,'4b) SL EPO Extended Data Sheet'!$A$5:$AB$176,16,FALSE)/1000000 -> 103.81815 | AA114: =VLOOKUP($C114,'4b) SL EPO Extended Data Sheet'!$A$5:$AC$176,19,FALSE) -> 45747 | AB114: =VLOOKUP($C114,'4b) SL EPO Extended Data Sheet'!$A$5:$AC$176,20,FALSE) -> 46660 | AC114: =VLOOKUP($C114,'4b) SL EPO Extended Data Sheet'!$A$5:$AC$176,21,FALSE) -> 0 | AD114: =VLOOKUP($C114,'4b) SL EPO Extended Data Sheet'!$A$5:$AB$176,15,FALSE)/1000000 -> 0.044865 | AE114: =VLOOKUP($C114,'4b) SL EPO Extended Data Sheet'!$A$5:$AC$176,22,FALSE)/1000000 -> 103.81815 | AF114: =VLOOKUP($C114,'4b) SL EPO Extended Data Sheet'!$A$5:$AC$176,23,FALSE)/1000000 -> 92.238614 | AG114: =VLOOKUP($C114,'4b) SL EPO Extended Data Sheet'!$A$5:$AC$176,24,FALSE)/1000000 -> 100.6027 | AH114: =VLOOKUP($C114,'4b) SL EPO Extended Data Sheet'!$A$5:$AC$176,25,FALSE) -> 0.91686021 | AI114: =VLOOKUP($C114,'4b) SL EPO Extended Data Sheet'!$A$5:$AC$176,26,FALSE) -> 0.88846326 | AJ114: =VLOOKUP($C114,'4b) SL EPO Extended Data Sheet'!$A$5:$AC$176,27,FALSE) -> 1 | AK114: =VLOOKUP($C114,'4b) SL EPO Extended Data Sheet'!$A$5:$AC$176,28,FALSE) -> 0.88846326 | AL114: =VLOOKUP($C114,'4b) SL EPO Extended Data Sheet'!$A$6:$AB$176,15,FALSE) -> 44865 | AM114: =VLOOKUP($C114,'4b) SL EPO Extended Data Sheet'!$A$5:$AC$176,29,FALSE) -> G | AV114: 101.94883 | AW114: 46660 | AY114: 103.81815 | AZ114: =W114-AY114 -> 0 | BA114: 45747 | BB114: =AA114-BA114 -> 0
A115: =C114 -> MSSS Upgrades for Retrievals & Resilience | B115: This is a Portfolio of smaller tasks, all of which have been historically sanctioned locally, including Building roof replacement and upgrades to Building services. The project has been delivering the final tasks, upgrading some building electrical switchboards and refurbishment of steam supplies, before closing the project. The first project benefit was realised in support of Magnox Swarf Storage Silo (MSSS) Facility resilience, by delivering numerous building services upgrades, in support of the start of MSSS retrievals in April 2022. The Delivery Confidence Assessment remains Green as remaining work is low complexity and low cost. The P50 cost and schedule remains within P50 sanction, however, the overall end date has exceeded the Baseline March 2025 date as Change Control Request (CCR)'s were not implemented on previously approved Business Cases recognising this is a portfolio of smaller tasks. The Baseline RAG status remains Amber as we will deliver within cost but beyond the reported baseline P50 date. The work on this stream is protracted as it requires interfaces with outages and other tasks, it is generally lower priority against other areas of the MSSS Facility. In period, the project did not achieve a window to complete Condensate system outage work. This was further impacted in October due to strike action and will continue to be so during strike action. Condensate system works will need to be halted and strategy for delivery will need to be revisited. Capability & Capacity RAG status is Green
B117: 35/09198 | C117: Sellafield 3m3 Box Supply - Tranche A | D117: Sellafield | F117: =VLOOKUP($C117,'4b) SL EPO Extended Data Sheet'!$A$5:$AB$176,2,FALSE) -> G | G117: =VLOOKUP($C117,'4b) SL EPO Extended Data Sheet'!$A$5:$AB$176,3, FALSE) -> 0 | I117: =VLOOKUP($C117,'4b) SL EPO Extended Data Sheet'!$A$5:$AD$176,30, FALSE) -> FBC (Sep-16) | J117: =VLOOKUP($C117,'4b) SL EPO Extended Data Sheet'!$A$5:$AB$176,6, FALSE)/1000000 -> 0 | K117: =VLOOKUP($C117,'4b) SL EPO Extended Data Sheet'!$A$5:$AB$176,7, FALSE)/1000000 -> 0 | L117: =VLOOKUP($C117,'4b) SL EPO Extended Data Sheet'!$A$5:$AB$176,8, FALSE) | M117: =VLOOKUP($C117,'4b) SL EPO Extended Data Sheet'!$A$5:$AB$176,9, FALSE) | O117: =VLOOKUP($C117,'4b) SL EPO Extended Data Sheet'!$A$5:$AB$176,10, FALSE)/1000000 -> 36.278 | P117: =VLOOKUP($C117,'4b) SL EPO Extended Data Sheet'!$A$5:$AB$176,11, FALSE)/1000000 -> 36.278 | R117: =VLOOKUP($C117,'4b) SL EPO Extended Data Sheet'!$A$5:$AB$176,12,FALSE) -> G | S117: =VLOOKUP($C117,'4b) SL EPO Extended Data Sheet'!$A$5:$AB$176,13,FALSE) -> 0 | U117: =VLOOKUP($C117,'4b) SL EPO Extended Data Sheet'!$A$5:$AE$176,31,FALSE) -> FBC (Apr-23) | W117: =VLOOKUP($C117,'4b) SL EPO Extended Data Sheet'!$A$5:$AC$176,16,FALSE)/1000000 -> 74.471369 | X117: =VLOOKUP($C117,'4b) SL EPO Extended Data Sheet'!$A$5:$AC$176,17,FALSE)/1000000 -> 36.17178 | Y117: =VLOOKUP($C117,'4b) SL EPO Extended Data Sheet'!$A$5:$AC$176,18,FALSE)/1000000 -> 0.00613517 | Z117: =VLOOKUP($C117,'4b) SL EPO Extended Data Sheet'!$A$5:$AB$176,16,FALSE)/1000000 -> 74.471369 | AA117: =VLOOKUP($C117,'4b) SL EPO Extended Data Sheet'!$A$5:$AC$176,19,FALSE) -> 55152 | AB117: =VLOOKUP($C117,'4b) SL EPO Extended Data Sheet'!$A$5:$AC$176,20,FALSE) -> 46010 | AC117: =VLOOKUP($C117,'4b) SL EPO Extended Data Sheet'!$A$5:$AC$176,21,FALSE) -> 0 | AD117: =VLOOKUP($C117,'4b) SL EPO Extended Data Sheet'!$A$5:$AB$176,15,FALSE)/1000000 -> 0.045017 | AE117: =VLOOKUP($C117,'4b) SL EPO Extended Data Sheet'!$A$5:$AC$176,22,FALSE)/1000000 -> 34.112975 | AF117: =VLOOKUP($C117,'4b) SL EPO Extended Data Sheet'!$A$5:$AC$176,23,FALSE)/1000000 -> 34.112975 | AG117: =VLOOKUP($C117,'4b) SL EPO Extended Data Sheet'!$A$5:$AC$176,24,FALSE)/1000000 -> 36.17178 | AH117: =VLOOKUP($C117,'4b) SL EPO Extended Data Sheet'!$A$5:$AC$176,25,FALSE) -> 0.94308255 | AI117: =VLOOKUP($C117,'4b) SL EPO Extended Data Sheet'!$A$5:$AC$176,26,FALSE) -> 0.99999999 | AJ117: =VLOOKUP($C117,'4b) SL EPO Extended Data Sheet'!$A$5:$AC$176,27,FALSE) -> 0.45806832 | AK117: =VLOOKUP($C117,'4b) SL EPO Extended Data Sheet'!$A$5:$AC$176,28,FALSE) -> 0.45806832 | AL117: =VLOOKUP($C117,'4b) SL EPO Extended Data Sheet'!$A$6:$AB$176,15,FALSE) -> 45017 | AM117: =VLOOKUP($C117,'4b) SL EPO Extended Data Sheet'!$A$5:$AC$176,29,FALSE) -> G | AV117: 36.165645 | AW117: 46010 | AY117: 74.471369 | AZ117: =W117-AY117 -> 0 | BA117: 55152 | BB117: =AA117-BA117 -> 0
A118: =C117 -> Sellafield 3m3 Box Supply - Tranche A | B118: Gate 5 SPER held 24th September 2025, Green rating achieved. Post Investment Appraisal (PIA) form to be discussed at GPOC on 12th November. Delivery Confidence Assessment Green. First project benefit complete; Pile Fuel Cladding Silo (PFCS) and Magnox Swarf Storage Silo (MSSS), boxes delivered remains healthy to satisfy current demand for at least the next 24 months. EAC remains within sanction value. Baseline RAG remains green. Handover to Manufacturing Products Organisation (MPO) for future box manufacture complete. SL team have received all Darchem Engineering Limited (DEL) products and are working with Metalcraft SMC to provide concessions for remaining skips and open up tolerances for future products. Capability and Capacity RAG remains Green, all resource in place to close out project.
B121: Value Stream: Remediation
B123: Portfolio Summary
B125: 35/10398 | C125: Calder Land Clearance | D125: Sellafield | F125: =VLOOKUP($C125,'4b) SL EPO Extended Data Sheet'!$A$5:$AB$176,2,FALSE) -> R | G125: =VLOOKUP($C125,'4b) SL EPO Extended Data Sheet'!$A$5:$AB$176,3, FALSE) -> 0 | I125: =VLOOKUP($C125,'4b) SL EPO Extended Data Sheet'!$A$5:$AD$176,30, FALSE) -> FBC (Jul-19) | J125: =VLOOKUP($C125,'4b) SL EPO Extended Data Sheet'!$A$5:$AB$176,6, FALSE)/1000000 -> 47.818 | K125: =VLOOKUP($C125,'4b) SL EPO Extended Data Sheet'!$A$5:$AB$176,7, FALSE)/1000000 -> 51.06 | L125: =VLOOKUP($C125,'4b) SL EPO Extended Data Sheet'!$A$5:$AB$176,8, FALSE) -> 46058 | M125: =VLOOKUP($C125,'4b) SL EPO Extended Data Sheet'!$A$5:$AB$176,9, FALSE) -> 46321 | O125: =VLOOKUP($C125,'4b) SL EPO Extended Data Sheet'!$A$5:$AB$176,10, FALSE)/1000000 -> 51.06 | P125: =VLOOKUP($C125,'4b) SL EPO Extended Data Sheet'!$A$5:$AB$176,11, FALSE)/1000000 -> 47.818 | R125: =VLOOKUP($C125,'4b) SL EPO Extended Data Sheet'!$A$5:$AB$176,12,FALSE) -> R | S125: =VLOOKUP($C125,'4b) SL EPO Extended Data Sheet'!$A$5:$AB$176,13,FALSE) -> 0 | U125: =VLOOKUP($C125,'4b) SL EPO Extended Data Sheet'!$A$5:$AE$176,31,FALSE) -> FBC (Mar-22) | W125: =VLOOKUP($C125,'4b) SL EPO Extended Data Sheet'!$A$5:$AC$176,16,FALSE)/1000000 -> 38.593832 | X125: =VLOOKUP($C125,'4b) SL EPO Extended Data Sheet'!$A$5:$AC$176,17,FALSE)/1000000 -> 38.416249 | Y125: =VLOOKUP($C125,'4b) SL EPO Extended Data Sheet'!$A$5:$AC$176,18,FALSE)/1000000 -> 0.00211471 | Z125: =VLOOKUP($C125,'4b) SL EPO Extended Data Sheet'!$A$5:$AB$176,16,FALSE)/1000000 -> 38.593832 | AA125: =VLOOKUP($C125,'4b) SL EPO Extended Data Sheet'!$A$5:$AC$176,19,FALSE) -> 46058 | AB125: =VLOOKUP($C125,'4b) SL EPO Extended Data Sheet'!$A$5:$AC$176,20,FALSE) -> 46818 | AC125: =VLOOKUP($C125,'4b) SL EPO Extended Data Sheet'!$A$5:$AC$176,21,FALSE) -> 61 | AD125: =VLOOKUP($C125,'4b) SL EPO Extended Data Sheet'!$A$5:$AB$176,15,FALSE)/1000000 -> 0.044634 | AE125: =VLOOKUP($C125,'4b) SL EPO Extended Data Sheet'!$A$5:$AC$176,22,FALSE)/1000000 -> 38.541338 | AF125: =VLOOKUP($C125,'4b) SL EPO Extended Data Sheet'!$A$5:$AC$176,23,FALSE)/1000000 -> 23.143714 | AG125: =VLOOKUP($C125,'4b) SL EPO Extended Data Sheet'!$A$5:$AC$176,24,FALSE)/1000000 -> 27.861415 | AH125: =VLOOKUP($C125,'4b) SL EPO Extended Data Sheet'!$A$5:$AC$176,25,FALSE) -> 0.8306726 | AI125: =VLOOKUP($C125,'4b) SL EPO Extended Data Sheet'!$A$5:$AC$176,26,FALSE) -> 0.60049068 | AJ125: =VLOOKUP($C125,'4b) SL EPO Extended Data Sheet'!$A$5:$AC$176,27,FALSE) -> 0.99863982 | AK125: =VLOOKUP($C125,'4b) SL EPO Extended Data Sheet'!$A$5:$AC$176,28,FALSE) -> 0.59967391 | AL125: =VLOOKUP($C125,'4b) SL EPO Extended Data Sheet'!$A$6:$AB$176,15,FALSE) -> #N/A | AM125: =VLOOKUP($C125,'4b) SL EPO Extended Data Sheet'!$A$5:$AC$176,29,FALSE) -> A | AV125: 38.414134 | AW125: 46757 | AY125: 38.593832 | AZ125: =W125-AY125 -> 0 | BA125: 46058 | BB125: =AA125-BA125 -> 0
A126: =C125 -> Calder Land Clearance | B126: The scope of the Calder Land Clearance (CLC) project is to demolish 4 major structures on the Calder Hall site to base slab level, to enable new capabilities to be built to support the Site Ion Exchange Effluent Plant (SIXEP). To date, 3 of the 4 major structures have been demolished – Turbine Hall A remains to be done. The Delivery Confidence Assessment remains Red, due to significant Turbine Hall A asbestos removal activities undertaken in FY23/24, 24/25 and 25/26, extending the scheduled completion date past P80 of the original Business Case; as a result, the project benefit – land being available to Sites Ion Exchange Effluent Plant (SIXEP) Waste Management Receipt Facility (SWMRF) Project - is delayed until Summer 2027 (note the project end date is 6 months later due to SL project close out activities). This new date is not currently impinging SWMRF planned work, and regular communications between projects continues to ensure if an impact is forecast, mitigations can be developed. To minimise impact to the SIXEP programme, agreements are now in place for early access to the West of the CLC site, to allow SIXEP drilling programme to commence, currently mobilizing (October 2025). Although a mitigator to the SIXEP schedule, providing West of site access introduces two new risks to the CLC project: firstly, the timely transfer of land back to CLC to complete demolition; and, secondly, the land constraints for laydown of waste during de-plant and demolition. These risks are currently not reflected within the CLC schedule. Stakeholder engagement with SIXEP is aiming to avoid an impact for transferring land back at the appropriate time, whilst additional land has been identified for CLC use to mitigate land constraints. There is no change to the P50 lifecycle schedule or cost the Baseline RAG remains Red due to schedule forecast. This is due to the Turbine Hall A asbestos removal activities extending the scheduled completion date beyond the baseline P50. A Change Control Request (CCR) is being developed for implementation in period 9 to include the additional asbestos removal scope. It is expected that the delivery confidence assessment, baseline RAG and CPI will go Green. In Period, the Contractor continues with asbestos cleaning specifically within Turbine 4 trench, and Turbine 1. In period slippage of -61 days is due to: The issue of trench cleaning taking longer than planned – problem solving is ongoing to understand options to prevent further schedule extensions, or recover, if possible; the removal of all planned weekend work from the schedule due to work to rule until February 2026 and further Industrial Action, which is a Sellafield risk under this contract. Compensation Events (CEs) are expected and may impact the lifecycle costs once understood. The Capability and Capacity RAG is now Amber due to the trench cleaning issue. The lifecycle remains unchanged this period.
B128: 35/09707 | C128: LAETP Floc Retrieval | D128: Sellafield | F128: =VLOOKUP(C128,'5a)NDA MPPR'!$B$9:$AK$61,3,FALSE) -> A | G128: =VLOOKUP(C128,'5a)NDA MPPR'!$B$9:$AK$61,4,FALSE) -> 0 | I128: =VLOOKUP(C128,'5a)NDA MPPR'!$B$9:$AK$61,6,FALSE) -> FBC (Jun-24) | J128: =VLOOKUP(C128,'5a)NDA MPPR'!$B$9:$AK$61,7,FALSE) -> 75.1 | K128: =VLOOKUP(C128,'5a)NDA MPPR'!$B$9:$AK$61,8,FALSE) -> 79.8 | L128: =VLOOKUP(C128,'5a)NDA MPPR'!$B$9:$AK$61,9,FALSE) -> 47189 | M128: =VLOOKUP(C128,'5a)NDA MPPR'!$B$9:$AK$61,10,FALSE) -> 47339 | O128: =VLOOKUP(C128,'5a)NDA MPPR'!$B$9:$AK$61,12,FALSE) -> 90.2 | P128: =VLOOKUP(C128,'5a)NDA MPPR'!$B$9:$AK$61,13,FALSE) -> 90.2 | R128: =VLOOKUP(C128,'5a)NDA MPPR'!$B$9:$AK$61,15,FALSE) -> R | S128: =VLOOKUP(C128,'5a)NDA MPPR'!$B$9:$AK$61,16,FALSE) -> 0 | U128: =VLOOKUP(C128,'5a)NDA MPPR'!$B$9:$AK$61,18,FALSE) -> FBC (Oct-23) | W128: =VLOOKUP(C128,'5a)NDA MPPR'!$B$9:$AK$61,20,FALSE) -> 57.796824 | X128: =VLOOKUP(C128,'5a)NDA MPPR'!$B$9:$AK$61,21,FALSE) -> 87.561965 | Y128: =VLOOKUP(C128,'5a)NDA MPPR'!$B$9:$AK$61,22,FALSE) -> 0 | AA128: =VLOOKUP(C128,'5a)NDA MPPR'!$B$9:$AK$61,24,FALSE) -> 46524 | AB128: =VLOOKUP(C128,'5a)NDA MPPR'!$B$9:$AK$61,25,FALSE) -> 47189 | AC128: =VLOOKUP(C128,'5a)NDA MPPR'!$B$9:$AK$61,26,FALSE) -> 0 | AE128: =VLOOKUP(C128,'5a)NDA MPPR'!$B$9:$AK$61,28,FALSE) -> 52.791888 | AF128: =VLOOKUP(C128,'5a)NDA MPPR'!$B$9:$AK$61,29,FALSE) -> 44.614723 | AG128: =VLOOKUP(C128,'5a)NDA MPPR'!$B$9:$AK$61,30,FALSE) -> 74.336656 | AH128: =VLOOKUP(C128,'5a)NDA MPPR'!$B$9:$AK$61,31,FALSE) -> 0.60017125 | AI128: =VLOOKUP(C128,'5a)NDA MPPR'!$B$9:$AK$61,32,FALSE) -> 0.84510566 | AJ128: =VLOOKUP(C128,'5a)NDA MPPR'!$B$9:$AK$61,33,FALSE) -> 0.91340465 | AK128: =VLOOKUP(C128,'5a)NDA MPPR'!$B$9:$AK$61,34,FALSE) -> 0.77192344 | AM128: =VLOOKUP(C128,'5a)NDA MPPR'!$B$9:$AK$61,36,FALSE) -> A | AV128: 87.561272 | AW128: 47189 | AY128: 57.796824 | AZ128: =W128-AY128 -> 0 | BA128: 46524 | BB128: =AA128-BA128 -> 0
A129: =C128 -> LAETP Floc Retrieval | B129: =VLOOKUP($C128,'5a)NDA MPPR'!$A$9:$AK$61,2,FALSE) -> The overall intent of the LAETP (Low Active Effluent Treatment Plant) Floc (flocculant) Retrieval project is to provide the necessary equipment, documentation, knowledge transfer and training to enable the Alpha Operations teams to safely and effectively remove circa 86m3 of non-adhered (loose) floc from four existing and degrading Holding Tanks located on the Sellafield site. The project benefit is handover of the retrieval’s equipment to the Alpha Remediation Operations team, the project provides the capability to retrieve floc from the four storage tanks. This benefit remains on track to be delivered within the strategic tolerances of the civil tank substantiation and Low-Active Effluent Management Group (LAEMG) downstream plant availability. Delivery Confidence Assessment remains at Amber due to the forecast project end date which is now 12 months later than the P80 date in the approved business case and uncertainty around the projects ability to stay within the P80 costs however cost forecast currently remains within the sanction approved to NDA. The project is executing planned recovery activities, along with a sanction drawdown timeline and is tracking to meet these commitments. The NDA GIC approved the drawdown of available sanction of £90.2M and 337 additional days, this subject to an additional hold point for further assurance towards the end of construction. This follows a project reset which included revised delivery strategy and amendments to contract. A Change Control Request (CCR) is forecast to be implemented for Period 9. The Project faces difficulty in several areas including contractor performance Cumbria Nuclear Solutions Limited (CNSL), credible and realistic schedule and estimate, contract management, management of change, design delivery and organisational structures (SL and CNSL). Output of the updated schedule is now reflected in outward reporting hence the significant change in project end date, this update reflects the model output which has been assured during a joint SL and NDA project review. The project forecast and subsequent impact on Key Decommissioning Milestone (KDM) Removal of non-adhered Floc by June 2030 is currently being assessed and will be evaluated in the coming periods. The Baseline RAG will be Amber on CCR implementation in Period 9 (currently Red). The project continues to face challenges in delivery and in period has been affected by recent industrial action at the Sellafield site, ongoing strike action continues to impact progress and poses significant risk to future delivery. Attention remains on completing detailed design to de-risk the remainder of the construction scope, a key focus is now on the United Kingdom Conformity Assessed (UKCA) A marking strategy for the equipment following the end of the current contract arrangements, maturity will be assessed at the wrap up Multi Disciplined Design Review (MDDR) in February 2026, where CNSL will hand over the work completed to date. Issues have been encountered in fabrication of key process modules; timely completion of these final procurements is key to enabling the remainder of the construction work. Capability and Capacity RAG is Amber, the self-delivery team following descope has largely been secured, Commissioning Request For Quote (RFQ) will mobilise remaining capability Period 9.
B131: 35/05396 | C131: Chimney Decommissioning Phase 2F | D131: Sellafield | F131: =VLOOKUP(C131,'5a)NDA MPPR'!$B$9:$AK$61,3,FALSE) -> A | G131: =VLOOKUP(C131,'5a)NDA MPPR'!$B$9:$AK$61,4,FALSE) -> 0 | I131: =VLOOKUP(C131,'5a)NDA MPPR'!$B$9:$AK$61,6,FALSE) -> FBC (Apr-21) | J131: =VLOOKUP(C131,'5a)NDA MPPR'!$B$9:$AK$61,7,FALSE) -> 116.6 | K131: =VLOOKUP(C131,'5a)NDA MPPR'!$B$9:$AK$61,8,FALSE) -> 122.6 | L131: =VLOOKUP(C131,'5a)NDA MPPR'!$B$9:$AK$61,9,FALSE) -> 46874 | M131: =VLOOKUP(C131,'5a)NDA MPPR'!$B$9:$AK$61,10,FALSE) -> 47239 | O131: =VLOOKUP(C131,'5a)NDA MPPR'!$B$9:$AK$61,12,FALSE) -> 139.6 | P131: =VLOOKUP(C131,'5a)NDA MPPR'!$B$9:$AK$61,13,FALSE) -> 116.6 | R131: =VLOOKUP(C131,'5a)NDA MPPR'!$B$9:$AK$61,15,FALSE) -> R | S131: =VLOOKUP(C131,'5a)NDA MPPR'!$B$9:$AK$61,16,FALSE) -> 0 | U131: =VLOOKUP(C131,'5a)NDA MPPR'!$B$9:$AK$61,18,FALSE) -> FBC (Feb-24) | W131: =VLOOKUP(C131,'5a)NDA MPPR'!$B$9:$AK$61,20,FALSE) -> 144.83408 | X131: =VLOOKUP(C131,'5a)NDA MPPR'!$B$9:$AK$61,21,FALSE) -> 148.90141 | Y131: =VLOOKUP(C131,'5a)NDA MPPR'!$B$9:$AK$61,22,FALSE) -> 0 | AA131: =VLOOKUP(C131,'5a)NDA MPPR'!$B$9:$AK$61,24,FALSE) -> 47882 | AB131: =VLOOKUP(C131,'5a)NDA MPPR'!$B$9:$AK$61,25,FALSE) -> 48684 | AC131: =VLOOKUP(C131,'5a)NDA MPPR'!$B$9:$AK$61,26,FALSE) -> 0 | AE131: =VLOOKUP(C131,'5a)NDA MPPR'!$B$9:$AK$61,28,FALSE) -> 112.60935 | AF131: =VLOOKUP(C131,'5a)NDA MPPR'!$B$9:$AK$61,29,FALSE) -> 100.76631 | AG131: =VLOOKUP(C131,'5a)NDA MPPR'!$B$9:$AK$61,30,FALSE) -> 100.57339 | AH131: =VLOOKUP(C131,'5a)NDA MPPR'!$B$9:$AK$61,31,FALSE) -> 1.0019182 | AI131: =VLOOKUP(C131,'5a)NDA MPPR'!$B$9:$AK$61,32,FALSE) -> 0.8948308 | AJ131: =VLOOKUP(C131,'5a)NDA MPPR'!$B$9:$AK$61,33,FALSE) -> 0.77750588 | AK131: =VLOOKUP(C131,'5a)NDA MPPR'!$B$9:$AK$61,34,FALSE) -> 0.69573621 | AM131: =VLOOKUP(C131,'5a)NDA MPPR'!$B$9:$AK$61,36,FALSE) -> G | AV131: 148.90179 | AW131: 48684 | AY131: 144.83408 | AZ131: =W131-AY131 -> 0 | BA131: 47882 | BB131: =AA131-BA131 -> 0
A132: =C131 -> Chimney Decommissioning Phase 2F | B132: =VLOOKUP($C131,'5a)NDA MPPR'!$A$9:$AK$61,2,FALSE) -> Pile 1 Chimney Demolition Project Phase 2F, to demolish the chimney contaminated during 1957 fire, is organised into 3 separate sub-projects. The first two, Filter Gallery Demolition and Diffuser Demolition are now complete, and the project is now in its final stage, Barrel Demolition. Barrel Demolition is the removal and disposal of the Barrel section of the chimney, using a unique specifically designed platform for demolition access with lifting operations supported by the existing Tower crane. Delivery Confidence Assessment remains amber based on current forecast completion being beyond Business Case P80 date, the position is supported by an independent project assurance review carried out in September 2025 for which the output also rated the project at Amber. As communicated to Nuclear Decommissioning Authority (NDA) Board in 2023, the project, following receipt of a conservative tender return for whole of Barrel Demolition that pressured business case tolerances, has adopted a phased approach to ensure learning and opportunities from Integrated Works Testing (IWT) is understood prior to future contract awards for the Installation and Commissioning of the Suspended Platform Incremental Descent (SPIDA) developed by ADAPT and Barrel Demolition scope. The Estimate At Completion (EAC) forecast remains at £148.9m. This is beyond the current sanctioned P80 value of £139.6m. The Project has been identified as being a candidate to receive inflation relief which would adjust the P80 sanction value up to £149m, however there is no clear decision on this at present. The request for Installation & Commissioning is £15m (P50 escalated). This will take the project beyond the current sanction P50 value of £116.57m and therefore will require P80 drawdown through the NDA or inflation relief to continue. A P80 Drawdown paper has been prepared and submitted to Final Decommissioning Sanction Board for consideration. A full revision of the existing baseline schedule/cost will be developed once IWT (July 2026) is complete and critical learning is obtained (i.e. from demolition demonstration) and future uncertainty is reduced. The first project benefit milestone (based on completion date) is on track. The P50 Delivery date remains April 2033. In IWT, the opportunities to mitigate last period's full schedule impacts have progressed to plan in period and means the P50 completion date for IWT remains early July 2026, with critical path elements completing early June 2026. The Baseline RAG remains Red as the forecast project end date is after the P50 baseline. License instrument submission forecast remains Q4 2025/26. Capability and Capacity RAG remains Green.
B134: 35/09000 | C134: Heat Exchanger Deplanting - Main Project | D134: Sellafield | F134: =VLOOKUP(C134,'5a)NDA MPPR'!$B$9:$AK$61,3,FALSE) -> G | G134: =VLOOKUP(C134,'5a)NDA MPPR'!$B$9:$AK$61,4,FALSE) -> 0 | I134: =VLOOKUP(C134,'5a)NDA MPPR'!$B$9:$AK$61,6,FALSE) -> OBC (Jan-24) | J134: =VLOOKUP(C134,'5a)NDA MPPR'!$B$9:$AK$61,7,FALSE) -> 54 | K134: =VLOOKUP(C134,'5a)NDA MPPR'!$B$9:$AK$61,8,FALSE) -> 65 | L134: =VLOOKUP(C134,'5a)NDA MPPR'!$B$9:$AK$61,9,FALSE) -> 47480 | M134: =VLOOKUP(C134,'5a)NDA MPPR'!$B$9:$AK$61,10,FALSE) -> 47831 | O134: =VLOOKUP(C134,'5a)NDA MPPR'!$B$9:$AK$61,12,FALSE) -> n/a | P134: =VLOOKUP(C134,'5a)NDA MPPR'!$B$9:$AK$61,13,FALSE) -> 11 | R134: =VLOOKUP(C134,'5a)NDA MPPR'!$B$9:$AK$61,15,FALSE) -> G | S134: =VLOOKUP(C134,'5a)NDA MPPR'!$B$9:$AK$61,16,FALSE) -> 1 | U134: =VLOOKUP(C134,'5a)NDA MPPR'!$B$9:$AK$61,18,FALSE) -> OBC (Oct-25) | W134: =VLOOKUP(C134,'5a)NDA MPPR'!$B$9:$AK$61,20,FALSE) -> 53.217953 | X134: =VLOOKUP(C134,'5a)NDA MPPR'!$B$9:$AK$61,21,FALSE) -> 53.218374 | Y134: =VLOOKUP(C134,'5a)NDA MPPR'!$B$9:$AK$61,22,FALSE) -> 0 | AA134: =VLOOKUP(C134,'5a)NDA MPPR'!$B$9:$AK$61,24,FALSE) -> 47465 | AB134: =VLOOKUP(C134,'5a)NDA MPPR'!$B$9:$AK$61,25,FALSE) -> 47528 | AC134: =VLOOKUP(C134,'5a)NDA MPPR'!$B$9:$AK$61,26,FALSE) -> 0 | AE134: =VLOOKUP(C134,'5a)NDA MPPR'!$B$9:$AK$61,28,FALSE) -> 6.2677563 | AF134: =VLOOKUP(C134,'5a)NDA MPPR'!$B$9:$AK$61,29,FALSE) -> 4.0485381 | AG134: =VLOOKUP(C134,'5a)NDA MPPR'!$B$9:$AK$61,30,FALSE) -> 4.8793046 | AH134: =VLOOKUP(C134,'5a)NDA MPPR'!$B$9:$AK$61,31,FALSE) -> 0.8297367 | AI134: =VLOOKUP(C134,'5a)NDA MPPR'!$B$9:$AK$61,32,FALSE) -> 0.64593101 | AJ134: =VLOOKUP(C134,'5a)NDA MPPR'!$B$9:$AK$61,33,FALSE) -> 0.11777522 | AK134: =VLOOKUP(C134,'5a)NDA MPPR'!$B$9:$AK$61,34,FALSE) -> 0.076074668 | AM134: =VLOOKUP(C134,'5a)NDA MPPR'!$B$9:$AK$61,36,FALSE) -> G | AV134: 53.1962 | AW134: 47528 | AY134: 53.19581 | AZ134: =W134-AY134 -> 0.022143 | BA134: 47296 | BB134: =AA134-BA134 -> 169
A135: =C134 -> Heat Exchanger Deplanting - Main Project | B135: =VLOOKUP($C134,'5a)NDA MPPR'!$A$9:$AK$61,2,FALSE) -> The scope of the Heat Exchanger (HEx) Deplanting 1 project is the removal and laydown of the first 6 Calder Hall Heat Exchangers, as an enabler for land clearance in preparation for a new Site Ion Exchange Effluent Plant (SIXEP) operating facility; subsequent disposal of these initial 6 Heat Exchangers and the deplanting & disposal of the remaining 10 Heat Exchangers is out-with this project. The Delivery Confidence Assessment is Green, as both lifecycle costs and end date remain within the approved P80 position. The Baseline RAG has moved to Green following approval and implementation of a recent change control to align with the Business Case revised Commercial strategy (6 month delay with no change to scope/cost), December 2029 (P50) and December 2030 (P80) project completion dates are now confirmed. In period, the laydown area design continues to mature with an Interpretative report now received from the Boreholes work, which confirms assumptions made during the in parallel completion of key design documents. Although a small amount of re-work is necessary, nothing fundamental has been identified and the project is anticipating design review completion by the end of December 2025, allowing enough time to place an Invitation To Tender (ITT) through the Decommissioning and Nuclear Waste Partnership (DNWP) framework by 2nd February 2026 (Ops plan milestone) which remains on target. On the main lifting contract, as previously reported, the evaluations have been completed and a successful candidate identified. Reviews prior to sign off of the evaluation report are ongoing which has delayed issue of the tender letters/standstill period of 7 days prior to contract award, this is now anticipated in Period 8 (award). Capability and Capacity, following the Change Control implementation, is now Green whilst the project work towards placement of the main HEx1 lifting contract.
B137: Enablers: Information Services Organisation (ISO)
B139: 35/10351 | C139: Data Centre Replacement Project | D139: Sellafield | F139: =VLOOKUP($C139,'4b) SL EPO Extended Data Sheet'!$A$5:$AB$176,2,FALSE) -> R | G139: =VLOOKUP($C139,'4b) SL EPO Extended Data Sheet'!$A$5:$AB$176,3, FALSE) -> 0 | I139: =VLOOKUP($C139,'4b) SL EPO Extended Data Sheet'!$A$5:$AD$176,30, FALSE) -> FBC (Oct-20) | J139: =VLOOKUP($C139,'4b) SL EPO Extended Data Sheet'!$A$5:$AB$176,6, FALSE)/1000000 -> 31.614 | K139: =VLOOKUP($C139,'4b) SL EPO Extended Data Sheet'!$A$5:$AB$176,7, FALSE)/1000000 -> 35.175 | L139: =VLOOKUP($C139,'4b) SL EPO Extended Data Sheet'!$A$5:$AB$176,8, FALSE) -> 45220 | M139: =VLOOKUP($C139,'4b) SL EPO Extended Data Sheet'!$A$5:$AB$176,9, FALSE) -> 45428 | O139: =VLOOKUP($C139,'4b) SL EPO Extended Data Sheet'!$A$5:$AB$176,10, FALSE)/1000000 -> 35.175 | P139: =VLOOKUP($C139,'4b) SL EPO Extended Data Sheet'!$A$5:$AB$176,11, FALSE)/1000000 -> 31.614 | R139: =VLOOKUP($C139,'4b) SL EPO Extended Data Sheet'!$A$5:$AB$176,12,FALSE) -> R | S139: =VLOOKUP($C139,'4b) SL EPO Extended Data Sheet'!$A$5:$AB$176,3, FALSE) -> 0 | U139: =VLOOKUP($C139,'4b) SL EPO Extended Data Sheet'!$A$5:$AE$176,31,FALSE) -> FBC (Apr-21) | W139: =VLOOKUP($C139,'4b) SL EPO Extended Data Sheet'!$A$5:$AC$176,16,FALSE)/1000000 -> 31.971082 | X139: =VLOOKUP($C139,'4b) SL EPO Extended Data Sheet'!$A$5:$AC$176,17,FALSE)/1000000 -> 26.901908 | Y139: =VLOOKUP($C139,'4b) SL EPO Extended Data Sheet'!$A$5:$AC$176,18,FALSE)/1000000 -> 0.02361152 | Z139: =VLOOKUP($C139,'4b) SL EPO Extended Data Sheet'!$A$5:$AB$176,16,FALSE)/1000000 -> 31.971082 | AA139: =VLOOKUP($C139,'4b) SL EPO Extended Data Sheet'!$A$5:$AC$176,19,FALSE) -> 45220 | AB139: =VLOOKUP($C139,'4b) SL EPO Extended Data Sheet'!$A$5:$AC$176,20,FALSE) -> 46244 | AC139: =VLOOKUP($C139,'4b) SL EPO Extended Data Sheet'!$A$5:$AC$176,21,FALSE) -> 0 | AD139: =VLOOKUP($C139,'4b) SL EPO Extended Data Sheet'!$A$5:$AB$176,15,FALSE)/1000000 -> 0.044287 | AE139: =VLOOKUP($C139,'4b) SL EPO Extended Data Sheet'!$A$5:$AC$176,22,FALSE)/1000000 -> 31.971083 | AF139: =VLOOKUP($C139,'4b) SL EPO Extended Data Sheet'!$A$5:$AC$176,23,FALSE)/1000000 -> 31.803346 | AG139: =VLOOKUP($C139,'4b) SL EPO Extended Data Sheet'!$A$5:$AC$176,24,FALSE)/1000000 -> 26.687217 | AH139: =VLOOKUP($C139,'4b) SL EPO Extended Data Sheet'!$A$5:$AC$176,25,FALSE) -> 1.1917071 | AI139: =VLOOKUP($C139,'4b) SL EPO Extended Data Sheet'!$A$5:$AC$176,26,FALSE) -> 0.9947535 | AJ139: =VLOOKUP($C139,'4b) SL EPO Extended Data Sheet'!$A$5:$AC$176,27,FALSE) -> 1 | AK139: =VLOOKUP($C139,'4b) SL EPO Extended Data Sheet'!$A$5:$AC$176,28,FALSE) -> 0.99475352 | AL139: =VLOOKUP($C139,'4b) SL EPO Extended Data Sheet'!$A$6:$AB$176,15,FALSE) -> 44287 | AM139: =VLOOKUP($C139,'4b) SL EPO Extended Data Sheet'!$A$5:$AC$176,29,FALSE) -> G | AV139: 26.878296 | AW139: 46244 | AY139: 31.971082 | AZ139: =W139-AY139 -> 0 | BA139: 45220 | BB139: =AA139-BA139 -> 0
A140: =C139 -> Data Centre Replacement Project | B140: The Data Centre Replacement Project is the design and build of a modern onsite data centre followed by the installation and migration of IT services from the legacy data centre. The First Project Benefit has been realised as all applications & network services have been migrated to the new data centre. Delivery Confidence Assessment is Red as the project has exceeded the P80 completion date of 16th May 2024. Current forecast completion of 10th August 2026 inclusive of Gate 5 SPER April 2026 and Post Investment Appraisal submission. Variations to existing scope reviewed with SPA, approval given to revise estimate and schedule to incorporate which will be followed by submission to ISO Change Board. The P50 cost and schedule; EAC ~£5.1m under P50 Sanction (not inclusive of studies); EAC increase £22k from last period following revision of Morgan Sindall Estimate at Completion. CE’s raised following design clarifications resulting in additional labour and materials & site wide industrial action. The Baseline RAG status sits at Red as the schedule position is not recoverable. The delays to project completion are derived from handover requirements and lack of pre-ops. Plant Room A commissioning complete with minor snags, re-energisation to follow. All cold works complete for Plant Room B to accelerate installation. Gate 4 review completed, final information to be provided to assurance to allow for gate passthrough. Physical labelling activities have halted until completion of Morgan Sindall Isolator Rack works within plant rooms, these will recommence in January. All building systems under planned preventative maintenance arrangements which are underway. Capability & Capacity RAG remains Green. Tri-Party Team (ISO, FM, and the Project) continue to collaborate effectively. AXIOM design resources retained to cover Intelligent Client Role for Isolator Rack installation.
B143: Table of Changes (vs Last Period)
B144: Project Name | F144: EAC | G144: Forecast End Date | I144: Baseline P50 Cost | J144: Baseline P50 End Date
B145: =C17 -> Enhanced CNC Airwave System (Encrypted Comms) | F145: =Y17 -> -7 | G145: =AC17 -> 0 | I145: =AZ17 -> 0 | J145: =BB17 -> 0
...

Sheet 3) BC and Sanction Changes PD6
A2: Project Name | B2: OpCo | D2: Approved Business Case and Sanction
D3: Approved Business Case | J3: Sanction
D4: Business Case Approval Date | E4: Whole Life Cost (P50) | F4: Whole Life Cost (P80) | G4: Project End Date (P50) | H4: Project End Date (P80) | J4: Sanction Approved to NDA | K4: Sanction Released to OpCo | M4: Reporting Period Change Made | N4: Description of Change
A7: SEP Solid Waste Storage Retrievals | B7: Sellafield | D7: FBC (Jan-16) | E7: 788 | F7: 846 | G7: 44986 | H7: 45170 | J7: 846 | K7: 846
D8: FBC (Jan-16) | E8: 788 | F8: 846 | G8: 44986 | H8: 45170 | J8: 871 | K8: 871 | M8: P8 2021/22 | N8: Both sanction values increased by £25.0m in line with Covid-19 impact drawdown approved by GIC in Aug-21.
D9: FBC (Jan-16) | E9: 788 | F9: 871 | G9: 44986 | H9: 45170 | J9: 871 | K9: 871 | M9: P10 2021/22 | N9: Whole Life Cost P80 increased by £25.0m in line with Covid-19 impact drawdown. Note: No point in updating the BC dates (P50) and (P80) to reflect Covid-19 impact drawdown as forecast completion and cost would still be such that SRO DCA remains red. The route to green SRO DCA for this project is a resubmission Business Case which is currently expected to go to SL IRP in Nov 2022, following which it will go to NDA and HMG.
D10: FBC (Jan-16) | E10: =E9+25 -> 813 | F10: 871 | G10: 44986 | H10: 45170 | J10: 871 | K10: 871 | M10: P4 2022/23 | N10: Whole Life Cost P50 increased by £25.0m in line with Covid-19 impact drawdown (should have done this in P10 21/22)
A12: Electrical Supply - New Construction | B12: Sellafield | D12: OBC (Dec-17) | E12: 218 | F12: 238 | G12: 44986 | H12: 44986 | J12: 238 | K12: 201.5
D13: OBC (Dec-17) | E13: 218 | F13: 249.3 | G13: 44986 | H13: 44986 | J13: 249.3 | K13: 201.5 | M13: P2 2022/23 | N13: Whole Life Cost P80 increased to £249.3m - no other changes requested. Note: no additional sanction released to the OpCo under this submission. Note: No point in updating the BC dates (P50) and (P80) to reflect Covid-19 impact drawdown as forecast completion and cost would still be such that SRO DCA remains red. The route to green SRO DCA for this project is a resubmission Business Case which is currently expected to be taken to TAP in Dec 2022.
D14: OBC (Dec-17) | E14: =E13+11.3 -> 229.3 | F14: 249.3 | G14: 44986 | H14: 44986 | J14: 249.3 | K14: 201.5 | M14: P4 2022/23 | N14: Whole Life Cost P50 increased by £11.3m in line with Covid-19 impact drawdown (should have done this in P2 22/23).
D15: OBC (Dec-17) | E15: 229.4 | F15: 249.4 | G15: 44810 | H15: 44986 | J15: =F15 -> 249.4 | K15: 201.5 | M15: P5 2022/23 | N15: Corrections provided by NDA Sanction Team
D16: FBC (May-23) | E16: 379.164 | F16: 403.001 | G16: 47362 | H16: 11140 | J16: 403.001 | K16: 379.164 | M16: P2 2023/24 | N16: Please note both P50 and P80 values quoted are inflated. See page 2 & 10 of the Full Business Case resubmission version 2. (Approved on 10 May 2023). Only month and year provided for P50 & P80 completion dates, so reverted to the 1st of the month.
A18: Box Encapsulation Plant | B18: Sellafield | D18: FBC (Dec-17) | E18: 769 | F18: 887 | G18: 44593 | H18: 45078 | J18: 887 | K18: 887
D19: FBC (Jul-22) | E19: 1316 | F19: 1512 | G19: 46226 | H19: 46847 | J19: 1512 | K19: 1316 | M19: P4 | N19: BEP FBC Resubmission received CST approval 26 July 2022
A21: Box Encapsulation Plant Product Store Direct Import Facility | B21: Sellafield | D21: FBC (Sep-20) | E21: 420 | F21: 435 | G21: 44652 | H21: 44743 | J21: 445 | K21: 445
D22: FBC (Sep-20) | E22: 458.9 | F22: 466.4 | G22: 45244 | H22: 45361 | J22: 458.9 | K22: 458.9 | M22: P12 2021/22 | N22: Both sanction values increased by £13.9m following the approach detailed within the NDA Covid-19 Sanction Request paper approved by HMT. Although the covid total impact was £38.9m the existing P80 contingency was used to partially offset the impact, thereby reducing the drawdown. Sellafield Ltd only requested NDA approval of the P50 (P80 is not required at this stage). £466.4 is the P80 figure identified in the Covid Sanction paper.
D23: FBC (Sep-20) | E23: 458.9 | F23: 466.4 | G23: 45244 | H23: 45361 | J23: 466.4 | K23: 458.9 | M23: P4 2022/23 | N23: Change Sanction Approved to NDA as £466.4m to align with the P80 (should have done this P12 21/22).
A25: SIXEP Continuity Plant | B25: Sellafield | D25: OBC (Jul-20) | E25: 574 | F25: 730 | G25: 46966 | H25: 11232 | J25: 313.5 | K25: ?
D26: FBC (Dec-21) | E26: 1007 | F26: 1182 | G26: 47849 | H26: 48611 | J26: 1182 | K26: 1007 | M26: P9 2021/22 | N26: To reflect HMT approval of FBC in Dec-21 and associated approval and release of sanction.
A28: Replacement Analytical Project | B28: Sellafield | D28: OBC (Jan-20) | E28: 680 | F28: 878 | G28: 46935 | H28: 47150 | J28: 360 (to FBC) | K28: 327.0 (to FBC)
D29: OBC (Jan-20) | E29: 680 | F29: 878 | G29: 46935 | H29: 47150 | J29: 384.6 (to FBC) | K29: 351.6 (to FBC) | M29: P3 2022/23 | N29: Both sanction values increased by £24.620m in line with Covid-19 impact drawdown approved by GIC in June 22. Please be advised that the RAP Covid Impact request paper reported the P80 @£360.714m. Past approvals have been checked and £360m has been confirmed. There are ongoing discussions with SL to explore where the additional £714k has come from.
D30: OBC (Jan-20) | E30: =E29+24.6 -> 704.6 | F30: =F29+24.6 -> 902.6 | G30: 46935 | H30: 47150 | J30: 384.6 (to FBC) | K30: 351.6 (to FBC) | M30: P4 2022/23 | N30: Whole Life Cost P50 and P80 increased by £24.6m in line with Covid-19 impact drawdown (should have done this in P3 22/23).
D31: OBC (Jan-20) | E31: 704.6 | F31: 902.6 | G31: 47209 | H31: 47423 | J31: 384.6 (to FBC) | K31: 351.6 (to FBC) | M31: P5 2022/23 | N31: P50 and P80 end date increased by 9 months in line with Covid-19 impact drawdown (should have done this in P3 22/23).
A33: Security Systems Architecture Upgrade (SSAU) | B33: Sellafield | D33: FBC (Mar-20) | E33: 284.3 | F33: 293.7 | G33: 44805 | H33: 44927 | J33: 293.7 | K33: 284.3
D34: FBC (Mar-20) | E34: 284.3 | F34: 293.7 | G34: 44805 | H34: 44927 | J34: 315.3 | K34: 305.93 | M34: P8 2021/22 | N34: Both sanction values increased by £21.6m in line with Covid-19 impact drawdown approved by GIC in Oct-21.
D35: FBC (Mar-20) | E35: 284.3 | F35: 315.3 | G35: 44805 | H35: 45627 | J35: 315.3 | K35: 305.93 | M35: P10 2021/22 | N35: Whole Life Cost P80 increased by £21.6m in line with Covid-19 impact drawdown. Business Case Project End Date (P80) of Dec-24 aligns with the £315.3m 'Covid-19 drawdown adjusted' Whole Life Cost (P80).
D36: FBC (Mar-20) | E36: =E35+21.6 -> 305.9 | F36: 315.3 | G36: 45392 | H36: 45627 | J36: 315.3 | K36: 305.93 | M36: P4 2022/23 | N36: Whole Life Cost P50 increased by £21.6m in line with Covid-19 impact drawdown (should have done this in P10 21/22). Project End Date P50 needs to be updated in line with the Covid-19 impact drawdown - i.e. aligned with the revised P80 date of 01-Dec-24. Have changed to current baseline P50 date of 10-Apr-24 (should have done this in P10 21/22).
A38: Chimney Decommissioning Phase 2F | B38: Sellafield | D38: FBC (Apr-21) | E38: 116.6 | F38: 122.6 | G38: 46874 | H38: 47239 | J38: 139.6 | K38: 116.6 | M38: P10 2021/22 | N38: Minor correction: Sanction Approved to NDA changed from £139.0m to £139.6m
