Workbook

Sheet 0) SL Project Structure
A1: SL Project Services Functional Strategy Project Landscape Map (Coded by Principle Current Commercial Delivery Framework) (Projects with Lifecycle Forecast over £20M)
A2: Total Lifetime EAC Value of SL Projects over £20M = | G2: =I5+P5+W5+AK5+P56 -> 8652.3656
D4: Project Delivery Directorate (PDD) | K4: Remediation | R4: Retrievals | AC4: Site Project Office
D5: Director / Lead: A. Sharples | G5: Lifecycle Value: | I5: =C15+C21+C27+C33+C39+C45+C51+G15+G21+G27+G33 -> 5770.5959 | K5: Director / Lead: G. McCracken | N5: Lifecycle Value: | P5: =L15+L21+L27+L33 -> 318.31725 | R5: Director / Lead: J. Millington | S5: C. Carruthers | U5: Lifecycle Value: | W5: =S15+S21+S27+S33+S39+S45 -> 1530.8012 | AC5: Director / Lead: M. Johns | AI5: Lifecycle Value: | AK5: =AD9+AD28+AD46+AL9 -> 1005.7258
D6: PC Lead: Lee Edgar & SPCMs | K6: PC Lead: A Grainger | R6: PC Lead: Programme PCMs | AC6: PC Lead: J Irving
Y8: Categorised / Value Streams | AG8: Infrastructure
D9: PPP | H9: Legacy | Y9: Director / Lead: J. Brocklebank | AB9: Lifecycle Value: | AD9: =+Z17+Z24 -> 52.856651 | AG9: Director / Lead: C. Mills | AJ9: Lifecycle Value: | AL9: =+AH17+AH24+AH31+AH38+AH45+AH52 -> 644.62303
R10: N.B. Project very close to completion | AG10: PC Lead: S Jackson
B11: Proj No: | C11: 35/09592 | F11: Proj No: | G11: 35/10137 | K11: Proj No: | L11: 35/05396 | R11: Proj No: | S11: 35/10095
B12: Programme: | C12: SNM Future State | F12: Programme: | G12: Magnox Swarf Storage Silo | K12: Programme: | L12: *1 - Final Decommissioning | R12: Programme: | S12: Pile Fuel Cladding Silo
B13: Title: | C13: Sellafield Product & Residue Store Retreatment Plant | F13: Title: | G13: Box Encapsulation Plant | K13: Title: | L13: Chimney Decommissioning Phase 2F | R13: Title: | S13: Box Encapsulation Plant Product Store Direct Import Facility | Y13: Proj No: | Z13: 35/10188 | AG13: Proj No: | AH13: 35/09140
B14: SRO | C14: Jeremy Hunt | F14: SPA | G14: Phil Reeve | K14: SPA | L14: Glenn McCracken | R14: SPA | S14: Kevin Brown | Y14: Programme: | Z14: AGROP | AG14: Programme: | AH14: Utilities and Future Energy
B15: Lifecycle P50: | C15: =VLOOKUP(C13,'5a)NDA MPPR'!$B$9:$AK$61,21,FALSE) -> 1466.5527 | F15: Lifecycle P50: | G15: =VLOOKUP(G13,'5a)NDA MPPR'!$B$9:$AK$61,21,FALSE) -> 1474.7309 | K15: Lifecycle P50: | L15: =VLOOKUP(L13,'5a)NDA MPPR'!$B$9:$AK$61,21,FALSE) -> 138.83422 | R15: Lifecycle P50: | S15: =VLOOKUP(S13,'5a)NDA MPPR'!$B$9:$AK$61,21,FALSE) -> 458.24501 | Y15: Title: | Z15: THORP Receipt & Storage Control Systems Replacement | AG15: Title: | AH15: Electrical Supply - New Construction
Y16: SPA | Z16: Andrew Pringle | AG16: SRO | AH16: Gavin Askew
B17: Proj No: | C17: 35/09343 | F17: Proj No: | G17: 35/09975 | K17: Proj No: | L17: 35/09707 | R17: Proj No: | S17: 35/06075 | Y17: Lifecycle P50: | Z17: =VLOOKUP(Z15,'4b) SL EPO Extended Data Sheet'!$A$5:$AB$168,17,FALSE)/1000000 -> 13.123352 | AG17: Lifecycle P50: | AH17: =VLOOKUP(AH15,'5a)NDA MPPR'!$B$9:$AK$61,21,FALSE) -> 427.83868
B18: Programme: | C18: SIXEP Capability | F18: Programme: | G18: Unified Command & Control | K18: Programme: | L18: *1 - Final Decommissioning | R18: Programme: | S18: Magnox Swarf Storage Silo | AG18: Infrastructure
B19: Title: | C19: SIXEP Continuity Plant | F19: Title: | G19: Security Systems Architecture Upgrade (SSAU) | K19: Title: | L19: LAETP Floc Retrieval | R19: Title: | S19: SEP Solid Waste Storage Retrievals
B20: SRO | C20: Jeremy Hunt | F20: SPA | G20: Michael Askew | K20: SPA | L20: Glenn McCracken | R20: SPA | S20: Phil Reeve | Y20: Proj No: | Z20: 35/10151 | AG20: Proj No: | AH20: 35/10565
B21: Lifecycle P50: | C21: =VLOOKUP(C19,'5a)NDA MPPR'!$B$9:$AK$61,21,FALSE) -> 1121.7088 | F21: Lifecycle P50: | G21: =VLOOKUP(G19,'5a)NDA MPPR'!$B$9:$AK$61,21,FALSE) -> 315.08838 | K21: Lifecycle P50: | L21: =VLOOKUP(L19,'5a)NDA MPPR'!$B$9:$AK$61,21,FALSE) -> 87.702751 | R21: Lifecycle P50: | S21: =VLOOKUP(S19,'5a)NDA MPPR'!$B$9:$AK$61,21,FALSE) -> 889.66115 | Y21: Programme: | Z21: No Programme | AG21: Programme: | AH21: No Programme
Y22: Title: | Z22: FHP & SIXEP Roof Replacement | AG22: Title: | AH22: EMRMS (Emergency Management Radiological Monitoring System)
B23: Proj No: | C23: 35/07654 | F23: Proj No: | G23: 35/09968 | K23: Proj No: | L23: 35/09000 | R23: Proj No: | S23: 35/05684 | Y23: SPA | Z23: Stuart Pearson | AG23: SPA | AH23: Rob Hargreaves
B24: Programme: | C24: Retrievals Value Stream Waste Capabilities | F24: Programme: | G24: Unified Command & Control | K24: Programme: | L24: *1 - Final Decommissioning | R24: Programme: | S24: Magnox Swarf Storage Silo | Y24: Lifecycle P50: | Z24: =VLOOKUP(Z22,'4b) SL EPO Extended Data Sheet'!$A$5:$AB$168,17,FALSE)/1000000 -> 39.733299 | AG24: Lifecycle P50: | AH24: =VLOOKUP(AH22,'4b) SL EPO Extended Data Sheet'!$A$5:$AB$168,17,FALSE)/1000000 -> 32.00462
B25: Title: | C25: BEPPS2 | F25: Title: | G25: CNC Operational Unit | K25: Title: | L25: Heat Exchanger Deplanting - Main Project | R25: Title: | S25: MSSS Upgrades for Retrievals & Resilience | AG25: Analytical Services
B26: SRO | C26: Kathryn McCloghrie | F26: SPA | G26: Michael Askew | K26: SPA | L26: Glenn McCracken | R26: SPA | S26: Phil Reeve
B27: Lifecycle P50: | C27: =VLOOKUP(C25,'5a)NDA MPPR'!$B$9:$AK$61,21,FALSE) -> 746.06354 | F27: Lifecycle P50: | G27: =VLOOKUP(G25,'5a)NDA MPPR'!$B$9:$AK$61,21,FALSE) -> 71.943748 | K27: Lifecycle P50: | L27: =VLOOKUP(L25,'5a)NDA MPPR'!$B$9:$AK$61,21,FALSE) -> 53.217744 | R27: Lifecycle P50: | S27: =VLOOKUP(S25,'4b) SL EPO Extended Data Sheet'!$A$5:$AB$168,17,FALSE)/1000000 -> 102.04751 | Y27: Special Nuclear Materials (SNM) | AG27: Proj No: | AH27: 35/10475
Y28: Director / Lead: P. Nichol | AB28: Lifecycle Value: | AD28: =Z35+Z42 -> 130.0165 | AG28: Programme: | AH28: Land and Infrastructure Future State
B29: Proj No: | C29: 35/09203 | F29: Proj No: | G29: 35/09976 | K29: Proj No: | L29: 35/10398 | R29: Proj No: | S29: 35/10342 | AG29: Title: | AH29: Product Zone Power Supply
B30: Programme: | C30: Decommissioning Higher Active Waste Capability (DHAWC) | F30: Programme: | G30: Unified Command & Control | K30: Programme: | L30: *1 - Final Decommissioning | R30: Programme: | S30: Magnox Swarf Storage Silos | AG30: SRO | AH30: Gavin Askew
B31: Title: | C31: Lightly Shielded Store (LSS) | F31: Title: | G31: Enhanced CNC Airwave System (Encrypted Comms) | K31: Title: | L31: Calder Land Clearance | R31: Title: | S31: MSSS SEP3 Rails & Brackets | Y31: Proj No: | Z31: 35/09244 | AG31: Lifecycle P50: | AH31: =VLOOKUP(AH29,'4b) SL EPO Extended Data Sheet'!$A$5:$AB$168,17,FALSE)/1000000 -> 68.884649
B32: SRO | C32: Kathryn McCloghrie | F32: SPA | G32: Michael Askew | K32: SPA | L32: Jeremy Hunt | R32: SPA | S32: Phil Reeve | Y32: Programme: | Z32: SNM Future State
B33: Lifecycle P50: | C33: =VLOOKUP(C31,'4b) SL EPO Extended Data Sheet'!$A$5:$AB$168,17,FALSE)/1000000 -> 158.107 | F33: Lifecycle P50: | G33: =VLOOKUP(G31,'5a)NDA MPPR'!$B$9:$AK$61,21,FALSE) -> 18.769073 | K33: Lifecycle P50: | L33: =VLOOKUP(L31,'4b) SL EPO Extended Data Sheet'!$A$5:$AB$168,17,FALSE)/1000000 -> 38.562536 | R33: Lifecycle P50: | S33: =VLOOKUP(S31,'4b) SL EPO Extended Data Sheet'!$A$5:$AB$168,17,FALSE)/1000000 -> 20.434619 | Y33: Title: | Z33: FGFL Ventilation Extract System Upgrade
F34: N.B. Project paused | K34: N.B *1 - Final Decommissioning OU is not a programme in the new construct | Y34: SPA | Z34: Simon Bremer | AG34: Proj No: | AH34: 35/10545
B35: Proj No: | C35: 35/10371 | R35: Proj No: | S35: 35/10274 | Y35: Lifecycle P50: | Z35: =VLOOKUP(Z33,'4b) SL EPO Extended Data Sheet'!$A$5:$AB$168,17,FALSE)/1000000 -> 91.739519 | AG35: Programme: | AH35: No Programme
B36: Programme: | C36: First Generation Magnox Storage Pond | R36: Programme: | S36: Magnox Swarf Storage Silos | AG36: Title: | AH36: Degradation of Pipebridge 57 (PB57) L14, L15, L16 Refurbishment
B37: Title: | C37: Sludge Handling & Export Plant | R37: Title: | S37: MSSS Electrical Distribution Upgrade for Retrievals | AG37: SPA | AH37: Stuart Latham
B38: SPA | C38: Carl Carruthers | R38: SPA | S38: Phil Reeve | Y38: Proj No: | Z38: 35/09357 | AG38: Lifecycle P50: | AH38: =VLOOKUP(AH36,'4b) SL EPO Extended Data Sheet'!$A$5:$AB$168,17,FALSE)/1000000 -> 31.20241
B39: Lifecycle P50: | C39: =VLOOKUP(C37,'4b) SL EPO Extended Data Sheet'!$A$5:$AB$168,17,FALSE)/1000000 -> 341.06661 | R39: Lifecycle P50: | S39: =VLOOKUP(S37,'4b) SL EPO Extended Data Sheet'!$A$5:$AB$168,17,FALSE)/1000000 -> 28.084728 | Y39: Programme: | Z39: SNM Future State | AG39: Utilites | AO39: Principle Project Commercial Delivery Framework Key
Y40: Title: | Z40: PMF North Transfers Project
B41: Proj No: | C41: 35/10417 | R41: Proj No: | S41: 35/09239 | Y41: SRO SPA | Z41: Jeremy Hunt Paul Nichol | AG41: Proj No: | AH41: 35/10563 | AQ41: Programme and Project Partners (PPP)
B42: Programme: | C42: Land and Infrastructure Future State | R42: Programme: | S42: First Generation Magnox Storage Pond | Y42: Lifecycle P50: | Z42: =VLOOKUP(Z40,'4b) SL EPO Extended Data Sheet'!$A$5:$AB$168,17,FALSE)/1000000 -> 38.276981 | AG42: Programme: | AH42: Utilities and Future Energy
B43: Title: | C43: ILW East Land Excavation | R43: Title: | S43: Effluent Distribution Asset Improvement | AG43: Title: | AH43: Substation 10 Replacement | AQ43: Legacy Bespoke Contracts (ie. BEP JV)
B44: SPA | C44: Gavin Askew | R44: SPA | S44: Carl Carruthers | AG44: SRO | AH44: Gavin Askew
B45: Lifecycle P50: | C45: =VLOOKUP(C43,'5a)NDA MPPR'!$B$9:$AK$61,21,FALSE) -> 35.886955 | R45: Lifecycle P50: | S45: =VLOOKUP(S43,'4b) SL EPO Extended Data Sheet'!$A$5:$AB$168,17,FALSE)/1000000 -> 32.328177 | Y45: Spent Fuel Management (SFM) | AG45: Lifecycle P50: | AH45: =VLOOKUP(AH43,'4b) SL EPO Extended Data Sheet'!$A$5:$AB$168,17,FALSE)/1000000 -> 42.426554 | AQ45: Decommissioning Delivery Partner (DDP)
Y46: Director / Lead: S. Pearson | AB46: Lifecycle Value: | AD46: =Z52+Z58 -> 178.22966
B47: Proj No: | C47: 35/10505 | AQ47: Design Services Alliance (DSA)
B48: Programme: | C48: SIXEP Capability | Y48: Proj No: | Z48: 35/10192 | AG48: Proj No: | AH48: 35/10564
B49: Title: | C49: SIXEP Receipt Facility | Y49: Programme: | Z49: AGROP | AG49: Programme: | AH49: Utilities and Future Energy | AQ49: Infrastructure Services Alliance (ISA)
B50: SRO | C50: Jeremy Hunt | Y50: Title: | Z50: TR&S Replacement Cooling System | AG50: Title: | AH50: Substation 15 Replacement
B51: Lifecycle P50: | C51: =VLOOKUP(C49,'4b) SL EPO Extended Data Sheet'!$A$5:$AB$168,17,FALSE)/1000000 -> 20.678211 | Y51: SPA | Z51: Steve Wordsworth | AG51: SRO | AH51: Gavin Askew
B52: N.B. Project known as SWMRF | Y52: Lifecycle P50: | Z52: =VLOOKUP(Z50,'4b) SL EPO Extended Data Sheet'!$A$5:$AB$168,17,FALSE)/1000000 -> 159.01214 | AG52: Lifecycle P50: | AH52: =VLOOKUP(AH50,'4b) SL EPO Extended Data Sheet'!$A$5:$AB$168,17,FALSE)/1000000 -> 42.266115
B53: Proj No: | C53: TBC
B54: Programme: | C54: SNM Future State | Y54: Proj No: | Z54: 35/09579
B55: Title: | C55: SNM Future Stores | K55: ISO | Y55: Programme: | Z55: Spent Fuel Services
B56: Lifecycle P50: | C56: TBC | K56: Director / Lead: G. Slater | N56: Lifecycle Value: | P56: =L64 -> 26.925406 | Y56: Title: | Z56: FGOFSP Effluent Route Project
F57: Future PPP Pipeline Projects currently in Study Phase and not currently reflected as a gated project | K57: PC Lead: J Beetham | Y57: SPA | Z57: Steve Wordsworth
B58: Proj No: | C58: 35/10489 | Y58: Lifecycle P50: | Z58: =VLOOKUP(Z56,'4b) SL EPO Extended Data Sheet'!$A$5:$AB$168,17,FALSE)/1000000 -> 19.217519
B59: Programme: | C59: No Programme
B60: Title: | C60: Common Data Environment (CDE) | K60: Proj No: | L60: 35/10351
B61: Lifecycle P50: | C61: TBC | K61: Programme: | L61: No Programme
K62: Title: | L62: Data Centre Replacement Project
B63: Proj No: | C63: TBC | K63: SPA | L63: Dominic Fitzsimmons
B64: Programme: | C64: Analytical Services | K64: Lifecycle P50: | L64: =VLOOKUP(L62,'4b) SL EPO Extended Data Sheet'!$A$5:$AB$168,17,FALSE)/1000000 -> 26.925406
B65: Title: | C65: RAP Option Selection
B66: Lifecycle P50: | C66: TBC

Sheet 0) SL Project Structure OLD
A1: SL Project Services Functional Strategy Project Landscape Map (Coded by Principle Current Commercial Delivery Framework) (Projects with Lifecycle Forecast over £20M)
A2: Total Lifetime EAC Value of SL Projects over £20M = | G2: =I5+P5+W5+AH5+P53 -> #N/A
D4: Project Delivery Directorate (PDD) | K4: Remediation | R4: Retrievals | AC4: Site Management Projects (SMPro)
D5: Director / Lead: A. Sharples | G5: Lifecycle Value: | I5: =C14+C19+C24+C29+C34+C39+C44+C49+G14+G19+G24+G29 -> #N/A | K5: Director / Lead: G. McCracken | N5: Lifecycle Value: | P5: =L14+L19+L24+L29+L34+L39 -> #N/A | R5: Director / Lead: A. Armett | U5: Lifecycle Value: | W5: =S14+S19+S24+S29+S34+S39+S44+S49 -> #N/A | AC5: Director / Lead: M. Johns | AF5: Lifecycle Value: | AH5: =AD9+AD47+AD60+AL9 -> #N/A
D6: PC Lead: Lee Edgar & SPCMs | K6: PC Lead: A Grainger | R6: PC Lead: J Kolbe | AC6: PC Lead: J Irving
Y8: Site Management | AG8: Infrastructure
D9: PPP | H9: Legacy | Y9: Director / Lead: J. Brocklebank | AB9: Lifecycle Value: | AD9: =Z14+Z19+Z24+Z29+Z34+Z39+Z44 -> 660.95839 | AG9: Director / Lead: C. Mills | AJ9: Lifecycle Value: | AL9: =AH16+AH22+AH28 -> #N/A
R10: N.B. Project very close to completion | AG10: PC Lead: S Jackson
B11: Proj No: | C11: 35/09592 | F11: Proj No: | G11: 35/10137 | K11: Proj No: | L11: 35/05396 | R11: Proj No: | S11: 35/10095 | Y11: Proj No: | Z11: 35/09140
B12: Title: | C12: Sellafield Product & Residue Store Retreatment Plant | F12: Title: | G12: Box Encapsulation Plant | K12: Title: | L12: Chimney Decommissioning Phase 2F | R12: Title: | S12: Box Encapsulation Plant Product Store Direct Import Facility | Y12: Title: | Z12: Electrical Supply - New Construction | AG12: Infrastructure
B13: SRO | C13: Jeremy Hunt | F13: SPA | G13: Phil Reeve | K13: SPA | L13: Glenn McCracken | R13: SPA | S13: Kevin Brown | Y13: SRO | Z13: Gavin Askew | AG13: Proj No: | AH13: 35/10565
B14: Lifecycle P50: | C14: =VLOOKUP(C12,'5a)NDA MPPR'!$B$9:$AK$61,21,FALSE) -> 1466.5527 | F14: Lifecycle P50: | G14: =VLOOKUP(G12,'5a)NDA MPPR'!$B$9:$AK$61,21,FALSE) -> 1474.7309 | K14: Lifecycle P50: | L14: =VLOOKUP(L12,'5a)NDA MPPR'!$B$9:$AK$61,21,FALSE) -> 138.83422 | R14: Lifecycle P50: | S14: =VLOOKUP(S12,'5a)NDA MPPR'!$B$9:$AK$61,21,FALSE) -> 458.24501 | Y14: Lifecycle P50: | Z14: =VLOOKUP(Z12,'5a)NDA MPPR'!$B$9:$AK$61,21,FALSE) -> 427.83868 | AG14: Title: | AH14: EMRMS (Emergency Management Radiological Monitoring System)
AG15: SPA | AH15: Rob Hargreaves
B16: Proj No: | C16: 35/09343 | F16: Proj No: | G16: 35/09975 | K16: Proj No: | L16: 35/09707 | R16: Proj No: | S16: 35/06075 | Y16: Proj No: | Z16: 35/10188 | AG16: Lifecycle P50: | AH16: =VLOOKUP(AH14,'4b) SL EPO Extended Data Sheet'!$A$5:$AB$168,16,FALSE)/1000000 -> 32.152519
B17: Title: | C17: SIXEP Continuity Plant | F17: Title: | G17: Security Systems Architecture Upgrade (SSAU) | K17: Title: | L17: LAETP Floc Retrieval | R17: Title: | S17: SEP Solid Waste Storage Retrievals | Y17: Title: | Z17: THORP Receipt & Storage Control Systems Replacement
B18: SRO | C18: Jeremy Hunt | F18: SPA | G18: Michael Askew | K18: SPA | L18: Glenn McCracken | R18: SPA | S18: Phil Reeve | Y18: SPA | Z18: Andrew Pringle | AG18: Utilites
B19: Lifecycle P50: | C19: =VLOOKUP(C17,'5a)NDA MPPR'!$B$9:$AK$61,21,FALSE) -> 1121.7088 | F19: Lifecycle P50: | G19: =VLOOKUP(G17,'5a)NDA MPPR'!$B$9:$AK$61,21,FALSE) -> 315.08838 | K19: Lifecycle P50: | L19: =VLOOKUP(L17,'5a)NDA MPPR'!$B$9:$AK$61,21,FALSE) -> 87.702751 | R19: Lifecycle P50: | S19: =VLOOKUP(S17,'5a)NDA MPPR'!$B$9:$AK$61,21,FALSE) -> 889.66115 | Y19: Lifecycle P50: | Z19: =VLOOKUP(Z17,'4b) SL EPO Extended Data Sheet'!$A$5:$AB$168,16,FALSE)/1000000 -> 20.914989 | AG19: Proj No: | AH19: 35/09248
AG20: Title: | AH20: Substations 6 & 7 Replacement
B21: Proj No: | C21: 35/09269 | F21: Proj No: | G21: 35/09968 | K21: Proj No: | L21: 35/09000 | R21: Proj No: | S21: 35/05684 | Y21: Proj No: | Z21: 35/10151 | AG21: SRO | AH21: Gavin Askew
B22: Title: | C22: Replacement Analytical Project | F22: Title: | G22: CNC Operational Unit | K22: Title: | L22: Heat Exchanger Deplanting - Main Project | R22: Title: | S22: MSSS Upgrades for Retrievals & Resilience | Y22: Title: | Z22: FHP & SIXEP Roof Replacement | AG22: Lifecycle P50: | AH22: =VLOOKUP(AH20,'4b) SL EPO Extended Data Sheet'!$A$5:$AB$168,16,FALSE)/1000000 -> #N/A
B23: SRO | C23: Gavin Askew | F23: SPA | G23: Michael Askew | K23: SPA | L23: Glenn McCracken | R23: SPA | S23: Phil Reeve | Y23: SPA | Z23: Stuart Pearson
B24: Lifecycle P50: | C24: =VLOOKUP(C22,'5a)NDA MPPR'!$B$9:$AK$61,21,FALSE) -> #N/A | F24: Lifecycle P50: | G24: =VLOOKUP(G22,'5a)NDA MPPR'!$B$9:$AK$61,21,FALSE) -> 71.943748 | K24: Lifecycle P50: | L24: =VLOOKUP(L22,'5a)NDA MPPR'!$B$9:$AK$61,21,FALSE) -> 53.217744 | R24: Lifecycle P50: | S24: =VLOOKUP(S22,'4b) SL EPO Extended Data Sheet'!$A$5:$AB$168,16,FALSE)/1000000 -> 103.81815 | Y24: Lifecycle P50: | Z24: =VLOOKUP(Z22,'4b) SL EPO Extended Data Sheet'!$A$5:$AB$168,16,FALSE)/1000000 -> 26.545167 | AG24: Analytical Services
B25: N.B. Project paused | AG25: Proj No: | AH25: 35/10523
B26: Proj No: | C26: 35/07654 | F26: Proj No: | G26: 35/09976 | K26: Proj No: | L26: 35/10398 | R26: Proj No: | S26: 35/10242 | Y26: Proj No: | Z26: 35/10475 | AG26: Title: | AH26: Sample Management Capability
B27: Title: | C27: BEPPS2 | F27: Title: | G27: Enhanced CNC Airwave System (Encrypted Comms) | K27: Title: | L27: Calder Land Clearance | R27: Title: | S27: PFCS Full Retrievals - Project 1 | Y27: Title: | Z27: Product Zone Power Supply | AG27: SRO | AH27: Gavin Askew
B28: SRO | C28: Kathryn McCloghrie | F28: SPA | G28: Michael Askew | K28: SPA | L28: Jeremy Hunt | R28: SPA | S28: Kevin Brown | Y28: SRO | Z28: Gavin Askew | AG28: Lifecycle P50: | AH28: =VLOOKUP(AH26,'4b) SL EPO Extended Data Sheet'!$A$5:$AB$168,16,FALSE)/1000000 -> #N/A
B29: Lifecycle P50: | C29: =VLOOKUP(C27,'5a)NDA MPPR'!$B$9:$AK$61,21,FALSE) -> 746.06354 | F29: Lifecycle P50: | G29: =VLOOKUP(G27,'5a)NDA MPPR'!$B$9:$AK$61,21,FALSE) -> 18.769073 | K29: Lifecycle P50: | L29: =VLOOKUP(L27,'4b) SL EPO Extended Data Sheet'!$A$5:$AB$168,16,FALSE)/1000000 -> 38.593832 | R29: Lifecycle P50: | S29: =VLOOKUP(S27,'5a)NDA MPPR'!$B$9:$AK$61,21,FALSE) -> #N/A | Y29: Lifecycle P50: | Z29: =VLOOKUP(Z27,'4b) SL EPO Extended Data Sheet'!$A$5:$AB$168,16,FALSE)/1000000 -> 69.236481
F30: N.B. Project paused
B31: Proj No: | C31: 35/09203 | K31: Proj No: | L31: 35/10401 | R31: Proj No: | S31: 35/09198 | Y31: Proj No: | Z31: 35/10545 | AG31: Principle Project Commercial Delivery Framework Key
B32: Title: | C32: Lightly Shielded Store (LSS) | K32: Title: | L32: Decommissioning Encapsulation Plant | R32: Title: | S32: Sellafield 3m3 Box Supply - Tranche A | Y32: Title: | Z32: Degradation of Pipebridge 57 (PB57) L14, L15, L16 Refurbishment
B33: SRO | C33: Kathryn McCloghrie | K33: SRO | L33: Kathryn McCloghrie | R33: SPA | S33: Kevin Brown | Y33: SPA | Z33: Stuart Latham | AH33: Programme and Project Partners (PPP)
B34: Lifecycle P50: | C34: =VLOOKUP(C32,'4b) SL EPO Extended Data Sheet'!$A$5:$AB$168,16,FALSE)/1000000 -> 142.42994 | K34: Lifecycle P50: | L34: =VLOOKUP(L32,'4b) SL EPO Extended Data Sheet'!$A$5:$AB$168,16,FALSE)/1000000 -> #N/A | R34: Lifecycle P50: | S34: =VLOOKUP(S32,'4b) SL EPO Extended Data Sheet'!$A$5:$AB$168,16,FALSE)/1000000 -> #N/A | Y34: Lifecycle P50: | Z34: =VLOOKUP(Z32,'4b) SL EPO Extended Data Sheet'!$A$5:$AB$168,16,FALSE)/1000000 -> 30.826939
AH35: Legacy Bespoke Contracts (ie. BEP JV)
B36: Proj No: | C36: 35/10371 | K36: Proj No: | L36: 35/10402 | R36: Proj No: | S36: 35/10128 | Y36: Proj No: | Z36: 35/10563
B37: Title: | C37: Sludge Handling & Export Plant | K37: Title: | L37: Remote Handlable Intermediate Level Waste (RHILW) | R37: Title: | S37: Self Shielded Boxes Design and Manufacture | Y37: Title: | Z37: Substation 10 Replacement | AH37: Decommissioning Delivery Partner (DDP)
B38: SPA | C38: Carl Carruthers | K38: SRO | L38: Kathryn McCloghrie | R38: SPA | S38: Carl Carruthers | Y38: SRO | Z38: Gavin Askew
B39: Lifecycle P50: | C39: =VLOOKUP(C37,'4b) SL EPO Extended Data Sheet'!$A$5:$AB$168,16,FALSE)/1000000 -> 340 | K39: Lifecycle P50: | L39: =VLOOKUP(L37,'4b) SL EPO Extended Data Sheet'!$A$5:$AB$168,16,FALSE)/1000000 -> #N/A | R39: Lifecycle P50: | S39: =VLOOKUP(S37,'4b) SL EPO Extended Data Sheet'!$A$5:$AB$168,16,FALSE)/1000000 -> #N/A | Y39: Lifecycle P50: | Z39: =VLOOKUP(Z37,'4b) SL EPO Extended Data Sheet'!$A$5:$AB$168,16,FALSE)/1000000 -> 42.841254 | AH39: Design Services Alliance (DSA)
B41: Proj No: | C41: 35/10417 | R41: Proj No: | S41: 35/10342 | Y41: Proj No: | Z41: 35/10564 | AH41: Infrastructure Services Alliance (ISA)
B42: Title: | C42: ILW East Land Excavation | R42: Title: | S42: MSSS SEP3 Rails & Brackets | Y42: Title: | Z42: Substation 15 Replacement
B43: SPA | C43: Gavin Askew | R43: SPA | S43: Phil Reeve | Y43: SRO | Z43: Gavin Askew
B44: Lifecycle P50: | C44: =VLOOKUP(C42,'5a)NDA MPPR'!$B$9:$AK$61,21,FALSE) -> 35.886955 | R44: Lifecycle P50: | S44: =VLOOKUP(S42,'4b) SL EPO Extended Data Sheet'!$A$5:$AB$168,16,FALSE)/1000000 -> 19.192466 | Y44: Lifecycle P50: | Z44: =VLOOKUP(Z42,'4b) SL EPO Extended Data Sheet'!$A$5:$AB$168,16,FALSE)/1000000 -> 42.754873
B46: Proj No: | C46: 35/10505 | R46: Proj No: | S46: 35/10274 | Y46: Special Nuclear Materials (SNM)
B47: Title: | C47: SIXEP Receipt Facility | R47: Title: | S47: MSSS Electrical Distribution Upgrade for Retrievals | Y47: Director / Lead: P. Nichol | AB47: Lifecycle Value: | AD47: =Z52+Z57 -> 128.80839
B48: SRO | C48: Jeremy Hunt | R48: SPA | S48: Phil Reeve
B49: Lifecycle P50: | C49: =VLOOKUP(C47,'4b) SL EPO Extended Data Sheet'!$A$5:$AB$168,16,FALSE)/1000000 -> 919.61826 | R49: Lifecycle P50: | S49: =VLOOKUP(S47,'4b) SL EPO Extended Data Sheet'!$A$5:$AB$168,16,FALSE)/1000000 -> 18.788383 | Y49: Proj No: | Z49: 35/09244
B50: N.B. Project known as SWMRF | Y50: Title: | Z50: FGFL Ventilation Extract System Upgrade
B51: Proj No: | C51: TBC | Y51: SPA | Z51: Simon Bremer
B52: Title: | C52: SNM Future Stores | K52: ISO | Y52: Lifecycle P50: | Z52: =VLOOKUP(Z50,'4b) SL EPO Extended Data Sheet'!$A$5:$AB$168,16,FALSE)/1000000 -> 92.707032
B53: Lifecycle P50: | C53: TBC | K53: Director / Lead: G. Slater | N53: Lifecycle Value: | P53: =L59+L64 -> #N/A
F54: Future PPP Pipeline Projects currently in Study Phase and not currently reflected as a gated project | K54: PC Lead: J Beetham / D Burns | Y54: Proj No: | Z54: 35/09357
B55: Proj No: | C55: 35/10489 | Y55: Title: | Z55: PMF North Transfers Project
B56: Title: | C56: Commoc Data Environment (CDE) | K56: Proj No: | L56: 35/10478 | Y56: SRO SPA | Z56: Jeremy Hunt Paul Nichol
B57: Lifecycle P50: | C57: TBC | K57: Title: | L57: ASC Exit (PICTS) | Y57: Lifecycle P50: | Z57: =VLOOKUP(Z55,'4b) SL EPO Extended Data Sheet'!$A$5:$AB$168,16,FALSE)/1000000 -> 36.101355
K58: SPA | L58: Graeme Slater
B59: Proj No: | C59: TBC | K59: Lifecycle P50: | L59: =VLOOKUP(L57,'4b) SL EPO Extended Data Sheet'!$A$5:$AB$168,16,FALSE)/1000000 -> #N/A | Y59: Spent Fual Management (SFM)
B60: Title: | C60: RAP Option Selection | Y60: Director / Lead: S. Pearson | AB60: Lifecycle Value: | AD60: =Z65 -> 155.65567
B61: Lifecycle P50: | C61: TBC | K61: Proj No: | L61: 35/10351
K62: Title: | L62: Data Centre Replacement Project | Y62: Proj No: | Z62: 35/10192
K63: SPA | L63: Dominic Fitzsimmons | Y63: Title: | Z63: TR&S Replacement Cooling System
K64: Lifecycle P50: | L64: =VLOOKUP(L62,'4b) SL EPO Extended Data Sheet'!$A$5:$AB$168,16,FALSE)/1000000 -> 31.971082 | Y64: SPA | Z64: Steve Wordsworth
Y65: Lifecycle P50: | Z65: =VLOOKUP(Z63,'4b) SL EPO Extended Data Sheet'!$A$5:$AB$168,16,FALSE)/1000000 -> 155.65567

Sheet 1) Report
B3: Project Number | C3: Project Name | D3: Occom | F3: Approved Business Case and Sanction | R3: Baseline | AM3: Capability and Capacity | AO3: DCA Comparison | AS3: Baseline RAG Comparison | AV3: Previous Period Data for Variance Calcs | AY3: Changes to Current Baseline (P50)
F4: Delivery Confidence Assessment (DCA) | I4: Approved Business Case | O4: Sanction | R4: Baseline RAG | U4: Current Baseline in Effect From | W4: Whole Life | AE4: Cumulative vs. Current Baseline
I5: Business Case Approval Date | J5: Project Cost | L5: Project End Date | O5: Sanction Approved to NDA | P5: Sanction Released to OpCo | W5: Project Cost | AA5: Project End Date | AE5: Budgeted Cost Work Scheduled (BCWS) | AF5: Budgeted Cost Work Performed (BCWP) | AG5: Actual Cost Work Performed (ACWP) | AH5: Cost Perf. Index (CPI) | AI5: Schedule Perf. Index (SPI) | AJ5: % Complete | AO5: EAC vs. Approved BC WLC (P80) | AP5: EAC vs. Sanction Approved to NDA (P80) | AQ5: Forecast End Date vs. Approved BC (P80) | AS5: EAC vs. Current Baseline (P50) | AT5: Forecast End Date vs. Current Baseline (P50) | AV5: Cost | AW5: End Date | AY5: Project Cost | BA5: Project End Date
J6: Business Case (P50) | K6: Business Case (P80) | L6: Business Case (P50) | M6: Business Case (P80) | W6: Current Baseline (P50) | X6: Estimate At Complete (EAC) | Y6: EAC vs. Last Period | AA6: Current Baseline (P50) | AB6: Forecast | AC6: Forecast vs. Last Period (Days) | AJ6: Plan | AK6: Actual | AV6: EAC Last Period | AW6: Forecast Last Period | AY6: Baseline (P50) Last Period | AZ6: Change to Baseline (P50) | BA6: Baseline (P50) Last Period | BB6: Change to Baseline (P50)
B8: Security & Resilience
B10: Portfolio Summary
B11: n/a | C11: Sellafield Security Enhancement Programme (SSEP) | D11: Sellafield | F11: =VLOOKUP(C11,'5a)NDA MPPR'!$B$9:$AK$61,3,FALSE) -> G | G11: =VLOOKUP(C11,'5a)NDA MPPR'!$B$9:$AK$61,4,FALSE) -> 0 | I11: =VLOOKUP(C11,'5a)NDA MPPR'!$B$9:$AK$61,6,FALSE) -> PBC (Jun-24) | J11: =VLOOKUP(C11,'5a)NDA MPPR'!$B$9:$AK$61,7,FALSE) -> 904 | K11: =VLOOKUP(C11,'5a)NDA MPPR'!$B$9:$AK$61,8,FALSE) -> 921.8 | L11: =VLOOKUP(C11,'5a)NDA MPPR'!$B$9:$AK$61,9,FALSE) -> 46022 | M11: =VLOOKUP(C11,'5a)NDA MPPR'!$B$9:$AK$61,10,FALSE) -> 46234 | O11: =VLOOKUP(C11,'5a)NDA MPPR'!$B$9:$AK$61,12,FALSE) -> 921.8 | P11: =VLOOKUP(C11,'5a)NDA MPPR'!$B$9:$AK$61,13,FALSE) -> 921.8 | R11: =VLOOKUP(C11,'5a)NDA MPPR'!$B$9:$AK$61,15,FALSE) -> N/A | S11: =VLOOKUP(C11,'5a)NDA MPPR'!$B$9:$AK$61,16,FALSE) -> 0 | U11: =VLOOKUP(C11,'5a)NDA MPPR'!$B$9:$AK$61,18,FALSE) -> PBC (Oct-21) | W11: =VLOOKUP(C11,'5a)NDA MPPR'!$B$9:$AK$61,20,FALSE) -> - | X11: =VLOOKUP(C11,'5a)NDA MPPR'!$B$9:$AK$61,21,FALSE) -> 915.43624 | Y11: =VLOOKUP(C11,'5a)NDA MPPR'!$B$9:$AK$61,22,FALSE) -> 0.6 | AA11: =VLOOKUP(C11,'5a)NDA MPPR'!$B$9:$AK$61,24,FALSE) -> - | AB11: =VLOOKUP(C11,'5a)NDA MPPR'!$B$9:$AK$61,25,FALSE) -> 46234 | AC11: =VLOOKUP(C11,'5a)NDA MPPR'!$B$9:$AK$61,26,FALSE) -> 0 | AE11: =VLOOKUP(C11,'5a)NDA MPPR'!$B$9:$AK$61,28,FALSE) -> 0 | AF11: =VLOOKUP(C11,'5a)NDA MPPR'!$B$9:$AK$61,29,FALSE) -> 0 | AG11: =VLOOKUP(C11,'5a)NDA MPPR'!$B$9:$AK$61,30,FALSE) -> 910.61685 | AH11: =VLOOKUP(C11,'5a)NDA MPPR'!$B$9:$AK$61,31,FALSE) -> 0 | AI11: =VLOOKUP(C11,'5a)NDA MPPR'!$B$9:$AK$61,32,FALSE) -> 0 | AJ11: =VLOOKUP(C11,'5a)NDA MPPR'!$B$9:$AK$61,33,FALSE) -> 0 | AK11: =VLOOKUP(C11,'5a)NDA MPPR'!$B$9:$AK$61,34,FALSE) -> 0 | AM11: =VLOOKUP(C11,'5a)NDA MPPR'!$B$9:$AK$61,36,FALSE) -> N/A | AV11: 914.87871 | AW11: 46234 | AY11: 0 | BA11: -
A12: =C11 -> Sellafield Security Enhancement Programme (SSEP) | B12: =VLOOKUP($C11,'5a)NDA MPPR'!$A$9:$AK$61,2,FALSE) -> The Sellafield Security Enhancement Programme (SSEP) represents a series of interdependent security enhancement projects, which encompass site-wide improvement initiatives, and some facility-specific asset improvements. The Delivery Confidence Assessment remains Green. The NDA revised Programme Business Case value of £921.8m was released to SL in June 2024, with Department for Energy Security and Net Zero (DESNZ) PIC holding the upper range figure of £929.8m. The SSAU and CNC OU P80 sanction request submissions were approved at the NDA Group Investment Committee (GIC) in September 2024. The assessment work on Encrypted Comms project is complete resulting in a significant reduction in the project scope. The project EAC has previously been reduced accordingly and formal governance steps completed to down scope the project. The programme lifecycle EAC has increased by £0.6m this period due to prolongation on the CNCOU project, as in period the contractor have completed commissioning resequencing workshops due to the previously reported gland issues and strike action compounded by the union imposed weekend working overtime ban, and the output of the workshops has moved the forecast end date. The Programme Ready for Full Operating Capability (FOC), based on the latest SSAU project data, remains forecast as March 2026 due to delays to the progression of the Legacy SMS migrations, which are scheduled to take place after the L1 commissioning of the new boundaries.. This is subject to ongoing reviews of the available operational, engineering and maintenance resources needed to review and sign off the various systems and assets being delivered by the projects to underpin the Custody Transfer Certificate (CTC). The overall outturn project delivery performance remains in line with sanctioned plans. Security Systems Architecture Upgrade (SSAU), Encrypted Comms (EC) & Civil Nuclear Constabulary (CNC) Operational Unit (CNC OU) Projects (all reported as projects in their own right on the MPPR) are, based on the respective projects latest EAC figures, affordable within the released SSEP sanction. The Main Site Command Facility (MSCF) continues to improve its operational capability with Phases 1 & 2 of the revised 3 Phase Capability Delivery Plan now complete. (Phase 1: The High Security Area (HSA)1 Boundary declared operational in March 2024 & Phase 2: The achievement of a Green rating for the complex and challenging Level 1 Regulator Evaluated Demonstration Exercise in November 2024). As a consequence the Regulator confirmed in December 2024, Physical Security no longer needs to be monitored at the “Enhanced Level” and has therefore been returned to “Routine Level” with the Nuclear Site Security Plan (NSSP) and Security Improvement Schedule (SIS) updated accordingly; a significant achievement for the Sellafield Site. Phase 3 will achieve the agreed security outcomes and associated security risk reduction benefits by no later than May 2027 for FOC. The latest programme forecast aligns with the current CNC OU P80 sanction date of 31 July 2026. The programme remains within its sanctioned tolerances.
B14: Project Delivery Directorate
B16: Portfolio Summary
B17: 35/09976 | C17: Enhanced CNC Airwave System (Encrypted Comms) | D17: Sellafield | F17: =VLOOKUP(C17,'5a)NDA MPPR'!$B$9:$AK$61,3,FALSE) -> R | G17: =VLOOKUP(C17,'5a)NDA MPPR'!$B$9:$AK$61,4,FALSE) -> 0 | I17: =VLOOKUP(C17,'5a)NDA MPPR'!$B$9:$AK$61,6,FALSE) -> OBC (Mar-20) | J17: =VLOOKUP(C17,'5a)NDA MPPR'!$B$9:$AK$61,7,FALSE) -> 25.838 | K17: =VLOOKUP(C17,'5a)NDA MPPR'!$B$9:$AK$61,8,FALSE) -> 31.94 | L17: =VLOOKUP(C17,'5a)NDA MPPR'!$B$9:$AK$61,9,FALSE) -> 45058 | M17: =VLOOKUP(C17,'5a)NDA MPPR'!$B$9:$AK$61,10,FALSE) -> 45412 | N17: ='3) BC and Sanction'!I94 -> 0 | O17: =VLOOKUP(C17,'5a)NDA MPPR'!$B$9:$AK$61,12,FALSE) -> 31.9 | P17: =VLOOKUP(C17,'5a)NDA MPPR'!$B$9:$AK$61,13,FALSE) -> 25.8 | R17: =VLOOKUP(C17,'5a)NDA MPPR'!$B$9:$AK$61,15,FALSE) -> R | S17: =VLOOKUP(C17,'5a)NDA MPPR'!$B$9:$AK$61,16,FALSE) -> 0 | U17: =VLOOKUP(C17,'5a)NDA MPPR'!$B$9:$AK$61,18,FALSE) -> OBC (Mar-25) | W17: =VLOOKUP(C17,'5a)NDA MPPR'!$B$9:$AK$61,20,FALSE) -> 25.979194 | X17: =VLOOKUP(C17,'5a)NDA MPPR'!$B$9:$AK$61,21,FALSE) -> 18.769073 | Y17: =VLOOKUP(C17,'5a)NDA MPPR'!$B$9:$AK$61,22,FALSE) -> 0 | AA17: =VLOOKUP(C17,'5a)NDA MPPR'!$B$9:$AK$61,24,FALSE) -> 45058 | AB17: =VLOOKUP(C17,'5a)NDA MPPR'!$B$9:$AK$61,25,FALSE) -> 46175 | AC17: =VLOOKUP(C17,'5a)NDA MPPR'!$B$9:$AK$61,26,FALSE) -> 0 | AE17: =VLOOKUP(C17,'5a)NDA MPPR'!$B$9:$AK$61,28,FALSE) -> 19.634303 | AF17: =VLOOKUP(C17,'5a)NDA MPPR'!$B$9:$AK$61,29,FALSE) -> 19.634303 | AG17: =VLOOKUP(C17,'5a)NDA MPPR'!$B$9:$AK$61,30,FALSE) -> 16.969073 | AH17: =VLOOKUP(C17,'5a)NDA MPPR'!$B$9:$AK$61,31,FALSE) -> 1.1570639 | AI17: =VLOOKUP(C17,'5a)NDA MPPR'!$B$9:$AK$61,32,FALSE) -> 1 | AJ17: =VLOOKUP(C17,'5a)NDA MPPR'!$B$9:$AK$61,33,FALSE) -> 0.75577028 | AK17: =VLOOKUP(C17,'5a)NDA MPPR'!$B$9:$AK$61,34,FALSE) -> 0.75577029 | AM17: =VLOOKUP(C17,'5a)NDA MPPR'!$B$9:$AK$61,36,FALSE) -> G | AO17: =#REF!-#REF! -> #REF! | AP17: =#REF!-#REF! -> #REF! | AQ17: =#REF!-#REF! -> #REF! | AS17: =#REF!-#REF! -> #REF! | AT17: =#REF!-#REF! -> #REF! | AV17: 18.769073 | AW17: 46175 | AY17: 25.979194 | AZ17: =W17-AY17 -> 0 | BA17: 45058 | BB17: =AA17-BA17 -> 0
A18: =C17 -> Enhanced CNC Airwave System (Encrypted Comms) | B18: =VLOOKUP($C17,'5a)NDA MPPR'!$A$9:$AK$61,2,FALSE) -> The Encrypted Communications (EC) project will deliver the ability for the Civil Nuclear Constabulary (CNC), and other emergency responders utilising current Airwave and/or future Emergency Services Network, to clearly communicate with their Command and Control, both during routine patrols and in emergency response, within a number of identified facilities. The Delivery Confidence Assessment remains Red, since the forecast end date is outside of the Business Case P80 date due to the project having been on hold pending a future scope delivery decision by the Security & Resilience (S&R) Programme. The project has now competed the installation and commissioning of the full new communications system installed in SMP, and shown that this is functioning, with coverage signal strength tested and proven to meet design requirements throughout. The decision timeline for further scope delivery was linked to the production by S&R of Facility Security Plans and their associated Physical Security Vulnerability Assessments (PSVA), since this would give the most robust answer (for both the EC project and the PSVA process) in terms of need. The assessment work on Encrypted Comms project is now complete, resulting in a significant reduction in the project scope. The project EAC has therefore been reduced accordingly and formal governance steps completed to down scope the project. The Baseline status is Red, reflective of the current pause. The project has implemented a deferral change control reflecting the impact of the pause to the project; this is within SL delegation and went to the Group Investment Panel (GIC) for noting in late April. Capability and Capacity RAG is Green and it should be noted minimal resource is assigned as the project is on hold.
B20: 35/10137 | C20: Box Encapsulation Plant | D20: Sellafield | F20: =VLOOKUP(C20,'5a)NDA MPPR'!$B$9:$AK$61,3,FALSE) -> A | G20: =VLOOKUP(C20,'5a)NDA MPPR'!$B$9:$AK$61,4,FALSE) -> 0 | I20: =VLOOKUP(C20,'5a)NDA MPPR'!$B$9:$AK$61,6,FALSE) -> FBC (Jul-22) | J20: =VLOOKUP(C20,'5a)NDA MPPR'!$B$9:$AK$61,7,FALSE) -> 1316 | K20: =VLOOKUP(C20,'5a)NDA MPPR'!$B$9:$AK$61,8,FALSE) -> 1512 | L20: =VLOOKUP(C20,'5a)NDA MPPR'!$B$9:$AK$61,9,FALSE) -> 46609 | M20: =VLOOKUP(C20,'5a)NDA MPPR'!$B$9:$AK$61,10,FALSE) -> 46847 | N20: ='3) BC and Sanction'!I97 -> 0 | O20: =VLOOKUP(C20,'5a)NDA MPPR'!$B$9:$AK$61,12,FALSE) -> 1512 | P20: =VLOOKUP(C20,'5a)NDA MPPR'!$B$9:$AK$61,13,FALSE) -> 1447.5 | R20: =VLOOKUP(C20,'5a)NDA MPPR'!$B$9:$AK$61,15,FALSE) -> A | S20: =VLOOKUP(C20,'5a)NDA MPPR'!$B$9:$AK$61,16,FALSE) -> 0 | U20: =VLOOKUP(C20,'5a)NDA MPPR'!$B$9:$AK$61,18,FALSE) -> FBC Re. (Nov-24) | W20: =VLOOKUP(C20,'5a)NDA MPPR'!$B$9:$AK$61,20,FALSE) -> 1335.4604 | X20: =VLOOKUP(C20,'5a)NDA MPPR'!$B$9:$AK$61,21,FALSE) -> 1474.7309 | Y20: =VLOOKUP(C20,'5a)NDA MPPR'!$B$9:$AK$61,22,FALSE) -> 0 | AA20: =VLOOKUP(C20,'5a)NDA MPPR'!$B$9:$AK$61,24,FALSE) -> 46402 | AB20: =VLOOKUP(C20,'5a)NDA MPPR'!$B$9:$AK$61,25,FALSE) -> 46721 | AC20: =VLOOKUP(C20,'5a)NDA MPPR'!$B$9:$AK$61,26,FALSE) -> 20 | AE20: =VLOOKUP(C20,'5a)NDA MPPR'!$B$9:$AK$61,28,FALSE) -> 1282.9507 | AF20: =VLOOKUP(C20,'5a)NDA MPPR'!$B$9:$AK$61,29,FALSE) -> 1223.446 | AG20: =VLOOKUP(C20,'5a)NDA MPPR'!$B$9:$AK$61,30,FALSE) -> 1355.3228 | AH20: =VLOOKUP(C20,'5a)NDA MPPR'!$B$9:$AK$61,31,FALSE) -> 0.90269717 | AI20: =VLOOKUP(C20,'5a)NDA MPPR'!$B$9:$AK$61,32,FALSE) -> 0.95361887 | AJ20: =VLOOKUP(C20,'5a)NDA MPPR'!$B$9:$AK$61,33,FALSE) -> 0.96068045 | AK20: =VLOOKUP(C20,'5a)NDA MPPR'!$B$9:$AK$61,34,FALSE) -> 0.91612301 | AM20: =VLOOKUP(C20,'5a)NDA MPPR'!$B$9:$AK$61,36,FALSE) -> G | AO20: =T30-G30 -> 0 | AP20: =T30-K30 -> 0 | AQ20: =X30-I30 -> 0 | AS20: =T30-S30 -> 0 | AT20: =X30-W30 -> 0 | AV20: 1474.7309 | AW20: 46701 | AY20: 1335.4604 | AZ20: =W20-AY20 -> 0 | BA20: 46402 | BB20: =AA20-BA20 -> 0
A21: =C20 -> Box Encapsulation Plant | B21: =VLOOKUP($C20,'5a)NDA MPPR'!$A$9:$AK$61,2,FALSE) -> The BEP Project provides the Magnox Swarf Storage Silos (MSSS) Programme the capability to receive, package, inspect, and transfer Intermediate Level Waste to interim stores. At completion, BEP will enable waste retrieval at pace, to maintain an As Low as Reasonably Practicable (ALARP) position, a fundamental requirement of Sellafield Ltd site license conditions. The first project benefit: Regulatory approval to Start Active Commissioning is now forecast November 2027. First MSSS box into BEP and Active Commissioning of MSSS waste is February 2028, with benefits realisation associated with the start of Operations July 2028. Project Completion including governance is currently forecast as November 2028, within the period of ‘up to 12 months’ after the Start of Active Commissioning defined in the approved Resubmitted Business Case. The Delivery Confidence Assessment (DCA) remains Amber recognising the Project challenges that are being managed, the Baseline RAG remains Amber, Lifetime EAC is beyond P50 but within P80. P80 Drawdown was presented and endorsed at NDA GIC on 16th December 2025 and sanction released to the project by the NDA on 18th December 2025. The P50 cost and schedule: Lifecycle EAC is £1,475m and Start Active Commissioning is forecast 30th November 2027. The project continues to be impacted by industrial action in the supply chain resulting in productivity losses, key skills unavailable, and constraints on work scope delivery. Impact assessment will be finalised on conclusion of the action with the intent to seek appropriate sanction relief subject to further review. This is not a dispute directly with Sellafield Ltd; Sellafield is engaged with the Supply Chain and Stakeholders to ensure effective management of the impacts; correct mitigations are in place and to effectively mobilise resources upon return to work. The project acknowledges pressure on the P80 position following cost growth and schedule slippage in the deterministic Joint Venture (JV) cost forecast and programme from the impact of Fault Observations (FOBs), on-going construction delays impacting the handover of Safety Transfer Certificates (STCs) to commissioning and ongoing industrial relations action. Cost impact of delays on the projects strategic decision to target more complex STCs first has been compounded by significant resource load deployed at the same time. Action is being taken to address each of these issues through an executive sponsored BEP Special Delivery Board. Whilst these delays have resulted in deterministic float erosion and with a potential range of (November 2027 to February 2028 and £1,475m to £1,494m) confidence remains in delivering within sanction P80 cost. We note, however, that on-going industrial relations action, since determination of the current range, has significantly impacted the deterministic programme in recent periods and is pressurising the forecast date range and potentially P80 date of April 2028 itself. Highlights in period are the endorsement of P80 drawdown paper at NDA GIC and confirmation of additional sanction release to the project by NDA. The Capability and Capacity RAG status remains Green this period as the project continues the transition from Construction to Commissioning, with resource transition plans developed. Sanction protection measures have been put in place to ensure resource redeployment achieves cost reduction targets whilst still maintaining capability and capacity to deliver remaining scope.
B23: 35/09592 | C23: Sellafield Product & Residue Store Retreatment Plant | D23: Sellafield | F23: =VLOOKUP(C23,'5a)NDA MPPR'!$B$9:$AK$61,3,FALSE) -> A | G23: =VLOOKUP(C23,'5a)NDA MPPR'!$B$9:$AK$61,4,FALSE) -> 0 | I23: =VLOOKUP(C23,'5a)NDA MPPR'!$B$9:$AK$61,6,FALSE) -> FBC (Jul-21) | J23: =VLOOKUP(C23,'5a)NDA MPPR'!$B$9:$AK$61,7,FALSE) -> 1335.43 | K23: =VLOOKUP(C23,'5a)NDA MPPR'!$B$9:$AK$61,8,FALSE) -> 1673 | L23: =VLOOKUP(C23,'5a)NDA MPPR'!$B$9:$AK$61,9,FALSE) -> 47400 | M23: =VLOOKUP(C23,'5a)NDA MPPR'!$B$9:$AK$61,10,FALSE) -> 48274 | N23: ='3) BC and Sanction'!I106 -> 0 | O23: =VLOOKUP(C23,'5a)NDA MPPR'!$B$9:$AK$61,12,FALSE) -> 1673 | P23: =VLOOKUP(C23,'5a)NDA MPPR'!$B$9:$AK$61,13,FALSE) -> 1482.9 | R23: =VLOOKUP(C23,'5a)NDA MPPR'!$B$9:$AK$61,15,FALSE) -> A | S23: =VLOOKUP(C23,'5a)NDA MPPR'!$B$9:$AK$61,16,FALSE) -> 0 | U23: =VLOOKUP(C23,'5a)NDA MPPR'!$B$9:$AK$61,18,FALSE) -> FBC (Oct-25) | W23: =VLOOKUP(C23,'5a)NDA MPPR'!$B$9:$AK$61,20,FALSE) -> 1479.319 | X23: =VLOOKUP(C23,'5a)NDA MPPR'!$B$9:$AK$61,21,FALSE) -> 1466.5527 | Y23: =VLOOKUP(C23,'5a)NDA MPPR'!$B$9:$AK$61,22,FALSE) -> 0 | AA23: =VLOOKUP(C23,'5a)NDA MPPR'!$B$9:$AK$61,24,FALSE) -> 47574 | AB23: =VLOOKUP(C23,'5a)NDA MPPR'!$B$9:$AK$61,25,FALSE) -> 47574 | AC23: =VLOOKUP(C23,'5a)NDA MPPR'!$B$9:$AK$61,26,FALSE) -> 0 | AE23: =VLOOKUP(C23,'5a)NDA MPPR'!$B$9:$AK$61,28,FALSE) -> 1159.6947 | AF23: =VLOOKUP(C23,'5a)NDA MPPR'!$B$9:$AK$61,29,FALSE) -> 988.78109 | AG23: =VLOOKUP(C23,'5a)NDA MPPR'!$B$9:$AK$61,30,FALSE) -> 1063.1163 | AH23: =VLOOKUP(C23,'5a)NDA MPPR'!$B$9:$AK$61,31,FALSE) -> 0.93007799 | AI23: =VLOOKUP(C23,'5a)NDA MPPR'!$B$9:$AK$61,32,FALSE) -> 0.85262188 | AJ23: =VLOOKUP(C23,'5a)NDA MPPR'!$B$9:$AK$61,33,FALSE) -> 0.78393821 | AK23: =VLOOKUP(C23,'5a)NDA MPPR'!$B$9:$AK$61,34,FALSE) -> 0.66840288 | AM23: =VLOOKUP(C23,'5a)NDA MPPR'!$B$9:$AK$61,36,FALSE) -> A | AO23: =T21-G21 -> 0 | AP23: =T21-K21 -> 0 | AQ23: =X21-I21 -> 0 | AS23: =T21-S21 -> 0 | AT23: =X21-W21 -> 0 | AV23: 1466.5527 | AW23: 47574 | AY23: 1479.319 | AZ23: =W23-AY23 -> -1.0000001e-06 | BA23: 47574 | BB23: =AA23-BA23 -> 0
A24: =C23 -> Sellafield Product & Residue Store Retreatment Plant | B24: =VLOOKUP($C23,'5a)NDA MPPR'!$A$9:$AK$61,2,FALSE) -> The Sellafield Product & Residue Store Retreatment Plant (SRP) project is a key element of the Sellafield Ltd ‘Special Nuclear Materials (SNM) Future State Programme’. The SRP is a complex major project required to provide the capability to receive special nuclear material in existing packages, from existing stores on the Sellafield site, and process the material into a form and package suitable for safe and secure long-term interim storage. The SRO Delivery Confidence Assessment (DCA) remains Amber against the P80 cost and schedule from the Full Business Case (FBC) approved by HMG in July 2021. This is primarily reflective of the previously reported emerging issue relating to legislative changes to Passive Fire Protection standards and the implementation of the changes to the Building Safety Act (2022) following the Grenfell Tower Inquiry. The impact of the changes to the Passive Fire Protection standards will require a significant amount of engineering design rework and additional installation work in the new facility; the key impact is expected to be on the schedule to achieve readiness of the facility for Glove box installation, which has now become the critical path for the project. The schedule and cost impact assessment of the additional work is being carried out and will be complete in Quarter 4 2026, this will include an assessment as to how this issue should be considered in terms of the projects current P80 sanctioned cost and schedule. The project continues to be impacted by industrial action in the supply chain resulting in productivity losses, key skills unavailable, and constraints on work scope delivery. Impact assessment will be finalised on conclusion of the action with the intent to seek appropriate sanction relief subject to further review. This is not a dispute directly with Sellafield Ltd; Sellafield is engaged with the Supply Chain and Stakeholders to ensure effective management of the impacts; correct mitigations are in place and to effectively mobilise resources upon return to work. Additionally, as previously reported, the project P80 contingency has already been impacted by having to manage extraordinary inflation incurred on the project to date. To date £128.9m of the P50 – P80 sanctioned contingency for the project has been utilised to absorb the impact of the inflation thereby substantially eroding the remaining contingency available (there is £190m of P50-P80 sanction remaining). This is in the context of an increasing likelihood of a future re-sanction request of additional P50-P80 contingency due to further events arising that potentially impact the remaining P50 – P80 contingency available. The project will be submitting a request to the DESNZ PIC when appropriate to enable these issues to be managed accordingly. In period: On site, installation of primary steelwork is ongoing, with secondary steel install progressing towards readiness for cladding. Off-site, Integrated Works Testing progressing on Residues and Repackaging glovebox lines, other glovebox line and support systems are completing final assembly and Factory Acceptance Testing. The Capability and Capacity RAG status remains Amber with ongoing challenges in recruitment principally across several disciplines including construction, engineering, commissioning, and quality. Finally, the successful active commissioning and future operations of the SRP facility are contingent upon several dependencies managed within the SNM Future State Programme. A critical dependency is the availability of SNM analytical capability, which is essential to support both commissioning and ongoing operational activities. To address this, a dedicated project is being developed and delivered through the PPP to ensure the required analytical capability is in place. The SNM Future State Programme team is responsible for managing all dependencies associated with SRP, with the overarching goal of ensuring that all necessary capabilities are aligned and available to enable the delivery of SRP outcomes and the realisation of associated benefits.
B26: 35/07654 | C26: BEPPS2 | D26: Sellafield | F26: =VLOOKUP(C26,'5a)NDA MPPR'!$B$9:$AK$61,3,FALSE) -> A | G26: =VLOOKUP(C26,'5a)NDA MPPR'!$B$9:$AK$61,4,FALSE) -> -1 | I26: =VLOOKUP(C26,'5a)NDA MPPR'!$B$9:$AK$61,6,FALSE) -> OBC (Sep-23) | J26: =VLOOKUP(C26,'5a)NDA MPPR'!$B$9:$AK$61,7,FALSE) -> 776 | K26: =VLOOKUP(C26,'5a)NDA MPPR'!$B$9:$AK$61,8,FALSE) -> 837 | L26: =VLOOKUP(C26,'5a)NDA MPPR'!$B$9:$AK$61,9,FALSE) -> 49490 | M26: =VLOOKUP(C26,'5a)NDA MPPR'!$B$9:$AK$61,10,FALSE) -> 49795 | N26: ='3) BC and Sanction'!I103 -> 0 | O26: =VLOOKUP(C26,'5a)NDA MPPR'!$B$9:$AK$61,12,FALSE) -> 382 | P26: =VLOOKUP(C26,'5a)NDA MPPR'!$B$9:$AK$61,13,FALSE) -> 186 | R26: =VLOOKUP(C26,'5a)NDA MPPR'!$B$9:$AK$61,15,FALSE) -> A | S26: =VLOOKUP(C26,'5a)NDA MPPR'!$B$9:$AK$61,16,FALSE) -> -1 | U26: =VLOOKUP(C26,'5a)NDA MPPR'!$B$9:$AK$61,18,FALSE) -> OBC (Mar-23) | W26: =VLOOKUP(C26,'5a)NDA MPPR'!$B$9:$AK$61,20,FALSE) -> 751.17472 | X26: =VLOOKUP(C26,'5a)NDA MPPR'!$B$9:$AK$61,21,FALSE) -> 746.06354 | Y26: =VLOOKUP(C26,'5a)NDA MPPR'!$B$9:$AK$61,22,FALSE) -> -3.1 | AA26: =VLOOKUP(C26,'5a)NDA MPPR'!$B$9:$AK$61,24,FALSE) -> 49490 | AB26: =VLOOKUP(C26,'5a)NDA MPPR'!$B$9:$AK$61,25,FALSE) -> 49490 | AC26: =VLOOKUP(C26,'5a)NDA MPPR'!$B$9:$AK$61,26,FALSE) -> 0 | AE26: =VLOOKUP(C26,'5a)NDA MPPR'!$B$9:$AK$61,28,FALSE) -> 130.87674 | AF26: =VLOOKUP(C26,'5a)NDA MPPR'!$B$9:$AK$61,29,FALSE) -> 122.09891 | AG26: =VLOOKUP(C26,'5a)NDA MPPR'!$B$9:$AK$61,30,FALSE) -> 109.74899 | AH26: =VLOOKUP(C26,'5a)NDA MPPR'!$B$9:$AK$61,31,FALSE) -> 1.1125287 | AI26: =VLOOKUP(C26,'5a)NDA MPPR'!$B$9:$AK$61,32,FALSE) -> 0.93293054 | AJ26: =VLOOKUP(C26,'5a)NDA MPPR'!$B$9:$AK$61,33,FALSE) -> 0.17422943 | AK26: =VLOOKUP(C26,'5a)NDA MPPR'!$B$9:$AK$61,34,FALSE) -> 0.16254395 | AM26: =VLOOKUP(C26,'5a)NDA MPPR'!$B$9:$AK$61,36,FALSE) -> G | AO26: =T33-G33 -> 0 | AP26: =T33-K33 -> 0 | AQ26: =X33-I33 -> 0 | AS26: =T33-S33 -> 0 | AT26: =X33-W33 -> 0 | AV26: 749.16803 | AW26: 49490 | AY26: 751.17472 | AZ26: =W26-AY26 -> 0 | BA26: 49490 | BB26: =AA26-BA26 -> 0
A27: =C26 -> BEPPS2 | B27: =VLOOKUP($C26,'5a)NDA MPPR'!$A$9:$AK$61,2,FALSE) -> The Box Encapsulation Plant Product Store 2 (BEPPS2) is a critical enabler for continued high hazard retrievals from the Magnox Swarf Storage Silo (MSSS) and Pile Fuel Cladding Silo (PFCS). It will provide modern, safe and secure long term interim storage for approximately 7,500 packages of Intermediate Level Waste. The strategic requirement has been confirmed. The first project benefit is the ability to receive packages from MSSS and PFCS without constraining hazard reduction programmes. The Senior Responsible Owner (SRO) Delivery Confidence Assessment has been changed to Amber. The Baseline RAG has also changed to amber in line with this decision. Close out of actions this month will enable confirmation that target design maturity has been achieved. Good progress continues in bulk excavation and preparation for construction on the site. A decision has been made to hold up the placement of the civil substructure sub-contract to allow more time to challenge procurement plans to ensure value for money. The client is also undertaking an independent review of cost and schedule ahead of negotiations on the Major Project Baseline. The OBC sanction hold point release is dependent on these activities being successfully achieved; therefore, a prudent assessment of Amber recognises the potential to impact future key commitments required to progress project delivery. The project is in the Define Phase, completing the detailed design for transition to civil construction and procurement of long-lead items. The critical path runs through civil construction, mechanical and electrical installation, and commissioning. Engagement with Programme and Project Partnership (PPP) Key Delivery Partners is ongoing to underpin delivery phase planning, cost estimation, and Quantitative Risk Analysis (QRA), informing both the OBC sanction hold point release in Quarter 4 FY2025/26 and the Full Business Case (FBC) submission planned for FY2026/27. The project continues to be impacted by industrial action in the supply chain resulting in productivity losses, key skills unavailable, and constraints on work scope delivery. Impact assessment will be finalised on conclusion of the action with the intent to seek appropriate sanction relief subject to further review. This is not a dispute directly with Sellafield Ltd; Sellafield is engaged with the Supply Chain and Stakeholders to ensure effective management of the impacts; correct mitigations are in place and to effectively mobilise resources upon return to work. The SPI reflects both historic design delays due to historic resource constraints and the non-utilisation of risk and estimating uncertainty. The forthcoming OBC sanction hold point release will include updates on the lifecycle cost estimates that will be underpinned by an updated QRA and will reflect proactive management of opportunities and realisation of threats during the Define Stage. Capability RAG remains Green. The reduction in Lifecycle EAC is an error in AIF forecasting that will be rectified next period.
B29: 35/09975 | C29: Security Systems Architecture Upgrade (SSAU) | D29: Sellafield | F29: =VLOOKUP(C29,'5a)NDA MPPR'!$B$9:$AK$61,3,FALSE) -> G | G29: =VLOOKUP(C29,'5a)NDA MPPR'!$B$9:$AK$61,4,FALSE) -> 0 | I29: =VLOOKUP(C29,'5a)NDA MPPR'!$B$9:$AK$61,6,FALSE) -> FBC (Mar-20) | J29: =VLOOKUP(C29,'5a)NDA MPPR'!$B$9:$AK$61,7,FALSE) -> 305.9 | K29: =VLOOKUP(C29,'5a)NDA MPPR'!$B$9:$AK$61,8,FALSE) -> 315.4 | L29: =VLOOKUP(C29,'5a)NDA MPPR'!$B$9:$AK$61,9,FALSE) -> 46053 | M29: =VLOOKUP(C29,'5a)NDA MPPR'!$B$9:$AK$61,10,FALSE) -> 46112 | N29: ='3) BC and Sanction'!I91 -> 0 | O29: =VLOOKUP(C29,'5a)NDA MPPR'!$B$9:$AK$61,12,FALSE) -> 315.4 | P29: =VLOOKUP(C29,'5a)NDA MPPR'!$B$9:$AK$61,13,FALSE) -> 315.4 | R29: =VLOOKUP(C29,'5a)NDA MPPR'!$B$9:$AK$61,15,FALSE) -> R | S29: =VLOOKUP(C29,'5a)NDA MPPR'!$B$9:$AK$61,16,FALSE) -> 0 | U29: =VLOOKUP(C29,'5a)NDA MPPR'!$B$9:$AK$61,18,FALSE) -> OBC (Oct-24) | W29: =VLOOKUP(C29,'5a)NDA MPPR'!$B$9:$AK$61,20,FALSE) -> 297.38168 | X29: =VLOOKUP(C29,'5a)NDA MPPR'!$B$9:$AK$61,21,FALSE) -> 315.08838 | Y29: =VLOOKUP(C29,'5a)NDA MPPR'!$B$9:$AK$61,22,FALSE) -> 0 | AA29: =VLOOKUP(C29,'5a)NDA MPPR'!$B$9:$AK$61,24,FALSE) -> 46107 | AB29: =VLOOKUP(C29,'5a)NDA MPPR'!$B$9:$AK$61,25,FALSE) -> 46107 | AC29: =VLOOKUP(C29,'5a)NDA MPPR'!$B$9:$AK$61,26,FALSE) -> 0 | AE29: =VLOOKUP(C29,'5a)NDA MPPR'!$B$9:$AK$61,28,FALSE) -> 293.87327 | AF29: =VLOOKUP(C29,'5a)NDA MPPR'!$B$9:$AK$61,29,FALSE) -> 292.93552 | AG29: =VLOOKUP(C29,'5a)NDA MPPR'!$B$9:$AK$61,30,FALSE) -> 314.06941 | AH29: =VLOOKUP(C29,'5a)NDA MPPR'!$B$9:$AK$61,31,FALSE) -> 0.9327095 | AI29: =VLOOKUP(C29,'5a)NDA MPPR'!$B$9:$AK$61,32,FALSE) -> 0.99680901 | AJ29: =VLOOKUP(C29,'5a)NDA MPPR'!$B$9:$AK$61,33,FALSE) -> 0.98820232 | AK29: =VLOOKUP(C29,'5a)NDA MPPR'!$B$9:$AK$61,34,FALSE) -> 0.98504898 | AM29: =VLOOKUP(C29,'5a)NDA MPPR'!$B$9:$AK$61,36,FALSE) -> A | AO29: =T18-G18 -> 0 | AP29: =T18-K18 -> 0 | AQ29: =X18-I18 -> 0 | AS29: =T18-S18 -> 0 | AT29: =X18-W18 -> 0 | AV29: 315.13483 | AW29: 46107 | AY29: 297.38168 | AZ29: =W29-AY29 -> 0 | BA29: 46107 | BB29: =AA29-BA29 -> 0
A30: =C29 -> Security Systems Architecture Upgrade (SSAU) | B30: =VLOOKUP($C29,'5a)NDA MPPR'!$A$9:$AK$61,2,FALSE) -> The SSAU project will provide infrastructure and equipment that will provide security and emergency response teams with a significantly improved capability to react to and manage security and/or emergency events on the Sellafield site. The first project benefit is equipment which, once operational in the command centre, will provide a significantly improved capability to react and manage security and/or emergency events on the Sellafield site - thereby complying with the standards, expectations and objectives set by nuclear regulators. The Delivery Confidence Assessment remains stable at Green recognising forecast delivery within the Projects P80 Sanction. The Baseline RAG has remained Red in period, as the Cost forecast remains beyond the P50 baseline. The Project is still however forecasting to deliver within the P80 Sanction released to Sellafield. The project continues to be impacted by industrial action in the supply chain resulting in productivity losses, key skills unavailable, and constraints on work scope delivery. Impact assessment will be finalised on conclusion of the action with the intent to seek appropriate sanction relief subject to further review. This is not a dispute directly with Sellafield Ltd; Sellafield is engaged with the Supply Chain and Stakeholders to ensure effective management of the impacts; correct mitigations are in place and to effectively mobilise resources upon return to work. In period the Lifecycle EAC has remained stable at £315.1m and within the P80 Sanction. Level 2 commissioning has been successfully completed in the period, which has enabled the script updates to commence, and the Level 1 commissioning to commence in early January, the Completion of Level 1 commissioning Report remains in early March. The Amber rating on the Capability and Capacity RAG recognises that schedule adherence is reliant on skilled resources and the project team is now a very thin layer and any loss of resources would impact delivery as has occurred in this period with sickness and a pass issue.
B32: 35/09968 | C32: CNC Operational Unit | D32: Sellafield | F32: =VLOOKUP(C32,'5a)NDA MPPR'!$B$9:$AK$61,3,FALSE) -> G | G32: =VLOOKUP(C32,'5a)NDA MPPR'!$B$9:$AK$61,4,FALSE) -> 0 | I32: =VLOOKUP(C32,'5a)NDA MPPR'!$B$9:$AK$61,6,FALSE) -> FBC (Jun-24) | J32: =VLOOKUP(C32,'5a)NDA MPPR'!$B$9:$AK$61,7,FALSE) -> 72.6 | K32: =VLOOKUP(C32,'5a)NDA MPPR'!$B$9:$AK$61,8,FALSE) -> 79 | L32: =VLOOKUP(C32,'5a)NDA MPPR'!$B$9:$AK$61,9,FALSE) -> 46106 | M32: =VLOOKUP(C32,'5a)NDA MPPR'!$B$9:$AK$61,10,FALSE) -> 46234 | N32: ='3) BC and Sanction'!I85 -> 0 | O32: =VLOOKUP(C32,'5a)NDA MPPR'!$B$9:$AK$61,12,FALSE) -> 72.6 | P32: =VLOOKUP(C32,'5a)NDA MPPR'!$B$9:$AK$61,13,FALSE) -> 72.6 | R32: =VLOOKUP(C32,'5a)NDA MPPR'!$B$9:$AK$61,15,FALSE) -> G | S32: =VLOOKUP(C32,'5a)NDA MPPR'!$B$9:$AK$61,16,FALSE) -> 0 | U32: =VLOOKUP(C32,'5a)NDA MPPR'!$B$9:$AK$61,18,FALSE) -> FBC (Sep-24) | W32: =VLOOKUP(C32,'5a)NDA MPPR'!$B$9:$AK$61,20,FALSE) -> 72.672543 | X32: =VLOOKUP(C32,'5a)NDA MPPR'!$B$9:$AK$61,21,FALSE) -> 71.943748 | Y32: =VLOOKUP(C32,'5a)NDA MPPR'!$B$9:$AK$61,22,FALSE) -> 0.6 | AA32: =VLOOKUP(C32,'5a)NDA MPPR'!$B$9:$AK$61,24,FALSE) -> 46106 | AB32: =VLOOKUP(C32,'5a)NDA MPPR'!$B$9:$AK$61,25,FALSE) -> 46231 | AC32: =VLOOKUP(C32,'5a)NDA MPPR'!$B$9:$AK$61,26,FALSE) -> 99 | AE32: =VLOOKUP(C32,'5a)NDA MPPR'!$B$9:$AK$61,28,FALSE) -> 72.642747 | AF32: =VLOOKUP(C32,'5a)NDA MPPR'!$B$9:$AK$61,29,FALSE) -> 65.985415 | AG32: =VLOOKUP(C32,'5a)NDA MPPR'!$B$9:$AK$61,30,FALSE) -> 70.04333 | AH32: =VLOOKUP(C32,'5a)NDA MPPR'!$B$9:$AK$61,31,FALSE) -> 0.94206566 | AI32: =VLOOKUP(C32,'5a)NDA MPPR'!$B$9:$AK$61,32,FALSE) -> 0.90835518 | AJ32: =VLOOKUP(C32,'5a)NDA MPPR'!$B$9:$AK$61,33,FALSE) -> 0.99958999 | AK32: =VLOOKUP(C32,'5a)NDA MPPR'!$B$9:$AK$61,34,FALSE) -> 0.90798275 | AM32: =VLOOKUP(C32,'5a)NDA MPPR'!$B$9:$AK$61,36,FALSE) -> G | AO32: =T24-G24 -> 0 | AP32: =T24-K24 -> 0 | AQ32: =X24-I24 -> 0 | AS32: =T24-S24 -> 0 | AT32: =X24-W24 -> 0 | AV32: 71.339767 | AW32: 46132 | AY32: 72.672543 | AZ32: =W32-AY32 -> 0 | BA32: 46106 | BB32: =AA32-BA32 -> 0
A33: =C32 -> CNC Operational Unit | B33: =VLOOKUP($C32,'5a)NDA MPPR'!$A$9:$AK$61,2,FALSE) -> The Civil Nuclear Constabulary (CNC) Operational Unit project will provide one location on site to house all CNC personnel, with space allowance for future uplift of officers, whilst mitigating health and safety risks associated with the current facilities. The Delivery Confidence Assessment (DCA) is stable at Green as the Resubmission Full Business Case (FBC) has received approval from His Majesty’s Treasury (HMT) in June 2024. Bulk Construction was claimed as complete on the 19th of December by CNSL. This milestone has been used to reduce the amount of construction resources on the project, there will be some remaining Construction works ongoing in parallel with the Commissioning works. The project continues to be impacted by industrial action in the supply chain resulting in productivity losses, key skills unavailable, and constraints on work scope delivery. Impact assessment will be finalised on conclusion of the action with the intent to seek appropriate sanction relief subject to further review. This is not a dispute directly with Sellafield Ltd; Sellafield is engaged with the Supply Chain and Stakeholders to ensure effective management of the impacts; correct mitigations are in place and to effectively mobilise resources upon return to work. The completion of the Level 1 Board rooms was initially impacted by the replacement of the non-complaint glands, yet it has continued to be further impacted by the industrial action as well as slower than anticipated progress of the other works required to be completed and higher level of snagging than anticipated following contractor and client inspections. These delays have been compounded through the loss of opportunity to recover through additional weekend working due the Union imposed overtime ban related to the on-going industrial action. Level 1 boards pre-commissioning is forecast to commence in early January 2026. As reported last period, CNSL were still undertaking commissioning workshops to resequence the planned works and decouple the Level 1 Board commissioning from the critical path. The output of these workshops has been bought into by CNSL executives and was presented to SL in P9 reporting. The impact of this resequencing, in addition to the industrial action impact to date, the loss of opportunity of weekend working and the rework associated with the Level 1 boards, has seen the SL project end date move from 20th April 2026 to the 28th July 2026. However, it is important to note that July 2026 includes an SL risk buffer, and Commissioning is forecasted to complete in April 2026 with Building Handover forecast to take place in May 2026. There remains an opportunity within Commissioning to increase working hours through varied shift patterns and overtime working as these resources are not affected by the industrial action. The change in end date has also seen the EAC increase by £0.6m from £71.3m to £71.9m, this remains below the P50 value of £72.5m. On-site work continues to progress well, civils scope is focused on external works and building finishes, Control, Electrical & Instrumentation (CE&I) works is focused on ensuring the Level 1 boards are ready for commissioning starting in the new year with the Project working closely with Utilities. Heat, Ventilation and Air Conditioning (HVAC) installation works is almost complete. The Capability and Capacity RAG remains Green for the period with no current vacancies.
B35: 35/09343 | C35: SIXEP Continuity Plant | D35: Sellafield | F35: =VLOOKUP(C35,'5a)NDA MPPR'!$B$9:$AK$61,3,FALSE) -> G | G35: =VLOOKUP(C35,'5a)NDA MPPR'!$B$9:$AK$61,4,FALSE) -> 0 | I35: =VLOOKUP(C35,'5a)NDA MPPR'!$B$9:$AK$61,6,FALSE) -> FBC (Dec-21) | J35: =VLOOKUP(C35,'5a)NDA MPPR'!$B$9:$AK$61,7,FALSE) -> 1007 | K35: =VLOOKUP(C35,'5a)NDA MPPR'!$B$9:$AK$61,8,FALSE) -> 1182 | L35: =VLOOKUP(C35,'5a)NDA MPPR'!$B$9:$AK$61,9,FALSE) -> 47849 | M35: =VLOOKUP(C35,'5a)NDA MPPR'!$B$9:$AK$61,10,FALSE) -> 48611 | N35: ='3) BC and Sanction'!I109 -> 0 | O35: =VLOOKUP(C35,'5a)NDA MPPR'!$B$9:$AK$61,12,FALSE) -> 1182 | P35: =VLOOKUP(C35,'5a)NDA MPPR'!$B$9:$AK$61,13,FALSE) -> 1150.7 | R35: =VLOOKUP(C35,'5a)NDA MPPR'!$B$9:$AK$61,15,FALSE) -> G | S35: =VLOOKUP(C35,'5a)NDA MPPR'!$B$9:$AK$61,16,FALSE) -> 0 | U35: =VLOOKUP(C35,'5a)NDA MPPR'!$B$9:$AK$61,18,FALSE) -> FBC (Dec-25) | W35: =VLOOKUP(C35,'5a)NDA MPPR'!$B$9:$AK$61,20,FALSE) -> 1161.8395 | X35: =VLOOKUP(C35,'5a)NDA MPPR'!$B$9:$AK$61,21,FALSE) -> 1121.7088 | Y35: =VLOOKUP(C35,'5a)NDA MPPR'!$B$9:$AK$61,22,FALSE) -> 0.8 | AA35: =VLOOKUP(C35,'5a)NDA MPPR'!$B$9:$AK$61,24,FALSE) -> 48142 | AB35: =VLOOKUP(C35,'5a)NDA MPPR'!$B$9:$AK$61,25,FALSE) -> 48142 | AC35: =VLOOKUP(C35,'5a)NDA MPPR'!$B$9:$AK$61,26,FALSE) -> 0 | AE35: =VLOOKUP(C35,'5a)NDA MPPR'!$B$9:$AK$61,28,FALSE) -> 780.4267 | AF35: =VLOOKUP(C35,'5a)NDA MPPR'!$B$9:$AK$61,29,FALSE) -> 733.71603 | AG35: =VLOOKUP(C35,'5a)NDA MPPR'!$B$9:$AK$61,30,FALSE) -> 764.57702 | AH35: =VLOOKUP(C35,'5a)NDA MPPR'!$B$9:$AK$61,31,FALSE) -> 0.95963652 | AI35: =VLOOKUP(C35,'5a)NDA MPPR'!$B$9:$AK$61,32,FALSE) -> 0.94014727 | AJ35: =VLOOKUP(C35,'5a)NDA MPPR'!$B$9:$AK$61,33,FALSE) -> 0.67171646 | AK35: =VLOOKUP(C35,'5a)NDA MPPR'!$B$9:$AK$61,34,FALSE) -> 0.63151239 | AM35: =VLOOKUP(C35,'5a)NDA MPPR'!$B$9:$AK$61,36,FALSE) -> G | AO35: =T27-G27 -> 0 | AP35: =T27-K27 -> 0 | AQ35: =X27-I27 -> 0 | AS35: =T27-S27 -> 0 | AT35: =X27-W27 -> 0 | AV35: 1120.8757 | AW35: 48142 | AY35: 1133.0636 | AZ35: =W35-AY35 -> 28.775835 | BA35: 48142 | BB35: =AA35-BA35 -> 0
A36: =C35 -> SIXEP Continuity Plant | B36: =VLOOKUP($C35,'5a)NDA MPPR'!$A$9:$AK$61,2,FALSE) -> The SIXEP Continuity Plant (SCP) is required to deliver a continued site effluent treatment capability in support of radioactive liquid effluent discharge permits, fuel pond management, high hazard reduction projects and the overall NDA mission. This project provides a replacement for the existing SIXEP Sea Discharge Treatment plant and is therefore mission critical to the safe operation of the site. The SRO DCA RAG currently remains green echoed by National Infrastructure and Service Transformation Authority (NISTA) Green rating received in June 2025. However, there is a significant risk posed by the impact of extraordinary inflation that has been incurred to date. This follows the decision made by DESNZ Project Investment Committee (PIC) in Q2 24/25 to not approve the P80 Inflation Sanction relief for SCP. As an interim measure to mitigate the inflation impact, in December 2024 the NDA released £108.7m sanction to SL from P80, however this substantially erodes the P80 contingency. The scope driven P80 sanction drawdown, Adjustment Event (AE) for the project has been approved by SL Investment Review Panel (IRP) in November 2025 , This drawdown leaves a net £31m P80 contingency remaining. The SRO considers that this is likely to be insufficient for the next four years and has submitted a sanction release paper to DESNZ September 2025. The paper has now been endorsed by PIC and the Permanent Secretary for onward submission to Treasury Approval Process (TAP) & Chief Secretary to the Treasury (CST), targeting approval in Q4 25/26. Without this additional sanction the current DCA rating would change from Green to Red, hence this will be kept under review by the SRO. The Baseline RAG remains Green as the project forecast is within P50 cost and schedule parameters. A Change Control Request (CCR) was implemented in period to update the baseline as a result of the impact of an agreed AE post-Grenfell for fire safety. The project continues to be impacted by industrial action in the supply chain resulting in productivity losses, key skills unavailable, and constraints on work scope delivery. Impact assessment will be finalised on conclusion of the action with the intent to seek appropriate sanction relief subject to further review. This is not a dispute directly with Sellafield Ltd; Sellafield is engaged with the Supply Chain and Stakeholders to ensure effective management of the impacts; correct mitigations are in place and to effectively mobilise resources upon return to work. Fabrication of off-site pipework planned for completion Q4 25/26. Site pipework, vessel install, and welding of BST rings have been impacted by ongoing Industrial action in both the Effluent Treatment Cell (ETC) and Bulk Storage Tank (BST) cells. Progress continues across all floors within the Service Building, although the industrial relations impact has hindered productivity and subsequent handover to Mechanical, Electrical, Instrumentation, Control & Automation (MEICA) trades. Industrial relations issues have impacted delivery on the Project Wide Objectives (PWO) 4 - Handover of BST cell to Commissioning, PWO 5 - Handover Services Building to Commissioning and PWO 6 - Handover of ETC to Commissioning. Issues in period are there are increasing concerns due to the impact of industrial action between supply chain organisations and their employees impacting projects at Sellafield. At this time, productivity, efficiency and interim milestones are being affected. The Capability and Capacity RAG: remains Green with no issues to report.
B38: 35/10417 | C38: ILW East Land Excavation | D38: Sellafield | F38: =VLOOKUP(C38,'5a)NDA MPPR'!$B$9:$AK$61,3,FALSE) -> G | G38: =VLOOKUP(C38,'5a)NDA MPPR'!$B$9:$AK$61,4,FALSE) -> 0 | I38: =VLOOKUP(C38,'5a)NDA MPPR'!$B$9:$AK$61,6,FALSE) -> FBC (Jun-24) | J38: =VLOOKUP(C38,'5a)NDA MPPR'!$B$9:$AK$61,7,FALSE) -> 69.1 | K38: =VLOOKUP(C38,'5a)NDA MPPR'!$B$9:$AK$61,8,FALSE) -> 75.8 | L38: =VLOOKUP(C38,'5a)NDA MPPR'!$B$9:$AK$61,9,FALSE) -> 46295 | M38: =VLOOKUP(C38,'5a)NDA MPPR'!$B$9:$AK$61,10,FALSE) -> 46446 | N38: ='3) BC and Sanction'!I112 -> 0 | O38: =VLOOKUP(C38,'5a)NDA MPPR'!$B$9:$AK$61,12,FALSE) -> n/a | P38: =VLOOKUP(C38,'5a)NDA MPPR'!$B$9:$AK$61,13,FALSE) -> 69.1 | R38: =VLOOKUP(C38,'5a)NDA MPPR'!$B$9:$AK$61,15,FALSE) -> G | S38: =VLOOKUP(C38,'5a)NDA MPPR'!$B$9:$AK$61,16,FALSE) -> 0 | U38: =VLOOKUP(C38,'5a)NDA MPPR'!$B$9:$AK$61,18,FALSE) -> FBC (Mar-23) | W38: =VLOOKUP(C38,'5a)NDA MPPR'!$B$9:$AK$61,20,FALSE) -> 67.414678 | X38: =VLOOKUP(C38,'5a)NDA MPPR'!$B$9:$AK$61,21,FALSE) -> 35.886955 | Y38: =VLOOKUP(C38,'5a)NDA MPPR'!$B$9:$AK$61,22,FALSE) -> 0.4 | AA38: =VLOOKUP(C38,'5a)NDA MPPR'!$B$9:$AK$61,24,FALSE) -> 46266 | AB38: =VLOOKUP(C38,'5a)NDA MPPR'!$B$9:$AK$61,25,FALSE) -> 46112 | AC38: =VLOOKUP(C38,'5a)NDA MPPR'!$B$9:$AK$61,26,FALSE) -> 0 | AE38: =VLOOKUP(C38,'5a)NDA MPPR'!$B$9:$AK$61,28,FALSE) -> 63.664383 | AF38: =VLOOKUP(C38,'5a)NDA MPPR'!$B$9:$AK$61,29,FALSE) -> 62.738822 | AG38: =VLOOKUP(C38,'5a)NDA MPPR'!$B$9:$AK$61,30,FALSE) -> 35.506485 | AH38: =VLOOKUP(C38,'5a)NDA MPPR'!$B$9:$AK$61,31,FALSE) -> 1.766968 | AI38: =VLOOKUP(C38,'5a)NDA MPPR'!$B$9:$AK$61,32,FALSE) -> 0.98546187 | AJ38: =VLOOKUP(C38,'5a)NDA MPPR'!$B$9:$AK$61,33,FALSE) -> 0.94436975 | AK38: =VLOOKUP(C38,'5a)NDA MPPR'!$B$9:$AK$61,34,FALSE) -> 0.93064038 | AM38: =VLOOKUP(C38,'5a)NDA MPPR'!$B$9:$AK$61,36,FALSE) -> G | AO38: =T36-G36 -> 0 | AP38: =T36-K36 -> 0 | AQ38: =X36-I36 -> 0 | AS38: =T36-S36 -> 0 | AT38: =X36-W36 -> 0 | AV38: 35.500379 | AW38: 46112 | AY38: 67.414678 | AZ38: =W38-AY38 -> 0 | BA38: 46266 | BB38: =AA38-BA38 -> 0
A39: =C38 -> ILW East Land Excavation | B39: =VLOOKUP($C38,'5a)NDA MPPR'!$A$9:$AK$61,2,FALSE) -> The ILW EZ Phase 1 Excavation Project is a key enabler to allow the future major project Lightly Shielded Store 1 (LSS1) to commence construction and also de-risks LSS1 construction. The delays in issuing the Service Commencement Notification (SCN) and late Pre-Construction Information (PCI) caused a 4-month delay to the beginning of delivery, however the excavation work has now recovered. The first project benefit: This project delivers a number of benefits, both direct as a key enabler for LSS1, and indirect in adopting an Enterprise approach to zonal development. The Baseline remains green and phase 1A activities completed. Meeting held with Superintending Officer, post period end, and Custody Transfer Certificate signed off 07th January 2026. Lifecycle EAC and the forecast date for close out of Phase 1A remain stable. The project lifecycle EAC increase includes an initial assessment of the cost to deliver the 25/26 Phase 1B scope. The end date and the EAC for the remaining Phase 1B scope will be updated once the detailed delivery timeline has been agreed for Phase 1B scope. This is expected to be during Qtr 4. The Capability and Capacity RAG remains Green.
B41: 35/09203 | C41: Lightly Shielded Store (LSS) | D41: Sellafield | F41: =VLOOKUP($C41,'4b) SL EPO Extended Data Sheet'!$A$5:$AB$168,2,FALSE) -> N/A | G41: =VLOOKUP($C41,'4b) SL EPO Extended Data Sheet'!$A$5:$AB$168,3, FALSE) -> 0 | I41: =VLOOKUP($C41,'4b) SL EPO Extended Data Sheet'!$A$5:$AD$168,30, FALSE) -> N/A | J41: =VLOOKUP($C41,'4b) SL EPO Extended Data Sheet'!$A$5:$AC$168,6, FALSE)/1000000 -> 46.4 | K41: =VLOOKUP($C41,'4b) SL EPO Extended Data Sheet'!$A$5:$AC$168,7, FALSE)/1000000 -> 0 | L41: =VLOOKUP($C41,'4b) SL EPO Extended Data Sheet'!$A$5:$AB$168,8, FALSE) -> 46812 | M41: =VLOOKUP($C41,'4b) SL EPO Extended Data Sheet'!$A$5:$AC$168,9, FALSE) | N41: =VLOOKUP($C41,'4b) SL EPO Extended Data Sheet'!$A$5:$AB$168,5, FALSE) | O41: =VLOOKUP($C41,'4b) SL EPO Extended Data Sheet'!$A$5:$AC$168,10, FALSE)/1000000 -> 0 | P41: =VLOOKUP($C41,'4b) SL EPO Extended Data Sheet'!$A$5:$AC$168,11, FALSE)/1000000 -> 46.4 | R41: =VLOOKUP($C41,'4b) SL EPO Extended Data Sheet'!$A$5:$AC$168,12,FALSE) -> N/A | S41: =VLOOKUP($C41,'4b) SL EPO Extended Data Sheet'!$A$5:$AC$168,13,FALSE) -> 0 | U41: =VLOOKUP($C41,'4b) SL EPO Extended Data Sheet'!$A$5:$AE$168,31,FALSE) -> N/A (Aug-23) | W41: =VLOOKUP($C41,'4b) SL EPO Extended Data Sheet'!$A$5:$AC$168,16,FALSE)/1000000 -> 142.42994 | X41: =VLOOKUP($C41,'4b) SL EPO Extended Data Sheet'!$A$5:$AC$168,17,FALSE)/1000000 -> 158.107 | Y41: =VLOOKUP($C41,'4b) SL EPO Extended Data Sheet'!$A$5:$AC$168,18,FALSE)/1000000 -> -0.00032267 | Z41: =VLOOKUP($C41,'4b) SL EPO Extended Data Sheet'!$A$5:$AB$168,16,FALSE)/1000000 -> 142.42994 | AA41: =VLOOKUP($C41,'4b) SL EPO Extended Data Sheet'!$A$5:$AC$168,19,FALSE) -> 46951 | AB41: =VLOOKUP($C41,'4b) SL EPO Extended Data Sheet'!$A$5:$AC$168,20,FALSE) -> 46951 | AC41: =VLOOKUP($C41,'4b) SL EPO Extended Data Sheet'!$A$5:$AC$168,21,FALSE) -> 0 | AD41: =VLOOKUP($C41,'4b) SL EPO Extended Data Sheet'!$A$5:$AB$168,15,FALSE)/1000000 -> 0.045163 | AE41: =VLOOKUP($C41,'4b) SL EPO Extended Data Sheet'!$A$5:$AC$168,22,FALSE)/1000000 -> 30.885831 | AF41: =VLOOKUP($C41,'4b) SL EPO Extended Data Sheet'!$A$5:$AC$168,23,FALSE)/1000000 -> 18.532731 | AG41: =VLOOKUP($C41,'4b) SL EPO Extended Data Sheet'!$A$5:$AC$168,24,FALSE)/1000000 -> 27.223351 | AH41: =VLOOKUP($C41,'4b) SL EPO Extended Data Sheet'!$A$5:$AC$168,25,FALSE) -> 0.68076598 | AI41: =VLOOKUP($C41,'4b) SL EPO Extended Data Sheet'!$A$5:$AC$168,26,FALSE) -> 0.60003989 | AJ41: =VLOOKUP($C41,'4b) SL EPO Extended Data Sheet'!$A$5:$AC$168,27,FALSE) -> 0.21684929 | AK41: =VLOOKUP($C41,'4b) SL EPO Extended Data Sheet'!$A$5:$AC$168,28,FALSE) -> 0.13011822 | AL41: =VLOOKUP($C41,'4b) SL EPO Extended Data Sheet'!$A$6:$AB$168,15,FALSE) -> 45163 | AM41: =VLOOKUP($C41,'4b) SL EPO Extended Data Sheet'!$A$5:$AC$168,29,FALSE) -> G | AO41: =T39-G39 -> 0 | AP41: =T39-K39 -> 0 | AQ41: =X39-I39 -> 0 | AS41: =T39-S39 -> 0 | AT41: =X39-W39 -> 0 | AV41: 158.10732 | AW41: 46951 | AY41: 142.42994 | AZ41: =W41-AY41 -> 0 | BA41: 46951 | BB41: =AA41-BA41 -> 0
A42: =C41 -> Lightly Shielded Store (LSS) | B42: This project will provide safe and secure storage capacity for Contact Handleable Intermediate Level Waste (CHILW) packages until final treatment and disposal. The first project benefit will be receipt of the first package. The CHILW Programme Brief has been endorsed by the SL Enterprise Development Committee (EDC); this includes the LSS1 revised preferred option which incorporates identified optimisation opportunities. The Outline Business Case (OBC) Strategic and Economic Cases have been endorsed in principle by the EDC. The project have revised the OBC baseline to align to both the updated preferred option and affordability assumptions. Sellafield Project Execution Review (SPER) concluded this period with an amber rating, with findings on track for closure. SL Enhanced Commercial Assurance concluded an amber-green rating. Progress through NDA assurance is planned during January with OBC submission to SL Investment Review Panel (IRP) remaining on track for March 2026. Current sanction approval gives the project financial coverage until Q4 FY2026/2027. This sanction enables conclusion of the Appraise & Select phase whilst progressing the Define stage design in parallel, which will maintain momentum on the project critical path until the OBC is approved by HMT during FY2026/2027. Key interfaces will be funded by the Enterprise and provided prior to site establishment, including provision of services to the construction site (power is becoming critical due to lead times of equipment). The Lifecycle EAC will be updated once the OBC Change Control Record has been implemented. The Capability and Capacity RAG remains Green.
B44: Value Stream: Spent Fuel Management | AO44: =T42-G42 -> 0 | AP44: =T42-K42 -> 0 | AQ44: =X42-I42 -> 0 | AS44: =T42-S42 -> 0 | AT44: =X42-W42 -> 0
B45: Portfolio Summary | AV45: 70.5 | AW45: 46106 | AY45: 72.617237 | AZ45: -72.617237 | BA45: 46106 | BB45: -46106
B47: 35/10505 | C47: SIXEP Receipt Facility | D47: Sellafield | F47: =VLOOKUP($C47,'4b) SL EPO Extended Data Sheet'!$A$5:$AB$168,2,FALSE) -> N/A | G47: =VLOOKUP($C47,'4b) SL EPO Extended Data Sheet'!$A$5:$AB$168,3, FALSE) | I47: =VLOOKUP($C47,'4b) SL EPO Extended Data Sheet'!$A$5:$AD$168,30, FALSE) -> SOC (Mar-24) | J47: =VLOOKUP($C47,'4b) SL EPO Extended Data Sheet'!$A$5:$AB$168,6, FALSE)/1000000 -> 87 | K47: =VLOOKUP($C47,'4b) SL EPO Extended Data Sheet'!$A$5:$AB$168,7, FALSE)/1000000 -> 91 | L47: =VLOOKUP($C47,'4b) SL EPO Extended Data Sheet'!$A$5:$AB$168,8, FALSE) | M47: =VLOOKUP($C47,'4b) SL EPO Extended Data Sheet'!$A$5:$AB$168,9, FALSE) -> 47361 | N47: =VLOOKUP($C47,'4b) SL EPO Extended Data Sheet'!$A$5:$AB$168,5, FALSE) -> 45371 | O47: =VLOOKUP($C47,'4b) SL EPO Extended Data Sheet'!$A$5:$AB$168,10, FALSE)/1000000 -> 0 | P47: =VLOOKUP($C47,'4b) SL EPO Extended Data Sheet'!$A$5:$AB$168,11, FALSE)/1000000 -> 53 | R47: =VLOOKUP($C47,'4b) SL EPO Extended Data Sheet'!$A$5:$AB$168,12,FALSE) -> N/A | S47: 0 | U47: =VLOOKUP($C47,'4b) SL EPO Extended Data Sheet'!$A$5:$AE$168,31,FALSE) -> SOC (Mar-25) | W47: =VLOOKUP($C47,'4b) SL EPO Extended Data Sheet'!$A$5:$AC$168,16,FALSE)/1000000 -> 919.61826 | X47: =VLOOKUP($C47,'4b) SL EPO Extended Data Sheet'!$A$5:$AC$168,17,FALSE)/1000000 -> 20.678211 | Y47: =VLOOKUP($C47,'4b) SL EPO Extended Data Sheet'!$A$5:$AC$168,18,FALSE)/1000000 -> 0.0003084 | Z47: =VLOOKUP($C47,'4b) SL EPO Extended Data Sheet'!$A$5:$AB$168,16,FALSE)/1000000 -> 919.61826 | AA47: =VLOOKUP($C47,'4b) SL EPO Extended Data Sheet'!$A$5:$AC$168,19,FALSE) -> 50724 | AB47: =VLOOKUP($C47,'4b) SL EPO Extended Data Sheet'!$A$5:$AC$168,20,FALSE) -> 50724 | AC47: =VLOOKUP($C47,'4b) SL EPO Extended Data Sheet'!$A$5:$AC$168,21,FALSE) -> 0 | AD47: =VLOOKUP($C47,'4b) SL EPO Extended Data Sheet'!$A$5:$AB$168,15,FALSE)/1000000 -> 0.04573 | AE47: =VLOOKUP($C47,'4b) SL EPO Extended Data Sheet'!$A$5:$AC$168,22,FALSE)/1000000 -> 38.933642 | AF47: =VLOOKUP($C47,'4b) SL EPO Extended Data Sheet'!$A$5:$AC$168,23,FALSE)/1000000 -> 40.103855 | AG47: =VLOOKUP($C47,'4b) SL EPO Extended Data Sheet'!$A$5:$AC$168,24,FALSE)/1000000 -> 19.204409 | AH47: =VLOOKUP($C47,'4b) SL EPO Extended Data Sheet'!$A$5:$AC$168,25,FALSE) -> 2.0882629 | AI47: =VLOOKUP($C47,'4b) SL EPO Extended Data Sheet'!$A$5:$AC$168,26,FALSE) -> 1.0300566 | AJ47: =VLOOKUP($C47,'4b) SL EPO Extended Data Sheet'!$A$5:$AC$168,27,FALSE) -> 0.042336744 | AK47: =VLOOKUP($C47,'4b) SL EPO Extended Data Sheet'!$A$5:$AC$168,28,FALSE) -> 0.043609242 | AL47: =VLOOKUP($C47,'4b) SL EPO Extended Data Sheet'!$A$6:$AB$168,15,FALSE) -> 45730 | AM47: =VLOOKUP($C47,'4b) SL EPO Extended Data Sheet'!$A$5:$AC$168,29,FALSE) -> G | AO47: =#REF!-#REF! -> #REF! | AP47: =#REF!-#REF! -> #REF! | AQ47: =#REF!-#REF! -> #REF! | AS47: =#REF!-#REF! -> #REF! | AT47: =#REF!-#REF! -> #REF! | AV47: 20.677903 | AW47: 50724 | AY47: 919.61826 | AZ47: =W47-AY47 -> 0 | BA47: 50724 | BB47: =AA47-BA47 -> 0
A48: =C47 -> SIXEP Receipt Facility | B48: At the Enterprise Development Committee (EDC) on 14th October 2025, the decision to move to a straight to treatment project was approved. Consequently, the SWMRF (SIXEP Waste Management Receipt Facility) project is being strategically paused. The ramp down to a controlled close out has begun along with the commencement of the new SWMTF (SIXEP Waste Management Treatment Facility) project. A sanction re-use paper will be presented at the January 2026 IRP and GIC meetings. A peer assist event was undertaken involving key stakeholders to provide direction for implementing a streamlined straight to treatment strategy at pace. The full lifecycle EAC has dropped from £920.1m to £20.7m, as a consequence of pausing SWMRF and commencing SWMTF. The Lifecycle EAC now includes costs for both projects to end of FY 2025/26 only. Work continues to progress on the Enabling Works ground investigation (a separate project) along with other areas of the enabling works design packs. The Enabling Works have now transitioned to Programme and Project Partner (PPP). Capability and Capacity RAG remains Green. Baseline and DCA RAGs have moved to not applicable due to the strategic pause.
B50: Value Stream: Site Projects Office | AO50: =T48-G48 -> 0 | AP50: =T48-K48 -> 0 | AQ50: =X48-I48 -> 0 | AS50: =T48-S48 -> 0 | AT50: =X48-W48 -> 0
B52: Portfolio Summary | AV52: 70.5 | AW52: 46106 | AY52: 72.617237 | AZ52: -72.617237 | BA52: 46106 | BB52: -46106
AO53: =T51-G51 -> 0 | AP53: =T51-K51 -> 0 | AQ53: =X51-I51 -> 0 | AS53: =T51-S51 -> 0 | AT53: =X51-W51 -> 0
B54: 35/10188 | C54: THORP Receipt & Storage Control Systems Replacement | D54: Sellafield | F54: =VLOOKUP($C54,'4b) SL EPO Extended Data Sheet'!$A$5:$AB$168,2,FALSE) -> R | G54: =VLOOKUP($C54,'4b) SL EPO Extended Data Sheet'!$A$5:$AB$168,3, FALSE) -> 0 | I54: =VLOOKUP($C54,'4b) SL EPO Extended Data Sheet'!$A$5:$AD$168,30, FALSE) -> N/A (May-15) | J54: =VLOOKUP($C54,'4b) SL EPO Extended Data Sheet'!$A$5:$AB$168,6, FALSE)/1000000 -> 0 | K54: =VLOOKUP($C54,'4b) SL EPO Extended Data Sheet'!$A$5:$AB$168,7, FALSE)/1000000 -> 0 | L54: =VLOOKUP($C54,'4b) SL EPO Extended Data Sheet'!$A$5:$AB$168,8, FALSE) | M54: =VLOOKUP($C54,'4b) SL EPO Extended Data Sheet'!$A$5:$AB$168,9, FALSE) | N54: =VLOOKUP($C54,'4b) SL EPO Extended Data Sheet'!$A$5:$AB$168,5, FALSE) -> 42125 | O54: =VLOOKUP($C54,'4b) SL EPO Extended Data Sheet'!$A$5:$AB$168,10, FALSE)/1000000 -> 0 | P54: =VLOOKUP($C54,'4b) SL EPO Extended Data Sheet'!$A$5:$AB$168,11, FALSE)/1000000 -> 11.867767 | R54: =VLOOKUP($C54,'4b) SL EPO Extended Data Sheet'!$A$5:$AC$168,12,FALSE) -> A | S54: =VLOOKUP($C54,'4b) SL EPO Extended Data Sheet'!$A$5:$AB$168,13,FALSE) -> 0 | U54: =VLOOKUP($C54,'4b) SL EPO Extended Data Sheet'!$A$5:$AE$168,31,FALSE) -> N/A (Nov-25) | W54: =VLOOKUP($C54,'4b) SL EPO Extended Data Sheet'!$A$5:$AC$168,16,FALSE)/1000000 -> 20.914989 | X54: =VLOOKUP($C54,'4b) SL EPO Extended Data Sheet'!$A$5:$AC$168,17,FALSE)/1000000 -> 13.123352 | Y54: =VLOOKUP($C54,'4b) SL EPO Extended Data Sheet'!$A$5:$AC$168,18,FALSE)/1000000 -> -10.253977 | Z54: =VLOOKUP($C54,'4b) SL EPO Extended Data Sheet'!$A$5:$AB$168,16,FALSE)/1000000 -> 20.914989 | AA54: =VLOOKUP($C54,'4b) SL EPO Extended Data Sheet'!$A$5:$AC$168,19,FALSE) -> 48183 | AB54: =VLOOKUP($C54,'4b) SL EPO Extended Data Sheet'!$A$5:$AC$168,20,FALSE) -> 48934 | AC54: =VLOOKUP($C54,'4b) SL EPO Extended Data Sheet'!$A$5:$AC$168,21,FALSE) -> 751 | AD54: =VLOOKUP($C54,'4b) SL EPO Extended Data Sheet'!$A$5:$AB$168,15,FALSE)/1000000 -> 0.045968 | AE54: =VLOOKUP($C54,'4b) SL EPO Extended Data Sheet'!$A$5:$AC$168,22,FALSE)/1000000 -> 9.0356952 | AF54: =VLOOKUP($C54,'4b) SL EPO Extended Data Sheet'!$A$5:$AC$168,23,FALSE)/1000000 -> 7.7445885 | AG54: =VLOOKUP($C54,'4b) SL EPO Extended Data Sheet'!$A$5:$AC$168,24,FALSE)/1000000 -> 9.1474514 | AH54: =VLOOKUP($C54,'4b) SL EPO Extended Data Sheet'!$A$5:$AC$168,25,FALSE) -> 0.84663893 | AI54: =VLOOKUP($C54,'4b) SL EPO Extended Data Sheet'!$A$5:$AC$168,26,FALSE) -> 0.85711042 | AJ54: =VLOOKUP($C54,'4b) SL EPO Extended Data Sheet'!$A$5:$AC$168,27,FALSE) -> 0.43202008 | AK54: =VLOOKUP($C54,'4b) SL EPO Extended Data Sheet'!$A$5:$AC$168,28,FALSE) -> 0.37028891 | AL54: =VLOOKUP($C54,'4b) SL EPO Extended Data Sheet'!$A$6:$AB$168,15,FALSE) -> 45968 | AM54: =VLOOKUP($C54,'4b) SL EPO Extended Data Sheet'!$A$5:$AC$168,29,FALSE) -> G | AV54: 23.377329 | AW54: 48183 | AY54: 20.914989 | AZ54: =W54-AY54 -> 0 | BA54: 48183 | BB54: =AA54-BA54 -> 0
A55: =C54 -> THORP Receipt & Storage Control Systems Replacement | B55: Within the THORP Receipt and Store (R&S) and Feed pond areas, pond handler machines manoeuvre flasks or skips within the inlet, main and feed ponds, these are the Inlet Pond Handler (IPH); the Main Pond Handler (MPH); the Rack Transfer Machine (RTM). These machines provide the essential material move capability to support fuel reprocessing operations. Each of these pond handlers is controlled by programmable controller systems installed in the late 1980s, which are now obsolete, and spares are increasingly difficult to source. The Delivery Confidence Assessment remains Red, reflecting the history of the project which has suffered several scope and strategy challenges from programme, preventing progress and impacting the baseline. The project was split into six discrete Work Packages. Via a Change Control Request (CCR), three out of six work packages were closed earlier in financial year 2025/26. In period, a close out strategy has been agreed for the remaining scope, between the Head of Projects and Head of Operating Unit (OU). The project forecast cost has significantly reduced this period, reflecting the scope which has stopped with immediate effect, also impacting schedule. Capability and Capacity RAG remains Green, reflecting the remaining scope of 35/10188.
AO56: =T54-G54 -> 0 | AP56: =T54-K54 -> 0 | AQ56: =X54-I54 -> #VALUE! | AS56: =T54-S54 -> 0 | AT56: =X54-W54 -> -7.7916372
B57: 35/09140 | C57: Electrical Supply - New Construction | D57: Sellafield | F57: =VLOOKUP(C57,'5a)NDA MPPR'!$B$9:$AK$61,3,FALSE) -> A | G57: =VLOOKUP(C57,'5a)NDA MPPR'!$B$9:$AK$61,4,FALSE) -> 0 | I57: =VLOOKUP(C57,'5a)NDA MPPR'!$B$9:$AK$61,6,FALSE) -> FBC (May-23) | J57: =VLOOKUP(C57,'5a)NDA MPPR'!$B$9:$AK$61,7,FALSE) -> 403.5 | K57: =VLOOKUP(C57,'5a)NDA MPPR'!$B$9:$AK$61,8,FALSE) -> 430.4 | L57: =VLOOKUP(C57,'5a)NDA MPPR'!$B$9:$AK$61,9,FALSE) -> 47362 | M57: =VLOOKUP(C57,'5a)NDA MPPR'!$B$9:$AK$61,10,FALSE) -> 47665 | O57: =VLOOKUP(C57,'5a)NDA MPPR'!$B$9:$AK$61,12,FALSE) -> 430.4 | P57: =VLOOKUP(C57,'5a)NDA MPPR'!$B$9:$AK$61,13,FALSE) -> 403.5 | R57: =VLOOKUP(C57,'5a)NDA MPPR'!$B$9:$AK$61,15,FALSE) -> A | S57: =VLOOKUP(C57,'5a)NDA MPPR'!$B$9:$AK$61,16,FALSE) -> 0 | U57: =VLOOKUP(C57,'5a)NDA MPPR'!$B$9:$AK$61,18,FALSE) -> FBC (Jan-23) | W57: =VLOOKUP(C57,'5a)NDA MPPR'!$B$9:$AK$61,20,FALSE) -> 435.38198 | X57: =VLOOKUP(C57,'5a)NDA MPPR'!$B$9:$AK$61,21,FALSE) -> 427.83868 | Y57: =VLOOKUP(C57,'5a)NDA MPPR'!$B$9:$AK$61,22,FALSE) -> 0 | AA57: =VLOOKUP(C57,'5a)NDA MPPR'!$B$9:$AK$61,24,FALSE) -> 47364 | AB57: =VLOOKUP(C57,'5a)NDA MPPR'!$B$9:$AK$61,25,FALSE) -> 47826 | AC57: =VLOOKUP(C57,'5a)NDA MPPR'!$B$9:$AK$61,26,FALSE) -> 0 | AE57: =VLOOKUP(C57,'5a)NDA MPPR'!$B$9:$AK$61,28,FALSE) -> 343.16946 | AF57: =VLOOKUP(C57,'5a)NDA MPPR'!$B$9:$AK$61,29,FALSE) -> 309.56489 | AG57: =VLOOKUP(C57,'5a)NDA MPPR'!$B$9:$AK$61,30,FALSE) -> 306.47835 | AH57: =VLOOKUP(C57,'5a)NDA MPPR'!$B$9:$AK$61,31,FALSE) -> 1.010071 | AI57: =VLOOKUP(C57,'5a)NDA MPPR'!$B$9:$AK$61,32,FALSE) -> 0.90207585 | AJ57: =VLOOKUP(C57,'5a)NDA MPPR'!$B$9:$AK$61,33,FALSE) -> 0.78820319 | AK57: =VLOOKUP(C57,'5a)NDA MPPR'!$B$9:$AK$61,34,FALSE) -> 0.71101906 | AM57: =VLOOKUP(C57,'5a)NDA MPPR'!$B$9:$AK$61,36,FALSE) -> A | AV57: 427.82949 | AW57: 47826 | AY57: 435.38198 | AZ57: =W57-AY57 -> 0 | BA57: 47364 | BB57: =AA57-BA57 -> 0
A58: =C57 -> Electrical Supply - New Construction | B58: =VLOOKUP($C57,'5a)NDA MPPR'!$A$9:$AK$61,2,FALSE) -> The Electrical Distribution Network Upgrade Project (EDNUP) relates to the refurbishment of the Sellafield Site’s electricity network. The project will bolster the emergency power generation capability and improve site resilience which is important particularly in the event of a National Grid failure. The Delivery Confidence Assessment remains at Amber noting that the latest forecast for completion exceeds the current P80. An update paper was acknowledged at NDA GIC in June 2025, which noted that a P80 draw down will be necessary to enable continuity of project delivery (current forecast required in 2026/27 Qtr 1). The project continues to be impacted by industrial action in the supply chain resulting in productivity losses, key skills unavailable, and constraints on work scope delivery. Impact assessment will be finalised on conclusion of the action with the intent to seek appropriate sanction relief subject to further review. This is not a dispute directly with Sellafield Ltd; Sellafield is engaged with the Supply Chain and Stakeholders to ensure effective management of the impacts; correct mitigations are in place and to effectively mobilise resources upon return to work.The full lifecycle cost forecast is stable in period although under significant and increasing pressure from strike delay costs, further realised risks with in-ground conditions and increases in subcontract costs. The further review of the P50 to P80 delta and inflationary impact will be included in the next sanction request. The schedule is stable with no overall movement to the end date in period, although strike action and realised risk are continuing to reduce available schedule float. The baseline RAG remains Amber as the project completion date is beyond the P50 baseline. The current P50 baseline and approved NDA sanction differs as a result of indexation and historical positive cost variance on the project pre implementation of change control associated with the Full Business Case (FBC) resubmission. The project plan and progress to date indicates a steady recovery of the variance. Reoccurrences of radiological contamination are affecting interconnector critical path progress impacting construction duration. The first downstream connections from Substation 111 has finally been completed and energised after resolution of unexpected issues with existing cables. The next downstream connection has encountered different issues with existing cables which is being investigated before connections can be made. Continued strike impacts and existing asset risks have put the Key Target for downstream changeovers in jeopardy. Cable route construction is progressing on multiple fronts, including a ringfenced risk mitigation advanced dig team who are discovering a significant number of uncharted services and obstructions. Strike action continues to impact multiple workfaces including waste movements, scaffolding, electrical installations and daily productivity. The temporary cable installation which will mitigate delays to electrical isolations necessary for excavations near aged buried cables has also been impacted. Management and characterisation of waste from the site continues to be onerous. The Capability and Capacity RAG remains at Amber in period due to Construction and Protection Engineer resource issues, which are now critical and impacting site delivery, with timescales for backfill still to be determined.
AO59: =T57-G57 -> 0 | AP59: =T57-K57 -> -430.4 | AQ59: =X57-I57 -> #VALUE! | AS59: =T57-S57 -> 0 | AT59: =X57-W57 -> -7.5432941
B60: 35/10192 | C60: TR&S Replacement Cooling System | D60: Sellafield | F60: =VLOOKUP($C60,'4b) SL EPO Extended Data Sheet'!$A$5:$AB$168,2,FALSE) -> A | G60: =VLOOKUP($C60,'4b) SL EPO Extended Data Sheet'!$A$5:$AB$168,3, FALSE) -> 0 | I60: =VLOOKUP($C60,'4b) SL EPO Extended Data Sheet'!$A$5:$AD$168,30, FALSE) -> SOC (Apr-24) | J60: =VLOOKUP($C60,'4b) SL EPO Extended Data Sheet'!$A$5:$AB$168,6, FALSE)/1000000 -> 16 | K60: =VLOOKUP($C60,'4b) SL EPO Extended Data Sheet'!$A$5:$AB$168,7, FALSE)/1000000 -> 17 | L60: =VLOOKUP($C60,'4b) SL EPO Extended Data Sheet'!$A$5:$AB$168,8, FALSE) -> 48519 | M60: =VLOOKUP($C60,'4b) SL EPO Extended Data Sheet'!$A$5:$AB$168,9, FALSE) | N60: =VLOOKUP($C60,'4b) SL EPO Extended Data Sheet'!$A$5:$AB$168,5, FALSE) -> 45394 | O60: =VLOOKUP($C60,'4b) SL EPO Extended Data Sheet'!$A$5:$AB$168,10, FALSE)/1000000 -> 0 | P60: =VLOOKUP($C60,'4b) SL EPO Extended Data Sheet'!$A$5:$AB$168,11, FALSE)/1000000 -> 16 | R60: =VLOOKUP($C60,'4b) SL EPO Extended Data Sheet'!$A$5:$AB$168,12,FALSE) -> A | S60: =VLOOKUP($C60,'4b) SL EPO Extended Data Sheet'!$A$5:$AB$168,13,FALSE) -> 0 | U60: =VLOOKUP($C60,'4b) SL EPO Extended Data Sheet'!$A$5:$AE$168,31,FALSE) -> SOC (Feb-24) | W60: =VLOOKUP($C60,'4b) SL EPO Extended Data Sheet'!$A$5:$AC$168,16,FALSE)/1000000 -> 155.65567 | X60: =VLOOKUP($C60,'4b) SL EPO Extended Data Sheet'!$A$5:$AC$168,17,FALSE)/1000000 -> 159.01214 | Y60: =VLOOKUP($C60,'4b) SL EPO Extended Data Sheet'!$A$5:$AC$168,18,FALSE)/1000000 -> -2.3e-05 | Z60: =VLOOKUP($C60,'4b) SL EPO Extended Data Sheet'!$A$5:$AB$168,16,FALSE)/1000000 -> 155.65567 | AA60: =VLOOKUP($C60,'4b) SL EPO Extended Data Sheet'!$A$5:$AC$168,19,FALSE) -> 48530 | AB60: =VLOOKUP($C60,'4b) SL EPO Extended Data Sheet'!$A$5:$AC$168,20,FALSE) -> 48530 | AC60: =VLOOKUP($C60,'4b) SL EPO Extended Data Sheet'!$A$5:$AC$168,21,FALSE) -> 0 | AD60: =VLOOKUP($C60,'4b) SL EPO Extended Data Sheet'!$A$5:$AB$168,15,FALSE)/1000000 -> 0.04533 | AE60: =VLOOKUP($C60,'4b) SL EPO Extended Data Sheet'!$A$5:$AC$168,22,FALSE)/1000000 -> 10.733227 | AF60: =VLOOKUP($C60,'4b) SL EPO Extended Data Sheet'!$A$5:$AC$168,23,FALSE)/1000000 -> 7.0608812 | AG60: =VLOOKUP($C60,'4b) SL EPO Extended Data Sheet'!$A$5:$AC$168,24,FALSE)/1000000 -> 11.017341 | AH60: =VLOOKUP($C60,'4b) SL EPO Extended Data Sheet'!$A$5:$AC$168,25,FALSE) -> 0.64088796 | AI60: =VLOOKUP($C60,'4b) SL EPO Extended Data Sheet'!$A$5:$AC$168,26,FALSE) -> 0.65785259 | AJ60: =VLOOKUP($C60,'4b) SL EPO Extended Data Sheet'!$A$5:$AC$168,27,FALSE) -> 0.068954939 | AK60: =VLOOKUP($C60,'4b) SL EPO Extended Data Sheet'!$A$5:$AC$168,28,FALSE) -> 0.045362185 | AL60: =VLOOKUP($C60,'4b) SL EPO Extended Data Sheet'!$A$6:$AB$168,15,FALSE) -> 45330 | AM60: =VLOOKUP($C60,'4b) SL EPO Extended Data Sheet'!$A$5:$AC$168,29,FALSE) -> A | AV60: 159.01216 | AW60: 48530 | AY60: 155.65567 | AZ60: =W60-AY60 -> 0 | BA60: 48530 | BB60: =AA60-BA60 -> 0
A61: =C60 -> TR&S Replacement Cooling System | B61: This project is to provide the long-term cooling requirements for Thorp Receipt and Storage (TR&S) facility. The first project benefit is to provide a modern and efficient cooling system to support the unconstrained and timely import of the Advanced Gas Reactor (AGR) Fuel for Long Term Interim Safe Storage. The Delivery Confidence Assessment remains Amber, following evaluation of the decision to relocate the cooling system from the South to East side of the building. Baseline RAG remains Amber whilst the project team continue to review the impact of the strategic change on the get to gate plan (movement of Plant and Equipment Room from Product Zone). The Capability and Capacity RAG remains Amber due to the resource shortfalls now affecting delivery confidence. Senior Project Engineering Manager, Project Controls (P/T) and Commercial lead are required. Work continues on risk assessing the plant room move from south to East of the building which will underpin the delivery strategy option to support the OBC.
B63: 35/09244 | C63: FGFL Ventilation Extract System Upgrade | D63: Sellafield | F63: =VLOOKUP($C63,'4b) SL EPO Extended Data Sheet'!$A$5:$AB$168,2,FALSE) -> G | G63: =VLOOKUP($C63,'4b) SL EPO Extended Data Sheet'!$A$5:$AB$168,3, FALSE) -> 0 | I63: =VLOOKUP($C63,'4b) SL EPO Extended Data Sheet'!$A$5:$AD$168,30, FALSE) -> OBC (Nov-25) | J63: =VLOOKUP($C63,'4b) SL EPO Extended Data Sheet'!$A$5:$AB$168,6, FALSE)/1000000 -> 67.607 | K63: =VLOOKUP($C63,'4b) SL EPO Extended Data Sheet'!$A$5:$AB$168,7, FALSE)/1000000 -> 94.587 | L63: =VLOOKUP($C63,'4b) SL EPO Extended Data Sheet'!$A$5:$AB$168,8, FALSE) | M63: =VLOOKUP($C63,'4b) SL EPO Extended Data Sheet'!$A$5:$AB$168,9, FALSE) | O63: =VLOOKUP($C63,'4b) SL EPO Extended Data Sheet'!$A$5:$AB$168,10, FALSE)/1000000 -> 0 | P63: =VLOOKUP($C63,'4b) SL EPO Extended Data Sheet'!$A$5:$AB$168,11, FALSE)/1000000 -> 29.109 | R63: =VLOOKUP($C63,'4b) SL EPO Extended Data Sheet'!$A$5:$AB$168,12,FALSE) -> G | S63: =VLOOKUP($C63,'4b) SL EPO Extended Data Sheet'!$A$5:$AB$168,13,FALSE) -> 1 | U63: =VLOOKUP($C63,'4b) SL EPO Extended Data Sheet'!$A$5:$AE$168,31,FALSE) -> OBC (Apr-25) | W63: =VLOOKUP($C63,'4b) SL EPO Extended Data Sheet'!$A$5:$AC$168,16,FALSE)/1000000 -> 92.707032 | X63: =VLOOKUP($C63,'4b) SL EPO Extended Data Sheet'!$A$5:$AC$168,17,FALSE)/1000000 -> 91.739519 | Y63: =VLOOKUP($C63,'4b) SL EPO Extended Data Sheet'!$A$5:$AC$168,18,FALSE)/1000000 -> 7.5577788 | Z63: =VLOOKUP($C63,'4b) SL EPO Extended Data Sheet'!$A$5:$AB$168,16,FALSE)/1000000 -> 92.707032 | AA63: =VLOOKUP($C63,'4b) SL EPO Extended Data Sheet'!$A$5:$AC$168,19,FALSE) -> 48982 | AB63: =VLOOKUP($C63,'4b) SL EPO Extended Data Sheet'!$A$5:$AC$168,20,FALSE) -> 48982 | AC63: =VLOOKUP($C63,'4b) SL EPO Extended Data Sheet'!$A$5:$AC$168,21,FALSE) -> -79 | AD63: =VLOOKUP($C63,'4b) SL EPO Extended Data Sheet'!$A$5:$AB$168,15,FALSE)/1000000 -> 0.045748 | AE63: =VLOOKUP($C63,'4b) SL EPO Extended Data Sheet'!$A$5:$AC$168,22,FALSE)/1000000 -> 22.782394 | AF63: =VLOOKUP($C63,'4b) SL EPO Extended Data Sheet'!$A$5:$AC$168,23,FALSE)/1000000 -> 22.13546 | AG63: =VLOOKUP($C63,'4b) SL EPO Extended Data Sheet'!$A$5:$AC$168,24,FALSE)/1000000 -> 17.098059 | AH63: =VLOOKUP($C63,'4b) SL EPO Extended Data Sheet'!$A$5:$AC$168,25,FALSE) -> 1.2946184 | AI63: =VLOOKUP($C63,'4b) SL EPO Extended Data Sheet'!$A$5:$AC$168,26,FALSE) -> 0.97160382 | AJ63: =VLOOKUP($C63,'4b) SL EPO Extended Data Sheet'!$A$5:$AC$168,27,FALSE) -> 0.24574612 | AK63: =VLOOKUP($C63,'4b) SL EPO Extended Data Sheet'!$A$5:$AC$168,28,FALSE) -> 0.23876787 | AL63: =VLOOKUP($C63,'4b) SL EPO Extended Data Sheet'!$A$6:$AB$168,15,FALSE) -> 45748 | AM63: =VLOOKUP($C63,'4b) SL EPO Extended Data Sheet'!$A$5:$AC$168,29,FALSE) -> A | AV63: 84.181741 | AW63: 49061 | AY63: 66.045682 | AZ63: =W63-AY63 -> 26.66135 | BA63: 48760 | BB63: =AA63-BA63 -> 222
A64: =C63 -> FGFL Ventilation Extract System Upgrade | B64: The Ventilation Extract System Upgrade (VESU) project is required to replace the existing ventilation system in Special Nuclear Materials (SNM), the current system is in a degraded state and requires replacement. The first project benefit is the capability of a new ventilation system that meets all regulations and enables safe operations. Project Lifecycle: Stage 3 - Define stage via continuity funding whilst proceeding through sanction. The Delivery Confidence Assessment remains Green. An Infrastructure and Projects Authority (IPA) style review took place in May 2025 and achieved an Amber/Green. The Outline Business Case (OBC) predicted to be at Government Q4 2025/26. The baseline RAG has improved to Green due to implementation of Change Control request (CCR), the forecast end date has been updated to align with the CCR, resulting in a 79 day improvement and a movement in the Anticipated Final Cost (AFC) . There is a discrepancy of £950k for costs prior to Performance Plan 2014, this is under review by reporting team. Capability and Capacity is Amber due to not securing ring-fenced resources to support project delivery (Design/Project Controls/Construction and PMP Managers).
B66: 35/09357 | C66: PMF North Transfers Project | D66: Sellafield | F66: =VLOOKUP($C66,'4b) SL EPO Extended Data Sheet'!$A$5:$AB$168,2,FALSE) -> G | G66: =VLOOKUP($C66,'4b) SL EPO Extended Data Sheet'!$A$5:$AB$168,3, FALSE) -> 0 | I66: =VLOOKUP($C66,'4b) SL EPO Extended Data Sheet'!$A$5:$AD$168,30, FALSE) -> OBC (Feb-21) | J66: =VLOOKUP($C66,'4b) SL EPO Extended Data Sheet'!$A$5:$AB$168,6, FALSE)/1000000 -> 30.216 | K66: =VLOOKUP($C66,'4b) SL EPO Extended Data Sheet'!$A$5:$AB$168,7, FALSE)/1000000 -> 31.312 | L66: =VLOOKUP($C66,'4b) SL EPO Extended Data Sheet'!$A$5:$AB$168,8, FALSE) -> 46660 | M66: =VLOOKUP($C66,'4b) SL EPO Extended Data Sheet'!$A$5:$AB$168,9, FALSE) -> 46782 | O66: =VLOOKUP($C66,'4b) SL EPO Extended Data Sheet'!$A$5:$AB$168,10, FALSE)/1000000 -> 0 | P66: =VLOOKUP($C66,'4b) SL EPO Extended Data Sheet'!$A$5:$AB$168,11, FALSE)/1000000 -> 13.911625 | R66: =VLOOKUP($C66,'4b) SL EPO Extended Data Sheet'!$A$5:$AB$168,12,FALSE) -> G | S66: =VLOOKUP($C66,'4b) SL EPO Extended Data Sheet'!$A$5:$AB$168,13,FALSE) -> 0 | U66: =VLOOKUP($C66,'4b) SL EPO Extended Data Sheet'!$A$5:$AE$168,31,FALSE) -> OBC (Aug-21) | W66: =VLOOKUP($C66,'4b) SL EPO Extended Data Sheet'!$A$5:$AC$168,16,FALSE)/1000000 -> 36.101355 | X66: =VLOOKUP($C66,'4b) SL EPO Extended Data Sheet'!$A$5:$AC$168,17,FALSE)/1000000 -> 38.276981 | Y66: =VLOOKUP($C66,'4b) SL EPO Extended Data Sheet'!$A$5:$AC$168,18,FALSE)/1000000 -> 0 | Z66: =VLOOKUP($C66,'4b) SL EPO Extended Data Sheet'!$A$5:$AB$168,16,FALSE)/1000000 -> 36.101355 | AA66: =VLOOKUP($C66,'4b) SL EPO Extended Data Sheet'!$A$5:$AC$168,19,FALSE) -> 47367 | AB66: =VLOOKUP($C66,'4b) SL EPO Extended Data Sheet'!$A$5:$AC$168,20,FALSE) -> 47367 | AC66: =VLOOKUP($C66,'4b) SL EPO Extended Data Sheet'!$A$5:$AC$168,21,FALSE) -> 0 | AD66: =VLOOKUP($C66,'4b) SL EPO Extended Data Sheet'!$A$5:$AB$168,15,FALSE)/1000000 -> 0.044439 | AE66: =VLOOKUP($C66,'4b) SL EPO Extended Data Sheet'!$A$5:$AC$168,22,FALSE)/1000000 -> 15.557303 | AF66: =VLOOKUP($C66,'4b) SL EPO Extended Data Sheet'!$A$5:$AC$168,23,FALSE)/1000000 -> 15.531137 | AG66: =VLOOKUP($C66,'4b) SL EPO Extended Data Sheet'!$A$5:$AC$168,24,FALSE)/1000000 -> 10.956863 | AH66: =VLOOKUP($C66,'4b) SL EPO Extended Data Sheet'!$A$5:$AC$168,25,FALSE) -> 1.4174802 | AI66: =VLOOKUP($C66,'4b) SL EPO Extended Data Sheet'!$A$5:$AC$168,26,FALSE) -> 0.99831807 | AJ66: =VLOOKUP($C66,'4b) SL EPO Extended Data Sheet'!$A$5:$AC$168,27,FALSE) -> 0.43093406 | AK66: =VLOOKUP($C66,'4b) SL EPO Extended Data Sheet'!$A$5:$AC$168,28,FALSE) -> 0.43020926 | AL66: =VLOOKUP($C66,'4b) SL EPO Extended Data Sheet'!$A$6:$AB$168,15,FALSE) -> 44439 | AM66: =VLOOKUP($C66,'4b) SL EPO Extended Data Sheet'!$A$5:$AC$168,29,FALSE) -> G | AV66: 38.276981 | AW66: 47367 | AY66: 36.101355 | AZ66: =W66-AY66 -> 0 | BA66: 47367 | BB66: =AA66-BA66 -> 0
A67: =C66 -> PMF North Transfers Project | B67: The North Transfers Project will deliver the capability to retrieve and transport packages from Special Nuclear Materials (SNM) North Stores to the Sellafield Product and Residue Store Retreatment Plant (SRP), enabling the retreatment and repackaging of plutonium for long term, safe and secure storage. The Delivery Confidence Assessment and Baseline RAG remain Green. The project remains on track to realise project and NDA benefits. The capability and capacity RAG status is Green due to adequate resources being in place to deliver the scope. North Transfers Project has commenced get to gate activities.
AO68: =T66-G66 -> 0 | AP68: =T66-K66 -> -31.312 | AQ68: =X66-I66 -> #VALUE! | AS68: =T66-S66 -> 0 | AT68: =X66-W66 -> 2.1756265
B69: 35/10151 | C69: FHP & SIXEP Roof Replacement | D69: Sellafield | F69: =VLOOKUP($C69,'4b) SL EPO Extended Data Sheet'!$A$5:$AB$168,2,FALSE) -> G | G69: =VLOOKUP($C69,'4b) SL EPO Extended Data Sheet'!$A$5:$AB$168,3, FALSE) -> 0 | I69: =VLOOKUP($C69,'4b) SL EPO Extended Data Sheet'!$A$5:$AD$168,30, FALSE) -> OBC (Jan-25) | J69: =VLOOKUP($C69,'4b) SL EPO Extended Data Sheet'!$A$5:$AB$168,6, FALSE)/1000000 -> 28.586 | K69: =VLOOKUP($C69,'4b) SL EPO Extended Data Sheet'!$A$5:$AB$168,7, FALSE)/1000000 -> 29.889 | L69: =VLOOKUP($C69,'4b) SL EPO Extended Data Sheet'!$A$5:$AB$168,8, FALSE) -> 48373 | M69: =VLOOKUP($C69,'4b) SL EPO Extended Data Sheet'!$A$5:$AB$168,9, FALSE) -> 48373 | N69: =VLOOKUP($C69,'4b) SL EPO Extended Data Sheet'!$A$5:$AB$168,5, FALSE) -> 45681 | O69: =VLOOKUP($C69,'4b) SL EPO Extended Data Sheet'!$A$5:$AB$168,10, FALSE)/1000000 -> 0 | P69: =VLOOKUP($C69,'4b) SL EPO Extended Data Sheet'!$A$5:$AB$168,11, FALSE)/1000000 -> 3.30948 | R69: =VLOOKUP($C69,'4b) SL EPO Extended Data Sheet'!$A$5:$AB$168,12,FALSE) -> G | S69: =VLOOKUP($C69,'4b) SL EPO Extended Data Sheet'!$A$5:$AB$168,13,FALSE) -> 0 | U69: =VLOOKUP($C69,'4b) SL EPO Extended Data Sheet'!$A$5:$AE$168,31,FALSE) -> OBC (Mar-25) | W69: =VLOOKUP($C69,'4b) SL EPO Extended Data Sheet'!$A$5:$AC$168,16,FALSE)/1000000 -> 26.545167 | X69: =VLOOKUP($C69,'4b) SL EPO Extended Data Sheet'!$A$5:$AC$168,17,FALSE)/1000000 -> 39.733299 | Y69: =VLOOKUP($C69,'4b) SL EPO Extended Data Sheet'!$A$5:$AC$168,18,FALSE)/1000000 -> -0.00762439 | Z69: =VLOOKUP($C69,'4b) SL EPO Extended Data Sheet'!$A$5:$AB$168,16,FALSE)/1000000 -> 26.545167 | AA69: =VLOOKUP($C69,'4b) SL EPO Extended Data Sheet'!$A$5:$AC$168,19,FALSE) -> 48374 | AB69: =VLOOKUP($C69,'4b) SL EPO Extended Data Sheet'!$A$5:$AC$168,20,FALSE) -> 48410 | AC69: =VLOOKUP($C69,'4b) SL EPO Extended Data Sheet'!$A$5:$AC$168,21,FALSE) -> 0 | AD69: =VLOOKUP($C69,'4b) SL EPO Extended Data Sheet'!$A$5:$AB$168,15,FALSE)/1000000 -> 0.04572 | AE69: =VLOOKUP($C69,'4b) SL EPO Extended Data Sheet'!$A$5:$AC$168,22,FALSE)/1000000 -> 3.0711193 | AF69: =VLOOKUP($C69,'4b) SL EPO Extended Data Sheet'!$A$5:$AC$168,23,FALSE)/1000000 -> 3.0464359 | AG69: =VLOOKUP($C69,'4b) SL EPO Extended Data Sheet'!$A$5:$AC$168,24,FALSE)/1000000 -> 3.0384451 | AH69: =VLOOKUP($C69,'4b) SL EPO Extended Data Sheet'!$A$5:$AC$168,25,FALSE) -> 1.0026299 | AI69: =VLOOKUP($C69,'4b) SL EPO Extended Data Sheet'!$A$5:$AC$168,26,FALSE) -> 0.99196272 | AJ69: =VLOOKUP($C69,'4b) SL EPO Extended Data Sheet'!$A$5:$AC$168,27,FALSE) -> 0.1156941 | AK69: =VLOOKUP($C69,'4b) SL EPO Extended Data Sheet'!$A$5:$AC$168,28,FALSE) -> 0.11476424 | AL69: =VLOOKUP($C69,'4b) SL EPO Extended Data Sheet'!$A$6:$AB$168,15,FALSE) -> 45720 | AM69: =VLOOKUP($C69,'4b) SL EPO Extended Data Sheet'!$A$5:$AC$168,29,FALSE) -> A | AV69: 39.740923 | AW69: 48410 | AY69: 26.545167 | AZ69: =W69-AY69 -> 0 | BA69: 48374 | BB69: =AA69-BA69 -> 0
A70: =C69 -> FHP & SIXEP Roof Replacement | B70: The scope of this project is to remove and replace the existing Fuel Handling Plant (FHP) and Site Ion Exchange Effluent Plant (SIXEP) roofs with a new Kalzip Roof. The first project benefit to be realised will be the completion of the SIXEP Roof, enabling them to continue in delivery of their mission through to completion with the same benefit being realised for FHP some years later. The Delivery Confidence Assessment is Green following the approval of the revised OBC at OUSB. The Baseline is Green. The Capability & Capacity RAG has remained at Amber. This will move to green once approval is gained at IRP and the contracts are in place to progress this project through to completion, not expected until Q4 FY 2025/26. The FBC is now scheduled to go to the Investment Review Committee (IRP) in March 2026, as this was the next available slot following completion of the Enhanced Commercial Assurance (ECA). While pressurised, the CCR should still be implemented this FY year as DBD Admin checks etc. are already under way.
AO71: =T69-G69 -> 0 | AP71: =T69-K69 -> -29.889 | AQ71: =X69-I69 -> #VALUE! | AS71: =T69-S69 -> 0 | AT71: =X69-W69 -> 13.188132
B72: 35/10565 | C72: EMRMS (Emergency Management Radiological Monitoring System) | D72: Sellafield | F72: =VLOOKUP($C72,'4b) SL EPO Extended Data Sheet'!$A$5:$AB$168,2,FALSE) -> G | G72: =VLOOKUP($C72,'4b) SL EPO Extended Data Sheet'!$A$5:$AB$168,3, FALSE) -> 0 | I72: =VLOOKUP($C72,'4b) SL EPO Extended Data Sheet'!$A$5:$AD$168,30, FALSE) -> SOC (Sep-23) | J72: =VLOOKUP($C72,'4b) SL EPO Extended Data Sheet'!$A$5:$AB$168,6, FALSE)/1000000 -> 2.173096 | K72: =VLOOKUP($C72,'4b) SL EPO Extended Data Sheet'!$A$5:$AB$168,7, FALSE)/1000000 -> 0 | L72: =VLOOKUP($C72,'4b) SL EPO Extended Data Sheet'!$A$5:$AB$168,8, FALSE) -> 46722 | M72: =VLOOKUP($C72,'4b) SL EPO Extended Data Sheet'!$A$5:$AB$168,9, FALSE) | N72: =VLOOKUP($C72,'4b) SL EPO Extended Data Sheet'!$A$5:$AB$168,5, FALSE) -> 45170 | O72: =VLOOKUP($C72,'4b) SL EPO Extended Data Sheet'!$A$5:$AB$168,10, FALSE)/1000000 -> 0 | P72: =VLOOKUP($C72,'4b) SL EPO Extended Data Sheet'!$A$5:$AB$168,11, FALSE)/1000000 -> 2.173096 | R72: =VLOOKUP($C72,'4b) SL EPO Extended Data Sheet'!$A$5:$AB$168,12,FALSE) -> G | S72: =VLOOKUP($C72,'4b) SL EPO Extended Data Sheet'!$A$5:$AB$168,13,FALSE) -> 0 | U72: =VLOOKUP($C72,'4b) SL EPO Extended Data Sheet'!$A$5:$AE$168,31,FALSE) -> SOC (Sep-23) | W72: =VLOOKUP($C72,'4b) SL EPO Extended Data Sheet'!$A$5:$AC$168,16,FALSE)/1000000 -> 32.152519 | X72: =VLOOKUP($C72,'4b) SL EPO Extended Data Sheet'!$A$5:$AC$168,17,FALSE)/1000000 -> 32.00462 | Y72: =VLOOKUP($C72,'4b) SL EPO Extended Data Sheet'!$A$5:$AC$168,18,FALSE)/1000000 -> -0.19970976 | Z72: =VLOOKUP($C72,'4b) SL EPO Extended Data Sheet'!$A$5:$AB$168,16,FALSE)/1000000 -> 32.152519 | AA72: =VLOOKUP($C72,'4b) SL EPO Extended Data Sheet'!$A$5:$AC$168,19,FALSE) -> 46744 | AB72: =VLOOKUP($C72,'4b) SL EPO Extended Data Sheet'!$A$5:$AC$168,20,FALSE) -> 46744 | AC72: =VLOOKUP($C72,'4b) SL EPO Extended Data Sheet'!$A$5:$AC$168,21,FALSE) -> 0 | AD72: =VLOOKUP($C72,'4b) SL EPO Extended Data Sheet'!$A$5:$AB$168,15,FALSE)/1000000 -> 0.045188 | AE72: =VLOOKUP($C72,'4b) SL EPO Extended Data Sheet'!$A$5:$AC$168,22,FALSE)/1000000 -> 2.264228 | AF72: =VLOOKUP($C72,'4b) SL EPO Extended Data Sheet'!$A$5:$AC$168,23,FALSE)/1000000 -> 1.5739049 | AG72: =VLOOKUP($C72,'4b) SL EPO Extended Data Sheet'!$A$5:$AC$168,24,FALSE)/1000000 -> 1.4632752 | AH72: =VLOOKUP($C72,'4b) SL EPO Extended Data Sheet'!$A$5:$AC$168,25,FALSE) -> 1.0756042 | AI72: =VLOOKUP($C72,'4b) SL EPO Extended Data Sheet'!$A$5:$AC$168,26,FALSE) -> 0.69511768 | AJ72: =VLOOKUP($C72,'4b) SL EPO Extended Data Sheet'!$A$5:$AC$168,27,FALSE) -> 0.070421482 | AK72: =VLOOKUP($C72,'4b) SL EPO Extended Data Sheet'!$A$5:$AC$168,28,FALSE) -> 0.048951217 | AL72: =VLOOKUP($C72,'4b) SL EPO Extended Data Sheet'!$A$6:$AB$168,15,FALSE) -> 45188 | AM72: =VLOOKUP($C72,'4b) SL EPO Extended Data Sheet'!$A$5:$AC$168,29,FALSE) -> A | AV72: 32.204329 | AW72: 46744 | AY72: 32.152519 | AZ72: =W72-AY72 -> 0 | BA72: 46744 | BB72: =AA72-BA72 -> 0
A73: =C72 -> EMRMS (Emergency Management Radiological Monitoring System) | B73: The project has developed and assured a Single Preferred (engineering) Solution (SPS) which will be subjected to an Infrastructure Design Engineering assurance review in January 2026, this has been delayed due to electrical loading details being required and the revised Project Functional Spec not currently being approved by the client. The end of phase date is now deemed to be next financial year and has been affected by the lack of signed off PFS and availability of assurance resource from the Programme and Project Assurance team. The Delivery Confidence Assessment and Baseline RAG remain Green as a new estimate has been developed. Capability and Capacity RAG status has been moved to Amber due to Sellafield Project Execution Review (SPER) resource availability and the PFS maturity. The team are aligning the EAC forecast with the P50 estimate to enable stable forecasting up to the next maturity point.
B75: 35/10475 | C75: Product Zone Power Supply | D75: Sellafield | F75: =VLOOKUP($C75,'4b) SL EPO Extended Data Sheet'!$A$5:$AB$168,2,FALSE) -> G | G75: =VLOOKUP($C75,'4b) SL EPO Extended Data Sheet'!$A$5:$AB$168,3, FALSE) -> 0 | I75: =VLOOKUP($C75,'4b) SL EPO Extended Data Sheet'!$A$5:$AD$168,30, FALSE) -> SOC (Mar-24) | J75: =VLOOKUP($C75,'4b) SL EPO Extended Data Sheet'!$A$5:$AB$168,6, FALSE)/1000000 -> 81.71669 | K75: =VLOOKUP($C75,'4b) SL EPO Extended Data Sheet'!$A$5:$AB$168,7, FALSE)/1000000 -> 164.37964 | L75: =VLOOKUP($C75,'4b) SL EPO Extended Data Sheet'!$A$5:$AB$168,8, FALSE) -> 48549 | M75: =VLOOKUP($C75,'4b) SL EPO Extended Data Sheet'!$A$5:$AB$168,9, FALSE) -> 49310 | N75: =VLOOKUP($C75,'4b) SL EPO Extended Data Sheet'!$A$5:$AB$168,5, FALSE) -> 45352 | O75: =VLOOKUP($C75,'4b) SL EPO Extended Data Sheet'!$A$5:$AB$168,10, FALSE)/1000000 -> 0 | P75: =VLOOKUP($C75,'4b) SL EPO Extended Data Sheet'!$A$5:$AB$168,11, FALSE)/1000000 -> 11.961 | R75: =VLOOKUP($C75,'4b) SL EPO Extended Data Sheet'!$A$5:$AB$168,12,FALSE) -> G | S75: =VLOOKUP($C75,'4b) SL EPO Extended Data Sheet'!$A$5:$AB$168,13,FALSE) -> 0 | U75: =VLOOKUP($C75,'4b) SL EPO Extended Data Sheet'!$A$5:$AE$168,31,FALSE) -> SOC (Dec-25) | W75: =VLOOKUP($C75,'4b) SL EPO Extended Data Sheet'!$A$5:$AC$168,16,FALSE)/1000000 -> 69.236481 | X75: =VLOOKUP($C75,'4b) SL EPO Extended Data Sheet'!$A$5:$AC$168,17,FALSE)/1000000 -> 68.884649 | Y75: =VLOOKUP($C75,'4b) SL EPO Extended Data Sheet'!$A$5:$AC$168,18,FALSE)/1000000 -> -14.033692 | Z75: =VLOOKUP($C75,'4b) SL EPO Extended Data Sheet'!$A$5:$AB$168,16,FALSE)/1000000 -> 69.236481 | AA75: =VLOOKUP($C75,'4b) SL EPO Extended Data Sheet'!$A$5:$AC$168,19,FALSE) -> 48235 | AB75: =VLOOKUP($C75,'4b) SL EPO Extended Data Sheet'!$A$5:$AC$168,20,FALSE) -> 48235 | AC75: =VLOOKUP($C75,'4b) SL EPO Extended Data Sheet'!$A$5:$AC$168,21,FALSE) -> 125 | AD75: =VLOOKUP($C75,'4b) SL EPO Extended Data Sheet'!$A$5:$AB$168,15,FALSE)/1000000 -> 0.045999 | AE75: =VLOOKUP($C75,'4b) SL EPO Extended Data Sheet'!$A$5:$AC$168,22,FALSE)/1000000 -> 9.5649373 | AF75: =VLOOKUP($C75,'4b) SL EPO Extended Data Sheet'!$A$5:$AC$168,23,FALSE)/1000000 -> 8.0500086 | AG75: =VLOOKUP($C75,'4b) SL EPO Extended Data Sheet'!$A$5:$AC$168,24,FALSE)/1000000 -> 6.2159794 | AH75: =VLOOKUP($C75,'4b) SL EPO Extended Data Sheet'!$A$5:$AC$168,25,FALSE) -> 1.2950507 | AI75: =VLOOKUP($C75,'4b) SL EPO Extended Data Sheet'!$A$5:$AC$168,26,FALSE) -> 0.84161645 | AJ75: =VLOOKUP($C75,'4b) SL EPO Extended Data Sheet'!$A$5:$AC$168,27,FALSE) -> 0.13814881 | AK75: =VLOOKUP($C75,'4b) SL EPO Extended Data Sheet'!$A$5:$AC$168,28,FALSE) -> 0.11626831 | AL75: =VLOOKUP($C75,'4b) SL EPO Extended Data Sheet'!$A$6:$AB$168,15,FALSE) -> 45999 | AM75: =VLOOKUP($C75,'4b) SL EPO Extended Data Sheet'!$A$5:$AC$168,29,FALSE) -> G | AV75: 82.918341 | AW75: 48110 | AY75: 84.328299 | AZ75: =W75-AY75 -> -15.091818 | BA75: 48234 | BB75: =AA75-BA75 -> 1
A76: =C75 -> Product Zone Power Supply | B76: The existing site electrical distribution network is expected to be overloaded in c2030. The Product Zone Power Supply Project (PZPSP) exists to improve electrical distribution system reliability through installation of new modular substations and interconnectors that will complete the site end state network upgrades (Substation 78) and provide capacity to feed the new Product Zone areas of site (Substation 48). The first project benefit is enabling the completion of the end state network. Project Lifecycle: Stage 2 'Appraise & Select'. The SRO Delivery Confidence Assessment (DCA) remains Green, representing delivery against the Strategic Outline Case (SOC) approved by the Nuclear Decommissioning Authority (NDA). The P50 completion cost and schedule has been aligned to the revised baseline values / dates in period following the implementation of the CCR that has transferred the Substation 48 scope from this project to 35/10653 Product Zone Power Supply (Note the name change of the existing project also from PZPSP to Sub 78 will be in effect from p10). The Baseline RAG status remains Green. An updated Project Functional Specification has been issued to the project to progress the site end state network upgrades scope (Substation 78) and can continue to progress to the Outline Business Case (OBC) preparation, Appraise & Select stage, with a change control to align to the OBC expected to follow in 2026/27. Capability & Capacity are Green as there are no current resource issues on the Project.
B78: 35/10563 | C78: Substation 10 Replacement | D78: Sellafield | F78: =VLOOKUP($C78,'4b) SL EPO Extended Data Sheet'!$A$5:$AB$168,2,FALSE) -> G | G78: =VLOOKUP($C78,'4b) SL EPO Extended Data Sheet'!$A$5:$AB$168,3, FALSE) -> 0 | I78: =VLOOKUP($C78,'4b) SL EPO Extended Data Sheet'!$A$5:$AD$168,30, FALSE) -> SOC (Nov-23) | J78: =VLOOKUP($C78,'4b) SL EPO Extended Data Sheet'!$A$5:$AB$168,6, FALSE)/1000000 -> 44.848309 | K78: =VLOOKUP($C78,'4b) SL EPO Extended Data Sheet'!$A$5:$AB$168,7, FALSE)/1000000 -> 45.887309 | L78: =VLOOKUP($C78,'4b) SL EPO Extended Data Sheet'!$A$5:$AB$168,8, FALSE) -> 47543 | M78: =VLOOKUP($C78,'4b) SL EPO Extended Data Sheet'!$A$5:$AB$168,9, FALSE) | N78: =VLOOKUP($C78,'4b) SL EPO Extended Data Sheet'!$A$5:$AB$168,5, FALSE) -> 45239 | O78: =VLOOKUP($C78,'4b) SL EPO Extended Data Sheet'!$A$5:$AB$168,10, FALSE)/1000000 -> 0 | P78: =VLOOKUP($C78,'4b) SL EPO Extended Data Sheet'!$A$5:$AB$168,11, FALSE)/1000000 -> 3.087102 | R78: =VLOOKUP($C78,'4b) SL EPO Extended Data Sheet'!$A$5:$AB$168,12,FALSE) -> G | S78: =VLOOKUP($C78,'4b) SL EPO Extended Data Sheet'!$A$5:$AB$168,13,FALSE) -> 0 | U78: =VLOOKUP($C78,'4b) SL EPO Extended Data Sheet'!$A$5:$AE$168,31,FALSE) -> SOC (Jan-24) | W78: =VLOOKUP($C78,'4b) SL EPO Extended Data Sheet'!$A$5:$AC$168,16,FALSE)/1000000 -> 42.841254 | X78: =VLOOKUP($C78,'4b) SL EPO Extended Data Sheet'!$A$5:$AC$168,17,FALSE)/1000000 -> 42.426554 | Y78: =VLOOKUP($C78,'4b) SL EPO Extended Data Sheet'!$A$5:$AC$168,18,FALSE)/1000000 -> 0.00125057 | Z78: =VLOOKUP($C78,'4b) SL EPO Extended Data Sheet'!$A$5:$AB$168,16,FALSE)/1000000 -> 42.841254 | AA78: =VLOOKUP($C78,'4b) SL EPO Extended Data Sheet'!$A$5:$AC$168,19,FALSE) -> 47416 | AB78: =VLOOKUP($C78,'4b) SL EPO Extended Data Sheet'!$A$5:$AC$168,20,FALSE) -> 47416 | AC78: =VLOOKUP($C78,'4b) SL EPO Extended Data Sheet'!$A$5:$AC$168,21,FALSE) -> 0 | AD78: =VLOOKUP($C78,'4b) SL EPO Extended Data Sheet'!$A$5:$AB$168,15,FALSE)/1000000 -> 0.045306 | AE78: =VLOOKUP($C78,'4b) SL EPO Extended Data Sheet'!$A$5:$AC$168,22,FALSE)/1000000 -> 3.6318902 | AF78: =VLOOKUP($C78,'4b) SL EPO Extended Data Sheet'!$A$5:$AC$168,23,FALSE)/1000000 -> 2.8911061 | AG78: =VLOOKUP($C78,'4b) SL EPO Extended Data Sheet'!$A$5:$AC$168,24,FALSE)/1000000 -> 2.3575828 | AH78: =VLOOKUP($C78,'4b) SL EPO Extended Data Sheet'!$A$5:$AC$168,25,FALSE) -> 1.226301 | AI78: =VLOOKUP($C78,'4b) SL EPO Extended Data Sheet'!$A$5:$AC$168,26,FALSE) -> 0.79603346 | AJ78: =VLOOKUP($C78,'4b) SL EPO Extended Data Sheet'!$A$5:$AC$168,27,FALSE) -> 0.084775535 | AK78: =VLOOKUP($C78,'4b) SL EPO Extended Data Sheet'!$A$5:$AC$168,28,FALSE) -> 0.067484162 | AL78: =VLOOKUP($C78,'4b) SL EPO Extended Data Sheet'!$A$6:$AB$168,15,FALSE) -> 45306 | AM78: =VLOOKUP($C78,'4b) SL EPO Extended Data Sheet'!$A$5:$AC$168,29,FALSE) -> G | AV78: 42.425303 | AW78: 47416 | AY78: 42.841254 | AZ78: =W78-AY78 -> 0 | BA78: 47416 | BB78: =AA78-BA78 -> 0
A79: =C78 -> Substation 10 Replacement | B79: Project Lifecycle: Stage 1 'Feasibility'. The project benefit is the provision of a stable supply. The SRO Delivery Confidence Assessment (DCA) remains Green, representing progress against shortlisting activities. The P50 completion cost has been maintained. The P50 schedule position has been maintained in period as we are preparing for the Strategic Outline Case. The Strategic Outline Case Single Phase SPER was completed early in the period, a Green rating and 0 critical findings have been confirmed. Investment Review Panel is planned for January 2026, and an expected Change Control this financial year following approval of the business case in February 2026 at NDA Group Investment Committee. The Baseline RAG status remains Green. Capability & Capacity RAG status remains Green.
B81: 35/10564 | C81: Substation 15 Replacement | D81: Sellafield | F81: =VLOOKUP($C81,'4b) SL EPO Extended Data Sheet'!$A$5:$AB$168,2,FALSE) -> G | G81: =VLOOKUP($C81,'4b) SL EPO Extended Data Sheet'!$A$5:$AB$168,3, FALSE) -> 0 | I81: =VLOOKUP($C81,'4b) SL EPO Extended Data Sheet'!$A$5:$AD$168,30, FALSE) -> SOC (Sep-23) | J81: =VLOOKUP($C81,'4b) SL EPO Extended Data Sheet'!$A$5:$AB$168,6, FALSE)/1000000 -> 44 | K81: =VLOOKUP($C81,'4b) SL EPO Extended Data Sheet'!$A$5:$AB$168,7, FALSE)/1000000 -> 45.039 | L81: =VLOOKUP($C81,'4b) SL EPO Extended Data Sheet'!$A$5:$AB$168,8, FALSE) -> 47119 | M81: =VLOOKUP($C81,'4b) SL EPO Extended Data Sheet'!$A$5:$AB$168,9, FALSE) | N81: =VLOOKUP($C81,'4b) SL EPO Extended Data Sheet'!$A$5:$AB$168,5, FALSE) -> 45170 | O81: =VLOOKUP($C81,'4b) SL EPO Extended Data Sheet'!$A$5:$AB$168,10, FALSE)/1000000 -> 0 | P81: =VLOOKUP($C81,'4b) SL EPO Extended Data Sheet'!$A$5:$AB$168,11, FALSE)/1000000 -> 2.601 | R81: =VLOOKUP($C81,'4b) SL EPO Extended Data Sheet'!$A$5:$AB$168,12,FALSE) -> G | S81: =VLOOKUP($C81,'4b) SL EPO Extended Data Sheet'!$A$5:$AB$168,13,FALSE) -> 0 | U81: =VLOOKUP($C81,'4b) SL EPO Extended Data Sheet'!$A$5:$AE$168,31,FALSE) -> SOC (Jan-24) | W81: =VLOOKUP($C81,'4b) SL EPO Extended Data Sheet'!$A$5:$AC$168,16,FALSE)/1000000 -> 42.754873 | X81: =VLOOKUP($C81,'4b) SL EPO Extended Data Sheet'!$A$5:$AC$168,17,FALSE)/1000000 -> 42.266115 | Y81: =VLOOKUP($C81,'4b) SL EPO Extended Data Sheet'!$A$5:$AC$168,18,FALSE)/1000000 -> 0.00246268 | Z81: =VLOOKUP($C81,'4b) SL EPO Extended Data Sheet'!$A$5:$AB$168,16,FALSE)/1000000 -> 42.754873 | AA81: =VLOOKUP($C81,'4b) SL EPO Extended Data Sheet'!$A$5:$AC$168,19,FALSE) -> 47129 | AB81: =VLOOKUP($C81,'4b) SL EPO Extended Data Sheet'!$A$5:$AC$168,20,FALSE) -> 47129 | AC81: =VLOOKUP($C81,'4b) SL EPO Extended Data Sheet'!$A$5:$AC$168,21,FALSE) -> 0 | AD81: =VLOOKUP($C81,'4b) SL EPO Extended Data Sheet'!$A$5:$AB$168,15,FALSE)/1000000 -> 0.045306 | AE81: =VLOOKUP($C81,'4b) SL EPO Extended Data Sheet'!$A$5:$AC$168,22,FALSE)/1000000 -> 4.254163 | AF81: =VLOOKUP($C81,'4b) SL EPO Extended Data Sheet'!$A$5:$AC$168,23,FALSE)/1000000 -> 2.4950075 | AG81: =VLOOKUP($C81,'4b) SL EPO Extended Data Sheet'!$A$5:$AC$168,24,FALSE)/1000000 -> 2.467552 | AH81: =VLOOKUP($C81,'4b) SL EPO Extended Data Sheet'!$A$5:$AC$168,25,FALSE) -> 1.0111266 | AI81: =VLOOKUP($C81,'4b) SL EPO Extended Data Sheet'!$A$5:$AC$168,26,FALSE) -> 0.5864861 | AJ81: =VLOOKUP($C81,'4b) SL EPO Extended Data Sheet'!$A$5:$AC$168,27,FALSE) -> 0.099501244 | AK81: =VLOOKUP($C81,'4b) SL EPO Extended Data Sheet'!$A$5:$AC$168,28,FALSE) -> 0.058356096 | AL81: =VLOOKUP($C81,'4b) SL EPO Extended Data Sheet'!$A$6:$AB$168,15,FALSE) -> 45306 | AM81: =VLOOKUP($C81,'4b) SL EPO Extended Data Sheet'!$A$5:$AC$168,29,FALSE) -> G | AV81: 42.263652 | AW81: 47129 | AY81: 42.754873 | AZ81: =W81-AY81 -> 0 | BA81: 47129 | BB81: =AA81-BA81 -> 0
A82: =C81 -> Substation 15 Replacement | B82: Project Lifecycle: Stage 1 'Feasibility'. The project benefit is the provision of a stable supply. The SRO Delivery Confidence Assessment (DCA) remains Green, representing progress against shortlisting activities. The Strategic Outline Case SPER in August 25, resulted in a red rating, all actions have been Closed Out and the learning transferred to Substation 10. Investment Review Panel is planned for January 2026, with an expected change control this financial year following approval of the business case in February 2026 at NDA Group Investment Committee. The P50 completion has been maintained. The P50 schedule position has been maintained. The Baseline RAG status remains Green. Capability & Capacity RAG status remains Green.
B84: 35/09579 | C84: FGOFSP Effluent Route Project | D84: Sellafield | F84: =VLOOKUP($C84,'4b) SL EPO Extended Data Sheet'!$A$5:$AB$168,2,FALSE) -> G | G84: =VLOOKUP($C84,'4b) SL EPO Extended Data Sheet'!$A$5:$AB$168,3, FALSE) -> 0 | I84: =VLOOKUP($C84,'4b) SL EPO Extended Data Sheet'!$A$5:$AD$168,30, FALSE) -> SOC (Aug-25) | J84: =VLOOKUP($C84,'4b) SL EPO Extended Data Sheet'!$A$5:$AB$168,6, FALSE)/1000000 -> 28.293193 | K84: =VLOOKUP($C84,'4b) SL EPO Extended Data Sheet'!$A$5:$AB$168,7, FALSE)/1000000 -> 0 | L84: =VLOOKUP($C84,'4b) SL EPO Extended Data Sheet'!$A$5:$AB$168,8, FALSE) -> 47756 | M84: =VLOOKUP($C84,'4b) SL EPO Extended Data Sheet'!$A$5:$AB$168,9, FALSE) | N84: =VLOOKUP($C84,'4b) SL EPO Extended Data Sheet'!$A$5:$AB$168,5, FALSE) -> 45874 | O84: =VLOOKUP($C84,'4b) SL EPO Extended Data Sheet'!$A$5:$AB$168,10, FALSE)/1000000 -> 0 | P84: =VLOOKUP($C84,'4b) SL EPO Extended Data Sheet'!$A$5:$AB$168,11, FALSE)/1000000 -> 2.704643 | R84: =VLOOKUP($C84,'4b) SL EPO Extended Data Sheet'!$A$5:$AB$168,12,FALSE) -> G | S84: =VLOOKUP($C84,'4b) SL EPO Extended Data Sheet'!$A$5:$AB$168,13,FALSE) -> 0 | U84: =VLOOKUP($C84,'4b) SL EPO Extended Data Sheet'!$A$5:$AE$168,31,FALSE) -> SOC (Apr-25) | W84: =VLOOKUP($C84,'4b) SL EPO Extended Data Sheet'!$A$5:$AC$168,16,FALSE)/1000000 -> 28.293193 | X84: =VLOOKUP($C84,'4b) SL EPO Extended Data Sheet'!$A$5:$AC$168,17,FALSE)/1000000 -> 19.217519 | Y84: =VLOOKUP($C84,'4b) SL EPO Extended Data Sheet'!$A$5:$AC$168,18,FALSE)/1000000 -> 0.05331346 | Z84: =VLOOKUP($C84,'4b) SL EPO Extended Data Sheet'!$A$5:$AB$168,16,FALSE)/1000000 -> 28.293193 | AA84: =VLOOKUP($C84,'4b) SL EPO Extended Data Sheet'!$A$5:$AC$168,19,FALSE) -> 48474 | AB84: =VLOOKUP($C84,'4b) SL EPO Extended Data Sheet'!$A$5:$AC$168,20,FALSE) -> 48474 | AC84: =VLOOKUP($C84,'4b) SL EPO Extended Data Sheet'!$A$5:$AC$168,21,FALSE) -> 0 | AD84: =VLOOKUP($C84,'4b) SL EPO Extended Data Sheet'!$A$5:$AB$168,15,FALSE)/1000000 -> 0.045748 | AE84: =VLOOKUP($C84,'4b) SL EPO Extended Data Sheet'!$A$5:$AC$168,22,FALSE)/1000000 -> 0.54741154 | AF84: =VLOOKUP($C84,'4b) SL EPO Extended Data Sheet'!$A$5:$AC$168,23,FALSE)/1000000 -> 0.39104901 | AG84: =VLOOKUP($C84,'4b) SL EPO Extended Data Sheet'!$A$5:$AC$168,24,FALSE)/1000000 -> 0.73372417 | AH84: =VLOOKUP($C84,'4b) SL EPO Extended Data Sheet'!$A$5:$AC$168,25,FALSE) -> 0.5329646 | AI84: =VLOOKUP($C84,'4b) SL EPO Extended Data Sheet'!$A$5:$AC$168,26,FALSE) -> 0.71436018 | AJ84: =VLOOKUP($C84,'4b) SL EPO Extended Data Sheet'!$A$5:$AC$168,27,FALSE) -> 0.019347818 | AK84: =VLOOKUP($C84,'4b) SL EPO Extended Data Sheet'!$A$5:$AC$168,28,FALSE) -> 0.013821311 | AL84: =VLOOKUP($C84,'4b) SL EPO Extended Data Sheet'!$A$6:$AB$168,15,FALSE) -> 45748 | AM84: =VLOOKUP($C84,'4b) SL EPO Extended Data Sheet'!$A$5:$AC$168,29,FALSE) -> G | AV84: 19.164206 | AW84: 48474 | AY84: 28.293193 | AZ84: =W84-AY84 -> 0 | BA84: 48474 | BB84: =AA84-BA84 -> 0
A85: =C84 -> FGOFSP Effluent Route Project | B85: The FGOFSP Effluent Route Project (FERP) project is to provide an effluent route between the First-Generation Oxide Storage Pond and the Break Pressure Tank in response to the Segregated Effluent Treatment Plant (SETP) - Enhanced Actinide Removal Plant (EARP) switch. The project is currently in Appraise and Select following sanction at SOC in August 2025 and as such is maturing tactical options to develop a single preferred solution. The Delivery Confidence Assessment in getting to Gate 2 is Green with OBC currently planned for November 2027 (P50) in line with baseline dates and cost remains unchanged. The Baseline RAG status against SL P50 Project Baseline is Green. The project continues to work through the options, from £2.4m - £34.0m, whilst the SL Baseline is based on the most likely value of £31.8m. There has been a minor increase in the EAC this period of £53k due to the correction of a misalignment against the released sanction. Capability & Capacity RAG status is Green.
B87: 35/10545 | C87: Degradation of Pipebridge 57 (PB57) L14, L15, L16 Refurbishment | D87: Sellafield | F87: =VLOOKUP($C87,'4b) SL EPO Extended Data Sheet'!$A$5:$AB$168,2,FALSE) -> N/A | G87: =VLOOKUP($C87,'4b) SL EPO Extended Data Sheet'!$A$5:$AB$168,3, FALSE) -> 0 | I87: =VLOOKUP($C87,'4b) SL EPO Extended Data Sheet'!$A$5:$AD$168,30, FALSE) -> OBC (Jul-23) | J87: =VLOOKUP($C87,'4b) SL EPO Extended Data Sheet'!$A$5:$AB$168,6, FALSE)/1000000 -> 30 | K87: =VLOOKUP($C87,'4b) SL EPO Extended Data Sheet'!$A$5:$AB$168,7, FALSE)/1000000 -> 31.039 | L87: =VLOOKUP($C87,'4b) SL EPO Extended Data Sheet'!$A$5:$AB$168,8, FALSE) | M87: =VLOOKUP($C87,'4b) SL EPO Extended Data Sheet'!$A$5:$AB$168,9, FALSE) | N87: =VLOOKUP($C87,'4b) SL EPO Extended Data Sheet'!$A$5:$AB$168,5, FALSE) -> 45108 | O87: =VLOOKUP($C87,'4b) SL EPO Extended Data Sheet'!$A$5:$AB$168,10, FALSE)/1000000 -> 0 | P87: =VLOOKUP($C87,'4b) SL EPO Extended Data Sheet'!$A$5:$AB$168,11, FALSE)/1000000 -> 3.393 | R87: =VLOOKUP($C87,'4b) SL EPO Extended Data Sheet'!$A$5:$AB$168,12,FALSE) -> G | S87: =VLOOKUP($C87,'4b) SL EPO Extended Data Sheet'!$A$5:$AB$168,13,FALSE) -> 0 | U87: =VLOOKUP($C87,'4b) SL EPO Extended Data Sheet'!$A$5:$AE$168,31,FALSE) -> OBC (Dec-23) | W87: =VLOOKUP($C87,'4b) SL EPO Extended Data Sheet'!$A$5:$AC$168,16,FALSE)/1000000 -> 30.826939 | X87: =VLOOKUP($C87,'4b) SL EPO Extended Data Sheet'!$A$5:$AC$168,17,FALSE)/1000000 -> 31.20241 | Y87: =VLOOKUP($C87,'4b) SL EPO Extended Data Sheet'!$A$5:$AC$168,18,FALSE)/1000000 -> 0.00031763 | Z87: =VLOOKUP($C87,'4b) SL EPO Extended Data Sheet'!$A$5:$AB$168,16,FALSE)/1000000 -> 30.826939 | AA87: =VLOOKUP($C87,'4b) SL EPO Extended Data Sheet'!$A$5:$AC$168,19,FALSE) -> 47204 | AB87: =VLOOKUP($C87,'4b) SL EPO Extended Data Sheet'!$A$5:$AC$168,20,FALSE) -> 47529 | AC87: =VLOOKUP($C87,'4b) SL EPO Extended Data Sheet'!$A$5:$AC$168,21,FALSE) -> 0 | AD87: =VLOOKUP($C87,'4b) SL EPO Extended Data Sheet'!$A$5:$AB$168,15,FALSE)/1000000 -> 0.045271 | AE87: =VLOOKUP($C87,'4b) SL EPO Extended Data Sheet'!$A$5:$AC$168,22,FALSE)/1000000 -> 5.4891845 | AF87: =VLOOKUP($C87,'4b) SL EPO Extended Data Sheet'!$A$5:$AC$168,23,FALSE)/1000000 -> 1.8341167 | AG87: =VLOOKUP($C87,'4b) SL EPO Extended Data Sheet'!$A$5:$AC$168,24,FALSE)/1000000 -> 2.5145478 | AH87: =VLOOKUP($C87,'4b) SL EPO Extended Data Sheet'!$A$5:$AC$168,25,FALSE) -> 0.72940223 | AI87: =VLOOKUP($C87,'4b) SL EPO Extended Data Sheet'!$A$5:$AC$168,26,FALSE) -> 0.33413283 | AJ87: =VLOOKUP($C87,'4b) SL EPO Extended Data Sheet'!$A$5:$AC$168,27,FALSE) -> 0.17806453 | AK87: =VLOOKUP($C87,'4b) SL EPO Extended Data Sheet'!$A$5:$AC$168,28,FALSE) -> 0.059497206 | AL87: =VLOOKUP($C87,'4b) SL EPO Extended Data Sheet'!$A$6:$AB$168,15,FALSE) -> 45271 | AM87: =VLOOKUP($C87,'4b) SL EPO Extended Data Sheet'!$A$5:$AC$168,29,FALSE) -> G | AV87: 31.202093 | AW87: 47529 | AY87: 30.826939 | AZ87: =W87-AY87 -> 0 | BA87: 47204 | BB87: =AA87-BA87 -> 0
A88: =C87 -> Degradation of Pipebridge 57 (PB57) L14, L15, L16 Refurbishment | B88: Project Lifecycle: Stage 2 'Appraise & Select'. Pipebridge 57 spans the river Calder from East to West of site. The civil structure and services carried across it have been exposed to coastal conditions and are in an advanced state of degradation. The PB57 project exists to provide continuity of Mechanical & Control, Electrical & Instrumentation (CE&I) services currently supplied by PB57 to end users across the site network and to remove risk to the SL & external environment resulting from bridge and support collapse as it reaches end of life. The first project benefit focusses on achievement of the successful diversion of key services from PB57 whilst maintaining continuity of services to end users. The Delivery Confidence Assessment (DCA) remains stable (N/A due to no requirement for Strategic Outline Case (SOC)). The Baseline RAG remains Green due to the review of the stress modelling to underpin and present an optimised solution to mitigate the risk sooner. The project is currently reviewing the delivery strategy inline with these discussions and a Change Control Record (CCR) will follow next financial year in alignment to the Outline Business Case (OBC). The P50 completion cost and the schedule position has been maintained in period. The Capability & Capacity RAG status remains Green.
B90: Value Stream: Retrievals
B91: Portfolio Summary | AV91: 70.5 | AW91: 46106 | AY91: 72.617237 | AZ91: -72.617237 | BA91: 46106 | BB91: -46075.173
B93: n/a(1) | C93: MSSS 2nd and 3rd Extension Sub-Programme | D93: Sellafield | F93: =VLOOKUP(C93,'5a)NDA MPPR'!$B$9:$AK$61,3,FALSE) -> A | G93: =VLOOKUP(C93,'5a)NDA MPPR'!$B$9:$AK$61,4,FALSE) -> 0 | I93: =VLOOKUP(C93,'5a)NDA MPPR'!$B$9:$AK$61,6,FALSE) -> FBC (Oct-23) | J93: =VLOOKUP(C93,'5a)NDA MPPR'!$B$9:$AK$61,7,FALSE) -> 130 | K93: =VLOOKUP(C93,'5a)NDA MPPR'!$B$9:$AK$61,8,FALSE) -> 200 | L93: =VLOOKUP(C93,'5a)NDA MPPR'!$B$9:$AK$61,9,FALSE) -> - | M93: =VLOOKUP(C93,'5a)NDA MPPR'!$B$9:$AK$61,10,FALSE) -> - | O93: =VLOOKUP(C93,'5a)NDA MPPR'!$B$9:$AK$61,12,FALSE) -> 200 | P93: =VLOOKUP(C93,'5a)NDA MPPR'!$B$9:$AK$61,13,FALSE) -> 200 | R93: =VLOOKUP(C93,'5a)NDA MPPR'!$B$9:$AK$61,15,FALSE) -> A | S93: =VLOOKUP(C93,'5a)NDA MPPR'!$B$9:$AK$61,16,FALSE) -> 0 | U93: =VLOOKUP(C93,'5a)NDA MPPR'!$B$9:$AK$61,18,FALSE) -> FBC (Nov-23) | W93: =VLOOKUP(C93,'5a)NDA MPPR'!$B$9:$AK$61,20,FALSE) -> 127.73208 | X93: =VLOOKUP(C93,'5a)NDA MPPR'!$B$9:$AK$61,21,FALSE) -> 141.50573 | Y93: =VLOOKUP(C93,'5a)NDA MPPR'!$B$9:$AK$61,22,FALSE) -> 0 | AA93: =VLOOKUP(C93,'5a)NDA MPPR'!$B$9:$AK$61,24,FALSE) -> 48935 | AB93: =VLOOKUP(C93,'5a)NDA MPPR'!$B$9:$AK$61,25,FALSE) -> 48935 | AC93: =VLOOKUP(C93,'5a)NDA MPPR'!$B$9:$AK$61,26,FALSE) -> 0 | AE93: =VLOOKUP(C93,'5a)NDA MPPR'!$B$9:$AK$61,28,FALSE) -> 0 | AF93: =VLOOKUP(C93,'5a)NDA MPPR'!$B$9:$AK$61,29,FALSE) -> 0 | AG93: =VLOOKUP(C93,'5a)NDA MPPR'!$B$9:$AK$61,30,FALSE) -> 37.756586 | AH93: =VLOOKUP(C93,'5a)NDA MPPR'!$B$9:$AK$61,31,FALSE) -> 0 | AI93: =VLOOKUP(C93,'5a)NDA MPPR'!$B$9:$AK$61,32,FALSE) -> 0 | AJ93: =VLOOKUP(C93,'5a)NDA MPPR'!$B$9:$AK$61,33,FALSE) -> 0 | AK93: =VLOOKUP(C93,'5a)NDA MPPR'!$B$9:$AK$61,34,FALSE) -> 0 | AM93: =VLOOKUP(C93,'5a)NDA MPPR'!$B$9:$AK$61,36,FALSE) -> R | AV93: 141.5005 | AW93: 48935 | AY93: 127.73208 | AZ93: =W93-AY93 -> 0 | BA93: 48935 | BB93: =AA93-BA93 -> 0
A94: =C93 -> MSSS 2nd and 3rd Extension Sub-Programme | B94: =VLOOKUP($C93,'5a)NDA MPPR'!$A$9:$AK$61,2,FALSE) -> In October 2023, the Magnox Swarf Storage Silos (MSSS) Retrievals Programme received re-sanctioning approval, establishing an overall upper funding limit of £1,098m. As part of that endorsement, a revised management framework and sanctioning strategy was introduced to govern the MSSS 2nd Extension (2E) & 3rd Extension (3E) Tranche, as discrete projects. These projects are delivering critical enablers that will facilitate the commencement of waste retrieval operations using Silo Emptying Plant (SEP) 3. They have an upper sanction limit of £200m. The key enablers included are 1) SEP3; Complete design/rectification, installation and commissioning of the machine and associated components. 2) Final manufacture and installation scope for the Nitrogen Inlet system. 3) 2E Liquor Level management system. 4) The remaining Packages required to support full retrievals. The programme has prioritised the OB/FE and as a result the expected specialist resources (e.g. design capability) will not be available to concurrently deliver the SEP3 project (1). Without further action the delivery will take substantially longer, challenging tolerances. To address this SL is pursuing an alternative delivery model with a fully integrated programme partner that will increase effective delivery by enabling access to a different part of the skilled labour market. Confidence in the revised strategy continues to increase through ongoing engagement sessions with the delivery partners, therefore the Delivery Confidence Assessment remains at Amber until completion of the opportunity scoping phase in Qtr 4.The capability and capacity RAG is Red driven by resource constraints and commercial disruption following the administration of a key supply chain partner on the packages project (4). In response, the integrated team is actively working with administrators to recover part-manufactured equipment, having identified secure interim storage, and identified a replacement supplier to complete outstanding packages, with the required contract placements achieved in period to support the removal of equipment. There remain a number of challenges to removing SL equipment from the administrator including building condition and crane certification, however plans are in place and removal of equipment has commenced this period. This disruption has led to increased in-year expenditure due to associated recovery and transition costs. Nitrogen Inlet project (2) and 2E LLM project (3) continue to deliver within baseline and sanction forecast. Overall, the tranche remains in the early stages of its lifecycle, with only six of the nine 2E/3E projects sanctioned, and a total released value of £66.3m. While future cost and schedule pressures are anticipated, the project is forecasting lifecycle EAC within the sanctioned upper limit of £200m and to timelines that align with the critical path of the Magnox Swarf Storage Silo (MSSS) Programme and as such, no direct impact is expected on sustained retrievals. There has been no change to the EAC during this period. The Baseline RAG status is Amber, reflecting anticipated impacts from ongoing commercial challenges and supply chain, but also in acknowledgement of the recovery plan currently being enacted by the project team to ensure delivery of packages in support of the programme requirements. Given the level of uncertainty but also increasing confidence in the revised strategy for SEP 3 delivery the Forecast project end date is being held at December 2033, and the Delivery Confidence Assessment at Amber, this will be revisited once the project has received a decision on the revised strategy through the delivery plan process specifically in relation to SEP 3 and the packages project scope.
B96: 35/10342 | C96: MSSS SEP3 Rails & Brackets | D96: Sellafield | F96: =VLOOKUP($C96,'4b) SL EPO Extended Data Sheet'!$A$5:$AB$168,2,FALSE) -> A | G96: =VLOOKUP($C96,'4b) SL EPO Extended Data Sheet'!$A$5:$AB$168,3, FALSE) -> 0 | I96: =VLOOKUP($C96,'4b) SL EPO Extended Data Sheet'!$A$5:$AD$168,30, FALSE) -> FBC (Dec-21) | J96: =VLOOKUP($C96,'4b) SL EPO Extended Data Sheet'!$A$5:$AB$168,6, FALSE)/1000000 -> 20.366653 | K96: =VLOOKUP($C96,'4b) SL EPO Extended Data Sheet'!$A$5:$AB$168,7, FALSE)/1000000 -> 21.84146 | L96: =VLOOKUP($C96,'4b) SL EPO Extended Data Sheet'!$A$5:$AB$168,8, FALSE) -> 46234 | M96: =VLOOKUP($C96,'4b) SL EPO Extended Data Sheet'!$A$5:$AB$168,9, FALSE) -> 46477 | O96: =VLOOKUP($C96,'4b) SL EPO Extended Data Sheet'!$A$5:$AB$168,10, FALSE)/1000000 -> 0 | P96: =VLOOKUP($C96,'4b) SL EPO Extended Data Sheet'!$A$5:$AB$168,11, FALSE)/1000000 -> 20.366653 | R96: =VLOOKUP($C96,'4b) SL EPO Extended Data Sheet'!$A$5:$AB$168,12,FALSE) -> R | S96: =VLOOKUP($C96,'4b) SL EPO Extended Data Sheet'!$A$5:$AB$168,13,FALSE) -> -1 | U96: =VLOOKUP($C96,'4b) SL EPO Extended Data Sheet'!$A$5:$AE$168,31,FALSE) -> FBC (Mar-22) | W96: =VLOOKUP($C96,'4b) SL EPO Extended Data Sheet'!$A$5:$AC$168,16,FALSE)/1000000 -> 19.192466 | X96: =VLOOKUP($C96,'4b) SL EPO Extended Data Sheet'!$A$5:$AC$168,17,FALSE)/1000000 -> 20.434619 | Y96: =VLOOKUP($C96,'4b) SL EPO Extended Data Sheet'!$A$5:$AC$168,18,FALSE)/1000000 -> -0.0552814 | Z96: =VLOOKUP($C96,'4b) SL EPO Extended Data Sheet'!$A$5:$AB$168,16,FALSE)/1000000 -> 19.192466 | AA96: =VLOOKUP($C96,'4b) SL EPO Extended Data Sheet'!$A$5:$AC$168,19,FALSE) -> 46230 | AB96: =VLOOKUP($C96,'4b) SL EPO Extended Data Sheet'!$A$5:$AC$168,20,FALSE) -> 47039 | AC96: =VLOOKUP($C96,'4b) SL EPO Extended Data Sheet'!$A$5:$AC$168,21,FALSE) -> 0 | AD96: =VLOOKUP($C96,'4b) SL EPO Extended Data Sheet'!$A$5:$AB$168,15,FALSE)/1000000 -> 0.044651 | AE96: =VLOOKUP($C96,'4b) SL EPO Extended Data Sheet'!$A$5:$AC$168,22,FALSE)/1000000 -> 18.974144 | AF96: =VLOOKUP($C96,'4b) SL EPO Extended Data Sheet'!$A$5:$AC$168,23,FALSE)/1000000 -> 14.255622 | AG96: =VLOOKUP($C96,'4b) SL EPO Extended Data Sheet'!$A$5:$AC$168,24,FALSE)/1000000 -> 16.626002 | AH96: =VLOOKUP($C96,'4b) SL EPO Extended Data Sheet'!$A$5:$AC$168,25,FALSE) -> 0.85742933 | AI96: =VLOOKUP($C96,'4b) SL EPO Extended Data Sheet'!$A$5:$AC$168,26,FALSE) -> 0.75131829 | AJ96: =VLOOKUP($C96,'4b) SL EPO Extended Data Sheet'!$A$5:$AC$168,27,FALSE) -> 0.98862462 | AK96: =VLOOKUP($C96,'4b) SL EPO Extended Data Sheet'!$A$5:$AC$168,28,FALSE) -> 0.74277175 | AL96: =VLOOKUP($C96,'4b) SL EPO Extended Data Sheet'!$A$6:$AB$168,15,FALSE) -> 44651 | AM96: =VLOOKUP($C96,'4b) SL EPO Extended Data Sheet'!$A$5:$AC$168,29,FALSE) -> A | AV96: 20.489901 | AW96: 47039 | AY96: 19.192466 | AZ96: =W96-AY96 -> 0 | BA96: 46230 | BB96: =AA96-BA96 -> 0
A97: =C96 -> MSSS SEP3 Rails & Brackets | B97: This project relates to the manufacture and installation of the Rails supporting Silo Emptying Plant 3 (SEP3) and is prioritised into zones, aligned with installation and retrievals. The first project benefit was delivered on the 6th February 2025 with the installation of the Zone 1 rails, ready for the start of SEP3 installation. The Delivery Confidence Assessment is Amber as full project delivery is now not forecast until after the P80 date of March 2027. The project is currently forecast to be delivered for less than the P80 sanction value of £21.8m, however ongoing supply chain issues are likely to impact this. The Baseline RAG status has been moved to Red, in recognition of the supply chain contractor entering administration. The project and commercial teams are working with the administrator to progress the retrieval of the part-manufactured equipment, secure a medium-term storage facility and identify an alternative supply chain partner to complete the packages, however it is expected that this will impact both schedule and cost, hence the movement to red baseline RAG. It is, however, currently expected that the project can still be delivered within timescales acceptable to the critical path of the Magnox Swarf Storage Silo (MSSS) Programme and will not directly impact Sustained Retrievals as the Zone 3 rails are not a requirement for the installation of the SEP3 machine. Capability & Capacity RAG status is Amber due to the ongoing supply chain issues.
B99: 35/10274 | C99: MSSS Electrical Distribution Upgrade for Retrievals | D99: Sellafield | F99: =VLOOKUP($C99,'4b) SL EPO Extended Data Sheet'!$A$5:$AB$168,2,FALSE) -> A | G99: =VLOOKUP($C99,'4b) SL EPO Extended Data Sheet'!$A$5:$AB$168,3, FALSE) -> 0 | I99: =VLOOKUP($C99,'4b) SL EPO Extended Data Sheet'!$A$5:$AD$168,30, FALSE) -> FBC (Jan-23) | J99: =VLOOKUP($C99,'4b) SL EPO Extended Data Sheet'!$A$5:$AB$168,6, FALSE)/1000000 -> 27.608 | K99: =VLOOKUP($C99,'4b) SL EPO Extended Data Sheet'!$A$5:$AB$168,7, FALSE)/1000000 -> 28.241 | L99: =VLOOKUP($C99,'4b) SL EPO Extended Data Sheet'!$A$5:$AB$168,8, FALSE) -> 46053 | M99: =VLOOKUP($C99,'4b) SL EPO Extended Data Sheet'!$A$5:$AB$168,9, FALSE) -> 46203 | O99: =VLOOKUP($C99,'4b) SL EPO Extended Data Sheet'!$A$5:$AB$168,10, FALSE)/1000000 -> 0 | P99: =VLOOKUP($C99,'4b) SL EPO Extended Data Sheet'!$A$5:$AB$168,11, FALSE)/1000000 -> 28.241 | R99: =VLOOKUP($C99,'4b) SL EPO Extended Data Sheet'!$A$5:$AB$168,12,FALSE) -> R | S99: =VLOOKUP($C99,'4b) SL EPO Extended Data Sheet'!$A$5:$AB$168,13,FALSE) -> -1 | U99: =VLOOKUP($C99,'4b) SL EPO Extended Data Sheet'!$A$5:$AE$168,31,FALSE) -> FBC (Mar-23) | W99: =VLOOKUP($C99,'4b) SL EPO Extended Data Sheet'!$A$5:$AC$168,16,FALSE)/1000000 -> 18.788383 | X99: =VLOOKUP($C99,'4b) SL EPO Extended Data Sheet'!$A$5:$AC$168,17,FALSE)/1000000 -> 28.084728 | Y99: =VLOOKUP($C99,'4b) SL EPO Extended Data Sheet'!$A$5:$AC$168,18,FALSE)/1000000 -> 0.01471561 | Z99: =VLOOKUP($C99,'4b) SL EPO Extended Data Sheet'!$A$5:$AB$168,16,FALSE)/1000000 -> 18.788383 | AA99: =VLOOKUP($C99,'4b) SL EPO Extended Data Sheet'!$A$5:$AC$168,19,FALSE) -> 46043 | AB99: =VLOOKUP($C99,'4b) SL EPO Extended Data Sheet'!$A$5:$AC$168,20,FALSE) -> 46463 | AC99: =VLOOKUP($C99,'4b) SL EPO Extended Data Sheet'!$A$5:$AC$168,21,FALSE) -> -5 | AD99: =VLOOKUP($C99,'4b) SL EPO Extended Data Sheet'!$A$5:$AB$168,15,FALSE)/1000000 -> 0.045015 | AE99: =VLOOKUP($C99,'4b) SL EPO Extended Data Sheet'!$A$5:$AC$168,22,FALSE)/1000000 -> 26.873074 | AF99: =VLOOKUP($C99,'4b) SL EPO Extended Data Sheet'!$A$5:$AC$168,23,FALSE)/1000000 -> 26.130578 | AG99: =VLOOKUP($C99,'4b) SL EPO Extended Data Sheet'!$A$5:$AC$168,24,FALSE)/1000000 -> 27.732211 | AH99: =VLOOKUP($C99,'4b) SL EPO Extended Data Sheet'!$A$5:$AC$168,25,FALSE) -> 0.94224647 | AI99: =VLOOKUP($C99,'4b) SL EPO Extended Data Sheet'!$A$5:$AC$168,26,FALSE) -> 0.97237025 | AJ99: =VLOOKUP($C99,'4b) SL EPO Extended Data Sheet'!$A$5:$AC$168,27,FALSE) -> 1.4303027 | AK99: =VLOOKUP($C99,'4b) SL EPO Extended Data Sheet'!$A$5:$AC$168,28,FALSE) -> 1.3907838 | AL99: =VLOOKUP($C99,'4b) SL EPO Extended Data Sheet'!$A$6:$AB$168,15,FALSE) -> 45015 | AM99: =VLOOKUP($C99,'4b) SL EPO Extended Data Sheet'!$A$5:$AC$168,29,FALSE) -> G | AV99: 28.070013 | AW99: 46468 | AY99: 18.788383 | AZ99: =W99-AY99 -> 0 | BA99: 46043 | BB99: =AA99-BA99 -> 0
A100: =C99 -> MSSS Electrical Distribution Upgrade for Retrievals | B100: The Electrical Distribution project is required to replace the aged and obsolete building electrical “Level 2” infrastructure with modern Power Distribution boards which will power the Silo Emptying Plant (SEP) machines throughout waste retrieval operation. The project is in the final stages of construction following energisation of the board and continues with load transfers. The first project benefit was realised in support of Magnox Swarf Storage Silo (MSSS) Facility resilience at the start of retrievals in April 2022. The Delivery Confidence Assessment is Amber with the date unlikely to be recovered but still forecast to complete within the business case P80 sanction (which has now been fully released to the project), with a close out date of March 2027. The Baseline RAG is Red with delivery now beyond the baseline P80 date, however, transfer of all critical systems and power to SEP 1 and 2 have been delivered, ongoing load transfers address obsolescence issues on some existing equipment however not all load transfers will take place ahead of the baseline P80 date. Many of the remaining load transfers require outages and are now aligned with the programme integrated schedule to minimise disruption to plant. The project continues to be impacted by industrial action in the supply chain resulting in productivity losses, key skills unavailable, and constraints on work scope delivery. Impact assessment will be finalised on conclusion of the action with the intent to seek appropriate sanction relief subject to further review. This is not a dispute directly with Sellafield Ltd; Sellafield is engaged with the Supply Chain and Stakeholders to ensure effective management of the impacts; correct mitigations are in place and to effectively mobilise resources upon return to work. This schedule is, however, being further pressured by the impact from the current industrial action although the project will mitigate this by adjusting the order of transfers where possible. Note: The Baseline is showing a much lower value than the sanction, as some previous early works were completed under a different project (Sanction transferred, but Baseline not included). Capability & Capacity RAG status is Green.
B102: 35/06075 | C102: SEP Solid Waste Storage Retrievals | D102: Sellafield | F102: =VLOOKUP(C102,'5a)NDA MPPR'!$B$9:$AK$61,3,FALSE) -> A | G102: =VLOOKUP(C102,'5a)NDA MPPR'!$B$9:$AK$61,4,FALSE) -> 0 | I102: =VLOOKUP(C102,'5a)NDA MPPR'!$B$9:$AK$61,6,FALSE) -> FBC (Oct-23) | J102: =VLOOKUP(C102,'5a)NDA MPPR'!$B$9:$AK$61,7,FALSE) -> 866.7 | K102: =VLOOKUP(C102,'5a)NDA MPPR'!$B$9:$AK$61,8,FALSE) -> 897.9 | L102: =VLOOKUP(C102,'5a)NDA MPPR'!$B$9:$AK$61,9,FALSE) -> 46505 | M102: =VLOOKUP(C102,'5a)NDA MPPR'!$B$9:$AK$61,10,FALSE) -> 47053 | O102: =VLOOKUP(C102,'5a)NDA MPPR'!$B$9:$AK$61,12,FALSE) -> 897.9 | P102: =VLOOKUP(C102,'5a)NDA MPPR'!$B$9:$AK$61,13,FALSE) -> 897.9 | R102: =VLOOKUP(C102,'5a)NDA MPPR'!$B$9:$AK$61,15,FALSE) -> R | S102: =VLOOKUP(C102,'5a)NDA MPPR'!$B$9:$AK$61,16,FALSE) -> -1 | U102: =VLOOKUP(C102,'5a)NDA MPPR'!$B$9:$AK$61,18,FALSE) -> FBC (Apr-22) | W102: =VLOOKUP(C102,'5a)NDA MPPR'!$B$9:$AK$61,20,FALSE) -> 803.03225 | X102: =VLOOKUP(C102,'5a)NDA MPPR'!$B$9:$AK$61,21,FALSE) -> 889.66115 | Y102: =VLOOKUP(C102,'5a)NDA MPPR'!$B$9:$AK$61,22,FALSE) -> 1.8 | AA102: =VLOOKUP(C102,'5a)NDA MPPR'!$B$9:$AK$61,24,FALSE) -> 46505 | AB102: =VLOOKUP(C102,'5a)NDA MPPR'!$B$9:$AK$61,25,FALSE) -> 47262 | AC102: =VLOOKUP(C102,'5a)NDA MPPR'!$B$9:$AK$61,26,FALSE) -> 99 | AE102: =VLOOKUP(C102,'5a)NDA MPPR'!$B$9:$AK$61,28,FALSE) -> 799.49914 | AF102: =VLOOKUP(C102,'5a)NDA MPPR'!$B$9:$AK$61,29,FALSE) -> 786.20195 | AG102: =VLOOKUP(C102,'5a)NDA MPPR'!$B$9:$AK$61,30,FALSE) -> 872.40328 | AH102: =VLOOKUP(C102,'5a)NDA MPPR'!$B$9:$AK$61,31,FALSE) -> 0.90119096 | AI102: =VLOOKUP(C102,'5a)NDA MPPR'!$B$9:$AK$61,32,FALSE) -> 0.9833681 | AJ102: =VLOOKUP(C102,'5a)NDA MPPR'!$B$9:$AK$61,33,FALSE) -> 0.99560028 | AK102: =VLOOKUP(C102,'5a)NDA MPPR'!$B$9:$AK$61,34,FALSE) -> 0.97904156 | AM102: =VLOOKUP(C102,'5a)NDA MPPR'!$B$9:$AK$61,36,FALSE) -> G | AV102: 887.84724 | AW102: 47163 | AY102: 803.03225 | AZ102: =W102-AY102 -> 0 | BA102: 46505 | BB102: =AA102-BA102 -> 0
A103: =C102 -> SEP Solid Waste Storage Retrievals | B103: =VLOOKUP($C102,'5a)NDA MPPR'!$A$9:$AK$61,2,FALSE) -> This project enables retrievals in Magnox Swarf Storage Silos (MSSS) Original Building and the 1st Extension. This includes completion of Silo Emptying Plant (SEP) 2 and SEP 1. The first project benefit was completed in 2022, enabling the successful start of Retrievals from SEP 2. The project continues to be impacted by industrial action in the supply chain resulting in productivity losses, key skills unavailable, and constraints on work scope delivery. Impact assessment will be finalised on conclusion of the action with the intent to seek appropriate sanction relief subject to further review. This is not a dispute directly with Sellafield Ltd; Sellafield is engaged with the Supply Chain and Stakeholders to ensure effective management of the impacts; correct mitigations are in place and to effectively mobilise resources upon return to work. The Delivery Confidence Assessment remains Amber in light of the challenges to the SEP1 commissioning schedule and in delivering the Vent Extract works. In context of the full project, the current site works issues appear resolvable but are resulting in the SEP1 capability date being adversely effected. This period, SEP2 close out made some positive progress, however the SEP1 and Vent elements of the project achieved limited progress as work was halted by industrial action and water ingress issues respectively. This has resulted in the planned first SEP1 skip out date moving to May 2028, and the subsequent deterioration of the project end date to May 2029 challenges the lifecycle cost to remain within P80 values, although the integrated team are working to recover this date. The prolongation has also caused a £1.8m increase in the EAC to £889.7m, and the Baseline RAG now reflects Red. Of the significant negative cost variance between the EAC and Baseline, £64.3m of this was historical (prior to 2022) and although included in the current sanction, is not included in the Baseline. The Capability and Capacity remains Green as resources are being made available to support the prioritised Original Building/1st Extension scope. The Skip Fill Optimisation opportunity and key SEP Retrievals Improvements such as capability to manage large items, deal with pressurised containers and manage waste craters has been integrated into the MSSS capability delivery schedule and the project and programme are working together to minimise the impact of implementation of this scope on the project.
B105: 35/10371 | C105: Sludge Handling & Export Plant | D105: Sellafield | F105: =VLOOKUP($C105,'4b) SL EPO Extended Data Sheet'!$A$5:$AB$168,2,FALSE) -> A | G105: =VLOOKUP($C105,'4b) SL EPO Extended Data Sheet'!$A$5:$AB$168,3, FALSE) -> 0 | I105: =VLOOKUP($C105,'4b) SL EPO Extended Data Sheet'!$A$5:$AD$168,30, FALSE) -> SOC (Sep-21) | J105: =VLOOKUP($C105,'4b) SL EPO Extended Data Sheet'!$A$5:$AB$168,6, FALSE)/1000000 -> 38.1 | K105: =VLOOKUP($C105,'4b) SL EPO Extended Data Sheet'!$A$5:$AB$168,7, FALSE)/1000000 -> 0 | L105: =VLOOKUP($C105,'4b) SL EPO Extended Data Sheet'!$A$5:$AB$168,8, FALSE) | M105: =VLOOKUP($C105,'4b) SL EPO Extended Data Sheet'!$A$5:$AB$168,9, FALSE) | O105: =VLOOKUP($C105,'4b) SL EPO Extended Data Sheet'!$A$5:$AB$168,10, FALSE)/1000000 -> 0 | P105: =VLOOKUP($C105,'4b) SL EPO Extended Data Sheet'!$A$5:$AB$168,11, FALSE)/1000000 -> 38.1 | R105: =VLOOKUP($C105,'4b) SL EPO Extended Data Sheet'!$A$5:$AB$168,12,FALSE) -> A | S105: =VLOOKUP($C105,'4b) SL EPO Extended Data Sheet'!$A$5:$AB$168,13,FALSE) -> 0 | U105: =VLOOKUP($C105,'4b) SL EPO Extended Data Sheet'!$A$5:$AE$168,31,FALSE) -> SOC (Feb-23) | W105: =VLOOKUP($C105,'4b) SL EPO Extended Data Sheet'!$A$5:$AC$168,16,FALSE)/1000000 -> 340 | X105: =VLOOKUP($C105,'4b) SL EPO Extended Data Sheet'!$A$5:$AC$168,17,FALSE)/1000000 -> 341.06661 | Y105: =VLOOKUP($C105,'4b) SL EPO Extended Data Sheet'!$A$5:$AC$168,18,FALSE)/1000000 -> -0.02869646 | Z105: =VLOOKUP($C105,'4b) SL EPO Extended Data Sheet'!$A$5:$AB$168,16,FALSE)/1000000 -> 340 | AA105: =VLOOKUP($C105,'4b) SL EPO Extended Data Sheet'!$A$5:$AC$168,19,FALSE) -> 48746 | AB105: =VLOOKUP($C105,'4b) SL EPO Extended Data Sheet'!$A$5:$AC$168,20,FALSE) -> 48850 | AC105: =VLOOKUP($C105,'4b) SL EPO Extended Data Sheet'!$A$5:$AC$168,21,FALSE) -> 0 | AD105: =VLOOKUP($C105,'4b) SL EPO Extended Data Sheet'!$A$5:$AB$168,15,FALSE)/1000000 -> 0.044985 | AE105: =VLOOKUP($C105,'4b) SL EPO Extended Data Sheet'!$A$5:$AC$168,22,FALSE)/1000000 -> 31.302793 | AF105: =VLOOKUP($C105,'4b) SL EPO Extended Data Sheet'!$A$5:$AC$168,23,FALSE)/1000000 -> 27.190405 | AG105: =VLOOKUP($C105,'4b) SL EPO Extended Data Sheet'!$A$5:$AC$168,24,FALSE)/1000000 -> 27.460886 | AH105: =VLOOKUP($C105,'4b) SL EPO Extended Data Sheet'!$A$5:$AC$168,25,FALSE) -> 0.9901503 | AI105: =VLOOKUP($C105,'4b) SL EPO Extended Data Sheet'!$A$5:$AC$168,26,FALSE) -> 0.86862553 | AJ105: =VLOOKUP($C105,'4b) SL EPO Extended Data Sheet'!$A$5:$AC$168,27,FALSE) -> 0.092067037 | AK105: =VLOOKUP($C105,'4b) SL EPO Extended Data Sheet'!$A$5:$AC$168,28,FALSE) -> 0.079971779 | AL105: =VLOOKUP($C105,'4b) SL EPO Extended Data Sheet'!$A$6:$AB$168,15,FALSE) -> 44985 | AM105: =VLOOKUP($C105,'4b) SL EPO Extended Data Sheet'!$A$5:$AC$168,29,FALSE) -> A | AV105: 341.0953 | AW105: 48850 | AY105: 340 | AZ105: =W105-AY105 -> 0 | BA105: 48746 | BB105: =AA105-BA105 -> 0
A106: =C105 -> Sludge Handling & Export Plant | B106: Sludge Handling & Export Plant aims to provide a capability to receive and process sludge from Sludge Packaging Plant 1 (SPP1) and export it to a downstream facility to enable the safe treatment into a suitable waste form/product for interim storage. Delivery Confidence Assessment is Amber, the project is still within its appraise and select phase and uncertainty remains until Outline Business Case (OBC) assurance and governance is complete. This has management oversight and is being worked through accordingly. The down-selected preferred solution (Option 1 -Sludge dewatering in a 500-litre drum in a flask and export to Waste Encapsulation Plant (WEP) for conditioning and interim storage of the resultant waste product in Encapsulated Product Store 3 (EPS3)) is now being further developed in parallel to project planning to support submission of the OBC. Project is trending right, current forecast OBC is July 2026. Output and decisions from Independent review are required. Completion of PPP Intervention points, schedule and estimate build are required to reset Get to Gate assurance plan. The schedule and estimate build is complete, awaiting final assurance. Cumulative sanction released to the project is £30.6m to deliver OBC. SL Investment Review Panel (IRP) are currently holding a further £7.442m bringing the overall sanction to £38.1m. Baseline RAG is Amber to reflect the current forecast OBC date of July 2026 being later than the current baseline. A Change Control Request will be prepared and implemented to update the baseline following OBC Approval. Capability and Capacity remains amber. Internal project resource challenges remain, however have addressed Construction PM, Commercial Lead and Environmental and Sustainability resources. Further ramp up to support transition to PPP has been put on hold. Additional assurance requirements remain a capacity challenge to balance with delivery. Programme resources have been identified and mobilised to support the ‘get to gate’ plan.
B108: 35/10095 | C108: Box Encapsulation Plant Product Store Direct Import Facility | D108: Sellafield | F108: =VLOOKUP(C108,'5a)NDA MPPR'!$B$9:$AK$61,3,FALSE) -> A | G108: =VLOOKUP(C108,'5a)NDA MPPR'!$B$9:$AK$61,4,FALSE) -> 0 | I108: =VLOOKUP(C108,'5a)NDA MPPR'!$B$9:$AK$61,6,FALSE) -> FBC (Mar-22) | J108: =VLOOKUP(C108,'5a)NDA MPPR'!$B$9:$AK$61,7,FALSE) -> 458.9 | K108: =VLOOKUP(C108,'5a)NDA MPPR'!$B$9:$AK$61,8,FALSE) -> 466.4 | L108: =VLOOKUP(C108,'5a)NDA MPPR'!$B$9:$AK$61,9,FALSE) -> 45244 | M108: =VLOOKUP(C108,'5a)NDA MPPR'!$B$9:$AK$61,10,FALSE) -> 45361 | O108: =VLOOKUP(C108,'5a)NDA MPPR'!$B$9:$AK$61,12,FALSE) -> 466.4 | P108: =VLOOKUP(C108,'5a)NDA MPPR'!$B$9:$AK$61,13,FALSE) -> 458.9 | R108: =VLOOKUP(C108,'5a)NDA MPPR'!$B$9:$AK$61,15,FALSE) -> A | S108: =VLOOKUP(C108,'5a)NDA MPPR'!$B$9:$AK$61,16,FALSE) -> 0 | U108: =VLOOKUP(C108,'5a)NDA MPPR'!$B$9:$AK$61,18,FALSE) -> FBC Add. (Mar-21) | W108: =VLOOKUP(C108,'5a)NDA MPPR'!$B$9:$AK$61,20,FALSE) -> 419.95364 | X108: =VLOOKUP(C108,'5a)NDA MPPR'!$B$9:$AK$61,21,FALSE) -> 458.24501 | Y108: =VLOOKUP(C108,'5a)NDA MPPR'!$B$9:$AK$61,22,FALSE) -> 0 | AA108: =VLOOKUP(C108,'5a)NDA MPPR'!$B$9:$AK$61,24,FALSE) -> 45050 | AB108: =VLOOKUP(C108,'5a)NDA MPPR'!$B$9:$AK$61,25,FALSE) -> 46142 | AC108: =VLOOKUP(C108,'5a)NDA MPPR'!$B$9:$AK$61,26,FALSE) -> 0 | AE108: =VLOOKUP(C108,'5a)NDA MPPR'!$B$9:$AK$61,28,FALSE) -> 419.95364 | AF108: =VLOOKUP(C108,'5a)NDA MPPR'!$B$9:$AK$61,29,FALSE) -> 419.93138 | AG108: =VLOOKUP(C108,'5a)NDA MPPR'!$B$9:$AK$61,30,FALSE) -> 458.19501 | AH108: =VLOOKUP(C108,'5a)NDA MPPR'!$B$9:$AK$61,31,FALSE) -> 0.91649052 | AI108: =VLOOKUP(C108,'5a)NDA MPPR'!$B$9:$AK$61,32,FALSE) -> 0.99994701 | AJ108: =VLOOKUP(C108,'5a)NDA MPPR'!$B$9:$AK$61,33,FALSE) -> 1 | AK108: =VLOOKUP(C108,'5a)NDA MPPR'!$B$9:$AK$61,34,FALSE) -> 0.99994701 | AM108: =VLOOKUP(C108,'5a)NDA MPPR'!$B$9:$AK$61,36,FALSE) -> G | AV108: 458.24423 | AW108: 46142 | AY108: 419.95364 | AZ108: =W108-AY108 -> 0 | BA108: 45050 | BB108: =AA108-BA108 -> 0
A109: =C108 -> Box Encapsulation Plant Product Store Direct Import Facility | B109: =VLOOKUP($C108,'5a)NDA MPPR'!$A$9:$AK$61,2,FALSE) -> BEPPS-DIF project is essential to remediation of Pile Fuel Cladding Silo (PFCS) and provides capability to receive and store waste from remediation work. PFCS active commissioning is now complete. Project has now received 1 Waste Packaging and Encapsulation Plant (WPEP) package to enable start of WPEP active commissioning. Fault observations (FOBs) and remaining project scope ongoing. Work to repair shield door has now started. Duly Authorised Person (DAP) move to support Advanced Gas Reactor (AGR) / Encapsulated Product Store (EPS) transfers may challenge rectifying subsequent faults in parallel with plant operations. Project resources are substantially redeployed on other scope for Retrievals Operations keeping project spend to a minimum. Endorsement to Operate planned for 31st March 2026. Delivery Confidence Assessment remains Amber. Baseline RAG remains Amber. Capability and Capacity RAG remains Green, project has resource to complete scope. The project completion date remains April 2026, which is aligned with the anticipated Gated Project Oversight Committe (GPOC) date of the Post Investment Appraisal.
B111: 35/05684 | C111: MSSS Upgrades for Retrievals & Resilience | D111: Sellafield | F111: =VLOOKUP($C111,'4b) SL EPO Extended Data Sheet'!$A$5:$AB$168,2,FALSE) -> G | G111: =VLOOKUP($C111,'4b) SL EPO Extended Data Sheet'!$A$5:$AB$168,3, FALSE) -> 0 | I111: =VLOOKUP($C111,'4b) SL EPO Extended Data Sheet'!$A$5:$AD$168,30, FALSE) -> FBC (Feb-23) | J111: =VLOOKUP($C111,'4b) SL EPO Extended Data Sheet'!$A$5:$AB$168,6, FALSE)/1000000 -> 105 | K111: =VLOOKUP($C111,'4b) SL EPO Extended Data Sheet'!$A$5:$AB$168,7, FALSE)/1000000 -> 105.5 | L111: =VLOOKUP($C111,'4b) SL EPO Extended Data Sheet'!$A$5:$AB$168,8, FALSE) -> 45747 | M111: =VLOOKUP($C111,'4b) SL EPO Extended Data Sheet'!$A$5:$AB$168,9, FALSE) -> 47361 | O111: =VLOOKUP($C111,'4b) SL EPO Extended Data Sheet'!$A$5:$AB$168,10, FALSE)/1000000 -> 0 | P111: =VLOOKUP($C111,'4b) SL EPO Extended Data Sheet'!$A$5:$AB$168,11, FALSE)/1000000 -> 105.5 | R111: =VLOOKUP($C111,'4b) SL EPO Extended Data Sheet'!$A$5:$AB$168,12,FALSE) -> R | S111: =VLOOKUP($C111,'4b) SL EPO Extended Data Sheet'!$A$5:$AB$168,13,FALSE) -> -1 | U111: =VLOOKUP($C111,'4b) SL EPO Extended Data Sheet'!$A$5:$AE$168,31,FALSE) -> FBC (Oct-22) | W111: =VLOOKUP($C111,'4b) SL EPO Extended Data Sheet'!$A$5:$AC$168,16,FALSE)/1000000 -> 103.81815 | X111: =VLOOKUP($C111,'4b) SL EPO Extended Data Sheet'!$A$5:$AC$168,17,FALSE)/1000000 -> 102.04751 | Y111: =VLOOKUP($C111,'4b) SL EPO Extended Data Sheet'!$A$5:$AC$168,18,FALSE)/1000000 -> 0.06549431 | Z111: =VLOOKUP($C111,'4b) SL EPO Extended Data Sheet'!$A$5:$AB$168,16,FALSE)/1000000 -> 103.81815 | AA111: =VLOOKUP($C111,'4b) SL EPO Extended Data Sheet'!$A$5:$AC$168,19,FALSE) -> 45747 | AB111: =VLOOKUP($C111,'4b) SL EPO Extended Data Sheet'!$A$5:$AC$168,20,FALSE) -> 46660 | AC111: =VLOOKUP($C111,'4b) SL EPO Extended Data Sheet'!$A$5:$AC$168,21,FALSE) -> 0 | AD111: =VLOOKUP($C111,'4b) SL EPO Extended Data Sheet'!$A$5:$AB$168,15,FALSE)/1000000 -> 0.044865 | AE111: =VLOOKUP($C111,'4b) SL EPO Extended Data Sheet'!$A$5:$AC$168,22,FALSE)/1000000 -> 103.81815 | AF111: =VLOOKUP($C111,'4b) SL EPO Extended Data Sheet'!$A$5:$AC$168,23,FALSE)/1000000 -> 92.240615 | AG111: =VLOOKUP($C111,'4b) SL EPO Extended Data Sheet'!$A$5:$AC$168,24,FALSE)/1000000 -> 100.66618 | AH111: =VLOOKUP($C111,'4b) SL EPO Extended Data Sheet'!$A$5:$AC$168,25,FALSE) -> 0.91630192 | AI111: =VLOOKUP($C111,'4b) SL EPO Extended Data Sheet'!$A$5:$AC$168,26,FALSE) -> 0.88848253 | AJ111: =VLOOKUP($C111,'4b) SL EPO Extended Data Sheet'!$A$5:$AC$168,27,FALSE) -> 1 | AK111: =VLOOKUP($C111,'4b) SL EPO Extended Data Sheet'!$A$5:$AC$168,28,FALSE) -> 0.88848253 | AL111: =VLOOKUP($C111,'4b) SL EPO Extended Data Sheet'!$A$6:$AB$168,15,FALSE) -> 44865 | AM111: =VLOOKUP($C111,'4b) SL EPO Extended Data Sheet'!$A$5:$AC$168,29,FALSE) -> G | AV111: 101.98202 | AW111: 46660 | AY111: 103.81815 | AZ111: =W111-AY111 -> 0 | BA111: 45747 | BB111: =AA111-BA111 -> 0
A112: =C111 -> MSSS Upgrades for Retrievals & Resilience | B112: This is a Portfolio of smaller tasks, all of which have been historically sanctioned locally, including Building roof replacement and upgrades to Building services. The first project benefit was realised in support of Magnox Swarf Storage Silo (MSSS) Facility resilience, by delivering numerous building services upgrades, in support of the start of MSSS retrievals in April 2022. The project continues to be impacted by industrial action in the supply chain resulting in productivity losses, key skills unavailable, and constraints on work scope delivery. Impact assessment will be finalised on conclusion of the action with the intent to seek appropriate sanction relief subject to further review. This is not a dispute directly with Sellafield Ltd; Sellafield is engaged with the Supply Chain and Stakeholders to ensure effective management of the impacts; correct mitigations are in place and to effectively mobilise resources upon return to work. The Delivery Confidence Assessment remains Green as remaining work is low complexity and low cost, however industrial action has meant site works cannot continue in year. The P50 cost and schedule remains within P50 sanction, however, the overall end date has exceeded the Baseline March 2025 date as Change Control Request (CCR)'s were not implemented on previously approved Business Cases recognising this is a portfolio of smaller tasks. The Baseline RAG status has moved to Red as the Project are forecast to deliver within cost but beyond the reported baseline date. The work on this stream has been protracted as it requires interfaces with outages and other tasks, it is generally lower priority against other areas of the MSSS Facility. In period, the project did not achieve a window to complete Condensate system outage work, nor is it in a position to commence Essential Power Distribution 301 electrical scope. This project is being reviewed in light of the low complexity, remaining scope and the deliverability issues, as such we have held the end date at 30/09/2027 until a way forward is agreed with all stakeholders. Consultation will be carried out with key stakeholders in terms of a project close out strategy in January. Capability and Capacity is Green.
B115: 35/09239 | C115: Effluent Distribution Asset Improvement | D115: Sellafield | F115: =VLOOKUP($C115,'4b) SL EPO Extended Data Sheet'!$A$5:$AB$168,2,FALSE) -> G | G115: =VLOOKUP($C115,'4b) SL EPO Extended Data Sheet'!$A$5:$AB$168,3, FALSE) -> 0 | I115: =VLOOKUP($C115,'4b) SL EPO Extended Data Sheet'!$A$5:$AD$168,30, FALSE) -> 0 (Aug-25) | J115: =VLOOKUP($C115,'4b) SL EPO Extended Data Sheet'!$A$5:$AB$168,6, FALSE)/1000000 -> 28.293193 | K115: =VLOOKUP($C115,'4b) SL EPO Extended Data Sheet'!$A$5:$AB$168,7, FALSE)/1000000 -> 0 | L115: =VLOOKUP($C115,'4b) SL EPO Extended Data Sheet'!$A$5:$AB$168,8, FALSE) -> 47756 | M115: =VLOOKUP($C115,'4b) SL EPO Extended Data Sheet'!$A$5:$AB$168,9, FALSE) | O115: =VLOOKUP($C115,'4b) SL EPO Extended Data Sheet'!$A$5:$AB$168,10, FALSE)/1000000 -> 0 | P115: =VLOOKUP($C115,'4b) SL EPO Extended Data Sheet'!$A$5:$AB$168,11, FALSE)/1000000 -> 2.704643 | R115: =VLOOKUP($C115,'4b) SL EPO Extended Data Sheet'!$A$5:$AB$168,12,FALSE) -> A | S115: =VLOOKUP($C115,'4b) SL EPO Extended Data Sheet'!$A$5:$AB$168,13,FALSE) -> 0 | U115: =VLOOKUP($C115,'4b) SL EPO Extended Data Sheet'!$A$5:$AE$168,31,FALSE) -> 0 (Aug-23) | W115: =VLOOKUP($C115,'4b) SL EPO Extended Data Sheet'!$A$5:$AC$168,16,FALSE)/1000000 -> 25.602972 | X115: =VLOOKUP($C115,'4b) SL EPO Extended Data Sheet'!$A$5:$AC$168,17,FALSE)/1000000 -> 32.328177 | Y115: =VLOOKUP($C115,'4b) SL EPO Extended Data Sheet'!$A$5:$AC$168,18,FALSE)/1000000 -> 0.04223667 | Z115: =VLOOKUP($C115,'4b) SL EPO Extended Data Sheet'!$A$5:$AB$168,16,FALSE)/1000000 -> 25.602972 | AA115: =VLOOKUP($C115,'4b) SL EPO Extended Data Sheet'!$A$5:$AC$168,19,FALSE) -> 46637 | AB115: =VLOOKUP($C115,'4b) SL EPO Extended Data Sheet'!$A$5:$AC$168,20,FALSE) -> 46647 | AC115: =VLOOKUP($C115,'4b) SL EPO Extended Data Sheet'!$A$5:$AC$168,21,FALSE) -> 17 | AD115: =VLOOKUP($C115,'4b) SL EPO Extended Data Sheet'!$A$5:$AB$168,15,FALSE)/1000000 -> 0.045159 | AE115: =VLOOKUP($C115,'4b) SL EPO Extended Data Sheet'!$A$5:$AC$168,22,FALSE)/1000000 -> 23.363959 | AF115: =VLOOKUP($C115,'4b) SL EPO Extended Data Sheet'!$A$5:$AC$168,23,FALSE)/1000000 -> 22.930891 | AG115: =VLOOKUP($C115,'4b) SL EPO Extended Data Sheet'!$A$5:$AC$168,24,FALSE)/1000000 -> 29.865991 | AH115: =VLOOKUP($C115,'4b) SL EPO Extended Data Sheet'!$A$5:$AC$168,25,FALSE) -> 0.76779275 | AI115: =VLOOKUP($C115,'4b) SL EPO Extended Data Sheet'!$A$5:$AC$168,26,FALSE) -> 0.9814643 | AJ115: =VLOOKUP($C115,'4b) SL EPO Extended Data Sheet'!$A$5:$AC$168,27,FALSE) -> 0.9125487 | AK115: =VLOOKUP($C115,'4b) SL EPO Extended Data Sheet'!$A$5:$AC$168,28,FALSE) -> 0.89563397 | AL115: =VLOOKUP($C115,'4b) SL EPO Extended Data Sheet'!$A$6:$AB$168,15,FALSE) -> 45159 | AM115: =VLOOKUP($C115,'4b) SL EPO Extended Data Sheet'!$A$5:$AC$168,29,FALSE) -> A | AV115: 32.28594 | AW115: 46630 | AY115: 25.602972 | AZ115: =W115-AY115 -> 0 | BA115: 46637 | BB115: =AA115-BA115 -> 0
A116: =C115 -> Effluent Distribution Asset Improvement | B116: The Effluent Distribution project provides critical support to the hazard reduction of key plants within Retrievals value streams. It allows effluent to be transferred from First Generation Magnox Storage Pond (FGMSP) and the Magnox Swarf Storage Silos (MSSS) to the downstream effluent treatment facilities. The Delivery Confidence Assessment is currently Green against the P80 cost and schedule detailed within the Full Business Case (FBC). However, the project has experienced some issues in the lead up to the commencement of active commissioning (due to start April 26). This period, we have seen a slippage of 17 days resulting in a forecast mid-September 2027 which is outside of the P50. This has been due to the Effluent Distribution Tanks (EDT) Plant configuration not being understood by operations & maintenance to enable the isolation of Critical Safety Equipment which is preventing the installation of a 4-pole isolator (critical path). The baseline RAG is Amber, which reflects the slippage experienced this period which has resulted in the project completion now forecasting beyond the baseline end date of early Sept 27. Re-sanction approved in August 2023 giving a total P50 sanction of £38.2m and a P80 of £41.7m. The latest EAC forecast is 37.8m which includes £5.5m of spend prior to 2014. Capability and Capacity is Amber due to the availability of Legacy Ponds Maintenance Team to support the project.
B118: Value Stream: Remediation
B120: Portfolio Summary
B122: 35/10398 | C122: Calder Land Clearance | D122: Sellafield | F122: =VLOOKUP($C122,'4b) SL EPO Extended Data Sheet'!$A$5:$AB$168,2,FALSE) -> R | G122: =VLOOKUP($C122,'4b) SL EPO Extended Data Sheet'!$A$5:$AB$168,3, FALSE) -> 0 | I122: =VLOOKUP($C122,'4b) SL EPO Extended Data Sheet'!$A$5:$AD$168,30, FALSE) -> FBC (Jul-19) | J122: =VLOOKUP($C122,'4b) SL EPO Extended Data Sheet'!$A$5:$AB$168,6, FALSE)/1000000 -> 47.818 | K122: =VLOOKUP($C122,'4b) SL EPO Extended Data Sheet'!$A$5:$AB$168,7, FALSE)/1000000 -> 51.06 | L122: =VLOOKUP($C122,'4b) SL EPO Extended Data Sheet'!$A$5:$AB$168,8, FALSE) -> 46058 | M122: =VLOOKUP($C122,'4b) SL EPO Extended Data Sheet'!$A$5:$AB$168,9, FALSE) -> 46321 | O122: =VLOOKUP($C122,'4b) SL EPO Extended Data Sheet'!$A$5:$AB$168,10, FALSE)/1000000 -> 51.06 | P122: =VLOOKUP($C122,'4b) SL EPO Extended Data Sheet'!$A$5:$AB$168,11, FALSE)/1000000 -> 47.818 | R122: =VLOOKUP($C122,'4b) SL EPO Extended Data Sheet'!$A$5:$AB$168,12,FALSE) -> R | S122: =VLOOKUP($C122,'4b) SL EPO Extended Data Sheet'!$A$5:$AB$168,13,FALSE) -> 0 | U122: =VLOOKUP($C122,'4b) SL EPO Extended Data Sheet'!$A$5:$AE$168,31,FALSE) -> FBC (Mar-22) | W122: =VLOOKUP($C122,'4b) SL EPO Extended Data Sheet'!$A$5:$AC$168,16,FALSE)/1000000 -> 38.593832 | X122: =VLOOKUP($C122,'4b) SL EPO Extended Data Sheet'!$A$5:$AC$168,17,FALSE)/1000000 -> 38.562536 | Y122: =VLOOKUP($C122,'4b) SL EPO Extended Data Sheet'!$A$5:$AC$168,18,FALSE)/1000000 -> 0.02950003 | Z122: =VLOOKUP($C122,'4b) SL EPO Extended Data Sheet'!$A$5:$AB$168,16,FALSE)/1000000 -> 38.593832 | AA122: =VLOOKUP($C122,'4b) SL EPO Extended Data Sheet'!$A$5:$AC$168,19,FALSE) -> 46058 | AB122: =VLOOKUP($C122,'4b) SL EPO Extended Data Sheet'!$A$5:$AC$168,20,FALSE) -> 46836 | AC122: =VLOOKUP($C122,'4b) SL EPO Extended Data Sheet'!$A$5:$AC$168,21,FALSE) -> 0 | AD122: =VLOOKUP($C122,'4b) SL EPO Extended Data Sheet'!$A$5:$AB$168,15,FALSE)/1000000 -> 0.044634 | AE122: =VLOOKUP($C122,'4b) SL EPO Extended Data Sheet'!$A$5:$AC$168,22,FALSE)/1000000 -> 38.574743 | AF122: =VLOOKUP($C122,'4b) SL EPO Extended Data Sheet'!$A$5:$AC$168,23,FALSE)/1000000 -> 23.196601 | AG122: =VLOOKUP($C122,'4b) SL EPO Extended Data Sheet'!$A$5:$AC$168,24,FALSE)/1000000 -> 28.369283 | AH122: =VLOOKUP($C122,'4b) SL EPO Extended Data Sheet'!$A$5:$AC$168,25,FALSE) -> 0.81766611 | AI122: =VLOOKUP($C122,'4b) SL EPO Extended Data Sheet'!$A$5:$AC$168,26,FALSE) -> 0.60134168 | AJ122: =VLOOKUP($C122,'4b) SL EPO Extended Data Sheet'!$A$5:$AC$168,27,FALSE) -> 0.99950539 | AK122: =VLOOKUP($C122,'4b) SL EPO Extended Data Sheet'!$A$5:$AC$168,28,FALSE) -> 0.60104425 | AL122: =VLOOKUP($C122,'4b) SL EPO Extended Data Sheet'!$A$6:$AB$168,15,FALSE) -> #N/A | AM122: =VLOOKUP($C122,'4b) SL EPO Extended Data Sheet'!$A$5:$AC$168,29,FALSE) -> A | AV122: 38.533036 | AW122: 46836 | AY122: 38.593832 | AZ122: =W122-AY122 -> 0 | BA122: 46058 | BB122: =AA122-BA122 -> 0
A123: =C122 -> Calder Land Clearance | B123: The scope of the Calder Land Clearance (CLC) project is to demolish 4 major structures on the Calder Hall site to base slab level, to enable new capabilities to be built to support the Site Ion Exchange Effluent Plant (SIXEP). To date, 3 of the 4 major structures have been demolished – Turbine Hall A remains to be done. The Delivery Confidence Assessment remains Red, due to significant Turbine Hall A asbestos removal activities undertaken in FY23/24, 24/25 and 25/26, extending the scheduled completion date past P80 of the original Business Case; as a result, the project benefit – land being available to Sites Ion Exchange Effluent Plant (SIXEP) Waste Management Receipt Facility (SWMRF) Project - is delayed until Summer 2027 (note the project end date is 6 months later due to SL project close out activities). This new date is not currently impinging SWMRF planned work, nor HEX (who will partially set up on the CLC plot). Regular communications between CLC, SWM and HEX projects continues to ensure that if an impact is forecast, mitigations can be developed. To minimise impact the SIXEP programme are now in control of the West Side of the Site which will allow the SIXEP drilling programme to commence. This resulted in two new risks to the CLC project: firstly, the timely transfer of land back to CLC to complete demolition; and, secondly, the land constraints for laydown of waste during de-plant and demolition. These risks are currently not reflected within the CLC schedule. Stakeholder engagement with SIXEP is aiming to avoid an impact for transferring land back at the appropriate time, whilst additional land has been identified for CLC use to mitigate land constraints. The Baseline RAG remains Red due to schedule forecast. This is due to the Turbine Hall A asbestos removal activities extending the scheduled completion date beyond the baseline P50. A Change Control Request (CCR) is approved and will be implemented in period 10 to include this additional asbestos removal scope. It is expected that the delivery confidence assessment, baseline RAG and CPI will go Green. This includes staff retraining and a robust implementation plan which will incorporate new supervision arrangements. The project continues to be impacted by industrial action in the supply chain resulting in productivity losses, key skills unavailable, and constraints on work scope delivery. Impact assessment will be finalised on conclusion of the action with the intent to seek appropriate sanction relief subject to further review. This is not a dispute directly with Sellafield Ltd; Sellafield is engaged with the Supply Chain and Stakeholders to ensure effective management of the impacts; correct mitigations are in place and to effectively mobilise resources upon return to work. There is an assumption that the scaffolders will return to work at the end of January which is incorporated into the schedule. The Capability and Capacity RAG is Amber due to the trench cleaning issue. Recent engagement with the Contractor’s senior management has led to the development of a Project Improvement Plan, aimed at schedule improvement with the Contractor and is close to finalising the detail, further commentary will be made in P10.
B125: 35/09707 | C125: LAETP Floc Retrieval | D125: Sellafield | F125: =VLOOKUP(C125,'5a)NDA MPPR'!$B$9:$AK$61,3,FALSE) -> A | G125: =VLOOKUP(C125,'5a)NDA MPPR'!$B$9:$AK$61,4,FALSE) -> 0 | I125: =VLOOKUP(C125,'5a)NDA MPPR'!$B$9:$AK$61,6,FALSE) -> FBC (Jun-24) | J125: =VLOOKUP(C125,'5a)NDA MPPR'!$B$9:$AK$61,7,FALSE) -> 75.1 | K125: =VLOOKUP(C125,'5a)NDA MPPR'!$B$9:$AK$61,8,FALSE) -> 79.8 | L125: =VLOOKUP(C125,'5a)NDA MPPR'!$B$9:$AK$61,9,FALSE) -> 47189 | M125: =VLOOKUP(C125,'5a)NDA MPPR'!$B$9:$AK$61,10,FALSE) -> 47339 | O125: =VLOOKUP(C125,'5a)NDA MPPR'!$B$9:$AK$61,12,FALSE) -> 90.2 | P125: =VLOOKUP(C125,'5a)NDA MPPR'!$B$9:$AK$61,13,FALSE) -> 90.2 | R125: =VLOOKUP(C125,'5a)NDA MPPR'!$B$9:$AK$61,15,FALSE) -> R | S125: =VLOOKUP(C125,'5a)NDA MPPR'!$B$9:$AK$61,16,FALSE) -> 0 | U125: =VLOOKUP(C125,'5a)NDA MPPR'!$B$9:$AK$61,18,FALSE) -> FBC (Oct-23) | W125: =VLOOKUP(C125,'5a)NDA MPPR'!$B$9:$AK$61,20,FALSE) -> 57.796824 | X125: =VLOOKUP(C125,'5a)NDA MPPR'!$B$9:$AK$61,21,FALSE) -> 87.702751 | Y125: =VLOOKUP(C125,'5a)NDA MPPR'!$B$9:$AK$61,22,FALSE) -> 0.1 | AA125: =VLOOKUP(C125,'5a)NDA MPPR'!$B$9:$AK$61,24,FALSE) -> 46524 | AB125: =VLOOKUP(C125,'5a)NDA MPPR'!$B$9:$AK$61,25,FALSE) -> 47189 | AC125: =VLOOKUP(C125,'5a)NDA MPPR'!$B$9:$AK$61,26,FALSE) -> 0 | AE125: =VLOOKUP(C125,'5a)NDA MPPR'!$B$9:$AK$61,28,FALSE) -> 53.769457 | AF125: =VLOOKUP(C125,'5a)NDA MPPR'!$B$9:$AK$61,29,FALSE) -> 44.76915 | AG125: =VLOOKUP(C125,'5a)NDA MPPR'!$B$9:$AK$61,30,FALSE) -> 75.375883 | AH125: =VLOOKUP(C125,'5a)NDA MPPR'!$B$9:$AK$61,31,FALSE) -> 0.59394528 | AI125: =VLOOKUP(C125,'5a)NDA MPPR'!$B$9:$AK$61,32,FALSE) -> 0.83261303 | AJ125: =VLOOKUP(C125,'5a)NDA MPPR'!$B$9:$AK$61,33,FALSE) -> 0.93031854 | AK125: =VLOOKUP(C125,'5a)NDA MPPR'!$B$9:$AK$61,34,FALSE) -> 0.77459534 | AM125: =VLOOKUP(C125,'5a)NDA MPPR'!$B$9:$AK$61,36,FALSE) -> A | AV125: 87.58571 | AW125: 47189 | AY125: 57.796824 | AZ125: =W125-AY125 -> 0 | BA125: 46524 | BB125: =AA125-BA125 -> 0
A126: =C125 -> LAETP Floc Retrieval | B126: =VLOOKUP($C125,'5a)NDA MPPR'!$A$9:$AK$61,2,FALSE) -> The overall intent of the LAETP (Low Active Effluent Treatment Plant) Floc (flocculant) Retrieval project is to provide the necessary equipment, documentation, knowledge transfer and training to enable the Alpha Operations teams to safely and effectively remove circa 86m3 of non-adhered (loose) floc from four existing and degrading Holding Tanks located on the Sellafield site. The project benefit is handover of the retrieval’s equipment to the Alpha Remediation Operations team, the project provides the capability to retrieve floc from the four storage tanks. This benefit remains on track to be delivered within the strategic tolerances of the civil tank substantiation and Low-Active Effluent Management Group (LAEMG) downstream plant availability. Delivery Confidence Assessment remains Amber due to the forecast project end date which is now 12 months later than the P80 date in the approved business case and uncertainty around the projects ability to stay within the P80 costs however following a project reset, which included revised delivery strategy and amendments to contract, cost forecast currently remains within the sanction approved by NDA. A Change Control Request (CCR) has now been approved and will be implemented for period 10, allowing reporting aligned to the recently approved P80 drawdown. The Project continually works to improve Contractor performance, Cumbria Nuclear Solutions Limited (CNSL) key focus areas are credible and realistic schedule and estimate, contract management, management of change and design delivery. Output of the updated schedule is now reflected in outward reporting; this reflects the model output which has been assured during a joint SL and NDA project review. The project forecast and subsequent impact on Key Decommissioning Milestone (KDM) Removal of non-adhered Floc by June 2030 is currently being assessed and will be evaluated in the coming periods. The Baseline RAG remains Amber. The project continues to be impacted by industrial action in the supply chain resulting in productivity losses, key skills unavailable, and constraints on work scope delivery. Impact assessment will be finalised on conclusion of the action with the intent to seek appropriate sanction relief subject to further review. This is not a dispute directly with Sellafield Ltd; Sellafield is engaged with the Supply Chain and Stakeholders to ensure effective management of the impacts; correct mitigations are in place and to effectively mobilise resources upon return to work. The project has implemented a strategic pause of the construction work face, to prevent inefficient working whilst key resources are involved in industrial action and to protect the project sanction position. This has resulted in a minor increase in overall EAC (£117k) due to prolongation of key resources required to maintain momentum on key activities such as the handover of completed systems and ensure an effective restart in January 2026. A mitigated schedule to reduce the impact of absent scaffolding resource has been implemented; to protect key project milestones, this will be monitored closely by the project team. Attention remains on completing detailed design to de-risk the remainder of the construction scope, the design work remains on track to be completed in Q4 in line with the key target milestone date. Issues have been encountered in fabrication of key process modules, timely completion of these final procurements is key to enabling the remainder of the construction work. Capability and Capacity RAG remains Amber, a contract to supplement the SL led commissioning and pre-ops teams has been awarded, mobilisation of these resources is ongoing.
B128: 35/05396 | C128: Chimney Decommissioning Phase 2F | D128: Sellafield | F128: =VLOOKUP(C128,'5a)NDA MPPR'!$B$9:$AK$61,3,FALSE) -> A | G128: =VLOOKUP(C128,'5a)NDA MPPR'!$B$9:$AK$61,4,FALSE) -> 0 | I128: =VLOOKUP(C128,'5a)NDA MPPR'!$B$9:$AK$61,6,FALSE) -> FBC (Apr-21) | J128: =VLOOKUP(C128,'5a)NDA MPPR'!$B$9:$AK$61,7,FALSE) -> 125.5 | K128: =VLOOKUP(C128,'5a)NDA MPPR'!$B$9:$AK$61,8,FALSE) -> 132.1 | L128: =VLOOKUP(C128,'5a)NDA MPPR'!$B$9:$AK$61,9,FALSE) -> 46874 | M128: =VLOOKUP(C128,'5a)NDA MPPR'!$B$9:$AK$61,10,FALSE) -> 47239 | O128: =VLOOKUP(C128,'5a)NDA MPPR'!$B$9:$AK$61,12,FALSE) -> 149.1 | P128: =VLOOKUP(C128,'5a)NDA MPPR'!$B$9:$AK$61,13,FALSE) -> 125.5 | R128: =VLOOKUP(C128,'5a)NDA MPPR'!$B$9:$AK$61,15,FALSE) -> R | S128: =VLOOKUP(C128,'5a)NDA MPPR'!$B$9:$AK$61,16,FALSE) -> 0 | U128: =VLOOKUP(C128,'5a)NDA MPPR'!$B$9:$AK$61,18,FALSE) -> FBC (Feb-24) | W128: =VLOOKUP(C128,'5a)NDA MPPR'!$B$9:$AK$61,20,FALSE) -> 144.83408 | X128: =VLOOKUP(C128,'5a)NDA MPPR'!$B$9:$AK$61,21,FALSE) -> 138.83422 | Y128: =VLOOKUP(C128,'5a)NDA MPPR'!$B$9:$AK$61,22,FALSE) -> -10.1 | AA128: =VLOOKUP(C128,'5a)NDA MPPR'!$B$9:$AK$61,24,FALSE) -> 47882 | AB128: =VLOOKUP(C128,'5a)NDA MPPR'!$B$9:$AK$61,25,FALSE) -> 48684 | AC128: =VLOOKUP(C128,'5a)NDA MPPR'!$B$9:$AK$61,26,FALSE) -> 0 | AE128: =VLOOKUP(C128,'5a)NDA MPPR'!$B$9:$AK$61,28,FALSE) -> 114.54412 | AF128: =VLOOKUP(C128,'5a)NDA MPPR'!$B$9:$AK$61,29,FALSE) -> 102.89863 | AG128: =VLOOKUP(C128,'5a)NDA MPPR'!$B$9:$AK$61,30,FALSE) -> 101.7259 | AH128: =VLOOKUP(C128,'5a)NDA MPPR'!$B$9:$AK$61,31,FALSE) -> 1.0115283 | AI128: =VLOOKUP(C128,'5a)NDA MPPR'!$B$9:$AK$61,32,FALSE) -> 0.89833185 | AJ128: =VLOOKUP(C128,'5a)NDA MPPR'!$B$9:$AK$61,33,FALSE) -> 0.79086442 | AK128: =VLOOKUP(C128,'5a)NDA MPPR'!$B$9:$AK$61,34,FALSE) -> 0.7104587 | AM128: =VLOOKUP(C128,'5a)NDA MPPR'!$B$9:$AK$61,36,FALSE) -> G | AV128: 148.90102 | AW128: 48684 | AY128: 144.83408 | AZ128: =W128-AY128 -> 0 | BA128: 47882 | BB128: =AA128-BA128 -> 0
A129: =C128 -> Chimney Decommissioning Phase 2F | B129: =VLOOKUP($C128,'5a)NDA MPPR'!$A$9:$AK$61,2,FALSE) -> Please note; the reduction to the projects lifecycle Estimate At Completion (EAC) is as a result of a reporting error, the true lifecycle forecast is unchanged from the previous period and remains at £148.9m. Pile 1 Chimney Demolition Project Phase 2F, to demolish the chimney contaminated during 1957 fire, is organised into 3 separate sub-projects. The first two, Filter Gallery Demolition and Diffuser Demolition are now complete, and the project is now in its final stage, Barrel Demolition. Barrel Demolition is the removal and disposal of the Barrel section of the chimney, using a unique specifically designed platform for demolition access with lifting operations supported by the existing Tower crane. Delivery Confidence Assessment remains amber based on current forecast completion being beyond Business Case P80 date, the position is supported by an independent project assurance review carried out in September 2025 for which the output also rated the project at Amber. As communicated to Nuclear Decommissioning Authority (NDA) Board in 2023, the project, following receipt of a conservative tender return for whole of Barrel Demolition that pressured business case tolerances, has adopted a phased approach to ensure learning and opportunities from Integrated Works Testing (IWT) is understood prior to future contract awards for the Installation and Commissioning of the Suspended Platform Incremental Descent developed by ADAPT (SPIDA) and Barrel Demolition scope. Following the recent approval of inflation relief the project’s sanctioned P80 value is now £149.1m. The sanction release request for Installation & Commissioning (£15m P50 escalated) has now been approved and is now within the new sanctioned P50 (£125.5m following inflation relief approval). Recognising that the project’s EAC is close to the revised P80 sanction value, the project will continue with its strategy for a full revision of the existing baseline schedule/cost once IWT (July 2026) is complete, critical learning is obtained (i.e. from demolition demonstration) and future uncertainty is reduced. The first project benefit milestone (based on completion date) is on track. The P50 Delivery date remains April 2033. During key testing on IWT, an issue was identified with respect to the platform maintaining a balanced load across all hangers, particularly during changes in external temperatures. Testing of solutions has been successful so far and is ongoing, however this will lead to a delay in commencement of FAT-18 Demolition Demonstration. P50 completion date for IWT remains June 2026. SPIDA Installation and Commissioning contract award now forecast for February 2026. The Baseline RAG remains Red as the forecast project end date is after the P50 baseline. License instrument submission forecast remains Q4 2025/26 a safety case design review was undertaken this period with minor actions required to close out. The project has been impacted by industrial action in the supply chain resulting in productivity losses, key skills unavailable, and constraints on workscope delivery. Impact assessment will be finalised on conclusion of the action with the intent to seek appropriate sanction relief subject to further review. This is not a dispute directly with Sellafield Ltd; Sellafield is engaged with the Supply Chain and Stakeholders to ensure effective management of the impacts; correct mitigations are in place and to effectively mobilise resources upon return to work. Capability and Capacity RAG remains green.
B131: 35/09000 | C131: Heat Exchanger Deplanting - Main Project | D131: Sellafield | F131: =VLOOKUP(C131,'5a)NDA MPPR'!$B$9:$AK$61,3,FALSE) -> G | G131: =VLOOKUP(C131,'5a)NDA MPPR'!$B$9:$AK$61,4,FALSE) -> 0 | I131: =VLOOKUP(C131,'5a)NDA MPPR'!$B$9:$AK$61,6,FALSE) -> OBC (Jan-24) | J131: =VLOOKUP(C131,'5a)NDA MPPR'!$B$9:$AK$61,7,FALSE) -> 54 | K131: =VLOOKUP(C131,'5a)NDA MPPR'!$B$9:$AK$61,8,FALSE) -> 65 | L131: =VLOOKUP(C131,'5a)NDA MPPR'!$B$9:$AK$61,9,FALSE) -> 47480 | M131: =VLOOKUP(C131,'5a)NDA MPPR'!$B$9:$AK$61,10,FALSE) -> 47831 | O131: =VLOOKUP(C131,'5a)NDA MPPR'!$B$9:$AK$61,12,FALSE) -> n/a | P131: =VLOOKUP(C131,'5a)NDA MPPR'!$B$9:$AK$61,13,FALSE) -> 11 | R131: =VLOOKUP(C131,'5a)NDA MPPR'!$B$9:$AK$61,15,FALSE) -> G | S131: =VLOOKUP(C131,'5a)NDA MPPR'!$B$9:$AK$61,16,FALSE) -> 0 | U131: =VLOOKUP(C131,'5a)NDA MPPR'!$B$9:$AK$61,18,FALSE) -> OBC (Oct-25) | W131: =VLOOKUP(C131,'5a)NDA MPPR'!$B$9:$AK$61,20,FALSE) -> 53.217953 | X131: =VLOOKUP(C131,'5a)NDA MPPR'!$B$9:$AK$61,21,FALSE) -> 53.217744 | Y131: =VLOOKUP(C131,'5a)NDA MPPR'!$B$9:$AK$61,22,FALSE) -> 0 | AA131: =VLOOKUP(C131,'5a)NDA MPPR'!$B$9:$AK$61,24,FALSE) -> 47465 | AB131: =VLOOKUP(C131,'5a)NDA MPPR'!$B$9:$AK$61,25,FALSE) -> 47528 | AC131: =VLOOKUP(C131,'5a)NDA MPPR'!$B$9:$AK$61,26,FALSE) -> 0 | AE131: =VLOOKUP(C131,'5a)NDA MPPR'!$B$9:$AK$61,28,FALSE) -> 6.8649791 | AF131: =VLOOKUP(C131,'5a)NDA MPPR'!$B$9:$AK$61,29,FALSE) -> 4.1085647 | AG131: =VLOOKUP(C131,'5a)NDA MPPR'!$B$9:$AK$61,30,FALSE) -> 5.0076656 | AH131: =VLOOKUP(C131,'5a)NDA MPPR'!$B$9:$AK$61,31,FALSE) -> 0.82045509 | AI131: =VLOOKUP(C131,'5a)NDA MPPR'!$B$9:$AK$61,32,FALSE) -> 0.59848175 | AJ131: =VLOOKUP(C131,'5a)NDA MPPR'!$B$9:$AK$61,33,FALSE) -> 0.12899743 | AK131: =VLOOKUP(C131,'5a)NDA MPPR'!$B$9:$AK$61,34,FALSE) -> 0.077202607 | AM131: =VLOOKUP(C131,'5a)NDA MPPR'!$B$9:$AK$61,36,FALSE) -> G | AV131: 53.198964 | AW131: 47528 | AY131: 53.19581 | AZ131: =W131-AY131 -> 0.022143 | BA131: 47465 | BB131: =AA131-BA131 -> 0
A132: =C131 -> Heat Exchanger Deplanting - Main Project | B132: =VLOOKUP($C131,'5a)NDA MPPR'!$A$9:$AK$61,2,FALSE) -> The scope of the Heat Exchanger (HEx) Deplanting 1 project is the removal and laydown of the first 6 Calder Hall Heat Exchangers, as an enabler for land clearance in preparation for a new Site Ion Exchange Effluent Plant (SIXEP) operating facility; subsequent disposal of these initial 6 Heat Exchangers and the deplanting & disposal of the remaining 10 Heat Exchangers is out-with this project. The Delivery Confidence Assessment and Baseline RAG remain Green. In period, the laydown area detailed design has been through a formal review and received a green rating; the project are pursuing accelerated sanction through IRP to allow for contract placement of the laydown works. The Ops Plan Milestone remains on target with Invitation To Tender (ITT) documents, through Decommissioning and Nuclear Waste Partnership (DNWP), now at an advanced stage. On the main lifting contract the opening up meeting was held and a further design engineering meeting planned for the new year to confirm project deliverables and schedule. The project continues to be impacted by industrial action in the supply chain resulting in productivity losses, key skills unavailable, and constraints on work scope delivery. Impact assessment will be finalised on conclusion of the action with the intent to seek appropriate sanction relief subject to further review. This is not a dispute directly with Sellafield Ltd; Sellafield is engaged with the Supply Chain and Stakeholders to ensure effective management of the impacts; correct mitigations are in place and to effectively mobilise resources upon return to work. Capability and Capacity remains Green with the project now having placed the main HEx1 lifting contract.
B134: Enablers: Information Services Organisation (ISO)
B136: 35/10351 | C136: Data Centre Replacement Project | D136: Sellafield | F136: =VLOOKUP($C136,'4b) SL EPO Extended Data Sheet'!$A$5:$AB$168,2,FALSE) -> R | G136: =VLOOKUP($C136,'4b) SL EPO Extended Data Sheet'!$A$5:$AB$168,3, FALSE) -> 0 | I136: =VLOOKUP($C136,'4b) SL EPO Extended Data Sheet'!$A$5:$AD$168,30, FALSE) -> FBC (Oct-20) | J136: =VLOOKUP($C136,'4b) SL EPO Extended Data Sheet'!$A$5:$AB$168,6, FALSE)/1000000 -> 31.614 | K136: =VLOOKUP($C136,'4b) SL EPO Extended Data Sheet'!$A$5:$AB$168,7, FALSE)/1000000 -> 35.175 | L136: =VLOOKUP($C136,'4b) SL EPO Extended Data Sheet'!$A$5:$AB$168,8, FALSE) -> 45220 | M136: =VLOOKUP($C136,'4b) SL EPO Extended Data Sheet'!$A$5:$AB$168,9, FALSE) -> 45428 | O136: =VLOOKUP($C136,'4b) SL EPO Extended Data Sheet'!$A$5:$AB$168,10, FALSE)/1000000 -> 35.175 | P136: =VLOOKUP($C136,'4b) SL EPO Extended Data Sheet'!$A$5:$AB$168,11, FALSE)/1000000 -> 31.614 | R136: =VLOOKUP($C136,'4b) SL EPO Extended Data Sheet'!$A$5:$AB$168,12,FALSE) -> R | S136: =VLOOKUP($C136,'4b) SL EPO Extended Data Sheet'!$A$5:$AB$168,3, FALSE) -> 0 | U136: =VLOOKUP($C136,'4b) SL EPO Extended Data Sheet'!$A$5:$AE$168,31,FALSE) -> FBC (Apr-21) | W136: =VLOOKUP($C136,'4b) SL EPO Extended Data Sheet'!$A$5:$AC$168,16,FALSE)/1000000 -> 31.971082 | X136: =VLOOKUP($C136,'4b) SL EPO Extended Data Sheet'!$A$5:$AC$168,17,FALSE)/1000000 -> 26.925406 | Y136: =VLOOKUP($C136,'4b) SL EPO Extended Data Sheet'!$A$5:$AC$168,18,FALSE)/1000000 -> 0.00768103 | Z136: =VLOOKUP($C136,'4b) SL EPO Extended Data Sheet'!$A$5:$AB$168,16,FALSE)/1000000 -> 31.971082 | AA136: =VLOOKUP($C136,'4b) SL EPO Extended Data Sheet'!$A$5:$AC$168,19,FALSE) -> 45220 | AB136: =VLOOKUP($C136,'4b) SL EPO Extended Data Sheet'!$A$5:$AC$168,20,FALSE) -> 46244 | AC136: =VLOOKUP($C136,'4b) SL EPO Extended Data Sheet'!$A$5:$AC$168,21,FALSE) -> 0 | AD136: =VLOOKUP($C136,'4b) SL EPO Extended Data Sheet'!$A$5:$AB$168,15,FALSE)/1000000 -> 0.044287 | AE136: =VLOOKUP($C136,'4b) SL EPO Extended Data Sheet'!$A$5:$AC$168,22,FALSE)/1000000 -> 31.971083 | AF136: =VLOOKUP($C136,'4b) SL EPO Extended Data Sheet'!$A$5:$AC$168,23,FALSE)/1000000 -> 31.803876 | AG136: =VLOOKUP($C136,'4b) SL EPO Extended Data Sheet'!$A$5:$AC$168,24,FALSE)/1000000 -> 26.785211 | AH136: =VLOOKUP($C136,'4b) SL EPO Extended Data Sheet'!$A$5:$AC$168,25,FALSE) -> 1.187367 | AI136: =VLOOKUP($C136,'4b) SL EPO Extended Data Sheet'!$A$5:$AC$168,26,FALSE) -> 0.99477006 | AJ136: =VLOOKUP($C136,'4b) SL EPO Extended Data Sheet'!$A$5:$AC$168,27,FALSE) -> 1 | AK136: =VLOOKUP($C136,'4b) SL EPO Extended Data Sheet'!$A$5:$AC$168,28,FALSE) -> 0.99477008 | AL136: =VLOOKUP($C136,'4b) SL EPO Extended Data Sheet'!$A$6:$AB$168,15,FALSE) -> 44287 | AM136: =VLOOKUP($C136,'4b) SL EPO Extended Data Sheet'!$A$5:$AC$168,29,FALSE) -> G | AV136: 26.917725 | AW136: 46244 | AY136: 31.971082 | AZ136: =W136-AY136 -> 0 | BA136: 45220 | BB136: =AA136-BA136 -> 0
A137: =C136 -> Data Centre Replacement Project | B137: The Data Centre Replacement Project is the design and build of a modern onsite data centre followed by the installation and migration of IT services from the legacy data centre. The First Project Benefit has been realised as all applications and network services have been migrated to the new data centre. Delivery Confidence Assessment is Red as the project has exceeded the P80 completion date of 16th May 2024. Current forecast completion of 10th August 2026 inclusive of Gate 5 SPER April 2026 and Post Investment Appraisal submission. Variations to existing scope reviewed with SPA, schedule updated and estimate awaiting additional information from requests for quotations, which will be followed by submission to ISO Change Board. The P50 cost and schedule; EAC ~£4.6m under P50 Sanction (not inclusive of studies); Latest best estimate funding request submitted for 2026/27 covering scope variations agreed with SPA, to be reflected in sanction position following approval at ISO Change Board. The Baseline RAG status sits at Red as the schedule position is not recoverable. The delays to project completion are derived from handover requirements and lack of pre-ops. Plant Room A re-energised. Plant Room B approaching completion, no issues in period, re-energisation by end of January on track. Installation of plant labelling to re-commence January. Commercial engagement underway for Coalescent filters & Puma operator panel quotes, these will be built into submission to ISO Change Board. Outline solution design and plant modification proposal being prepared for building management system connectivity to allow for remote alarm monitoring within main site command facility. All building systems under planned preventative maintenance arrangements which are underway. Capability & Capacity RAG remains Green. Tri-Party Team (ISO, FM, and the Project) continue to collaborate effectively. AXIOM design resources contract preparing to be closed. The project continues to be impacted by industrial action in the supply chain resulting in productivity losses, key skills unavailable, and constraints on work scope delivery. Impact assessment will be finalised on conclusion of the action with the intent to seek appropriate sanction relief subject to further review. This is not a dispute directly with Sellafield Ltd; Sellafield is engaged with the Supply Chain and Stakeholders to ensure effective management of the impacts; correct mitigations are in place and to effectively mobilise resources upon return to work. Industrial action risk remains a risk, Morgan Sindall team continue to monitor disruption to isolator scope of work.
B140: Table of Changes (vs Last Period)
B141: Project Name | F141: EAC | G141: Forecast End Date | I141: Baseline P50 Cost | J141: Baseline P50 End Date
B142: =C17 -> Enhanced CNC Airwave System (Encrypted Comms) | F142: =Y17 -> 0 | G142: =AC17 -> 0 | I142: =AZ17 -> 0 | J142: =BB17 -> 0
B143: =C29 -> Security Systems Architecture Upgrade (SSAU) | F143: =Y29 -> 0 | G143: =AC29 -> 0 | I143: =AZ29 -> 0 | J143: =BB29 -> 0
B144: =C20 -> Box Encapsulation Plant | F144: =Y20 -> 0 | G144: =AC20 -> 20 | I144: =AZ20 -> 0 | J144: =BB20 -> 0
B145: =C23 -> Sellafield Product & Residue Store Retreatment Plant | F145: =Y23 -> 0 | G145: =AC23 -> 0 | I145: =AZ23 -> -1.0000001e-06 | J145: =BB23 -> 0
...

Sheet 3) BC and Sanction Changes PD6
A2: Project Name | B2: OpCo | D2: Approved Business Case and Sanction
D3: Approved Business Case | J3: Sanction
D4: Business Case Approval Date | E4: Whole Life Cost (P50) | F4: Whole Life Cost (P80) | G4: Project End Date (P50) | H4: Project End Date (P80) | J4: Sanction Approved to NDA | K4: Sanction Released to OpCo | M4: Reporting Period Change Made | N4: Description of Change
A7: SEP Solid Waste Storage Retrievals | B7: Sellafield | D7: FBC (Jan-16) | E7: 788 | F7: 846 | G7: 44986 | H7: 45170 | J7: 846 | K7: 846
D8: FBC (Jan-16) | E8: 788 | F8: 846 | G8: 44986 | H8: 45170 | J8: 871 | K8: 871 | M8: P8 2021/22 | N8: Both sanction values increased by £25.0m in line with Covid-19 impact drawdown approved by GIC in Aug-21.
D9: FBC (Jan-16) | E9: 788 | F9: 871 | G9: 44986 | H9: 45170 | J9: 871 | K9: 871 | M9: P10 2021/22 | N9: Whole Life Cost P80 increased by £25.0m in line with Covid-19 impact drawdown. Note: No point in updating the BC dates (P50) and (P80) to reflect Covid-19 impact drawdown as forecast completion and cost would still be such that SRO DCA remains red. The route to green SRO DCA for this project is a resubmission Business Case which is currently expected to go to SL IRP in Nov 2022, following which it will go to NDA and HMG.
D10: FBC (Jan-16) | E10: =E9+25 -> 813 | F10: 871 | G10: 44986 | H10: 45170 | J10: 871 | K10: 871 | M10: P4 2022/23 | N10: Whole Life Cost P50 increased by £25.0m in line with Covid-19 impact drawdown (should have done this in P10 21/22)
A12: Electrical Supply - New Construction | B12: Sellafield | D12: OBC (Dec-17) | E12: 218 | F12: 238 | G12: 44986 | H12: 44986 | J12: 238 | K12: 201.5
D13: OBC (Dec-17) | E13: 218 | F13: 249.3 | G13: 44986 | H13: 44986 | J13: 249.3 | K13: 201.5 | M13: P2 2022/23 | N13: Whole Life Cost P80 increased to £249.3m - no other changes requested. Note: no additional sanction released to the OpCo under this submission. Note: No point in updating the BC dates (P50) and (P80) to reflect Covid-19 impact drawdown as forecast completion and cost would still be such that SRO DCA remains red. The route to green SRO DCA for this project is a resubmission Business Case which is currently expected to be taken to TAP in Dec 2022.
D14: OBC (Dec-17) | E14: =E13+11.3 -> 229.3 | F14: 249.3 | G14: 44986 | H14: 44986 | J14: 249.3 | K14: 201.5 | M14: P4 2022/23 | N14: Whole Life Cost P50 increased by £11.3m in line with Covid-19 impact drawdown (should have done this in P2 22/23).
D15: OBC (Dec-17) | E15: 229.4 | F15: 249.4 | G15: 44810 | H15: 44986 | J15: =F15 -> 249.4 | K15: 201.5 | M15: P5 2022/23 | N15: Corrections provided by NDA Sanction Team
D16: FBC (May-23) | E16: 379.164 | F16: 403.001 | G16: 47362 | H16: 11140 | J16: 403.001 | K16: 379.164 | M16: P2 2023/24 | N16: Please note both P50 and P80 values quoted are inflated. See page 2 & 10 of the Full Business Case resubmission version 2. (Approved on 10 May 2023). Only month and year provided for P50 & P80 completion dates, so reverted to the 1st of the month.
A18: Box Encapsulation Plant | B18: Sellafield | D18: FBC (Dec-17) | E18: 769 | F18: 887 | G18: 44593 | H18: 45078 | J18: 887 | K18: 887
D19: FBC (Jul-22) | E19: 1316 | F19: 1512 | G19: 46226 | H19: 46847 | J19: 1512 | K19: 1316 | M19: P4 | N19: BEP FBC Resubmission received CST approval 26 July 2022
A21: Box Encapsulation Plant Product Store Direct Import Facility | B21: Sellafield | D21: FBC (Sep-20) | E21: 420 | F21: 435 | G21: 44652 | H21: 44743 | J21: 445 | K21: 445
D22: FBC (Sep-20) | E22: 458.9 | F22: 466.4 | G22: 45244 | H22: 45361 | J22: 458.9 | K22: 458.9 | M22: P12 2021/22 | N22: Both sanction values increased by £13.9m following the approach detailed within the NDA Covid-19 Sanction Request paper approved by HMT. Although the covid total impact was £38.9m the existing P80 contingency was used to partially offset the impact, thereby reducing the drawdown. Sellafield Ltd only requested NDA approval of the P50 (P80 is not required at this stage). £466.4 is the P80 figure identified in the Covid Sanction paper.
D23: FBC (Sep-20) | E23: 458.9 | F23: 466.4 | G23: 45244 | H23: 45361 | J23: 466.4 | K23: 458.9 | M23: P4 2022/23 | N23: Change Sanction Approved to NDA as £466.4m to align with the P80 (should have done this P12 21/22).
A25: SIXEP Continuity Plant | B25: Sellafield | D25: OBC (Jul-20) | E25: 574 | F25: 730 | G25: 46966 | H25: 11232 | J25: 313.5 | K25: ?
D26: FBC (Dec-21) | E26: 1007 | F26: 1182 | G26: 47849 | H26: 48611 | J26: 1182 | K26: 1007 | M26: P9 2021/22 | N26: To reflect HMT approval of FBC in Dec-21 and associated approval and release of sanction.
